Workbook

Sheet Memo
A5: Scope
A6: The purpose of this workpaper is to verify the closing balances of trade payables as on 31/03/26.
A8: IPE: Listing
A9: Completeness: Completeness of IPE was ensured by tallying the balance of the schedule to the balance as per the financials.
A10: Accuracy: Accuracy of the IPE was ensured by Direct testing <<Refer Audit steps below>>
A12: Work Done
A13: 1. ET has obtained the schedule of Trade Payables as on March 31, 2026
A14: 2. ET has obtained the balance confirmations for the sample vendors. | F14: < Refer tab Balance Confirmations >
A15: 3. ET has obtained the subsequent status of the trade payables as on March 31, 2026 | F15: < Refer tab Invoice wise >
A16: 5. ET has obtained the Party wise list of the trade payables and reconcilied the balance with total trade payables. | F16: < Refer Tab Listing >
A17: 6. ET has verified the reinstatement of foreign debtors and verified the exchange rate taken for reinstatement from RBI website. | F17: < Refer tab forex rate >
A18: 7. ET has verified the disclosue of trade payables ageing as per the requirements of Schedule -3 (as amended). | F18: < Refer tab Schedule 3 >
A19: 8. ET has recalculate the Trade payables ageing . | F19: < Refer Tab Ageing >
A22: Observation
A23: Trade payables outstanding for more than 3 years for Related party and other than related party which needs a disclosure as per Ind AS 24 Related party dislosure and If there is any disputes with party that also has to be reported as per Schedule 3 .
A25: Conclusion
A26: Satisfactory

Sheet Reco & Summary 
A1: =Memo!A1 -> 0
A2: =Memo!A2 -> 0
A3: =Memo!A3 -> 0
A5: Purpose
A6: Purpose of this workpaper to summarize trade payable balance and bifurcate the TP balances into MSME and Non MSME.
A8: Reconciliation with Financial
A9: Particulars | B9: As per STIR Financials as on 31/03/26 | C9: As per working | D9: difference
A10: Due to micro and small enterprises (refer note 2.47) | B10: 123386123 | C10: =D25 -> 1.2333659e+08 | D10: =C10-B10 -> -49530.582
A11: Others creditors | B11: 482644475 | C11: =B25 -> 4.8241842e+08 | D11: =C11-B11 -> -226053.53
A13: - inter division | B13: 447634866 | C13: =F25 -> 4.4763486e+08 | D13: =C13-B13 -> -1.67
B14: =SUM(B10:B13) -> 1053665464 | C14: =SUM(C10:C13) -> 1.0533899e+09 | D14: =SUM(D10:D13) -> -275585.78 | E14: <<Immaterial>>
A16: Summary of TP listing
A17: Particulars | B17: Other than MSMED | D17: MSMED | F17: IDE | G17: Total | H17: Subsequently Status | I17: Subsequently Paid % | J17: ET Remarks
B18: Opex | C18: Capex | D18: Opex | E18: CAPEX
A19: Balance as per SL report (AP Liability) | B19: =SUMIFS('AP Liability Non MSME'!$R$21:$R$390,'AP Liability Non MSME'!$I$21:$I$390,B18) -> 1.8816731e+08 | C19: =SUMIFS('AP Liability Non MSME'!$R$21:$R$390,'AP Liability Non MSME'!$I$21:$I$390,C18) -> 306936.38 | D19: =SUMIFS('AP Liability MSME'!$R$21:$R$412,'AP Liability MSME'!$I$21:$I$412,'Reco & Summary '!D18) -> 47079777 | E19: =SUMIFS('AP Liability MSME'!$R$21:$R$412,'AP Liability MSME'!$I$21:$I$412,E18) -> 4872054.9 | F19: 0 | G19: =SUM(B19:F19) -> 2.4042608e+08 | H19: ='AP Liability Non MSME'!B15+'AP Liability MSME'!B15 -> 2.210367e+08 | I19: =H19/G19 -> 0.91935412
A20: SSS Accrual | B20: =SUMIFS('SSS Accrual Non MSME'!$N$21:$N$226,'SSS Accrual Non MSME'!$O$21:$O$226,'Reco & Summary '!B18) -> 1.535431e+08 | C20: =SUMIFS('SSS Accrual Non MSME'!$N$21:$N$226,'SSS Accrual Non MSME'!$O$21:$O$226,C18) -> 689531.8 | D20: =SUMIFS('SSS Accrual MSME'!$N$21:$N$195,'SSS Accrual MSME'!$O$21:$O$195,'Reco & Summary '!D18) -> 19759203 | E20: =SUMIFS('SSS Accrual MSME'!$N$21:$N$195,'SSS Accrual MSME'!$O$21:$O$195,E18) -> 6489622.9 | F20: 0 | G20: =SUM(B20:F20) -> 1.8048146e+08 | H20: ='SSS Accrual Non MSME'!B15+'SSS Accrual MSME'!B15 -> 1.7985262e+08 | I20: =H20/G20 -> 0.99651579
A21: Open PO Accruals | B21: =SUMIFS('PO Accrual Non MSME'!$O$19:$O$229,'PO Accrual Non MSME'!$E$19:$E$229,'Reco & Summary '!B18) -> 1.3424228e+08 | C21: =SUMIFS('PO Accrual Non MSME'!$O$19:$O$229,'PO Accrual Non MSME'!$E$19:$E$229,'Reco & Summary '!C18) -> 1084366 | D21: =SUMIFS('PO Accrual MSME'!$O$20:$O$212,'PO Accrual MSME'!$E$20:$E$212,'Reco & Summary '!D18) -> 56497612 | E21: =SUMIFS('PO Accrual MSME'!$O$20:$O$212,'PO Accrual MSME'!$E$20:$E$212,E18) -> 16601942 | F21: 0 | G21: =SUM(B21:F21) -> 2.084262e+08
A22: ESB Accruals | F22: ='ESB accrual '!I9 -> 28616339 | G22: =SUM(B22:F22) -> 28616339
A23: GEIIPL ESOP/RSU liability F.Y. 2025-26 | F23: =-'ESOP & RSU'!G17-'ESOP & RSU'!H27 -> 309752848 | G23: =SUM(B23:F23) -> 309752848
A24: IBS DT accruals | B24: 6465731.7 | F24: 1.0926568e+08 | G24: =SUM(B24:F24) -> 1.1573141e+08
B25: =SUM(B19:B24) -> 4.8241842e+08 | C25: =SUM(C19:C24) -> 2080834.2 | D25: =SUM(D19:D24) -> 1.2333659e+08 | E25: =SUM(E19:E24) -> 27963620 | F25: =SUM(F19:F24) -> 4.4763486e+08 | G25: =SUM(G19:G24) -> 1.0834343e+09

Sheet Schedule III 
A1: =Memo!A1 -> 0
A2: =Memo!A2 -> 0
A3: =Memo!A3 -> 0
A5: Purpose
A6: To verify the correctness of diclosure of Trade payables ageing as per Schedule III
A8: Work done | H8: *Excl Interdivison and Capital Creditros
A9: ET has obtained the Trade payable listing from the client.
A10: ET has reperformed the ageing calculation.
A11: Amount in MSME includes Capex amount pertaining to MSME
G12: Amount in Rs.
A13: Particulars | B13: Not Due | C13: Less than 1 Year | D13: 1-2 years | E13: 2-3 years | F13: More than 3 years | G13: Total
A14: (i) MSME | B14: =SUMIFS('AP Liability MSME'!R:R,'AP Liability MSME'!AQ:AQ,'Schedule III '!B13,'AP Liability MSME'!I:I,"Opex")+SUMIFS('SSS Accrual MSME'!$N:$N,'SSS Accrual MSME'!$AO:$AO,'Schedule III '!B13,'SSS Accrual MSME'!$O:$O,"Opex")+SUMIFS('PO Accrual MSME'!$O:$O,'PO Accrual MSME'!$E:$E,"Opex") -> 1.2330423e+08 | C14: =SUMIFS('AP Liability MSME'!R:R,'AP Liability MSME'!AQ:AQ,C13,'AP Liability MSME'!I:I,"Opex")+SUMIFS('SSS Accrual MSME'!$N:$N,'SSS Accrual MSME'!$AO:$AO,'Schedule III '!C13,'SSS Accrual MSME'!$O:$O,"Opex") -> 32363.5 | D14: 0 | E14: 0 | F14: 0 | G14: =SUM(B14:F14) -> 1.2333659e+08
A15: (ii) Others | B15: =SUMIFS('AP Liability Non MSME'!$R:$R,'AP Liability Non MSME'!$AP:$AP,'Schedule III '!B13,'AP Liability Non MSME'!I:I,"Opex")+SUMIFS('SSS Accrual Non MSME'!$N:$N,'SSS Accrual Non MSME'!$AO:$AO,'Schedule III '!B13,'SSS Accrual Non MSME'!O:O,"Opex")+SUMIFS('PO Accrual Non MSME'!O:O,'PO Accrual Non MSME'!E:E,"Opex")+'Reco & Summary '!B24 -> 4.5870159e+08 | C15: =SUMIFS('AP Liability Non MSME'!$R:$R,'AP Liability Non MSME'!$AP:$AP,'Schedule III '!C13,'AP Liability Non MSME'!I:I,"Opex")+SUMIFS('SSS Accrual Non MSME'!$N:$N,'SSS Accrual Non MSME'!$AO:$AO,'Schedule III '!C13,'SSS Accrual Non MSME'!O:O,"Opex") -> 23209050 | D15: =SUMIFS('AP Liability Non MSME'!$R:$R,'AP Liability Non MSME'!$AP:$AP,'Schedule III '!D13,'AP Liability Non MSME'!I:I,"Opex")+SUMIFS('SSS Accrual Non MSME'!$N:$N,'SSS Accrual Non MSME'!$AO:$AO,'Schedule III '!D13,'SSS Accrual Non MSME'!O:O,"Opex") -> 166497.26 | E15: =SUMIFS('AP Liability Non MSME'!$R:$R,'AP Liability Non MSME'!$AP:$AP,'Schedule III '!E13,'AP Liability Non MSME'!I:I,"Opex")+SUMIFS('SSS Accrual Non MSME'!$N:$N,'SSS Accrual Non MSME'!$AO:$AO,'Schedule III '!E13,'SSS Accrual Non MSME'!O:O,"Opex") -> 19103.131 | F15: =SUMIFS('AP Liability Non MSME'!$R:$R,'AP Liability Non MSME'!$AP:$AP,'Schedule III '!F13,'AP Liability Non MSME'!I:I,"Opex")+SUMIFS('SSS Accrual Non MSME'!$N:$N,'SSS Accrual Non MSME'!$AO:$AO,'Schedule III '!F13,'SSS Accrual Non MSME'!O:O,"Opex") -> 322182.08 | G15: =SUM(B15:F15) -> 4.8241842e+08
A16: (iii) Disputed dues - MSME | G16: =SUM(C16:F16) -> 0
A17: (iv) Disputed dues - Others | G17: =SUM(C17:F17) -> 0
B18: Balance as per schedule | G18: =SUM(G14:G15) -> 6.0575501e+08
B19: As per Financials | G19: 606030598
B20: Diff | G20: =G18-G19 -> -275584.11
F25: ap non
E26: Row Labels | F26: Sum of Amount as per RBI
E27: ABB INDIA LIMITED A37150 | F27: 10404.17
E28: Ambika Water Supply A38198 | F28: 132115.25
E29: Amplus Kn Solar Private Limited A37782 | F29: 9530759.7
E30: APSIS AEROCOM LIMITED | F30: 266717.51
E31: BAKER HUGHES DIGITAL SOLUTIONS GMBH N63671 | F31: 55253.164
E32: Bengaluru Marriott Hotel Whitefield A37515 | F32: 136880
E33: Bharti Airtel Limited A38979 | F33: 1548966.2
E34: BLUE DART EXPRESS LIMITED A35832 | F34: 11202.58
E35: CAPGEMINI TECHNOLOGY SERVICES INDIA LIMITED A16348 | F35: 3223584
E36: CHUBB SYSTEMS PRIVATE LIMITED A38431 | F36: 40411.8
E37: CISCO SYSTEMS CAPITAL INDIA PRIVATE LIMITED A37210 | F37: 10711526
E38: CONVERGINT INDIA PRIVATE LIMITED A36904 | F38: 444681.36
... E106: Grand Total | F106: 1.8847425e+08

Sheet AP Liability Non MSME
A1: =Memo!A1 -> 0 | U1: ='AP Liability MSME'!U1 -> 46112
A2: =Memo!A2 -> 0
A3: =Memo!A3 -> 0
A5: Work Done
A6: 1. ET has obtained the schedule for AP Liability (Non-MSME).
A7: 2. ET has verified the exchange rate considered for closing payable amount.
A8: 3. ET has recomputed the ageing of invoices payable from due date.
A9: 4. ET has checked the computation of due date and performed 3 way match on sample basis.
A11: Summary
A13: Particulars | B13: Amount
A14: Payable Amount | B14: =R19 -> 1.8847425e+08
A15: Subsequently Paid | B15: =AN19 -> 1.6907817e+08
A16: Subsequently Paid % | B16: =B15/B14 -> 0.89708896
A18: AP Liability Schedule - Non MSME
R19: =SUM(R21:R390) -> 1.8847425e+08 | S19: =SUM(S21:S390) -> 535453.67 | V19: =SUM(V21:V390) -> 4838174.6 | W19: =SUM(W21:W390) -> 570165.9 | X19: =SUM(X21:X390) -> 253681.24 | Y19: =SUM(Y21:Y390) -> 0 | Z19: =SUM(Z21:Z390) -> 125280 | AA19: =SUM(AA21:AA390) -> 185600.39 | AB19: =SUM(AB21:AB390) -> 322182.08 | AC19: =SUM(AC21:AC390) -> 1.8217916e+08 | AL19: =SUM(AL20:AL1900) -> 1.8847425e+08 | AM19: =SUM(AM20:AM1900) -> 0 | AN19: =SUM(AN20:AN1900) -> 1.6907817e+08 | AO19: 46112
A20: Division | B20: Company Code | C20: Account Code | D20: Account Description | E20: Vendor Name | F20: Related Party | G20: Foreign / Domestic | H20: Unique | I20: Nature (Capital/Trade) | J20: Invoice Number | K20: PO Number | L20: Invoice Date | M20: Currency | N20: Invoice Original Amount | O20: MOR Rate | P20: Invoice Amount INR | Q20: RBI Rate | R20: Amount as per RBI | S20: FX_Diff | T20: MSMED | U20: Ageing | V20: 0-30 days | W20: 30-60 days | X20: 60-90 days | Y20: 90-120 days | Z20: 120-180 days | AA20: 180 Days-3 year | AB20: >3 Years | AC20: Not Due | AD20: Invoice Id | AE20: Reson for more than 180 days/debit balances/No GE entity payables | AF20: Subsequent payment Doc # | AG20: Date of subsequent payment | AH20: Due date | AJ20: Currency | AK20: Exchange Rate | AL20: Amount in INR | AM20: Difference | AN20: Subsequently Paid | AO20: No. of Days | AP20: Ageing Bracket | AU20: =AS20+AS19+AS22+'AP Liability MSME'!AT19 -> 0
A21: GE India Industrial Pvt Ltd - GEITC | B21: GR16 | C21: 2070201000 | D21: Trade Accounts Payable-Subledge | E21: Gartner India Research and Advisory Services Pvt. Ltd. A37407 | F21: Non-IBS | G21: Domestic | I21: Opex | J21: IN5020806 | K21: 100069560 | L21: 45959 | M21: INR | N21: 107136 | O21: 1 | P21: =N21*O21 -> 107136 | Q21: 1 | R21: =N21*Q21 -> 107136 | S21: =R21-P21 -> 0 | T21: Non-MSME | U21: =$U$1-AH21 -> 33 | V21: 0 | W21: =R21 -> 107136 | X21: 0 | Y21: 0 | Z21: 0 | AA21: 0 | AB21: 0 | AC21: 0 | AD21: 38556214 | AE21: As per User confirmation Invoice cancelled in Apr26 | AH21: 46079 | AJ21: =M21 -> INR | AK21: 1 | AL21: =N21*AK21 -> 107136 | AM21: =R21-AL21 -> 0 | AO21: =$AO$19-AH21 -> 33 | AP21: =IF(AO21<0,"Not Due",IF(AO21<366,"Less than 1 year",IF(AO21<731,"1-2 years",IF(AO21<1096,"2-3 years","More than 3 years")))) -> Less than 1 year | AU21: =AS19+'AP Liability MSME'!AT19 -> 0
A22: GE India Industrial Pvt Ltd - GEITC | B22: GR16 | C22: 2070201000 | D22: Trade Accounts Payable-Subledge | E22: INDO-MIM LIMITED | F22: Non-IBS | G22: Domestic | I22: Opex | J22: D-D2815/2526 | K22: 100071136 | L22: 46094 | M22: INR | N22: 5140.44 | O22: 1 | P22: =N22*O22 -> 5140.44 | Q22: 1 | R22: =N22*Q22 -> 5140.44 | S22: =R22-P22 -> 0 | T22: Non-MSME | U22: =$U$1-AH22 -> -12 | V22: 0 | W22: 0 | X22: 0 | Y22: 0 | Z22: 0 | AA22: 0 | AB22: 0 | AC22: =R22 -> 5140.44 | AD22: 39011958 | AE22: Not Due | AF22: 88161 | AG22: 46121 | AH22: 46124 | AJ22: =M22 -> INR | AK22: 1 | AL22: =N22*AK22 -> 5140.44 | AM22: =R22-AL22 -> 0 | AN22: =AL22 -> 5140.44 | AO22: =$AO$19-AH22 -> -12 | AP22: =IF(AO22<0,"Not Due",IF(AO22<366,"Less than 1 year",IF(AO22<731,"1-2 years",IF(AO22<1096,"2-3 years","More than 3 years")))) -> Not Due | AU22: =AS21+'AP Liability MSME'!AT20+'SSS Accrual Non MSME'!AR19 -> 0
A23: GE India Industrial Pvt Ltd - GEITC | B23: GR16 | C23: 2070201000 | D23: Trade Accounts Payable-Subledge | E23: GENPACT INDIA PRIVATE LIMITED A37168 | F23: Non-IBS | G23: Domestic | I23: Opex | J23: B2ZXKA17929 | K23: 100066859 | L23: 46023 | M23: INR | N23: 197264.16 | O23: 1 | P23: =N23*O23 -> 197264.16 | Q23: 1 | R23: =N23*Q23 -> 197264.16 | S23: =R23-P23 -> 0 | T23: Non-MSME | U23: =$U$1-AH23 -> -61 | V23: 0 | W23: 0 | X23: 0 | Y23: 0 | Z23: 0 | AA23: 0 | AB23: 0 | AC23: =R23 -> 197264.16 | AD23: 38718522 | AE23: Not Due | AF23: 88955 | AG23: 46168 | AH23: 46173 | AJ23: =M23 -> INR | AK23: 1 | AL23: =N23*AK23 -> 197264.16 | AM23: =R23-AL23 -> 0 | AN23: =AL23 -> 197264.16 | AO23: =$AO$19-AH23 -> -61 | AP23: =IF(AO23<0,"Not Due",IF(AO23<366,"Less than 1 year",IF(AO23<731,"1-2 years",IF(AO23<1096,"2-3 years","More than 3 years")))) -> Not Due
A24: GE India Industrial Pvt Ltd - GEITC | B24: GR16 | C24: 2070201000 | D24: Trade Accounts Payable-Subledge | E24: Element14 India Private Limited A36095 | F24: Non-IBS | G24: Domestic | I24: Opex | J24: 1046566 | K24: 100070712 | L24: 46070 | M24: INR | N24: 8763.04 | O24: 1 | P24: =N24*O24 -> 8763.04 | Q24: 1 | R24: =N24*Q24 -> 8763.04 | S24: =R24-P24 -> 0 | T24: Non-MSME | U24: =$U$1-AH24 -> -78 | V24: 0 | W24: 0 | X24: 0 | Y24: 0 | Z24: 0 | AA24: 0 | AB24: 0 | AC24: =R24 -> 8763.04 | AD24: 38922414 | AE24: Not Due | AF24: 89210 | AG24: 46188 | AH24: 46190 | AJ24: =M24 -> INR | AK24: 1 | AL24: =N24*AK24 -> 8763.04 | AM24: =R24-AL24 -> 0 | AN24: =AL24 -> 8763.04 | AO24: =$AO$19-AH24 -> -78 | AP24: =IF(AO24<0,"Not Due",IF(AO24<366,"Less than 1 year",IF(AO24<731,"1-2 years",IF(AO24<1096,"2-3 years","More than 3 years")))) -> Not Due
A25: GE India Industrial Pvt Ltd - GEITC | B25: GR16 | C25: 2070201000 | D25: Trade Accounts Payable-Subledge | E25: Tata Consultancy Services Limited A11987 | F25: Non-IBS | G25: Domestic | I25: Opex | J25: KADI526013446 | K25: 100067695 | L25: 46078 | M25: INR | N25: 216000 | O25: 1 | P25: =N25*O25 -> 216000 | Q25: 1 | R25: =N25*Q25 -> 216000 | S25: =R25-P25 -> 0 | T25: Non-MSME | U25: =$U$1-AH25 -> -116 | V25: 0 | W25: 0 | X25: 0 | Y25: 0 | Z25: 0 | AA25: 0 | AB25: 0 | AC25: =R25 -> 216000 | AD25: 38976983 | AE25: Not Due | AH25: 46228 | AJ25: =M25 -> INR | AK25: 1 | AL25: =N25*AK25 -> 216000 | AM25: =R25-AL25 -> 0 | AO25: =$AO$19-AH25 -> -116 | AP25: =IF(AO25<0,"Not Due",IF(AO25<366,"Less than 1 year",IF(AO25<731,"1-2 years",IF(AO25<1096,"2-3 years","More than 3 years")))) -> Not Due
A26: GE India Industrial Pvt Ltd - GEITC | B26: GR16 | C26: 2070201000 | D26: Trade Accounts Payable-Subledge | E26: PERSOL INDIA PRIVATE LIMITED | F26: Non-IBS | G26: Domestic | I26: Opex | J26: KAT2526EH00155 | K26: 100068129 | L26: 46080 | M26: INR | N26: 174656.78 | O26: 1 | P26: =N26*O26 -> 174656.78 | Q26: 1 | R26: =N26*Q26 -> 174656.78 | S26: =R26-P26 -> 0 | T26: Non-MSME | U26: =$U$1-AH26 -> -28 | V26: 0 | W26: 0 | X26: 0 | Y26: 0 | Z26: 0 | AA26: 0 | AB26: 0 | AC26: =R26 -> 174656.78 | AD26: 38994055 | AE26: Not Due | AF26: 88417 | AG26: 46136 | AH26: 46140 | AJ26: =M26 -> INR | AK26: 1 | AL26: =N26*AK26 -> 174656.78 | AM26: =R26-AL26 -> 0 | AN26: =AL26 -> 174656.78 | AO26: =$AO$19-AH26 -> -28 | AP26: =IF(AO26<0,"Not Due",IF(AO26<366,"Less than 1 year",IF(AO26<731,"1-2 years",IF(AO26<1096,"2-3 years","More than 3 years")))) -> Not Due
A27: GE India Industrial Pvt Ltd - GEITC | B27: GR16 | C27: 2070201000 | D27: Trade Accounts Payable-Subledge | E27: Superseva Global Services Private Limited A38849 | F27: Non-IBS | G27: Domestic | I27: Opex | J27: FEB/25-26/5431 | K27: 100067740 | L27: 46083 | M27: INR | N27: 43074.28 | O27: 1 | P27: =N27*O27 -> 43074.28 | Q27: 1 | R27: =N27*Q27 -> 43074.28 | S27: =R27-P27 -> 0 | T27: Non-MSME | U27: =$U$1-AH27 -> -16 | V27: 0 | W27: 0 | X27: 0 | Y27: 0 | Z27: 0 | AA27: 0 | AB27: 0 | AC27: =R27 -> 43074.28 | AD27: 38976190 | AE27: Not Due | AF27: Payment on hold as per Notice received from GST department | AH27: 46128 | AJ27: =M27 -> INR | AK27: 1 | AL27: =N27*AK27 -> 43074.28 | AM27: =R27-AL27 -> 0 | AO27: =$AO$19-AH27 -> -16 | AP27: =IF(AO27<0,"Not Due",IF(AO27<366,"Less than 1 year",IF(AO27<731,"1-2 years",IF(AO27<1096,"2-3 years","More than 3 years")))) -> Not Due
A28: GE India Industrial Pvt Ltd - GEITC | B28: GR16 | C28: 2070201000 | D28: Trade Accounts Payable-Subledge | E28: Tata Consultancy Services Limited A11987 | F28: Non-IBS | G28: Domestic | I28: Opex | J28: KADI526012304 | K28: 100066399 | L28: 46049 | M28: INR | N28: 2511244.1 | O28: 1 | P28: =N28*O28 -> 2511244.1 | Q28: 1 | R28: =N28*Q28 -> 2511244.1 | S28: =R28-P28 -> 0 | T28: Non-MSME | U28: =$U$1-AH28 -> -87 | V28: 0 | W28: 0 | X28: 0 | Y28: 0 | Z28: 0 | AA28: 0 | AB28: 0 | AC28: =R28 -> 2511244.1 | AD28: 38838440 | AE28: Not Due | AH28: 46199 | AJ28: =M28 -> INR | AK28: 1 | AL28: =N28*AK28 -> 2511244.1 | AM28: =R28-AL28 -> 0 | AO28: =$AO$19-AH28 -> -87 | AP28: =IF(AO28<0,"Not Due",IF(AO28<366,"Less than 1 year",IF(AO28<731,"1-2 years",IF(AO28<1096,"2-3 years","More than 3 years")))) -> Not Due
A29: GE India Industrial Pvt Ltd - GEITC | B29: GR16 | C29: 2070201000 | D29: Trade Accounts Payable-Subledge | E29: SEDIN TECHNOLOGIES PVT LTD A36624 | F29: Non-IBS | G29: Domestic | I29: Opex | J29: 50001954 | K29: 100070049 | L29: 46091 | M29: INR | N29: 647862.3 | O29: 1 | P29: =N29*O29 -> 647862.3 | Q29: 1 | R29: =N29*Q29 -> 647862.3 | S29: =R29-P29 -> 0 | T29: Non-MSME | U29: =$U$1-AH29 -> -24 | V29: 0 | W29: 0 | X29: 0 | Y29: 0 | Z29: 0 | AA29: 0 | AB29: 0 | AC29: =R29 -> 647862.3 | AD29: 39006193 | AE29: Not Due | AF29: 88379 | AG29: 46133 | AH29: 46136 | AJ29: =M29 -> INR | AK29: 1 | AL29: =N29*AK29 -> 647862.3 | AM29: =R29-AL29 -> 0 | AN29: =AL29 -> 647862.3 | AO29: =$AO$19-AH29 -> -24 | AP29: =IF(AO29<0,"Not Due",IF(AO29<366,"Less than 1 year",IF(AO29<731,"1-2 years",IF(AO29<1096,"2-3 years","More than 3 years")))) -> Not Due
A30: GE India Industrial Pvt Ltd - GEITC | B30: GR16 | C30: 2070201000 | D30: Trade Accounts Payable-Subledge | E30: MOUSER ELECTRONICS INC. A02649 | F30: Non-IBS | G30: Foreign | I30: Opex | J30: 89076855 | K30: 100071065 | L30: 46084 | M30: USD | N30: 1320.28 | O30: 91.03395 | P30: =N30*O30 -> 120190.3 | Q30: 94.6543 | R30: =N30*Q30 -> 124970.18 | S30: =R30-P30 -> 4779.8757 | T30: Non-MSME | U30: =$U$1-AH30 -> -62 | V30: 0 | W30: 0 | X30: 0 | Y30: 0 | Z30: 0 | AA30: 0 | AB30: 0 | AC30: =R30 -> 124970.18 | AD30: 38987412 | AE30: Not Due | AF30: 90008291 | AG30: 46174 | AH30: 46174 | AJ30: =M30 -> USD | AK30: 94.6543 | AL30: =N30*AK30 -> 124970.18 | AM30: =R30-AL30 -> 0 | AN30: =AL30 -> 124970.18 | AO30: =$AO$19-AH30 -> -62 | AP30: =IF(AO30<0,"Not Due",IF(AO30<366,"Less than 1 year",IF(AO30<731,"1-2 years",IF(AO30<1096,"2-3 years","More than 3 years")))) -> Not Due
A31: GE India Industrial Pvt Ltd - GEITC | B31: GR16 | C31: 2070201000 | D31: Trade Accounts Payable-Subledge | E31: GENPACT INDIA PRIVATE LIMITED A37168 | F31: Non-IBS | G31: Domestic | I31: Opex | J31: B1Z3TS16731 | K31: 100064664 | L31: 46013 | M31: INR | N31: 1350745.2 | O31: 1 | P31: =N31*O31 -> 1350745.2 | Q31: 1 | R31: =N31*Q31 -> 1350745.2 | S31: =R31-P31 -> 0 | T31: Non-MSME | U31: =$U$1-AH31 -> -51 | V31: 0 | W31: 0 | X31: 0 | Y31: 0 | Z31: 0 | AA31: 0 | AB31: 0 | AC31: =R31 -> 1350745.2 | AD31: 38697159 | AE31: Not Due | AF31: 88807 | AG31: 46160 | AH31: 46163 | AJ31: =M31 -> INR | AK31: 1 | AL31: =N31*AK31 -> 1350745.2 | AM31: =R31-AL31 -> 0 | AN31: =AL31 -> 1350745.2 | AO31: =$AO$19-AH31 -> -51 | AP31: =IF(AO31<0,"Not Due",IF(AO31<366,"Less than 1 year",IF(AO31<731,"1-2 years",IF(AO31<1096,"2-3 years","More than 3 years")))) -> Not Due
A32: GE India Industrial Pvt Ltd - GEITC | B32: GR16 | C32: 2070201000 | D32: Trade Accounts Payable-Subledge | E32: GENPACT INDIA PRIVATE LIMITED A37168 | F32: Non-IBS | G32: Domestic | I32: Opex | J32: B2ZXKA17447 | K32: 100068107 | L32: 45971 | M32: INR | N32: 222879.6 | O32: 1 | P32: =N32*O32 -> 222879.6 | Q32: 1 | R32: =N32*Q32 -> 222879.6 | S32: =R32-P32 -> 0 | T32: Non-MSME | U32: =$U$1-AH32 -> -9 | V32: 0 | W32: 0 | X32: 0 | Y32: 0 | Z32: 0 | AA32: 0 | AB32: 0 | AC32: =R32 -> 222879.6 | AD32: 38514019 | AE32: Not Due | AF32: 88097 | AG32: 46118 | AH32: 46121 | AJ32: =M32 -> INR | AK32: 1 | AL32: =N32*AK32 -> 222879.6 | AM32: =R32-AL32 -> 0 | AN32: =AL32 -> 222879.6 | AO32: =$AO$19-AH32 -> -9 | AP32: =IF(AO32<0,"Not Due",IF(AO32<366,"Less than 1 year",IF(AO32<731,"1-2 years",IF(AO32<1096,"2-3 years","More than 3 years")))) -> Not Due
A33: GE India Industrial Pvt Ltd - GEITC | B33: GR16 | C33: 2070201000 | D33: Trade Accounts Payable-Subledge | E33: GENPACT INDIA PRIVATE LIMITED A37168 | F33: Non-IBS | G33: Domestic | I33: Opex | J33: B2ZXKA17671 | K33: 100068631 | L33: 45996 | M33: INR | N33: 354024 | O33: 1 | P33: =N33*O33 -> 354024 | Q33: 1 | R33: =N33*Q33 -> 354024 | S33: =R33-P33 -> 0 | T33: Non-MSME | U33: =$U$1-AH33 -> -34 | V33: 0 | W33: 0 | X33: 0 | Y33: 0 | Z33: 0 | AA33: 0 | AB33: 0 | AC33: =R33 -> 354024 | AD33: 38613688 | AE33: Not Due | AF33: 88495 | AG33: 46143 | AH33: 46146 | AJ33: =M33 -> INR | AK33: 1 | AL33: =N33*AK33 -> 354024 | AM33: =R33-AL33 -> 0 | AN33: =AL33 -> 354024 | AO33: =$AO$19-AH33 -> -34 | AP33: =IF(AO33<0,"Not Due",IF(AO33<366,"Less than 1 year",IF(AO33<731,"1-2 years",IF(AO33<1096,"2-3 years","More than 3 years")))) -> Not Due
A34: GE India Industrial Pvt Ltd - GEITC | B34: GR16 | C34: 2070201000 | D34: Trade Accounts Payable-Subledge | E34: QUEST GLOBAL ENGINEERING SERVICES PRIVATE LIMITED A36314 | F34: Non-IBS | G34: Domestic | I34: Opex | J34: 20250765616 | K34: 100065605 | L34: 46034 | M34: INR | N34: 362232 | O34: 1 | P34: =N34*O34 -> 362232 | Q34: 1 | R34: =N34*Q34 -> 362232 | S34: =R34-P34 -> 0 | T34: Non-MSME | U34: =$U$1-AH34 -> -12 | V34: 0 | W34: 0 | X34: 0 | Y34: 0 | Z34: 0 | AA34: 0 | AB34: 0 | AC34: =R34 -> 362232 | AD34: 38765216 | AE34: Not Due | AF34: 88152 | AG34: 46121 | AH34: 46124 | AJ34: =M34 -> INR | AK34: 1 | AL34: =N34*AK34 -> 362232 | AM34: =R34-AL34 -> 0 | AN34: =AL34 -> 362232 | AO34: =$AO$19-AH34 -> -12 | AP34: =IF(AO34<0,"Not Due",IF(AO34<366,"Less than 1 year",IF(AO34<731,"1-2 years",IF(AO34<1096,"2-3 years","More than 3 years")))) -> Not Due
A35: GE India Industrial Pvt Ltd - GEITC | B35: GR16 | C35: 2070201000 | D35: Trade Accounts Payable-Subledge | E35: CHUBB SYSTEMS PRIVATE LIMITED A38431 | F35: Non-IBS | G35: Domestic | I35: Opex | J35: 5114105277 | K35: 100070721 | L35: 46079 | M35: INR | N35: 36290.3 | O35: 1 | P35: =N35*O35 -> 36290.3 | Q35: 1 | R35: =N35*Q35 -> 36290.3 | S35: =R35-P35 -> 0 | T35: Non-MSME | U35: =$U$1-AH35 -> -12 | V35: 0 | W35: 0 | X35: 0 | Y35: 0 | Z35: 0 | AA35: 0 | AB35: 0 | AC35: =R35 -> 36290.3 | AD35: 38981680 | AE35: Not Due | AF35: 88160 | AG35: 46121 | AH35: 46124 | AJ35: =M35 -> INR | AK35: 1 | AL35: =N35*AK35 -> 36290.3 | AM35: =R35-AL35 -> 0 | AN35: =AL35 -> 36290.3 | AO35: =$AO$19-AH35 -> -12 | AP35: =IF(AO35<0,"Not Due",IF(AO35<366,"Less than 1 year",IF(AO35<731,"1-2 years",IF(AO35<1096,"2-3 years","More than 3 years")))) -> Not Due
A36: GE India Industrial Pvt Ltd - GEITC | B36: GR16 | C36: 2070201000 | D36: Trade Accounts Payable-Subledge | E36: Wonder Wash Pvt Ltd A37913 | F36: Non-IBS | G36: Domestic | I36: Opex | J36: WW325/2025-26 | K36: 100070183 | L36: 46085 | M36: INR | N36: 16182 | O36: 1 | P36: =N36*O36 -> 16182 | Q36: 1 | R36: =N36*Q36 -> 16182 | S36: =R36-P36 -> 0 | T36: Non-MSME | U36: =$U$1-AH36 -> -3 | V36: 0 | W36: 0 | X36: 0 | Y36: 0 | Z36: 0 | AA36: 0 | AB36: 0 | AC36: =R36 -> 16182 | AD36: 38977112 | AE36: Not Due | AF36: 88023 | AG36: 46113 | AH36: 46115 | AJ36: =M36 -> INR | AK36: 1 | AL36: =N36*AK36 -> 16182 | AM36: =R36-AL36 -> 0 | AN36: =AL36 -> 16182 | AO36: =$AO$19-AH36 -> -3 | AP36: =IF(AO36<0,"Not Due",IF(AO36<366,"Less than 1 year",IF(AO36<731,"1-2 years",IF(AO36<1096,"2-3 years","More than 3 years")))) -> Not Due
A37: GE India Industrial Pvt Ltd - GEITC | B37: GR16 | C37: 2070201000 | D37: Trade Accounts Payable-Subledge | E37: Infiniti Power Private Limited A37094 | F37: Non-IBS | G37: Domestic | I37: Opex | J37: 252900487 | K37: 100070245 | L37: 46086 | M37: INR | N37: 88639.08 | O37: 1 | P37: =N37*O37 -> 88639.08 | Q37: 1 | R37: =N37*Q37 -> 88639.08 | S37: =R37-P37 -> 0 | T37: Non-MSME | U37: =$U$1-AH37 -> -19 | V37: 0 | W37: 0 | X37: 0 | Y37: 0 | Z37: 0 | AA37: 0 | AB37: 0 | AC37: =R37 -> 88639.08 | AD37: 38982924 | AE37: Not Due | AF37: 88299 | AG37: 46128 | AH37: 46131 | AJ37: =M37 -> INR | AK37: 1 | AL37: =N37*AK37 -> 88639.08 | AM37: =R37-AL37 -> 0 | AN37: =AL37 -> 88639.08 | AO37: =$AO$19-AH37 -> -19 | AP37: =IF(AO37<0,"Not Due",IF(AO37<366,"Less than 1 year",IF(AO37<731,"1-2 years",IF(AO37<1096,"2-3 years","More than 3 years")))) -> Not Due
A38: GE India Industrial Pvt Ltd - GEITC | B38: GR16 | C38: 2070201000 | D38: Trade Accounts Payable-Subledge | E38: MOUSER ELECTRONICS INC. A02649 | F38: Non-IBS | G38: Foreign | I38: Opex | J38: 88817649 | K38: 100070864 | L38: 46069 | M38: USD | N38: 42.02 | O38: 91.82425 | P38: =N38*O38 -> 3858.455 | Q38: 94.6543 | R38: =N38*Q38 -> 3977.3737 | S38: =R38-P38 -> 118.9187 | T38: Non-MSME | U38: =$U$1-AH38 -> -47 | V38: 0 | W38: 0 | X38: 0 | Y38: 0 | Z38: 0 | AA38: 0 | AB38: 0 | AC38: =R38 -> 3977.3737 | AD38: 38939214 | AE38: Not Due | AF38: 90008285 | AG38: 46156 | AH38: 46159 | AJ38: =M38 -> USD | AK38: 94.6543 | AL38: =N38*AK38 -> 3977.3737 | AM38: =R38-AL38 -> 0 | AN38: =AL38 -> 3977.3737 | AO38: =$AO$19-AH38 -> -47 | AP38: =IF(AO38<0,"Not Due",IF(AO38<366,"Less than 1 year",IF(AO38<731,"1-2 years",IF(AO38<1096,"2-3 years","More than 3 years")))) -> Not Due
A39: GE India Industrial Pvt Ltd - GEITC | B39: GR16 | C39: 2070201000 | D39: Trade Accounts Payable-Subledge | E39: GENPACT INDIA PRIVATE LIMITED A37168 | F39: Non-IBS | G39: Domestic | I39: Opex | J39: B2ZXKA17986 | K39: 100065489 | L39: 46030 | M39: INR | N39: 446796 | O39: 1 | P39: =N39*O39 -> 446796 | Q39: 1 | R39: =N39*Q39 -> 446796 | S39: =R39-P39 -> 0 | T39: Non-MSME | U39: =$U$1-AH39 -> -68 | V39: 0 | W39: 0 | X39: 0 | Y39: 0 | Z39: 0 | AA39: 0 | AB39: 0 | AC39: =R39 -> 446796 | AD39: 38752456 | AE39: Not Due | AF39: 89064 | AG39: 46177 | AH39: 46180 | AJ39: =M39 -> INR | AK39: 1 | AL39: =N39*AK39 -> 446796 | AM39: =R39-AL39 -> 0 | AN39: =AL39 -> 446796 | AO39: =$AO$19-AH39 -> -68 | AP39: =IF(AO39<0,"Not Due",IF(AO39<366,"Less than 1 year",IF(AO39<731,"1-2 years",IF(AO39<1096,"2-3 years","More than 3 years")))) -> Not Due
A40: GE India Industrial Pvt Ltd - GEITC | B40: GR16 | C40: 2070201000 | D40: Trade Accounts Payable-Subledge | E40: GENPACT INDIA PRIVATE LIMITED A37168 | F40: Non-IBS | G40: Domestic | I40: Opex | J40: B2ZXKA17980 | K40: 100068530 | L40: 46030 | M40: INR | N40: 371736 | O40: 1 | P40: =N40*O40 -> 371736 | Q40: 1 | R40: =N40*Q40 -> 371736 | S40: =R40-P40 -> 0 | T40: Non-MSME | U40: =$U$1-AH40 -> -68 | V40: 0 | W40: 0 | X40: 0 | Y40: 0 | Z40: 0 | AA40: 0 | AB40: 0 | AC40: =R40 -> 371736 | AD40: 38746931 | AE40: Not Due | AF40: 89064 | AG40: 46177 | AH40: 46180 | AJ40: =M40 -> INR | AK40: 1 | AL40: =N40*AK40 -> 371736 | AM40: =R40-AL40 -> 0 | AN40: =AL40 -> 371736 | AO40: =$AO$19-AH40 -> -68 | AP40: =IF(AO40<0,"Not Due",IF(AO40<366,"Less than 1 year",IF(AO40<731,"1-2 years",IF(AO40<1096,"2-3 years","More than 3 years")))) -> Not Due
A41: GE India Industrial Pvt Ltd - GEITC | B41: GR16 | C41: 2070201000 | D41: Trade Accounts Payable-Subledge | E41: GENPACT INDIA PRIVATE LIMITED A37168 | F41: Non-IBS | G41: Domestic | I41: Opex | J41: B2ZXKA17480 | K41: 100067774 | L41: 45974 | M41: INR | N41: 2171110 | O41: 1 | P41: =N41*O41 -> 2171110 | Q41: 1 | R41: =N41*Q41 -> 2171110 | S41: =R41-P41 -> 0 | T41: Non-MSME | U41: =$U$1-AH41 -> -12 | V41: 0 | W41: 0 | X41: 0 | Y41: 0 | Z41: 0 | AA41: 0 | AB41: 0 | AC41: =R41 -> 2171110 | AD41: 38545723 | AE41: Not Due | AF41: 88158 | AG41: 46121 | AH41: 46124 | AJ41: =M41 -> INR | AK41: 1 | AL41: =N41*AK41 -> 2171110 | AM41: =R41-AL41 -> 0 | AN41: =AL41 -> 2171110 | AO41: =$AO$19-AH41 -> -12 | AP41: =IF(AO41<0,"Not Due",IF(AO41<366,"Less than 1 year",IF(AO41<731,"1-2 years",IF(AO41<1096,"2-3 years","More than 3 years")))) -> Not Due
A42: GE India Industrial Pvt Ltd - GEITC | B42: GR16 | C42: 2070201000 | D42: Trade Accounts Payable-Subledge | E42: GENPACT INDIA PRIVATE LIMITED A37168 | F42: Non-IBS | G42: Domestic | I42: Opex | J42: B2ZXKA17449 | K42: 100065083 | L42: 45971 | M42: INR | N42: 905212.8 | O42: 1 | P42: =N42*O42 -> 905212.8 | Q42: 1 | R42: =N42*Q42 -> 905212.8 | S42: =R42-P42 -> 0 | T42: Non-MSME | U42: =$U$1-AH42 -> -9 | V42: 0 | W42: 0 | X42: 0 | Y42: 0 | Z42: 0 | AA42: 0 | AB42: 0 | AC42: =R42 -> 905212.8 | AD42: 38513973 | AE42: Not Due | AF42: 88097 | AG42: 46118 | AH42: 46121 | AJ42: =M42 -> INR | AK42: 1 | AL42: =N42*AK42 -> 905212.8 | AM42: =R42-AL42 -> 0 | AN42: =AL42 -> 905212.8 | AO42: =$AO$19-AH42 -> -9 | AP42: =IF(AO42<0,"Not Due",IF(AO42<366,"Less than 1 year",IF(AO42<731,"1-2 years",IF(AO42<1096,"2-3 years","More than 3 years")))) -> Not Due
A43: GE India Industrial Pvt Ltd - GEITC | B43: GR16 | C43: 2070201000 | D43: Trade Accounts Payable-Subledge | E43: Wissen Infotech Pvt Ltd A38031 | F43: Non-IBS | G43: Domestic | I43: Opex | J43: WBD/25-26/2925 | K43: 100065403 | L43: 46035 | M43: INR | N43: 348105.6 | O43: 1 | P43: =N43*O43 -> 348105.6 | Q43: 1 | R43: =N43*Q43 -> 348105.6 | S43: =R43-P43 -> 0 | T43: Non-MSME | U43: =$U$1-AH43 -> -43 | V43: 0 | W43: 0 | X43: 0 | Y43: 0 | Z43: 0 | AA43: 0 | AB43: 0 | AC43: =R43 -> 348105.6 | AD43: 38765016 | AE43: Not Due | AF43: 88655 | AG43: 46153 | AH43: 46155 | AJ43: =M43 -> INR | AK43: 1 | AL43: =N43*AK43 -> 348105.6 | AM43: =R43-AL43 -> 0 | AN43: =AL43 -> 348105.6 | AO43: =$AO$19-AH43 -> -43 | AP43: =IF(AO43<0,"Not Due",IF(AO43<366,"Less than 1 year",IF(AO43<731,"1-2 years",IF(AO43<1096,"2-3 years","More than 3 years")))) -> Not Due
A44: GE India Industrial Pvt Ltd - GEITC | B44: GR16 | C44: 2070201000 | D44: Trade Accounts Payable-Subledge | E44: Mrk Water Supply A37976 | F44: Non-IBS | G44: Domestic | I44: Opex | J44: 354 | K44: 100070424 | L44: 46083 | M44: INR | N44: 160417.42 | O44: 1 | P44: =N44*O44 -> 160417.42 | Q44: 1 | R44: =N44*Q44 -> 160417.42 | S44: =R44-P44 -> 0 | T44: Non-MSME | U44: =$U$1-AH44 -> -16 | V44: 0 | W44: 0 | X44: 0 | Y44: 0 | Z44: 0 | AA44: 0 | AB44: 0 | AC44: =R44 -> 160417.42 | AD44: 38976216 | AE44: Not Due | AF44: 88213 | AG44: 46125 | AH44: 46128 | AJ44: =M44 -> INR | AK44: 1 | AL44: =N44*AK44 -> 160417.42 | AM44: =R44-AL44 -> 0 | AN44: =AL44 -> 160417.42 | AO44: =$AO$19-AH44 -> -16 | AP44: =IF(AO44<0,"Not Due",IF(AO44<366,"Less than 1 year",IF(AO44<731,"1-2 years",IF(AO44<1096,"2-3 years","More than 3 years")))) -> Not Due
A45: GE India Industrial Pvt Ltd - GEITC | B45: GR16 | C45: 2070201000 | D45: Trade Accounts Payable-Subledge | E45: Element14 India Private Limited A36095 | F45: Non-IBS | G45: Domestic | I45: Opex | J45: 1039609 | K45: 100069538 | L45: 46049 | M45: INR | N45: 58086.73 | O45: 1 | P45: =N45*O45 -> 58086.73 | Q45: 1 | R45: =N45*Q45 -> 58086.73 | S45: =R45-P45 -> 0 | T45: Non-MSME | U45: =$U$1-AH45 -> -57 | V45: 0 | W45: 0 | X45: 0 | Y45: 0 | Z45: 0 | AA45: 0 | AB45: 0 | AC45: =R45 -> 58086.73 | AD45: 38833116 | AE45: Not Due | AF45: 88892 | AG45: 46167 | AH45: 46169 | AJ45: =M45 -> INR | AK45: 1 | AL45: =N45*AK45 -> 58086.73 | AM45: =R45-AL45 -> 0 | AN45: =AL45 -> 58086.73 | AO45: =$AO$19-AH45 -> -57 | AP45: =IF(AO45<0,"Not Due",IF(AO45<366,"Less than 1 year",IF(AO45<731,"1-2 years",IF(AO45<1096,"2-3 years","More than 3 years")))) -> Not Due
A46: GE India Industrial Pvt Ltd - GEITC | B46: GR16 | C46: 2070201000 | D46: Trade Accounts Payable-Subledge | E46: Bengaluru Marriott Hotel Whitefield A37515 | F46: Non-IBS | G46: Domestic | I46: Opex | J46: 39854-247283 | K46: 100071208 | L46: 46093 | M46: INR | N46: 15080 | O46: 1 | P46: =N46*O46 -> 15080 | Q46: 1 | R46: =N46*Q46 -> 15080 | S46: =R46-P46 -> 0 | T46: Non-MSME | U46: =$U$1-AH46 -> -11 | V46: 0 | W46: 0 | X46: 0 | Y46: 0 | Z46: 0 | AA46: 0 | AB46: 0 | AC46: =R46 -> 15080 | AD46: 39017917 | AE46: Not Due | AF46: 88126 | AG46: 46120 | AH46: 46123 | AJ46: =M46 -> INR | AK46: 1 | AL46: =N46*AK46 -> 15080 | AM46: =R46-AL46 -> 0 | AN46: =AL46 -> 15080 | AO46: =$AO$19-AH46 -> -11 | AP46: =IF(AO46<0,"Not Due",IF(AO46<366,"Less than 1 year",IF(AO46<731,"1-2 years",IF(AO46<1096,"2-3 years","More than 3 years")))) -> Not Due
A47: GE India Industrial Pvt Ltd - GEITC | B47: GR16 | C47: 2070201000 | D47: Trade Accounts Payable-Subledge | E47: GENPACT INDIA PRIVATE LIMITED A37168 | F47: Non-IBS | G47: Domestic | I47: Opex | J47: B2ZXKA17638 | K47: 100064882 | L47: 45992 | M47: INR | N47: 538876.8 | O47: 1 | P47: =N47*O47 -> 538876.8 | Q47: 1 | R47: =N47*Q47 -> 538876.8 | S47: =R47-P47 -> 0 | T47: Non-MSME | U47: =$U$1-AH47 -> -30 | V47: 0 | W47: 0 | X47: 0 | Y47: 0 | Z47: 0 | AA47: 0 | AB47: 0 | AC47: =R47 -> 538876.8 | AD47: 38621018 | AE47: Not Due | AF47: 88426 | AG47: 46136 | AH47: 46142 | AJ47: =M47 -> INR | AK47: 1 | AL47: =N47*AK47 -> 538876.8 | AM47: =R47-AL47 -> 0 | AN47: =AL47 -> 538876.8 | AO47: =$AO$19-AH47 -> -30 | AP47: =IF(AO47<0,"Not Due",IF(AO47<366,"Less than 1 year",IF(AO47<731,"1-2 years",IF(AO47<1096,"2-3 years","More than 3 years")))) -> Not Due
A48: GE India Industrial Pvt Ltd - GEITC | B48: GR16 | C48: 2070201000 | D48: Trade Accounts Payable-Subledge | E48: CAPGEMINI TECHNOLOGY SERVICES INDIA LIMITED A16348 | F48: Non-IBS | G48: Domestic | I48: Opex | J48: 85207110164116 | K48: 100065031 | L48: 46013 | M48: INR | N48: 1134432 | O48: 1 | P48: =N48*O48 -> 1134432 | Q48: 1 | R48: =N48*Q48 -> 1134432 | S48: =R48-P48 -> 0 | T48: Non-MSME | U48: =$U$1-AH48 -> -51 | V48: 0 | W48: 0 | X48: 0 | Y48: 0 | Z48: 0 | AA48: 0 | AB48: 0 | AC48: =R48 -> 1134432 | AD48: 38702391 | AE48: Not Due | AF48: 88799 | AG48: 46160 | AH48: 46163 | AJ48: =M48 -> INR | AK48: 1 | AL48: =N48*AK48 -> 1134432 | AM48: =R48-AL48 -> 0 | AN48: =AL48 -> 1134432 | AO48: =$AO$19-AH48 -> -51 | AP48: =IF(AO48<0,"Not Due",IF(AO48<366,"Less than 1 year",IF(AO48<731,"1-2 years",IF(AO48<1096,"2-3 years","More than 3 years")))) -> Not Due
A49: GE India Industrial Pvt Ltd - GEITC | B49: GR16 | C49: 2070201000 | D49: Trade Accounts Payable-Subledge | E49: Tata Consultancy Services Limited A11987 | F49: Non-IBS | G49: Domestic | I49: Opex | J49: KADI526011750 | K49: 100067076 | L49: 46022 | M49: INR | N49: 225892.8 | O49: 1 | P49: =N49*O49 -> 225892.8 | Q49: 1 | R49: =N49*Q49 -> 225892.8 | S49: =R49-P49 -> 0 | T49: Non-MSME | U49: =$U$1-AH49 -> -60 | V49: 0 | W49: 0 | X49: 0 | Y49: 0 | Z49: 0 | AA49: 0 | AB49: 0 | AC49: =R49 -> 225892.8 | AD49: 38729864 | AE49: Not Due | AF49: 88939 | AG49: 46168 | AH49: 46172 | AJ49: =M49 -> INR | AK49: 1 | AL49: =N49*AK49 -> 225892.8 | AM49: =R49-AL49 -> 0 | AN49: =AL49 -> 225892.8 | AO49: =$AO$19-AH49 -> -60 | AP49: =IF(AO49<0,"Not Due",IF(AO49<366,"Less than 1 year",IF(AO49<731,"1-2 years",IF(AO49<1096,"2-3 years","More than 3 years")))) -> Not Due
A50: GE India Industrial Pvt Ltd - GEITC | B50: GR16 | C50: 2070201000 | D50: Trade Accounts Payable-Subledge | E50: QUEST GLOBAL ENGINEERING SERVICES PRIVATE LIMITED A36314 | F50: Non-IBS | G50: Domestic | I50: Opex | J50: 20250766473 | K50: 100070656 | L50: 46072 | M50: INR | N50: 279072 | O50: 1 | P50: =N50*O50 -> 279072 | Q50: 1 | R50: =N50*Q50 -> 279072 | S50: =R50-P50 -> 0 | T50: Non-MSME | U50: =$U$1-AH50 -> -50 | V50: 0 | W50: 0 | X50: 0 | Y50: 0 | Z50: 0 | AA50: 0 | AB50: 0 | AC50: =R50 -> 279072 | AD50: 38945379 | AE50: Not Due | AF50: 88871 | AG50: 46164 | AH50: 46162 | AJ50: =M50 -> INR | AK50: 1 | AL50: =N50*AK50 -> 279072 | AM50: =R50-AL50 -> 0 | AN50: =AL50 -> 279072 | AO50: =$AO$19-AH50 -> -50 | AP50: =IF(AO50<0,"Not Due",IF(AO50<366,"Less than 1 year",IF(AO50<731,"1-2 years",IF(AO50<1096,"2-3 years","More than 3 years")))) -> Not Due
A51: GE India Industrial Pvt Ltd - GEITC | B51: GR16 | C51: 2070201000 | D51: Trade Accounts Payable-Subledge | E51: Tuv Sud South Asia Private Limited A37599 | F51: Non-IBS | G51: Domestic | I51: Opex | J51: GG2900126483 | K51: 100069803 | L51: 46001 | M51: INR | N51: 5670 | O51: 1 | P51: =N51*O51 -> 5670 | Q51: 1 | R51: =N51*Q51 -> 5670 | S51: =R51-P51 -> 0 | T51: Non-MSME | U51: =$U$1-AH51 -> -9 | V51: 0 | W51: 0 | X51: 0 | Y51: 0 | Z51: 0 | AA51: 0 | AB51: 0 | AC51: =R51 -> 5670 | AD51: 38635065 | AE51: Not Due | AF51: 88100 | AG51: 46118 | AH51: 46121 | AJ51: =M51 -> INR | AK51: 1 | AL51: =N51*AK51 -> 5670 | AM51: =R51-AL51 -> 0 | AN51: =AL51 -> 5670 | AO51: =$AO$19-AH51 -> -9 | AP51: =IF(AO51<0,"Not Due",IF(AO51<366,"Less than 1 year",IF(AO51<731,"1-2 years",IF(AO51<1096,"2-3 years","More than 3 years")))) -> Not Due
A52: GE India Industrial Pvt Ltd - GEITC | B52: GR16 | C52: 2070201000 | D52: Trade Accounts Payable-Subledge | E52: Tata Consultancy Services Limited A11987 | F52: Non-IBS | G52: Domestic | I52: Opex | J52: KADI526010611 | K52: 100065402 | L52: 46000 | M52: INR | N52: 205286.4 | O52: 1 | P52: =N52*O52 -> 205286.4 | Q52: 1 | R52: =N52*Q52 -> 205286.4 | S52: =R52-P52 -> 0 | T52: Non-MSME | U52: =$U$1-AH52 -> -38 | V52: 0 | W52: 0 | X52: 0 | Y52: 0 | Z52: 0 | AA52: 0 | AB52: 0 | AC52: =R52 -> 205286.4 | AD52: 38646918 | AE52: Not Due | AF52: 88589 | AG52: 46147 | AH52: 46150 | AJ52: =M52 -> INR | AK52: 1 | AL52: =N52*AK52 -> 205286.4 | AM52: =R52-AL52 -> 0 | AN52: =AL52 -> 205286.4 | AO52: =$AO$19-AH52 -> -38 | AP52: =IF(AO52<0,"Not Due",IF(AO52<366,"Less than 1 year",IF(AO52<731,"1-2 years",IF(AO52<1096,"2-3 years","More than 3 years")))) -> Not Due
A53: GE India Industrial Pvt Ltd - GEITC | B53: GR16 | C53: 2070201000 | D53: Trade Accounts Payable-Subledge | E53: Updater Services Limited A38982 | F53: Non-IBS | G53: Domestic | I53: Opex | J53: 2529007942 | K53: 100070258 | L53: 46084 | M53: INR | N53: 1675265.1 | O53: 1 | P53: =N53*O53 -> 1675265.1 | Q53: 1 | R53: =N53*Q53 -> 1675265.1 | S53: =R53-P53 -> 0 | T53: Non-MSME | U53: =$U$1-AH53 -> -17 | V53: 0 | W53: 0 | X53: 0 | Y53: 0 | Z53: 0 | AA53: 0 | AB53: 0 | AC53: =R53 -> 1675265.1 | AD53: 38986501 | AE53: Not Due | AF53: 88250 | AG53: 46126 | AH53: 46129 | AJ53: =M53 -> INR | AK53: 1 | AL53: =N53*AK53 -> 1675265.1 | AM53: =R53-AL53 -> 0 | AN53: =AL53 -> 1675265.1 | AO53: =$AO$19-AH53 -> -17 | AP53: =IF(AO53<0,"Not Due",IF(AO53<366,"Less than 1 year",IF(AO53<731,"1-2 years",IF(AO53<1096,"2-3 years","More than 3 years")))) -> Not Due
A54: GE India Industrial Pvt Ltd - GEITC | B54: GR16 | C54: 2070201000 | D54: Trade Accounts Payable-Subledge | E54: Praxair India Private Limited A35841 | F54: Non-IBS | G54: Domestic | I54: Opex | J54: 5510081090 | K54: 100067112 | L54: 46085 | M54: INR | N54: 158240.37 | O54: 1 | P54: =N54*O54 -> 158240.37 | Q54: 1 | R54: =N54*Q54 -> 158240.37 | S54: =R54-P54 -> 0 | T54: Non-MSME | U54: =$U$1-AH54 -> -18 | V54: 0 | W54: 0 | X54: 0 | Y54: 0 | Z54: 0 | AA54: 0 | AB54: 0 | AC54: =R54 -> 158240.37 | AD54: 39006063 | AE54: Not Due | AF54: 88270 | AG54: 46127 | AH54: 46130 | AJ54: =M54 -> INR | AK54: 1 | AL54: =N54*AK54 -> 158240.37 | AM54: =R54-AL54 -> 0 | AN54: =AL54 -> 158240.37 | AO54: =$AO$19-AH54 -> -18 | AP54: =IF(AO54<0,"Not Due",IF(AO54<366,"Less than 1 year",IF(AO54<731,"1-2 years",IF(AO54<1096,"2-3 years","More than 3 years")))) -> Not Due
A55: GE India Industrial Pvt Ltd - GEITC | B55: GR16 | C55: 2070201000 | D55: Trade Accounts Payable-Subledge | E55: Teamlease Digital Pvt Ltd A38341 | F55: Non-IBS | G55: Domestic | I55: Opex | J55: TD29T2526-35981 | K55: 100067143 | L55: 46087 | M55: INR | N55: 83282.44 | O55: 1 | P55: =N55*O55 -> 83282.44 | Q55: 1 | R55: =N55*Q55 -> 83282.44 | S55: =R55-P55 -> 0 | T55: Non-MSME | U55: =$U$1-AH55 -> -20 | V55: 0 | W55: 0 | X55: 0 | Y55: 0 | Z55: 0 | AA55: 0 | AB55: 0 | AC55: =R55 -> 83282.44 | AD55: 39023641 | AE55: Not Due | AF55: 88313 | AG55: 46129 | AH55: 46132 | AJ55: =M55 -> INR | AK55: 1 | AL55: =N55*AK55 -> 83282.44 | AM55: =R55-AL55 -> 0 | AN55: =AL55 -> 83282.44 | AO55: =$AO$19-AH55 -> -20 | AP55: =IF(AO55<0,"Not Due",IF(AO55<366,"Less than 1 year",IF(AO55<731,"1-2 years",IF(AO55<1096,"2-3 years","More than 3 years")))) -> Not Due
A56: GE India Industrial Pvt Ltd - GEITC | B56: GR16 | C56: 2070201000 | D56: Trade Accounts Payable-Subledge | E56: LN MEP Contractors A37547 | F56: Non-IBS | G56: Domestic | I56: Opex | J56: LNM25-26-145 | K56: 100065501 | L56: 46086 | M56: INR | N56: 47196 | O56: 1 | P56: =N56*O56 -> 47196 | Q56: 1 | R56: =N56*Q56 -> 47196 | S56: =R56-P56 -> 0 | T56: Non-MSME | U56: =$U$1-AH56 -> -19 | V56: 0 | W56: 0 | X56: 0 | Y56: 0 | Z56: 0 | AA56: 0 | AB56: 0 | AC56: =R56 -> 47196 | AD56: 38992295 | AE56: Not Due | AF56: 88301 | AG56: 46128 | AH56: 46131 | AJ56: =M56 -> INR | AK56: 1 | AL56: =N56*AK56 -> 47196 | AM56: =R56-AL56 -> 0 | AN56: =AL56 -> 47196 | AO56: =$AO$19-AH56 -> -19 | AP56: =IF(AO56<0,"Not Due",IF(AO56<366,"Less than 1 year",IF(AO56<731,"1-2 years",IF(AO56<1096,"2-3 years","More than 3 years")))) -> Not Due
A57: GE India Industrial Pvt Ltd - GEITC | B57: GR16 | C57: 2070201000 | D57: Trade Accounts Payable-Subledge | E57: Infiniti Power Private Limited A37094 | F57: Non-IBS | G57: Domestic | I57: Opex | J57: 252900490 | K57: 100070560 | L57: 46086 | M57: INR | N57: 171675.36 | O57: 1 | P57: =N57*O57 -> 171675.36 | Q57: 1 | R57: =N57*Q57 -> 171675.36 | S57: =R57-P57 -> 0 | T57: Non-MSME | U57: =$U$1-AH57 -> -19 | V57: 0 | W57: 0 | X57: 0 | Y57: 0 | Z57: 0 | AA57: 0 | AB57: 0 | AC57: =R57 -> 171675.36 | AD57: 38981870 | AE57: Not Due | AF57: 88299 | AG57: 46128 | AH57: 46131 | AJ57: =M57 -> INR | AK57: 1 | AL57: =N57*AK57 -> 171675.36 | AM57: =R57-AL57 -> 0 | AN57: =AL57 -> 171675.36 | AO57: =$AO$19-AH57 -> -19 | AP57: =IF(AO57<0,"Not Due",IF(AO57<366,"Less than 1 year",IF(AO57<731,"1-2 years",IF(AO57<1096,"2-3 years","More than 3 years")))) -> Not Due
A58: GE India Industrial Pvt Ltd - GEITC | B58: GR16 | C58: 2070201000 | D58: Trade Accounts Payable-Subledge | E58: MOUSER ELECTRONICS INC. A02649 | F58: Non-IBS | G58: Foreign | I58: Opex | J58: 80091629 | K58: 100062005 | L58: 45490 | M58: USD | N58: 0.47 | O58: 83.473525 | P58: =N58*O58 -> 39.232557 | Q58: 94.6543 | R58: =N58*Q58 -> 44.487521 | S58: =R58-P58 -> 5.2549643 | T58: Non-MSME | U58: =$U$1-AH58 -> 592 | V58: 0 | W58: 0 | X58: 0 | Y58: 0 | Z58: 0 | AA58: =R58 -> 44.487521 | AB58: 0 | AC58: 0 | AD58: 36476014 | AE58: Payment on Hold as BOE not reflecting on IDPMS | AH58: 45520 | AJ58: =M58 -> USD | AK58: 94.6543 | AL58: =N58*AK58 -> 44.487521 | AM58: =R58-AL58 -> 0 | AO58: =$AO$19-AH58 -> 592 | AP58: =IF(AO58<0,"Not Due",IF(AO58<366,"Less than 1 year",IF(AO58<731,"1-2 years",IF(AO58<1096,"2-3 years","More than 3 years")))) -> 1-2 years
A59: GE India Industrial Pvt Ltd - GEITC | B59: GR16 | C59: 2070201000 | D59: Trade Accounts Payable-Subledge | E59: Bharti Airtel Limited A38979 | F59: Non-IBS | G59: Domestic | I59: Opex | J59: BBL292601B070244 | K59: 100065010 | L59: 46027 | M59: INR | N59: 242471.66 | O59: 1 | P59: =N59*O59 -> 242471.66 | Q59: 1 | R59: =N59*Q59 -> 242471.66 | S59: =R59-P59 -> 0 | T59: Non-MSME | U59: =$U$1-AH59 -> -5 | V59: 0 | W59: 0 | X59: 0 | Y59: 0 | Z59: 0 | AA59: 0 | AB59: 0 | AC59: =R59 -> 242471.66 | AD59: 38752625 | AE59: Not Due | AF59: 88051 | AG59: 46114 | AH59: 46117 | AJ59: =M59 -> INR | AK59: 1 | AL59: =N59*AK59 -> 242471.66 | AM59: =R59-AL59 -> 0 | AN59: =AL59 -> 242471.66 | AO59: =$AO$19-AH59 -> -5 | AP59: =IF(AO59<0,"Not Due",IF(AO59<366,"Less than 1 year",IF(AO59<731,"1-2 years",IF(AO59<1096,"2-3 years","More than 3 years")))) -> Not Due
A60: GE India Industrial Pvt Ltd - GEITC | B60: GR16 | C60: 2070201000 | D60: Trade Accounts Payable-Subledge | E60: Tata Consultancy Services Limited A11987 | F60: Non-IBS | G60: Domestic | I60: Opex | J60: KADI526011878 | K60: 100065402 | L60: 46034 | M60: INR | N60: 205286.4 | O60: 1 | P60: =N60*O60 -> 205286.4 | Q60: 1 | R60: =N60*Q60 -> 205286.4 | S60: =R60-P60 -> 0 | T60: Non-MSME | U60: =$U$1-AH60 -> -72 | V60: 0 | W60: 0 | X60: 0 | Y60: 0 | Z60: 0 | AA60: 0 | AB60: 0 | AC60: =R60 -> 205286.4 | AD60: 38770209 | AE60: Not Due | AF60: 89099 | AG60: 46181 | AH60: 46184 | AJ60: =M60 -> INR | AK60: 1 | AL60: =N60*AK60 -> 205286.4 | AM60: =R60-AL60 -> 0 | AN60: =AL60 -> 205286.4 | AO60: =$AO$19-AH60 -> -72 | AP60: =IF(AO60<0,"Not Due",IF(AO60<366,"Less than 1 year",IF(AO60<731,"1-2 years",IF(AO60<1096,"2-3 years","More than 3 years")))) -> Not Due
A61: GE India Industrial Pvt Ltd - GEITC | B61: GR16 | C61: 2070201000 | D61: Trade Accounts Payable-Subledge | E61: Superseva Global Services Private Limited A38849 | F61: Non-IBS | G61: Domestic | I61: Opex | J61: NOV/25-26/3995 | K61: 100066105 | L61: 45990 | M61: INR | N61: 2018.4 | O61: 1 | P61: =N61*O61 -> 2018.4 | Q61: 1 | R61: =N61*Q61 -> 2018.4 | S61: =R61-P61 -> 0 | T61: Non-MSME | U61: =$U$1-AH61 -> 77 | V61: 0 | W61: 0 | X61: =R61 -> 2018.4 | Y61: 0 | Z61: 0 | AA61: 0 | AB61: 0 | AC61: 0 | AD61: 38581829 | AE61: Payment hold as per Notice from GST Dept | AH61: 46035 | AJ61: =M61 -> INR | AK61: 1 | AL61: =N61*AK61 -> 2018.4 | AM61: =R61-AL61 -> 0 | AO61: =$AO$19-AH61 -> 77 | AP61: =IF(AO61<0,"Not Due",IF(AO61<366,"Less than 1 year",IF(AO61<731,"1-2 years",IF(AO61<1096,"2-3 years","More than 3 years")))) -> Less than 1 year
A62: GE India Industrial Pvt Ltd - GEITC | B62: GR16 | C62: 2070201000 | D62: Trade Accounts Payable-Subledge | E62: QUEST GLOBAL ENGINEERING SERVICES PRIVATE LIMITED A36314 | F62: Non-IBS | G62: Domestic | I62: Opex | J62: 20250765588 | K62: 100066777 | L62: 46031 | M62: INR | N62: 4191618.8 | O62: 1 | P62: =N62*O62 -> 4191618.8 | Q62: 1 | R62: =N62*Q62 -> 4191618.8 | S62: =R62-P62 -> 0 | T62: Non-MSME | U62: =$U$1-AH62 -> -9 | V62: 0 | W62: 0 | X62: 0 | Y62: 0 | Z62: 0 | AA62: 0 | AB62: 0 | AC62: =R62 -> 4191618.8 | AD62: 38765050 | AE62: Not Due | AF62: 88088 | AG62: 46118 | AH62: 46121 | AJ62: =M62 -> INR | AK62: 1 | AL62: =N62*AK62 -> 4191618.8 | AM62: =R62-AL62 -> 0 | AN62: =AL62 -> 4191618.8 | AO62: =$AO$19-AH62 -> -9 | AP62: =IF(AO62<0,"Not Due",IF(AO62<366,"Less than 1 year",IF(AO62<731,"1-2 years",IF(AO62<1096,"2-3 years","More than 3 years")))) -> Not Due
A63: GE India Industrial Pvt Ltd - GEITC | B63: GR16 | C63: 2070201000 | D63: Trade Accounts Payable-Subledge | E63: MOUSER ELECTRONICS INC. A02649 | F63: Non-IBS | G63: Foreign | I63: Opex | J63: 88691114 | K63: 100069788 | L63: 46061 | M63: USD | N63: 14.3 | O63: 91.82425 | P63: =N63*O63 -> 1313.0868 | Q63: 94.6543 | R63: =N63*Q63 -> 1353.5565 | S63: =R63-P63 -> 40.469715 | T63: Non-MSME | U63: =$U$1-AH63 -> -39 | V63: 0 | W63: 0 | X63: 0 | Y63: 0 | Z63: 0 | AA63: 0 | AB63: 0 | AC63: =R63 -> 1353.5565 | AD63: 38887937 | AE63: Not Due | AF63: 90008280 | AG63: 46148 | AH63: 46151 | AJ63: =M63 -> USD | AK63: 94.6543 | AL63: =N63*AK63 -> 1353.5565 | AM63: =R63-AL63 -> 0 | AN63: =AL63 -> 1353.5565 | AO63: =$AO$19-AH63 -> -39 | AP63: =IF(AO63<0,"Not Due",IF(AO63<366,"Less than 1 year",IF(AO63<731,"1-2 years",IF(AO63<1096,"2-3 years","More than 3 years")))) -> Not Due
A64: GE India Industrial Pvt Ltd - GEITC | B64: GR16 | C64: 2070201000 | D64: Trade Accounts Payable-Subledge | E64: Element14 India Private Limited A36095 | F64: Non-IBS | G64: Domestic | I64: Opex | J64: 1035656 | K64: 100070290 | L64: 46034 | M64: INR | N64: 17615.92 | O64: 1 | P64: =N64*O64 -> 17615.92 | Q64: 1 | R64: =N64*Q64 -> 17615.92 | S64: =R64-P64 -> 0 | T64: Non-MSME | U64: =$U$1-AH64 -> -42 | V64: 0 | W64: 0 | X64: 0 | Y64: 0 | Z64: 0 | AA64: 0 | AB64: 0 | AC64: =R64 -> 17615.92 | AD64: 38770231 | AE64: Not Due | AF64: 88677 | AG64: 46153 | AH64: 46154 | AJ64: =M64 -> INR | AK64: 1 | AL64: =N64*AK64 -> 17615.92 | AM64: =R64-AL64 -> 0 | AN64: =AL64 -> 17615.92 | AO64: =$AO$19-AH64 -> -42 | AP64: =IF(AO64<0,"Not Due",IF(AO64<366,"Less than 1 year",IF(AO64<731,"1-2 years",IF(AO64<1096,"2-3 years","More than 3 years")))) -> Not Due
A65: GE India Industrial Pvt Ltd - GEITC | B65: GR16 | C65: 2070201000 | D65: Trade Accounts Payable-Subledge | E65: PUNJAB OXYGEN PRIVATE LIMITED A38329 | F65: Non-IBS | G65: Domestic | I65: Opex | J65: BLR4363001664525 | K65: 100070237 | L65: 46086 | M65: INR | N65: 60519.92 | O65: 1 | P65: =N65*O65 -> 60519.92 | Q65: 1 | R65: =N65*Q65 -> 60519.92 | S65: =R65-P65 -> 0 | T65: Non-MSME | U65: =$U$1-AH65 -> -4 | V65: 0 | W65: 0 | X65: 0 | Y65: 0 | Z65: 0 | AA65: 0 | AB65: 0 | AC65: =R65 -> 60519.92 | AD65: 39018015 | AE65: Not Due | AF65: 88030 | AG65: 46113 | AH65: 46116 | AJ65: =M65 -> INR | AK65: 1 | AL65: =N65*AK65 -> 60519.92 | AM65: =R65-AL65 -> 0 | AN65: =AL65 -> 60519.92 | AO65: =$AO$19-AH65 -> -4 | AP65: =IF(AO65<0,"Not Due",IF(AO65<366,"Less than 1 year",IF(AO65<731,"1-2 years",IF(AO65<1096,"2-3 years","More than 3 years")))) -> Not Due
A66: GE India Industrial Pvt Ltd - GEITC | B66: GR16 | C66: 2070201000 | D66: Trade Accounts Payable-Subledge | E66: PERSOL INDIA PRIVATE LIMITED | F66: Non-IBS | G66: Domestic | I66: Opex | J66: KAT2526EH00157 | K66: 100066193 | L66: 46080 | M66: INR | N66: 148456.27 | O66: 1 | P66: =N66*O66 -> 148456.27 | Q66: 1 | R66: =N66*Q66 -> 148456.27 | S66: =R66-P66 -> 0 | T66: Non-MSME | U66: =$U$1-AH66 -> -28 | V66: 0 | W66: 0 | X66: 0 | Y66: 0 | Z66: 0 | AA66: 0 | AB66: 0 | AC66: =R66 -> 148456.27 | AD66: 38994065 | AE66: Not Due | AF66: 88417 | AG66: 46136 | AH66: 46140 | AJ66: =M66 -> INR | AK66: 1 | AL66: =N66*AK66 -> 148456.27 | AM66: =R66-AL66 -> 0 | AN66: =AL66 -> 148456.27 | AO66: =$AO$19-AH66 -> -28 | AP66: =IF(AO66<0,"Not Due",IF(AO66<366,"Less than 1 year",IF(AO66<731,"1-2 years",IF(AO66<1096,"2-3 years","More than 3 years")))) -> Not Due
A67: GE India Industrial Pvt Ltd - GEITC | B67: GR16 | C67: 2070201000 | D67: Trade Accounts Payable-Subledge | E67: TATA TECHNOLOGIES LIMITED A38494 | F67: Non-IBS | G67: Domestic | I67: Opex | J67: KA0000006503 | K67: 100070814 | L67: 46081 | M67: INR | N67: 1267552.8 | O67: 1 | P67: =N67*O67 -> 1267552.8 | Q67: 1 | R67: =N67*Q67 -> 1267552.8 | S67: =R67-P67 -> 0 | T67: Non-MSME | U67: =$U$1-AH67 -> -89 | V67: 0 | W67: 0 | X67: 0 | Y67: 0 | Z67: 0 | AA67: 0 | AB67: 0 | AC67: =R67 -> 1267552.8 | AD67: 38976222 | AE67: Not Due | AH67: 46201 | AJ67: =M67 -> INR | AK67: 1 | AL67: =N67*AK67 -> 1267552.8 | AM67: =R67-AL67 -> 0 | AO67: =$AO$19-AH67 -> -89 | AP67: =IF(AO67<0,"Not Due",IF(AO67<366,"Less than 1 year",IF(AO67<731,"1-2 years",IF(AO67<1096,"2-3 years","More than 3 years")))) -> Not Due
A68: GE India Industrial Pvt Ltd - GEITC | B68: GR16 | C68: 2070201000 | D68: Trade Accounts Payable-Subledge | E68: Teamlease Digital Pvt Ltd A38341 | F68: Non-IBS | G68: Domestic | I68: Opex | J68: TD29T2526-35982 | K68: 100067420 | L68: 46087 | M68: INR | N68: 41641.22 | O68: 1 | P68: =N68*O68 -> 41641.22 | Q68: 1 | R68: =N68*Q68 -> 41641.22 | S68: =R68-P68 -> 0 | T68: Non-MSME | U68: =$U$1-AH68 -> -20 | V68: 0 | W68: 0 | X68: 0 | Y68: 0 | Z68: 0 | AA68: 0 | AB68: 0 | AC68: =R68 -> 41641.22 | AD68: 39017985 | AE68: Not Due | AF68: 88313 | AG68: 46129 | AH68: 46132 | AJ68: =M68 -> INR | AK68: 1 | AL68: =N68*AK68 -> 41641.22 | AM68: =R68-AL68 -> 0 | AN68: =AL68 -> 41641.22 | AO68: =$AO$19-AH68 -> -20 | AP68: =IF(AO68<0,"Not Due",IF(AO68<366,"Less than 1 year",IF(AO68<731,"1-2 years",IF(AO68<1096,"2-3 years","More than 3 years")))) -> Not Due
A69: GE India Industrial Pvt Ltd - GEITC | B69: GR16 | C69: 2070201000 | D69: Trade Accounts Payable-Subledge | E69: Superseva Global Services Private Limited A38849 | F69: Non-IBS | G69: Domestic | I69: Opex | J69: DEC/25-26/4514 | K69: 100064599 | L69: 46024 | M69: INR | N69: 138325.36 | O69: 1 | P69: =N69*O69 -> 138325.36 | Q69: 1 | R69: =N69*Q69 -> 138325.36 | S69: =R69-P69 -> 0 | T69: Non-MSME | U69: =$U$1-AH69 -> 43 | V69: 0 | W69: =R69 -> 138325.36 | X69: 0 | Y69: 0 | Z69: 0 | AA69: 0 | AB69: 0 | AC69: 0 | AD69: 38723012 | AE69: Payment on hold as per Notice received from GST department | AH69: 46069 | AJ69: =M69 -> INR | AK69: 1 | AL69: =N69*AK69 -> 138325.36 | AM69: =R69-AL69 -> 0 | AO69: =$AO$19-AH69 -> 43 | AP69: =IF(AO69<0,"Not Due",IF(AO69<366,"Less than 1 year",IF(AO69<731,"1-2 years",IF(AO69<1096,"2-3 years","More than 3 years")))) -> Less than 1 year
A70: GE India Industrial Pvt Ltd - GEITC | B70: GR16 | C70: 2070201000 | D70: Trade Accounts Payable-Subledge | E70: Innmar Tourism and Hotels Private Limited A37416 | F70: Non-IBS | G70: Domestic | I70: Opex | J70: BLRWB-6310 | K70: 100070978 | L70: 46075 | M70: INR | N70: 10440 | O70: 1 | P70: =N70*O70 -> 10440 | Q70: 1 | R70: =N70*Q70 -> 10440 | S70: =R70-P70 -> 0 | T70: Non-MSME | U70: =$U$1-AH70 -> -38 | V70: 0 | W70: 0 | X70: 0 | Y70: 0 | Z70: 0 | AA70: 0 | AB70: 0 | AC70: =R70 -> 10440 | AD70: 38945449 | AE70: Not Due | AF70: 88572 | AG70: 46147 | AH70: 46150 | AJ70: =M70 -> INR | AK70: 1 | AL70: =N70*AK70 -> 10440 | AM70: =R70-AL70 -> 0 | AN70: =AL70 -> 10440 | AO70: =$AO$19-AH70 -> -38 | AP70: =IF(AO70<0,"Not Due",IF(AO70<366,"Less than 1 year",IF(AO70<731,"1-2 years",IF(AO70<1096,"2-3 years","More than 3 years")))) -> Not Due
A71: GE India Industrial Pvt Ltd - GEITC | B71: GR16 | C71: 2070201000 | D71: Trade Accounts Payable-Subledge | E71: Element14 India Private Limited A36095 | F71: Non-IBS | G71: Domestic | I71: Opex | J71: 1049140 | K71: 100070834 | L71: 46078 | M71: INR | N71: 18058.86 | O71: 1 | P71: =N71*O71 -> 18058.86 | Q71: 1 | R71: =N71*Q71 -> 18058.86 | S71: =R71-P71 -> 0 | T71: Non-MSME | U71: =$U$1-AH71 -> -86 | V71: 0 | W71: 0 | X71: 0 | Y71: 0 | Z71: 0 | AA71: 0 | AB71: 0 | AC71: =R71 -> 18058.86 | AD71: 38960183 | AE71: Not Due | AH71: 46198 | AJ71: =M71 -> INR | AK71: 1 | AL71: =N71*AK71 -> 18058.86 | AM71: =R71-AL71 -> 0 | AO71: =$AO$19-AH71 -> -86 | AP71: =IF(AO71<0,"Not Due",IF(AO71<366,"Less than 1 year",IF(AO71<731,"1-2 years",IF(AO71<1096,"2-3 years","More than 3 years")))) -> Not Due
A72: GE India Industrial Pvt Ltd - GEITC | B72: GR16 | C72: 2070201000 | D72: Trade Accounts Payable-Subledge | E72: Superseva Global Services Private Limited A38849 | F72: Non-IBS | G72: Domestic | I72: Opex | J72: JAN/25-26/4992 | K72: 100071125 | L72: 46056 | M72: INR | N72: 4410 | O72: 1 | P72: =N72*O72 -> 4410 | Q72: 1 | R72: =N72*Q72 -> 4410 | S72: =R72-P72 -> 0 | T72: Non-MSME | U72: =$U$1-AH72 -> 11 | V72: =R72 -> 4410 | W72: 0 | X72: 0 | Y72: 0 | Z72: 0 | AA72: 0 | AB72: 0 | AC72: 0 | AD72: 38976172 | AE72: Payment on hold as per Notice received from GST department | AH72: 46101 | AJ72: =M72 -> INR | AK72: 1 | AL72: =N72*AK72 -> 4410 | AM72: =R72-AL72 -> 0 | AO72: =$AO$19-AH72 -> 11 | AP72: =IF(AO72<0,"Not Due",IF(AO72<366,"Less than 1 year",IF(AO72<731,"1-2 years",IF(AO72<1096,"2-3 years","More than 3 years")))) -> Less than 1 year
A73: GE India Industrial Pvt Ltd - GEITC | B73: GR16 | C73: 2070201000 | D73: Trade Accounts Payable-Subledge | E73: Gartner India Research and Advisory Services Pvt. Ltd. A37407 | F73: Non-IBS | G73: Domestic | I73: Opex | J73: IN5020808 | K73: 100069560 | L73: 45959 | M73: INR | N73: 107136 | O73: 1 | P73: =N73*O73 -> 107136 | Q73: 1 | R73: =N73*Q73 -> 107136 | S73: =R73-P73 -> 0 | T73: Non-MSME | U73: =$U$1-AH73 -> 33 | V73: 0 | W73: =R73 -> 107136 | X73: 0 | Y73: 0 | Z73: 0 | AA73: 0 | AB73: 0 | AC73: 0 | AD73: 38550220 | AE73: As per User confirmation Invoice cancelled in Apr26 | AH73: 46079 | AJ73: =M73 -> INR | AK73: 1 | AL73: =N73*AK73 -> 107136 | AM73: =R73-AL73 -> 0 | AO73: =$AO$19-AH73 -> 33 | AP73: =IF(AO73<0,"Not Due",IF(AO73<366,"Less than 1 year",IF(AO73<731,"1-2 years",IF(AO73<1096,"2-3 years","More than 3 years")))) -> Less than 1 year
A74: GE India Industrial Pvt Ltd - GEITC | B74: GR16 | C74: 2070201000 | D74: Trade Accounts Payable-Subledge | E74: QUEST GLOBAL ENGINEERING SERVICES PRIVATE LIMITED A36314 | F74: Non-IBS | G74: Domestic | I74: Opex | J74: 20250765615 | K74: 100065786 | L74: 46034 | M74: INR | N74: 284549.76 | O74: 1 | P74: =N74*O74 -> 284549.76 | Q74: 1 | R74: =N74*Q74 -> 284549.76 | S74: =R74-P74 -> 0 | T74: Non-MSME | U74: =$U$1-AH74 -> -12 | V74: 0 | W74: 0 | X74: 0 | Y74: 0 | Z74: 0 | AA74: 0 | AB74: 0 | AC74: =R74 -> 284549.76 | AD74: 38765179 | AE74: Not Due | AF74: 88152 | AG74: 46121 | AH74: 46124 | AJ74: =M74 -> INR | AK74: 1 | AL74: =N74*AK74 -> 284549.76 | AM74: =R74-AL74 -> 0 | AN74: =AL74 -> 284549.76 | AO74: =$AO$19-AH74 -> -12 | AP74: =IF(AO74<0,"Not Due",IF(AO74<366,"Less than 1 year",IF(AO74<731,"1-2 years",IF(AO74<1096,"2-3 years","More than 3 years")))) -> Not Due
A75: GE India Industrial Pvt Ltd - GEITC | B75: GR16 | C75: 2070201000 | D75: Trade Accounts Payable-Subledge | E75: Desai Brothers Ltd A37483 | F75: Non-IBS | G75: Domestic | I75: Opex | J75: 4037-63305 | K75: 100070977 | L75: 46071 | M75: INR | N75: 12180 | O75: 1 | P75: =N75*O75 -> 12180 | Q75: 1 | R75: =N75*Q75 -> 12180 | S75: =R75-P75 -> 0 | T75: Non-MSME | U75: =$U$1-AH75 -> -4 | V75: 0 | W75: 0 | X75: 0 | Y75: 0 | Z75: 0 | AA75: 0 | AB75: 0 | AC75: =R75 -> 12180 | AD75: 38999197 | AE75: Not Due | AF75: 88007 | AG75: 46113 | AH75: 46116 | AJ75: =M75 -> INR | AK75: 1 | AL75: =N75*AK75 -> 12180 | AM75: =R75-AL75 -> 0 | AN75: =AL75 -> 12180 | AO75: =$AO$19-AH75 -> -4 | AP75: =IF(AO75<0,"Not Due",IF(AO75<366,"Less than 1 year",IF(AO75<731,"1-2 years",IF(AO75<1096,"2-3 years","More than 3 years")))) -> Not Due
A76: GE India Industrial Pvt Ltd - GEITC | B76: GR16 | C76: 2070201000 | D76: Trade Accounts Payable-Subledge | E76: GENPACT INDIA PRIVATE LIMITED A37168 | F76: Non-IBS | G76: Domestic | I76: Opex | J76: B1Z3TS16628 | K76: 100069549 | L76: 45995 | M76: INR | N76: 75600 | O76: 1 | P76: =N76*O76 -> 75600 | Q76: 1 | R76: =N76*Q76 -> 75600 | S76: =R76-P76 -> 0 | T76: Non-MSME | U76: =$U$1-AH76 -> -33 | V76: 0 | W76: 0 | X76: 0 | Y76: 0 | Z76: 0 | AA76: 0 | AB76: 0 | AC76: =R76 -> 75600 | AD76: 38697156 | AE76: Not Due | AF76: 88494 | AG76: 46143 | AH76: 46145 | AJ76: =M76 -> INR | AK76: 1 | AL76: =N76*AK76 -> 75600 | AM76: =R76-AL76 -> 0 | AN76: =AL76 -> 75600 | AO76: =$AO$19-AH76 -> -33 | AP76: =IF(AO76<0,"Not Due",IF(AO76<366,"Less than 1 year",IF(AO76<731,"1-2 years",IF(AO76<1096,"2-3 years","More than 3 years")))) -> Not Due
A77: GE India Industrial Pvt Ltd - GEITC | B77: GR16 | C77: 2070201000 | D77: Trade Accounts Payable-Subledge | E77: GENPACT INDIA PRIVATE LIMITED A37168 | F77: Non-IBS | G77: Domestic | I77: Opex | J77: B2ZXKA17979 | K77: 100067158 | L77: 46030 | M77: INR | N77: 217963.99 | O77: 1 | P77: =N77*O77 -> 217963.99 | Q77: 1 | R77: =N77*Q77 -> 217963.99 | S77: =R77-P77 -> 0 | T77: Non-MSME | U77: =$U$1-AH77 -> -68 | V77: 0 | W77: 0 | X77: 0 | Y77: 0 | Z77: 0 | AA77: 0 | AB77: 0 | AC77: =R77 -> 217963.99 | AD77: 38747222 | AE77: Not Due | AF77: 89064 | AG77: 46177 | AH77: 46180 | AJ77: =M77 -> INR | AK77: 1 | AL77: =N77*AK77 -> 217963.99 | AM77: =R77-AL77 -> 0 | AN77: =AL77 -> 217963.99 | AO77: =$AO$19-AH77 -> -68 | AP77: =IF(AO77<0,"Not Due",IF(AO77<366,"Less than 1 year",IF(AO77<731,"1-2 years",IF(AO77<1096,"2-3 years","More than 3 years")))) -> Not Due
A78: GE India Industrial Pvt Ltd - GEITC | B78: GR16 | C78: 2070201000 | D78: Trade Accounts Payable-Subledge | E78: Infiniti Power Private Limited A37094 | F78: Non-IBS | G78: Domestic | I78: Capex | J78: 252900474 | K78: 100070825 | L78: 46070 | M78: INR | N78: 106218.55 | O78: 1 | P78: =N78*O78 -> 106218.55 | Q78: 1 | R78: =N78*Q78 -> 106218.55 | S78: =R78-P78 -> 0 | T78: Non-MSME | U78: =$U$1-AH78 -> -3 | V78: 0 | W78: 0 | X78: 0 | Y78: 0 | Z78: 0 | AA78: 0 | AB78: 0 | AC78: =R78 -> 106218.55 | AD78: 38915702 | AE78: Not Due | AF78: 87997 | AG78: 46113 | AH78: 46115 | AJ78: =M78 -> INR | AK78: 1 | AL78: =N78*AK78 -> 106218.55 | AM78: =R78-AL78 -> 0 | AN78: =AL78 -> 106218.55 | AO78: =$AO$19-AH78 -> -3 | AP78: =IF(AO78<0,"Not Due",IF(AO78<366,"Less than 1 year",IF(AO78<731,"1-2 years",IF(AO78<1096,"2-3 years","More than 3 years")))) -> Not Due
A79: GE India Industrial Pvt Ltd - GEITC | B79: GR16 | C79: 2070201000 | D79: Trade Accounts Payable-Subledge | E79: Tata Consultancy Services Limited A11987 | F79: Non-IBS | G79: Domestic | I79: Opex | J79: KADI526010383 | K79: 100068570 | L79: 45989 | M79: INR | N79: 304992 | O79: 1 | P79: =N79*O79 -> 304992 | Q79: 1 | R79: =N79*Q79 -> 304992 | S79: =R79-P79 -> 0 | T79: Non-MSME | U79: =$U$1-AH79 -> -27 | V79: 0 | W79: 0 | X79: 0 | Y79: 0 | Z79: 0 | AA79: 0 | AB79: 0 | AC79: =R79 -> 304992 | AD79: 38618417 | AE79: Not Due | AF79: 88457 | AG79: 46136 | AH79: 46139 | AJ79: =M79 -> INR | AK79: 1 | AL79: =N79*AK79 -> 304992 | AM79: =R79-AL79 -> 0 | AN79: =AL79 -> 304992 | AO79: =$AO$19-AH79 -> -27 | AP79: =IF(AO79<0,"Not Due",IF(AO79<366,"Less than 1 year",IF(AO79<731,"1-2 years",IF(AO79<1096,"2-3 years","More than 3 years")))) -> Not Due
A80: GE India Industrial Pvt Ltd - GEITC | B80: GR16 | C80: 2070201000 | D80: Trade Accounts Payable-Subledge | E80: Nippon Express (India) Private Limited A37078 | F80: Non-IBS | G80: Domestic | I80: Opex | J80: 10A-23997/2026 | K80: 100066090 | L80: 46064 | M80: INR | N80: 8259.3 | O80: 1 | P80: =N80*O80 -> 8259.3 | Q80: 1 | R80: =N80*Q80 -> 8259.3 | S80: =R80-P80 -> 0 | T80: Non-MSME | U80: =$U$1-AH80 -> -12 | V80: 0 | W80: 0 | X80: 0 | Y80: 0 | Z80: 0 | AA80: 0 | AB80: 0 | AC80: =R80 -> 8259.3 | AD80: 38921348 | AE80: Not Due | AF80: 88150 | AG80: 46121 | AH80: 46124 | AJ80: =M80 -> INR | AK80: 1 | AL80: =N80*AK80 -> 8259.3 | AM80: =R80-AL80 -> 0 | AN80: =AL80 -> 8259.3 | AO80: =$AO$19-AH80 -> -12 | AP80: =IF(AO80<0,"Not Due",IF(AO80<366,"Less than 1 year",IF(AO80<731,"1-2 years",IF(AO80<1096,"2-3 years","More than 3 years")))) -> Not Due
A81: GE India Industrial Pvt Ltd - GEITC | B81: GR16 | C81: 2070201000 | D81: Trade Accounts Payable-Subledge | E81: Wissen Infotech Pvt Ltd A38031 | F81: Non-IBS | G81: Domestic | I81: Opex | J81: WBD/25-26/2795 | K81: 100065991 | L81: 46009 | M81: INR | N81: 380160 | O81: 1 | P81: =N81*O81 -> 380160 | Q81: 1 | R81: =N81*Q81 -> 380160 | S81: =R81-P81 -> 0 | T81: Non-MSME | U81: =$U$1-AH81 -> -17 | V81: 0 | W81: 0 | X81: 0 | Y81: 0 | Z81: 0 | AA81: 0 | AB81: 0 | AC81: =R81 -> 380160 | AD81: 38668928 | AE81: Not Due | AF81: 88256 | AG81: 46126 | AH81: 46129 | AJ81: =M81 -> INR | AK81: 1 | AL81: =N81*AK81 -> 380160 | AM81: =R81-AL81 -> 0 | AN81: =AL81 -> 380160 | AO81: =$AO$19-AH81 -> -17 | AP81: =IF(AO81<0,"Not Due",IF(AO81<366,"Less than 1 year",IF(AO81<731,"1-2 years",IF(AO81<1096,"2-3 years","More than 3 years")))) -> Not Due
A82: GE India Industrial Pvt Ltd - GEITC | B82: GR16 | C82: 2070201000 | D82: Trade Accounts Payable-Subledge | E82: Tata Consultancy Services Limited A11987 | F82: Non-IBS | G82: Domestic | I82: Opex | J82: KADI526012610 | K82: 100067695 | L82: 46052 | M82: INR | N82: 216000 | O82: 1 | P82: =N82*O82 -> 216000 | Q82: 1 | R82: =N82*Q82 -> 216000 | S82: =R82-P82 -> 0 | T82: Non-MSME | U82: =$U$1-AH82 -> -90 | V82: 0 | W82: 0 | X82: 0 | Y82: 0 | Z82: 0 | AA82: 0 | AB82: 0 | AC82: =R82 -> 216000 | AD82: 38862750 | AE82: Not Due | AH82: 46202 | AJ82: =M82 -> INR | AK82: 1 | AL82: =N82*AK82 -> 216000 | AM82: =R82-AL82 -> 0 | AO82: =$AO$19-AH82 -> -90 | AP82: =IF(AO82<0,"Not Due",IF(AO82<366,"Less than 1 year",IF(AO82<731,"1-2 years",IF(AO82<1096,"2-3 years","More than 3 years")))) -> Not Due
A83: GE India Industrial Pvt Ltd - GEITC | B83: GR16 | C83: 2070201000 | D83: Trade Accounts Payable-Subledge | E83: Element14 India Private Limited A36095 | F83: Non-IBS | G83: Domestic | I83: Opex | J83: 1026413 | K83: 100068721 | L83: 46002 | M83: INR | N83: 33272.91 | O83: 1 | P83: =N83*O83 -> 33272.91 | Q83: 1 | R83: =N83*Q83 -> 33272.91 | S83: =R83-P83 -> 0 | T83: Non-MSME | U83: =$U$1-AH83 -> -10 | V83: 0 | W83: 0 | X83: 0 | Y83: 0 | Z83: 0 | AA83: 0 | AB83: 0 | AC83: =R83 -> 33272.91 | AD83: 38641977 | AE83: Not Due | AF83: 88107 | AG83: 46119 | AH83: 46122 | AJ83: =M83 -> INR | AK83: 1 | AL83: =N83*AK83 -> 33272.91 | AM83: =R83-AL83 -> 0 | AN83: =AL83 -> 33272.91 | AO83: =$AO$19-AH83 -> -10 | AP83: =IF(AO83<0,"Not Due",IF(AO83<366,"Less than 1 year",IF(AO83<731,"1-2 years",IF(AO83<1096,"2-3 years","More than 3 years")))) -> Not Due
A84: GE India Industrial Pvt Ltd - GEITC | B84: GR16 | C84: 2070201000 | D84: Trade Accounts Payable-Subledge | E84: Hewlett Packard Enterprise India Private Limited A38981 | F84: Non-IBS | G84: Domestic | I84: Opex | J84: 25I1KA1L1805606 | K84: 100070190 | L84: 46025 | M84: INR | N84: 3823785.4 | O84: 1 | P84: =N84*O84 -> 3823785.4 | Q84: 1 | R84: =N84*Q84 -> 3823785.4 | S84: =R84-P84 -> 0 | T84: Non-MSME | U84: =$U$1-AH84 -> -3 | V84: 0 | W84: 0 | X84: 0 | Y84: 0 | Z84: 0 | AA84: 0 | AB84: 0 | AC84: =R84 -> 3823785.4 | AD84: 38746986 | AE84: Not Due | AF84: 87972 | AG84: 46113 | AH84: 46115 | AJ84: =M84 -> INR | AK84: 1 | AL84: =N84*AK84 -> 3823785.4 | AM84: =R84-AL84 -> 0 | AN84: =AL84 -> 3823785.4 | AO84: =$AO$19-AH84 -> -3 | AP84: =IF(AO84<0,"Not Due",IF(AO84<366,"Less than 1 year",IF(AO84<731,"1-2 years",IF(AO84<1096,"2-3 years","More than 3 years")))) -> Not Due
A85: GE India Industrial Pvt Ltd - GEITC | B85: GR16 | C85: 2070201000 | D85: Trade Accounts Payable-Subledge | E85: VELOCIS SYSTEMS PVT. LTD A36061 | F85: Non-IBS | G85: Domestic | I85: Opex | J85: KA/2026/S-001241 | K85: 100070573 | L85: 46062 | M85: INR | N85: 11765465 | O85: 1 | P85: =N85*O85 -> 11765465 | Q85: 1 | R85: =N85*Q85 -> 11765465 | S85: =R85-P85 -> 0 | T85: Non-MSME | U85: =$U$1-AH85 -> -40 | V85: 0 | W85: 0 | X85: 0 | Y85: 0 | Z85: 0 | AA85: 0 | AB85: 0 | AC85: =R85 -> 11765465 | AD85: 38895278 | AE85: Not Due | AF85: 88615 | AG85: 46149 | AH85: 46152 | AJ85: =M85 -> INR | AK85: 1 | AL85: =N85*AK85 -> 11765465 | AM85: =R85-AL85 -> 0 | AN85: =AL85 -> 11765465 | AO85: =$AO$19-AH85 -> -40 | AP85: =IF(AO85<0,"Not Due",IF(AO85<366,"Less than 1 year",IF(AO85<731,"1-2 years",IF(AO85<1096,"2-3 years","More than 3 years")))) -> Not Due
A86: GE India Industrial Pvt Ltd - GEITC | B86: GR16 | C86: 2070201000 | D86: Trade Accounts Payable-Subledge | E86: BLUE DART EXPRESS LIMITED A35832 | F86: Non-IBS | G86: Domestic | I86: Opex | J86: 2026229R00003641 | K86: 100070286 | L86: 46081 | M86: INR | N86: 7241.55 | O86: 1 | P86: =N86*O86 -> 7241.55 | Q86: 1 | R86: =N86*Q86 -> 7241.55 | S86: =R86-P86 -> 0 | T86: Non-MSME | U86: =$U$1-AH86 -> -14 | V86: 0 | W86: 0 | X86: 0 | Y86: 0 | Z86: 0 | AA86: 0 | AB86: 0 | AC86: =R86 -> 7241.55 | AD86: 38988519 | AE86: Not Due | AF86: 88237 | AG86: 46125 | AH86: 46126 | AJ86: =M86 -> INR | AK86: 1 | AL86: =N86*AK86 -> 7241.55 | AM86: =R86-AL86 -> 0 | AN86: =AL86 -> 7241.55 | AO86: =$AO$19-AH86 -> -14 | AP86: =IF(AO86<0,"Not Due",IF(AO86<366,"Less than 1 year",IF(AO86<731,"1-2 years",IF(AO86<1096,"2-3 years","More than 3 years")))) -> Not Due
A87: GE India Industrial Pvt Ltd - GEITC | B87: GR16 | C87: 2070201000 | D87: Trade Accounts Payable-Subledge | E87: Desai Brothers Ltd A37483 | F87: Non-IBS | G87: Domestic | I87: Opex | J87: 4037-63547 | K87: 100070915 | L87: 46077 | M87: INR | N87: 10440 | O87: 1 | P87: =N87*O87 -> 10440 | Q87: 1 | R87: =N87*Q87 -> 10440 | S87: =R87-P87 -> 0 | T87: Non-MSME | U87: =$U$1-AH87 -> -4 | V87: 0 | W87: 0 | X87: 0 | Y87: 0 | Z87: 0 | AA87: 0 | AB87: 0 | AC87: =R87 -> 10440 | AD87: 39011961 | AE87: Not Due | AF87: 88007 | AG87: 46113 | AH87: 46116 | AJ87: =M87 -> INR | AK87: 1 | AL87: =N87*AK87 -> 10440 | AM87: =R87-AL87 -> 0 | AN87: =AL87 -> 10440 | AO87: =$AO$19-AH87 -> -4 | AP87: =IF(AO87<0,"Not Due",IF(AO87<366,"Less than 1 year",IF(AO87<731,"1-2 years",IF(AO87<1096,"2-3 years","More than 3 years")))) -> Not Due
A88: GE India Industrial Pvt Ltd - GEITC | B88: GR16 | C88: 2070201000 | D88: Trade Accounts Payable-Subledge | E88: QUEST GLOBAL ENGINEERING SERVICES PRIVATE LIMITED A36314 | F88: Non-IBS | G88: Domestic | I88: Opex | J88: 20250766298 | K88: 100065943 | L88: 46066 | M88: INR | N88: 1452911.6 | O88: 1 | P88: =N88*O88 -> 1452911.6 | Q88: 1 | R88: =N88*Q88 -> 1452911.6 | S88: =R88-P88 -> 0 | T88: Non-MSME | U88: =$U$1-AH88 -> -44 | V88: 0 | W88: 0 | X88: 0 | Y88: 0 | Z88: 0 | AA88: 0 | AB88: 0 | AC88: =R88 -> 1452911.6 | AD88: 38916852 | AE88: Not Due | AF88: 88871 | AG88: 46164 | AH88: 46156 | AJ88: =M88 -> INR | AK88: 1 | AL88: =N88*AK88 -> 1452911.6 | AM88: =R88-AL88 -> 0 | AN88: =AL88 -> 1452911.6 | AO88: =$AO$19-AH88 -> -44 | AP88: =IF(AO88<0,"Not Due",IF(AO88<366,"Less than 1 year",IF(AO88<731,"1-2 years",IF(AO88<1096,"2-3 years","More than 3 years")))) -> Not Due
A89: GE India Industrial Pvt Ltd - GEITC | B89: GR16 | C89: 2070201000 | D89: Trade Accounts Payable-Subledge | E89: GENPACT INDIA PRIVATE LIMITED A37168 | F89: Non-IBS | G89: Domestic | I89: Opex | J89: B1Z3TS17036 | K89: 100070261 | L89: 46053 | M89: INR | N89: 1445298.1 | O89: 1 | P89: =N89*O89 -> 1445298.1 | Q89: 1 | R89: =N89*Q89 -> 1445298.1 | S89: =R89-P89 -> 0 | T89: Non-MSME | U89: =$U$1-AH89 -> -91 | V89: 0 | W89: 0 | X89: 0 | Y89: 0 | Z89: 0 | AA89: 0 | AB89: 0 | AC89: =R89 -> 1445298.1 | AD89: 38846145 | AE89: Not Due | AH89: 46203 | AJ89: =M89 -> INR | AK89: 1 | AL89: =N89*AK89 -> 1445298.1 | AM89: =R89-AL89 -> 0 | AO89: =$AO$19-AH89 -> -91 | AP89: =IF(AO89<0,"Not Due",IF(AO89<366,"Less than 1 year",IF(AO89<731,"1-2 years",IF(AO89<1096,"2-3 years","More than 3 years")))) -> Not Due
A90: GE India Industrial Pvt Ltd - GEITC | B90: GR16 | C90: 2070201000 | D90: Trade Accounts Payable-Subledge | E90: DHL EXPRESS INDIA PRIVATE LIMITED. | F90: Non-IBS | G90: Domestic | I90: Opex | J90: KASIR00494007 | K90: 100070361 | L90: 46059 | M90: INR | N90: 8308.81 | O90: 1 | P90: =N90*O90 -> 8308.81 | Q90: 1 | R90: =N90*Q90 -> 8308.81 | S90: =R90-P90 -> 0 | T90: Non-MSME | U90: =$U$1-AH90 -> -7 | V90: 0 | W90: 0 | X90: 0 | Y90: 0 | Z90: 0 | AA90: 0 | AB90: 0 | AC90: =R90 -> 8308.81 | AD90: 38906641 | AE90: Not Due | AF90: 88090 | AG90: 46118 | AH90: 46119 | AJ90: =M90 -> INR | AK90: 1 | AL90: =N90*AK90 -> 8308.81 | AM90: =R90-AL90 -> 0 | AN90: =AL90 -> 8308.81 | AO90: =$AO$19-AH90 -> -7 | AP90: =IF(AO90<0,"Not Due",IF(AO90<366,"Less than 1 year",IF(AO90<731,"1-2 years",IF(AO90<1096,"2-3 years","More than 3 years")))) -> Not Due
A91: GE India Industrial Pvt Ltd - GEITC | B91: GR16 | C91: 2070201000 | D91: Trade Accounts Payable-Subledge | E91: PERSOL INDIA PRIVATE LIMITED | F91: Non-IBS | G91: Domestic | I91: Opex | J91: KARI25260000603 | K91: 100067461 | L91: 46072 | M91: INR | N91: 3486.16 | O91: 1 | P91: =N91*O91 -> 3486.16 | Q91: 1 | R91: =N91*Q91 -> 3486.16 | S91: =R91-P91 -> 0 | T91: Non-MSME | U91: =$U$1-AH91 -> -20 | V91: 0 | W91: 0 | X91: 0 | Y91: 0 | Z91: 0 | AA91: 0 | AB91: 0 | AC91: =R91 -> 3486.16 | AD91: 38994133 | AE91: Not Due | AF91: 88306 | AG91: 46129 | AH91: 46132 | AJ91: =M91 -> INR | AK91: 1 | AL91: =N91*AK91 -> 3486.16 | AM91: =R91-AL91 -> 0 | AN91: =AL91 -> 3486.16 | AO91: =$AO$19-AH91 -> -20 | AP91: =IF(AO91<0,"Not Due",IF(AO91<366,"Less than 1 year",IF(AO91<731,"1-2 years",IF(AO91<1096,"2-3 years","More than 3 years")))) -> Not Due
A92: GE India Industrial Pvt Ltd - GEITC | B92: GR16 | C92: 2070201000 | D92: Trade Accounts Payable-Subledge | E92: Tata Consultancy Services Limited A11987 | F92: Non-IBS | G92: Domestic | I92: Opex | J92: KADI526010494 | K92: 100065402 | L92: 45996 | M92: INR | N92: 212976 | O92: 1 | P92: =N92*O92 -> 212976 | Q92: 1 | R92: =N92*Q92 -> 212976 | S92: =R92-P92 -> 0 | T92: Non-MSME | U92: =$U$1-AH92 -> -34 | V92: 0 | W92: 0 | X92: 0 | Y92: 0 | Z92: 0 | AA92: 0 | AB92: 0 | AC92: =R92 -> 212976 | AD92: 38635994 | AE92: Not Due | AF92: 88473 | AG92: 46143 | AH92: 46146 | AJ92: =M92 -> INR | AK92: 1 | AL92: =N92*AK92 -> 212976 | AM92: =R92-AL92 -> 0 | AN92: =AL92 -> 212976 | AO92: =$AO$19-AH92 -> -34 | AP92: =IF(AO92<0,"Not Due",IF(AO92<366,"Less than 1 year",IF(AO92<731,"1-2 years",IF(AO92<1096,"2-3 years","More than 3 years")))) -> Not Due
A93: GE India Industrial Pvt Ltd - GEITC | B93: GR16 | C93: 2070201000 | D93: Trade Accounts Payable-Subledge | E93: QUEST GLOBAL ENGINEERING SERVICES PRIVATE LIMITED A36314 | F93: Non-IBS | G93: Domestic | I93: Opex | J93: 20250765624 | K93: 100066777 | L93: 46034 | M93: INR | N93: 2099428.2 | O93: 1 | P93: =N93*O93 -> 2099428.2 | Q93: 1 | R93: =N93*Q93 -> 2099428.2 | S93: =R93-P93 -> 0 | T93: Non-MSME | U93: =$U$1-AH93 -> -12 | V93: 0 | W93: 0 | X93: 0 | Y93: 0 | Z93: 0 | AA93: 0 | AB93: 0 | AC93: =R93 -> 2099428.2 | AD93: 38765194 | AE93: Not Due | AF93: 88152 | AG93: 46121 | AH93: 46124 | AJ93: =M93 -> INR | AK93: 1 | AL93: =N93*AK93 -> 2099428.2 | AM93: =R93-AL93 -> 0 | AN93: =AL93 -> 2099428.2 | AO93: =$AO$19-AH93 -> -12 | AP93: =IF(AO93<0,"Not Due",IF(AO93<366,"Less than 1 year",IF(AO93<731,"1-2 years",IF(AO93<1096,"2-3 years","More than 3 years")))) -> Not Due
A94: GE India Industrial Pvt Ltd - GEITC | B94: GR16 | C94: 2070201000 | D94: Trade Accounts Payable-Subledge | E94: Tata Consultancy Services Limited A11987 | F94: Non-IBS | G94: Domestic | I94: Opex | J94: KADI526011875 | K94: 100068570 | L94: 46034 | M94: INR | N94: 274492.8 | O94: 1 | P94: =N94*O94 -> 274492.8 | Q94: 1 | R94: =N94*Q94 -> 274492.8 | S94: =R94-P94 -> 0 | T94: Non-MSME | U94: =$U$1-AH94 -> -72 | V94: 0 | W94: 0 | X94: 0 | Y94: 0 | Z94: 0 | AA94: 0 | AB94: 0 | AC94: =R94 -> 274492.8 | AD94: 38849750 | AE94: Not Due | AF94: 89099 | AG94: 46181 | AH94: 46184 | AJ94: =M94 -> INR | AK94: 1 | AL94: =N94*AK94 -> 274492.8 | AM94: =R94-AL94 -> 0 | AN94: =AL94 -> 274492.8 | AO94: =$AO$19-AH94 -> -72 | AP94: =IF(AO94<0,"Not Due",IF(AO94<366,"Less than 1 year",IF(AO94<731,"1-2 years",IF(AO94<1096,"2-3 years","More than 3 years")))) -> Not Due
A95: GE India Industrial Pvt Ltd - GEITC | B95: GR16 | C95: 2070201000 | D95: Trade Accounts Payable-Subledge | E95: Bharti Airtel Limited A38979 | F95: Non-IBS | G95: Domestic | I95: Opex | J95: BBL292602B075035 | K95: 100070284 | L95: 46056 | M95: INR | N95: 225498.65 | O95: 1 | P95: =N95*O95 -> 225498.65 | Q95: 1 | R95: =N95*Q95 -> 225498.65 | S95: =R95-P95 -> 0 | T95: Non-MSME | U95: =$U$1-AH95 -> -34 | V95: 0 | W95: 0 | X95: 0 | Y95: 0 | Z95: 0 | AA95: 0 | AB95: 0 | AC95: =R95 -> 225498.65 | AD95: 38856824 | AE95: Not Due | AF95: 88530 | AG95: 46143 | AH95: 46146 | AJ95: =M95 -> INR | AK95: 1 | AL95: =N95*AK95 -> 225498.65 | AM95: =R95-AL95 -> 0 | AN95: =AL95 -> 225498.65 | AO95: =$AO$19-AH95 -> -34 | AP95: =IF(AO95<0,"Not Due",IF(AO95<366,"Less than 1 year",IF(AO95<731,"1-2 years",IF(AO95<1096,"2-3 years","More than 3 years")))) -> Not Due
A96: GE India Industrial Pvt Ltd - GEITC | B96: GR16 | C96: 2070201000 | D96: Trade Accounts Payable-Subledge | E96: MOUSER ELECTRONICS INC. A02649 | F96: Non-IBS | G96: Foreign | I96: Opex | J96: 88607880 | K96: 100070631 | L96: 46064 | M96: USD | N96: 758.68 | O96: 91.82425 | P96: =N96*O96 -> 69665.222 | Q96: 94.6543 | R96: =N96*Q96 -> 71812.324 | S96: =R96-P96 -> 2147.1023 | T96: Non-MSME | U96: =$U$1-AH96 -> -42 | V96: 0 | W96: 0 | X96: 0 | Y96: 0 | Z96: 0 | AA96: 0 | AB96: 0 | AC96: =R96 -> 71812.324 | AD96: 38895281 | AE96: Not Due | AF96: 90008282 | AG96: 46153 | AH96: 46154 | AJ96: =M96 -> USD | AK96: 94.6543 | AL96: =N96*AK96 -> 71812.324 | AM96: =R96-AL96 -> 0 | AN96: =AL96 -> 71812.324 | AO96: =$AO$19-AH96 -> -42 | AP96: =IF(AO96<0,"Not Due",IF(AO96<366,"Less than 1 year",IF(AO96<731,"1-2 years",IF(AO96<1096,"2-3 years","More than 3 years")))) -> Not Due
A97: GE India Industrial Pvt Ltd - GEITC | B97: GR16 | C97: 2070201000 | D97: Trade Accounts Payable-Subledge | E97: TATA TECHNOLOGIES LIMITED A38494 | F97: Non-IBS | G97: Domestic | I97: Opex | J97: KA0000006145 | K97: 100066426 | L97: 46009 | M97: INR | N97: 1113609.6 | O97: 1 | P97: =N97*O97 -> 1113609.6 | Q97: 1 | R97: =N97*Q97 -> 1113609.6 | S97: =R97-P97 -> 0 | T97: Non-MSME | U97: =$U$1-AH97 -> -17 | V97: 0 | W97: 0 | X97: 0 | Y97: 0 | Z97: 0 | AA97: 0 | AB97: 0 | AC97: =R97 -> 1113609.6 | AD97: 38668859 | AE97: Not Due | AF97: 88267 | AG97: 46126 | AH97: 46129 | AJ97: =M97 -> INR | AK97: 1 | AL97: =N97*AK97 -> 1113609.6 | AM97: =R97-AL97 -> 0 | AN97: =AL97 -> 1113609.6 | AO97: =$AO$19-AH97 -> -17 | AP97: =IF(AO97<0,"Not Due",IF(AO97<366,"Less than 1 year",IF(AO97<731,"1-2 years",IF(AO97<1096,"2-3 years","More than 3 years")))) -> Not Due
A98: GE India Industrial Pvt Ltd - GEITC | B98: GR16 | C98: 2070201000 | D98: Trade Accounts Payable-Subledge | E98: GENPACT INDIA PRIVATE LIMITED A37168 | F98: Non-IBS | G98: Domestic | I98: Opex | J98: B2ZXKA17674 | K98: 100067233 | L98: 45996 | M98: INR | N98: 224856 | O98: 1 | P98: =N98*O98 -> 224856 | Q98: 1 | R98: =N98*Q98 -> 224856 | S98: =R98-P98 -> 0 | T98: Non-MSME | U98: =$U$1-AH98 -> -34 | V98: 0 | W98: 0 | X98: 0 | Y98: 0 | Z98: 0 | AA98: 0 | AB98: 0 | AC98: =R98 -> 224856 | AD98: 38641074 | AE98: Not Due | AF98: 88495 | AG98: 46143 | AH98: 46146 | AJ98: =M98 -> INR | AK98: 1 | AL98: =N98*AK98 -> 224856 | AM98: =R98-AL98 -> 0 | AN98: =AL98 -> 224856 | AO98: =$AO$19-AH98 -> -34 | AP98: =IF(AO98<0,"Not Due",IF(AO98<366,"Less than 1 year",IF(AO98<731,"1-2 years",IF(AO98<1096,"2-3 years","More than 3 years")))) -> Not Due
A99: GE India Industrial Pvt Ltd - GEITC | B99: GR16 | C99: 2070201000 | D99: Trade Accounts Payable-Subledge | E99: GENPACT INDIA PRIVATE LIMITED A37168 | F99: Non-IBS | G99: Domestic | I99: Opex | J99: B2ZXKA17981 | K99: 100065928 | L99: 46030 | M99: INR | N99: 305208 | O99: 1 | P99: =N99*O99 -> 305208 | Q99: 1 | R99: =N99*Q99 -> 305208 | S99: =R99-P99 -> 0 | T99: Non-MSME | U99: =$U$1-AH99 -> -68 | V99: 0 | W99: 0 | X99: 0 | Y99: 0 | Z99: 0 | AA99: 0 | AB99: 0 | AC99: =R99 -> 305208 | AD99: 38747226 | AE99: Not Due | AF99: 89064 | AG99: 46177 | AH99: 46180 | AJ99: =M99 -> INR | AK99: 1 | AL99: =N99*AK99 -> 305208 | AM99: =R99-AL99 -> 0 | AN99: =AL99 -> 305208 | AO99: =$AO$19-AH99 -> -68 | AP99: =IF(AO99<0,"Not Due",IF(AO99<366,"Less than 1 year",IF(AO99<731,"1-2 years",IF(AO99<1096,"2-3 years","More than 3 years")))) -> Not Due
A100: GE India Industrial Pvt Ltd - GEITC | B100: GR16 | C100: 2070201000 | D100: Trade Accounts Payable-Subledge | E100: GENPACT INDIA PRIVATE LIMITED A37168 | F100: Non-IBS | G100: Domestic | I100: Opex | J100: B2ZXKA17676 | K100: 100065928 | L100: 45996 | M100: INR | N100: 305208 | O100: 1 | P100: =N100*O100 -> 305208 | Q100: 1 | R100: =N100*Q100 -> 305208 | S100: =R100-P100 -> 0 | T100: Non-MSME | U100: =$U$1-AH100 -> -34 | V100: 0 | W100: 0 | X100: 0 | Y100: 0 | Z100: 0 | AA100: 0 | AB100: 0 | AC100: =R100 -> 305208 | AD100: 38635585 | AE100: Not Due | AF100: 88495 | AG100: 46143 | AH100: 46146 | AJ100: =M100 -> INR | AK100: 1 | AL100: =N100*AK100 -> 305208 | AM100: =R100-AL100 -> 0 | AN100: =AL100 -> 305208 | AO100: =$AO$19-AH100 -> -34 | AP100: =IF(AO100<0,"Not Due",IF(AO100<366,"Less than 1 year",IF(AO100<731,"1-2 years",IF(AO100<1096,"2-3 years","More than 3 years")))) -> Not Due
A101: GE India Industrial Pvt Ltd - GEITC | B101: GR16 | C101: 2070201000 | D101: Trade Accounts Payable-Subledge | E101: Teamlease Digital Pvt Ltd A38341 | F101: Non-IBS | G101: Domestic | I101: Opex | J101: TD29T2526-35979 | K101: 100066379 | L101: 46087 | M101: INR | N101: 367088.85 | O101: 1 | P101: =N101*O101 -> 367088.85 | Q101: 1 | R101: =N101*Q101 -> 367088.85 | S101: =R101-P101 -> 0 | T101: Non-MSME | U101: =$U$1-AH101 -> -20 | V101: 0 | W101: 0 | X101: 0 | Y101: 0 | Z101: 0 | AA101: 0 | AB101: 0 | AC101: =R101 -> 367088.85 | AD101: 39023614 | AE101: Not Due | AF101: 88313 | AG101: 46129 | AH101: 46132 | AJ101: =M101 -> INR | AK101: 1 | AL101: =N101*AK101 -> 367088.85 | AM101: =R101-AL101 -> 0 | AN101: =AL101 -> 367088.85 | AO101: =$AO$19-AH101 -> -20 | AP101: =IF(AO101<0,"Not Due",IF(AO101<366,"Less than 1 year",IF(AO101<731,"1-2 years",IF(AO101<1096,"2-3 years","More than 3 years")))) -> Not Due
A102: GE India Industrial Pvt Ltd - GEITC | B102: GR16 | C102: 2070201000 | D102: Trade Accounts Payable-Subledge | E102: ABB INDIA LIMITED A37150 | F102: Non-IBS | G102: Domestic | I102: Capex | J102: 252901187198 | K102: 100068568 | L102: 46079 | M102: INR | N102: 10404.17 | O102: 1 | P102: =N102*O102 -> 10404.17 | Q102: 1 | R102: =N102*Q102 -> 10404.17 | S102: =R102-P102 -> 0 | T102: Non-MSME | U102: =$U$1-AH102 -> -27 | V102: 0 | W102: 0 | X102: 0 | Y102: 0 | Z102: 0 | AA102: 0 | AB102: 0 | AC102: =R102 -> 10404.17 | AD102: 38966973 | AE102: Not Due | AF102: 88422 | AG102: 46136 | AH102: 46139 | AJ102: =M102 -> INR | AK102: 1 | AL102: =N102*AK102 -> 10404.17 | AM102: =R102-AL102 -> 0 | AN102: =AL102 -> 10404.17 | AO102: =$AO$19-AH102 -> -27 | AP102: =IF(AO102<0,"Not Due",IF(AO102<366,"Less than 1 year",IF(AO102<731,"1-2 years",IF(AO102<1096,"2-3 years","More than 3 years")))) -> Not Due
A103: GE India Industrial Pvt Ltd - GEITC | B103: GR16 | C103: 2070201000 | D103: Trade Accounts Payable-Subledge | E103: SR TECHTRONICS A39006 | F103: Non-IBS | G103: Domestic | I103: Opex | J103: SRT-CI/A/1070 | K103: 100070837 | L103: 46079 | M103: INR | N103: 153386.72 | O103: 1 | P103: =N103*O103 -> 153386.72 | Q103: 1 | R103: =N103*Q103 -> 153386.72 | S103: =R103-P103 -> 0 | T103: Non-MSME | U103: =$U$1-AH103 -> -12 | V103: 0 | W103: 0 | X103: 0 | Y103: 0 | Z103: 0 | AA103: 0 | AB103: 0 | AC103: =R103 -> 153386.72 | AD103: 38956814 | AE103: Not Due | AF103: 88169 | AG103: 46121 | AH103: 46124 | AJ103: =M103 -> INR | AK103: 1 | AL103: =N103*AK103 -> 153386.72 | AM103: =R103-AL103 -> 0 | AN103: =AL103 -> 153386.72 | AO103: =$AO$19-AH103 -> -12 | AP103: =IF(AO103<0,"Not Due",IF(AO103<366,"Less than 1 year",IF(AO103<731,"1-2 years",IF(AO103<1096,"2-3 years","More than 3 years")))) -> Not Due
A104: GE India Industrial Pvt Ltd - GEITC | B104: GR16 | C104: 2070201000 | D104: Trade Accounts Payable-Subledge | E104: GENPACT INDIA PRIVATE LIMITED A37168 | F104: Non-IBS | G104: Domestic | I104: Opex | J104: B2ZXKA17920 | K104: 100064783 | L104: 46023 | M104: INR | N104: 288203.4 | O104: 1 | P104: =N104*O104 -> 288203.4 | Q104: 1 | R104: =N104*Q104 -> 288203.4 | S104: =R104-P104 -> 0 | T104: Non-MSME | U104: =$U$1-AH104 -> -61 | V104: 0 | W104: 0 | X104: 0 | Y104: 0 | Z104: 0 | AA104: 0 | AB104: 0 | AC104: =R104 -> 288203.4 | AD104: 38718494 | AE104: Not Due | AF104: 88955 | AG104: 46168 | AH104: 46173 | AJ104: =M104 -> INR | AK104: 1 | AL104: =N104*AK104 -> 288203.4 | AM104: =R104-AL104 -> 0 | AN104: =AL104 -> 288203.4 | AO104: =$AO$19-AH104 -> -61 | AP104: =IF(AO104<0,"Not Due",IF(AO104<366,"Less than 1 year",IF(AO104<731,"1-2 years",IF(AO104<1096,"2-3 years","More than 3 years")))) -> Not Due
...

Sheet AP Liability MSME
A1: =Memo!A1 -> 0 | U1: ='SSS Accrual Non MSME'!Y1 -> 46112
A2: =Memo!A2 -> 0
A3: =Memo!A3 -> 0
A5: Work Done
A6: 1. ET has obtained the schedule for AP Liability (MSME).
A7: 2. ET has verified the exchange rate considered for closing payable amount.
A8: 3. ET has recomputed the ageing of invoices payable from due date.
A9: 4. ET has checked the computation of due date and performed 3 way match on sample basis.
A11: Summary
A13: Particulars | B13: Amount
A14: Payable Amount | B14: =R19 -> 51951832
A15: Subsequently Paid | B15: =$AO$19 -> 51958540
A16: Subsequently Paid % | B16: =B15/B14 -> 1.0001291
A18: AP Liability Schedule - MSME | AK18: DHS Testing
R19: =SUM(R21:R412) -> 51951832 | S19: =SUM(S20:S97) -> 0 | V19: =SUM(V21:V412) -> -8665.5 | W19: =SUM(W21:W412) -> 41029 | X19: =SUM(X21:X412) -> 0 | Y19: =SUM(Y21:Y412) -> 0 | Z19: =SUM(Z21:Z412) -> 0 | AA19: =SUM(AA21:AA412) -> 0 | AB19: =SUM(AB21:AB412) -> 0 | AC19: =SUM(AC21:AC412) -> 51919468 | AM19: =SUM(AM21:AM412) -> 51951832 | AN19: =SUM(AN21:AN412) -> 0 | AO19: =SUM(AO20:AO970) -> 51958540 | AP19: 46112
A20: Division | B20: Company Code | C20: Account Code | D20: Account Description | E20: Vendor Name | F20: Related Party | G20: Foreign / Domestic | H20: Unique | I20: Nature (Capital/Trade) | J20: Invoice Number | K20: PO Number | L20: Invoice Date | M20: Currency | N20: Invoice Original Amount | O20: MOR Rate | P20: Invoice Amount INR | Q20: RBI Rate | R20: Amount as per RBI | S20: FX_Diff | T20: MSMED | U20: Ageing | V20: 0-30 days | W20: 30-60 days | X20: 60-90 days | Y20: 90-120 days | Z20: 120-180 days | AA20: 180 Days-3 year | AB20: >3 Years | AC20: Not Due | AD20: Invoice Id | AE20: Reson for more than 180 days/debit balances/No GE entity payables | AF20: Subsequent payment Doc # | AG20: Date of subsequent payment | AH20: Due date | AK20: Currency | AL20: Exchange Rate | AM20: Amount in INR | AN20: Difference | AO20: Subsequently Paid | AP20: No. of Days | AQ20: Ageing Bracket
A21: GE India Industrial Pvt Ltd - GEITC | B21: GR16 | C21: 2070201000 | D21: Trade Accounts Payable-Subledge | E21: Eta Engineers Bangalore Private Limited A37548 | F21: Non-IBS | G21: Domestic | I21: Capex | J21: 339/HO/2025-26 | K21: 100069162 | L21: 46073 | M21: INR | N21: 105826.8 | O21: 1 | P21: =N21*O21 -> 105826.8 | Q21: 1 | R21: =N21*Q21 -> 105826.8 | S21: =R21-P21 -> 0 | T21: Small | U21: =$U$1-AH21 -> -6 | V21: 0 | W21: 0 | X21: 0 | Y21: 0 | Z21: 0 | AA21: 0 | AB21: 0 | AC21: =R21 -> 105826.8 | AD21: 38965277 | AE21: Not Due | AF21: 88061 | AG21: 46115 | AH21: 46118 | AK21: INR | AL21: 1 | AM21: =N21*AL21 -> 105826.8 | AN21: =R21-AM21 -> 0 | AO21: =AM21 -> 105826.8 | AP21: =$AP$19-AH21 -> -6 | AQ21: =IF(AP21<0,"Not Due",IF(AP21<366,"Less than 1 year",IF(AP21<731,"1-2 years",IF(AP21<1096,"2-3 years","More than 3 years")))) -> Not Due
A22: GE India Industrial Pvt Ltd - GEITC | B22: GR16 | C22: 2070201000 | D22: Trade Accounts Payable-Subledge | E22: Shobha Electricals A37602 | F22: Non-IBS | G22: Domestic | I22: Opex | J22: SER/448/25-26 | K22: 100069853 | L22: 46083 | M22: INR | N22: 17980 | O22: 1 | P22: =N22*O22 -> 17980 | Q22: 1 | R22: =N22*Q22 -> 17980 | S22: =R22-P22 -> 0 | T22: Small | U22: =$U$1-AH22 -> -16 | V22: 0 | W22: 0 | X22: 0 | Y22: 0 | Z22: 0 | AA22: 0 | AB22: 0 | AC22: =R22 -> 17980 | AD22: 38976052 | AE22: Not Due | AF22: 88201 | AG22: 46125 | AH22: 46128 | AK22: INR | AL22: 1 | AM22: =N22*AL22 -> 17980 | AN22: =R22-AM22 -> 0 | AO22: =AM22 -> 17980 | AP22: =$AP$19-AH22 -> -16 | AQ22: =IF(AP22<0,"Not Due",IF(AP22<366,"Less than 1 year",IF(AP22<731,"1-2 years",IF(AP22<1096,"2-3 years","More than 3 years")))) -> Not Due
A23: GE India Industrial Pvt Ltd - GEITC | B23: GR16 | C23: 2070201000 | D23: Trade Accounts Payable-Subledge | E23: Pro Team Solutions Private Limited A37469 | F23: Non-IBS | G23: Domestic | I23: Opex | J23: PTSB/25-26/4065 | K23: 100067691 | L23: 46082 | M23: INR | N23: 199263.51 | O23: 1 | P23: =N23*O23 -> 199263.51 | Q23: 1 | R23: =N23*Q23 -> 199263.51 | S23: =R23-P23 -> 0 | T23: Small | U23: =$U$1-AH23 -> -15 | V23: 0 | W23: 0 | X23: 0 | Y23: 0 | Z23: 0 | AA23: 0 | AB23: 0 | AC23: =R23 -> 199263.51 | AD23: 38964837 | AE23: Not Due | AF23: 88194 | AG23: 46125 | AH23: 46127 | AK23: INR | AL23: 1 | AM23: =N23*AL23 -> 199263.51 | AN23: =R23-AM23 -> 0 | AO23: =AM23 -> 199263.51 | AP23: =$AP$19-AH23 -> -15 | AQ23: =IF(AP23<0,"Not Due",IF(AP23<366,"Less than 1 year",IF(AP23<731,"1-2 years",IF(AP23<1096,"2-3 years","More than 3 years")))) -> Not Due
A24: GE India Industrial Pvt Ltd - GEITC | B24: GR16 | C24: 2070201000 | D24: Trade Accounts Payable-Subledge | E24: Sri Lakshmi Venkateshwara Prasanna A38498 | F24: Non-IBS | G24: Domestic | I24: Opex | J24: 1977/2026-2027 | K24: 100068172 | L24: 46083 | M24: INR | N24: 62129.6 | O24: 1 | P24: =N24*O24 -> 62129.6 | Q24: 1 | R24: =N24*Q24 -> 62129.6 | S24: =R24-P24 -> 0 | T24: Micro | U24: =$U$1-AH24 -> -16 | V24: 0 | W24: 0 | X24: 0 | Y24: 0 | Z24: 0 | AA24: 0 | AB24: 0 | AC24: =R24 -> 62129.6 | AD24: 38956575 | AE24: Not Due | AF24: 88220 | AG24: 46125 | AH24: 46128 | AK24: INR | AL24: 1 | AM24: =N24*AL24 -> 62129.6 | AN24: =R24-AM24 -> 0 | AO24: =AM24 -> 62129.6 | AP24: =$AP$19-AH24 -> -16 | AQ24: =IF(AP24<0,"Not Due",IF(AP24<366,"Less than 1 year",IF(AP24<731,"1-2 years",IF(AP24<1096,"2-3 years","More than 3 years")))) -> Not Due
A25: GE India Industrial Pvt Ltd - GEITC | B25: GR16 | C25: 2070201000 | D25: Trade Accounts Payable-Subledge | E25: Shobha Electricals A37602 | F25: Non-IBS | G25: Domestic | I25: Capex | J25: SER/453/25-26 | K25: 100068779 | L25: 46083 | M25: INR | N25: 52287.5 | O25: 1 | P25: =N25*O25 -> 52287.5 | Q25: 1 | R25: =N25*Q25 -> 52287.5 | S25: =R25-P25 -> 0 | T25: Small | U25: =$U$1-AH25 -> -16 | V25: 0 | W25: 0 | X25: 0 | Y25: 0 | Z25: 0 | AA25: 0 | AB25: 0 | AC25: =R25 -> 52287.5 | AD25: 38977124 | AE25: Not Due | AF25: 88201 | AG25: 46125 | AH25: 46128 | AK25: INR | AL25: 1 | AM25: =N25*AL25 -> 52287.5 | AN25: =R25-AM25 -> 0 | AO25: =AM25 -> 52287.5 | AP25: =$AP$19-AH25 -> -16 | AQ25: =IF(AP25<0,"Not Due",IF(AP25<366,"Less than 1 year",IF(AP25<731,"1-2 years",IF(AP25<1096,"2-3 years","More than 3 years")))) -> Not Due
A26: GE India Industrial Pvt Ltd - GEITC | B26: GR16 | C26: 2070201000 | D26: Trade Accounts Payable-Subledge | E26: Juice Junction A38216 | F26: Non-IBS | G26: Domestic | I26: Opex | J26: JJ/2025-26/277 | K26: 100066527 | L26: 46075 | M26: INR | N26: 9620.2 | O26: 1 | P26: =N26*O26 -> 9620.2 | Q26: 1 | R26: =N26*Q26 -> 9620.2 | S26: =R26-P26 -> 0 | T26: Small | U26: =$U$1-AH26 -> -8 | V26: 0 | W26: 0 | X26: 0 | Y26: 0 | Z26: 0 | AA26: 0 | AB26: 0 | AC26: =R26 -> 9620.2 | AD26: 38956680 | AE26: Not Due | AF26: 88083 | AG26: 46118 | AH26: 46120 | AK26: INR | AL26: 1 | AM26: =N26*AL26 -> 9620.2 | AN26: =R26-AM26 -> 0 | AO26: =AM26 -> 9620.2 | AP26: =$AP$19-AH26 -> -8 | AQ26: =IF(AP26<0,"Not Due",IF(AP26<366,"Less than 1 year",IF(AP26<731,"1-2 years",IF(AP26<1096,"2-3 years","More than 3 years")))) -> Not Due
A27: GE India Industrial Pvt Ltd - GEITC | B27: GR16 | C27: 2070201000 | D27: Trade Accounts Payable-Subledge | E27: Karnataka Kleening Korporation A38055 | F27: Non-IBS | G27: Domestic | I27: Opex | J27: 511/25-26 | K27: 100070800 | L27: 46069 | M27: INR | N27: 73731.92 | O27: 1 | P27: =N27*O27 -> 73731.92 | Q27: 1 | R27: =N27*Q27 -> 73731.92 | S27: =R27-P27 -> 0 | T27: Small | U27: =$U$1-AH27 -> -2 | V27: 0 | W27: 0 | X27: 0 | Y27: 0 | Z27: 0 | AA27: 0 | AB27: 0 | AC27: =R27 -> 73731.92 | AD27: 38921523 | AE27: Not Due | AF27: 88025 | AG27: 46113 | AH27: 46114 | AK27: INR | AL27: 1 | AM27: =N27*AL27 -> 73731.92 | AN27: =R27-AM27 -> 0 | AO27: =AM27 -> 73731.92 | AP27: =$AP$19-AH27 -> -2 | AQ27: =IF(AP27<0,"Not Due",IF(AP27<366,"Less than 1 year",IF(AP27<731,"1-2 years",IF(AP27<1096,"2-3 years","More than 3 years")))) -> Not Due
A28: GE India Industrial Pvt Ltd - GEITC | B28: GR16 | C28: 2070201000 | D28: Trade Accounts Payable-Subledge | E28: Alpha Lab Solutions A38403 | F28: Non-IBS | G28: Domestic | I28: Opex | J28: 135/2025-26 | K28: 100070770 | L28: 46085 | M28: INR | N28: 137026.92 | O28: 1 | P28: =N28*O28 -> 137026.92 | Q28: 1 | R28: =N28*Q28 -> 137026.92 | S28: =R28-P28 -> 0 | T28: Micro | U28: =$U$1-AH28 -> -18 | V28: 0 | W28: 0 | X28: 0 | Y28: 0 | Z28: 0 | AA28: 0 | AB28: 0 | AC28: =R28 -> 137026.92 | AD28: 39012044 | AE28: Not Due | AF28: 88285 | AG28: 46127 | AH28: 46130 | AK28: INR | AL28: 1 | AM28: =N28*AL28 -> 137026.92 | AN28: =R28-AM28 -> 0 | AO28: =AM28 -> 137026.92 | AP28: =$AP$19-AH28 -> -18 | AQ28: =IF(AP28<0,"Not Due",IF(AP28<366,"Less than 1 year",IF(AP28<731,"1-2 years",IF(AP28<1096,"2-3 years","More than 3 years")))) -> Not Due
A29: GE India Industrial Pvt Ltd - GEITC | B29: GR16 | C29: 2070201000 | D29: Trade Accounts Payable-Subledge | E29: Eta Engineers Bangalore Private Limited A37548 | F29: Non-IBS | G29: Domestic | I29: Opex | J29: 358/HO/2025-26 | K29: 100070668 | L29: 46087 | M29: INR | N29: 28001.25 | O29: 1 | P29: =N29*O29 -> 28001.25 | Q29: 1 | R29: =N29*Q29 -> 28001.25 | S29: =R29-P29 -> 0 | T29: Small | U29: =$U$1-AH29 -> -20 | V29: 0 | W29: 0 | X29: 0 | Y29: 0 | Z29: 0 | AA29: 0 | AB29: 0 | AC29: =R29 -> 28001.25 | AD29: 39017906 | AE29: Not Due | AF29: 88311 | AG29: 46129 | AH29: 46132 | AK29: INR | AL29: 1 | AM29: =N29*AL29 -> 28001.25 | AN29: =R29-AM29 -> 0 | AO29: =AM29 -> 28001.25 | AP29: =$AP$19-AH29 -> -20 | AQ29: =IF(AP29<0,"Not Due",IF(AP29<366,"Less than 1 year",IF(AP29<731,"1-2 years",IF(AP29<1096,"2-3 years","More than 3 years")))) -> Not Due
A30: GE India Industrial Pvt Ltd - GEITC | B30: GR16 | C30: 2070201000 | D30: Trade Accounts Payable-Subledge | E30: Mobiveil Technologies India Private Limited A38750 | F30: Non-IBS | G30: Domestic | I30: Opex | J30: MOBBLR25260030 | K30: 100070657 | L30: 46093 | M30: INR | N30: 194400 | O30: 1 | P30: =N30*O30 -> 194400 | Q30: 1 | R30: =N30*Q30 -> 194400 | S30: =R30-P30 -> 0 | T30: Small | U30: =$U$1-AH30 -> -11 | V30: 0 | W30: 0 | X30: 0 | Y30: 0 | Z30: 0 | AA30: 0 | AB30: 0 | AC30: =R30 -> 194400 | AD30: 39018596 | AE30: Not Due | AF30: 88141 | AG30: 46120 | AH30: 46123 | AK30: INR | AL30: 1 | AM30: =N30*AL30 -> 194400 | AN30: =R30-AM30 -> 0 | AO30: =AM30 -> 194400 | AP30: =$AP$19-AH30 -> -11 | AQ30: =IF(AP30<0,"Not Due",IF(AP30<366,"Less than 1 year",IF(AP30<731,"1-2 years",IF(AP30<1096,"2-3 years","More than 3 years")))) -> Not Due
A31: GE India Industrial Pvt Ltd - GEITC | B31: GR16 | C31: 2070201000 | D31: Trade Accounts Payable-Subledge | E31: V.K. Technologies and Services A38107 | F31: Non-IBS | G31: Domestic | I31: Opex | J31: VKTS/11049/25-26 | K31: 100070677 | L31: 46091 | M31: INR | N31: 64137.6 | O31: 1 | P31: =N31*O31 -> 64137.6 | Q31: 1 | R31: =N31*Q31 -> 64137.6 | S31: =R31-P31 -> 0 | T31: Micro | U31: =$U$1-AH31 -> -9 | V31: 0 | W31: 0 | X31: 0 | Y31: 0 | Z31: 0 | AA31: 0 | AB31: 0 | AC31: =R31 -> 64137.6 | AD31: 38999690 | AE31: Not Due | AF31: 88078 | AG31: 46118 | AH31: 46121 | AK31: INR | AL31: 1 | AM31: =N31*AL31 -> 64137.6 | AN31: =R31-AM31 -> 0 | AO31: =AM31 -> 64137.6 | AP31: =$AP$19-AH31 -> -9 | AQ31: =IF(AP31<0,"Not Due",IF(AP31<366,"Less than 1 year",IF(AP31<731,"1-2 years",IF(AP31<1096,"2-3 years","More than 3 years")))) -> Not Due
A32: GE India Industrial Pvt Ltd - GEITC | B32: GR16 | C32: 2070201000 | D32: Trade Accounts Payable-Subledge | E32: Amazing Blooms A38045 | F32: Non-IBS | G32: Domestic | I32: Opex | J32: 1085 | K32: 100070311 | L32: 46085 | M32: INR | N32: 250778.08 | O32: 1 | P32: =N32*O32 -> 250778.08 | Q32: 1 | R32: =N32*Q32 -> 250778.08 | S32: =R32-P32 -> 0 | T32: Small | U32: =$U$1-AH32 -> -18 | V32: 0 | W32: 0 | X32: 0 | Y32: 0 | Z32: 0 | AA32: 0 | AB32: 0 | AC32: =R32 -> 250778.08 | AD32: 38978551 | AE32: Not Due | AF32: 88276 | AG32: 46127 | AH32: 46130 | AK32: INR | AL32: 1 | AM32: =N32*AL32 -> 250778.08 | AN32: =R32-AM32 -> 0 | AO32: =AM32 -> 250778.08 | AP32: =$AP$19-AH32 -> -18 | AQ32: =IF(AP32<0,"Not Due",IF(AP32<366,"Less than 1 year",IF(AP32<731,"1-2 years",IF(AP32<1096,"2-3 years","More than 3 years")))) -> Not Due
A33: GE India Industrial Pvt Ltd - GEITC | B33: GR16 | C33: 2070201000 | D33: Trade Accounts Payable-Subledge | E33: Vinolya Services Pvt Ltd. A38997 | F33: Non-IBS | G33: Domestic | I33: Opex | J33: 13643/25 | K33: 100070312 | L33: 46082 | M33: INR | N33: 48192.1 | O33: 1 | P33: =N33*O33 -> 48192.1 | Q33: 1 | R33: =N33*Q33 -> 48192.1 | S33: =R33-P33 -> 0 | T33: Small | U33: =$U$1-AH33 -> -15 | V33: 0 | W33: 0 | X33: 0 | Y33: 0 | Z33: 0 | AA33: 0 | AB33: 0 | AC33: =R33 -> 48192.1 | AD33: 38956574 | AE33: Not Due | AF33: 88226 | AG33: 46125 | AH33: 46127 | AK33: INR | AL33: 1 | AM33: =N33*AL33 -> 48192.1 | AN33: =R33-AM33 -> 0 | AO33: =AM33 -> 48192.1 | AP33: =$AP$19-AH33 -> -15 | AQ33: =IF(AP33<0,"Not Due",IF(AP33<366,"Less than 1 year",IF(AP33<731,"1-2 years",IF(AP33<1096,"2-3 years","More than 3 years")))) -> Not Due
A34: GE India Industrial Pvt Ltd - GEITC | B34: GR16 | C34: 2070201000 | D34: Trade Accounts Payable-Subledge | E34: Karnataka Kleening Korporation A38055 | F34: Non-IBS | G34: Domestic | I34: Opex | J34: 513/25-26 | K34: 100070794 | L34: 46069 | M34: INR | N34: 71922.32 | O34: 1 | P34: =N34*O34 -> 71922.32 | Q34: 1 | R34: =N34*Q34 -> 71922.32 | S34: =R34-P34 -> 0 | T34: Small | U34: =$U$1-AH34 -> -2 | V34: 0 | W34: 0 | X34: 0 | Y34: 0 | Z34: 0 | AA34: 0 | AB34: 0 | AC34: =R34 -> 71922.32 | AD34: 38915680 | AE34: Not Due | AF34: 88025 | AG34: 46113 | AH34: 46114 | AK34: INR | AL34: 1 | AM34: =N34*AL34 -> 71922.32 | AN34: =R34-AM34 -> 0 | AO34: =AM34 -> 71922.32 | AP34: =$AP$19-AH34 -> -2 | AQ34: =IF(AP34<0,"Not Due",IF(AP34<366,"Less than 1 year",IF(AP34<731,"1-2 years",IF(AP34<1096,"2-3 years","More than 3 years")))) -> Not Due
A35: GE India Industrial Pvt Ltd - GEITC | B35: GR16 | C35: 2070201000 | D35: Trade Accounts Payable-Subledge | E35: Cool India A39008 | F35: Non-IBS | G35: Domestic | I35: Opex | J35: CI/25-26/241 | K35: 100067488 | L35: 46088 | M35: INR | N35: 489741.8 | O35: 1 | P35: =N35*O35 -> 489741.8 | Q35: 1 | R35: =N35*Q35 -> 489741.8 | S35: =R35-P35 -> 0 | T35: Micro | U35: =$U$1-AH35 -> -21 | V35: 0 | W35: 0 | X35: 0 | Y35: 0 | Z35: 0 | AA35: 0 | AB35: 0 | AC35: =R35 -> 489741.8 | AD35: 39018010 | AE35: Not Due | AF35: 88355 | AG35: 46132 | AH35: 46133 | AK35: INR | AL35: 1 | AM35: =N35*AL35 -> 489741.8 | AN35: =R35-AM35 -> 0 | AO35: =AM35 -> 489741.8 | AP35: =$AP$19-AH35 -> -21 | AQ35: =IF(AP35<0,"Not Due",IF(AP35<366,"Less than 1 year",IF(AP35<731,"1-2 years",IF(AP35<1096,"2-3 years","More than 3 years")))) -> Not Due
A36: GE India Industrial Pvt Ltd - GEITC | B36: GR16 | C36: 2070201000 | D36: Trade Accounts Payable-Subledge | E36: Pro Team Solutions Private Limited A37469 | F36: Non-IBS | G36: Domestic | I36: Opex | J36: PTSB/25-26/4069 | K36: 100066019 | L36: 46082 | M36: INR | N36: 60111 | O36: 1 | P36: =N36*O36 -> 60111 | Q36: 1 | R36: =N36*Q36 -> 60111 | S36: =R36-P36 -> 0 | T36: Small | U36: =$U$1-AH36 -> -15 | V36: 0 | W36: 0 | X36: 0 | Y36: 0 | Z36: 0 | AA36: 0 | AB36: 0 | AC36: =R36 -> 60111 | AD36: 38977101 | AE36: Not Due | AF36: 88194 | AG36: 46125 | AH36: 46127 | AK36: INR | AL36: 1 | AM36: =N36*AL36 -> 60111 | AN36: =R36-AM36 -> 0 | AO36: =AM36 -> 60111 | AP36: =$AP$19-AH36 -> -15 | AQ36: =IF(AP36<0,"Not Due",IF(AP36<366,"Less than 1 year",IF(AP36<731,"1-2 years",IF(AP36<1096,"2-3 years","More than 3 years")))) -> Not Due
A37: GE India Industrial Pvt Ltd - GEITC | B37: GR16 | C37: 2070201000 | D37: Trade Accounts Payable-Subledge | E37: Altair Engineering India Pvt LTD A37670 | F37: Non-IBS | G37: Domestic | I37: Opex | J37: INVALKA-04049 | K37: 100066402 | L37: 45930 | M37: INR | N37: 2384640 | O37: 1 | P37: =N37*O37 -> 2384640 | Q37: 1 | R37: =N37*Q37 -> 2384640 | S37: =R37-P37 -> 0 | T37: Medium | U37: =$U$1-AH37 -> -16 | V37: 0 | W37: 0 | X37: 0 | Y37: 0 | Z37: 0 | AA37: 0 | AB37: 0 | AC37: =R37 -> 2384640 | AD37: 39012917 | AE37: Not Due | AF37: 88204 | AG37: 46125 | AH37: 46128 | AK37: INR | AL37: 1 | AM37: =N37*AL37 -> 2384640 | AN37: =R37-AM37 -> 0 | AO37: =AM37 -> 2384640 | AP37: =$AP$19-AH37 -> -16 | AQ37: =IF(AP37<0,"Not Due",IF(AP37<366,"Less than 1 year",IF(AP37<731,"1-2 years",IF(AP37<1096,"2-3 years","More than 3 years")))) -> Not Due
A38: GE India Industrial Pvt Ltd - GEITC | B38: GR16 | C38: 2070201000 | D38: Trade Accounts Payable-Subledge | E38: Juice Junction A38216 | F38: Non-IBS | G38: Domestic | I38: Opex | J38: JJ/2025-26/301 | K38: 100066527 | L38: 46100 | M38: INR | N38: 8240 | O38: 1 | P38: =N38*O38 -> 8240 | Q38: 1 | R38: =N38*Q38 -> 8240 | S38: =R38-P38 -> 0 | T38: Small | U38: =$U$1-AH38 -> -33 | V38: 0 | W38: 0 | X38: 0 | Y38: 0 | Z38: 0 | AA38: 0 | AB38: 0 | AC38: =R38 -> 8240 | AD38: 39036215 | AE38: Not Due | AF38: 88523 | AG38: 46143 | AH38: 46145 | AK38: INR | AL38: 1 | AM38: =N38*AL38 -> 8240 | AN38: =R38-AM38 -> 0 | AO38: =AM38 -> 8240 | AP38: =$AP$19-AH38 -> -33 | AQ38: =IF(AP38<0,"Not Due",IF(AP38<366,"Less than 1 year",IF(AP38<731,"1-2 years",IF(AP38<1096,"2-3 years","More than 3 years")))) -> Not Due
A39: GE India Industrial Pvt Ltd - GEITC | B39: GR16 | C39: 2070201000 | D39: Trade Accounts Payable-Subledge | E39: Lakshya Tech India Pvt LTD A37629 | F39: Non-IBS | G39: Domestic | I39: Opex | J39: M1537/25-26 | K39: 100070644 | L39: 46085 | M39: INR | N39: 446322.24 | O39: 1 | P39: =N39*O39 -> 446322.24 | Q39: 1 | R39: =N39*Q39 -> 446322.24 | S39: =R39-P39 -> 0 | T39: Small | U39: =$U$1-AH39 -> -3 | V39: 0 | W39: 0 | X39: 0 | Y39: 0 | Z39: 0 | AA39: 0 | AB39: 0 | AC39: =R39 -> 446322.24 | AD39: 38981852 | AE39: Not Due | AF39: 88013 | AG39: 46113 | AH39: 46115 | AK39: INR | AL39: 1 | AM39: =N39*AL39 -> 446322.24 | AN39: =R39-AM39 -> 0 | AO39: =AM39 -> 446322.24 | AP39: =$AP$19-AH39 -> -3 | AQ39: =IF(AP39<0,"Not Due",IF(AP39<366,"Less than 1 year",IF(AP39<731,"1-2 years",IF(AP39<1096,"2-3 years","More than 3 years")))) -> Not Due
A40: GE India Industrial Pvt Ltd - GEITC | B40: GR16 | C40: 2070201000 | D40: Trade Accounts Payable-Subledge | E40: Sheen Electroplaters Private Limited A38710 | F40: Non-IBS | G40: Domestic | I40: Opex | J40: 25-26/08745 | K40: 100070724 | L40: 46088 | M40: INR | N40: 111179.7 | O40: 1 | P40: =N40*O40 -> 111179.7 | Q40: 1 | R40: =N40*Q40 -> 111179.7 | S40: =R40-P40 -> 0 | T40: Small | U40: =$U$1-AH40 -> -21 | V40: 0 | W40: 0 | X40: 0 | Y40: 0 | Z40: 0 | AA40: 0 | AB40: 0 | AC40: =R40 -> 111179.7 | AD40: 38993167 | AE40: Not Due | AF40: 88345 | AG40: 46132 | AH40: 46133 | AK40: INR | AL40: 1 | AM40: =N40*AL40 -> 111179.7 | AN40: =R40-AM40 -> 0 | AO40: =AM40 -> 111179.7 | AP40: =$AP$19-AH40 -> -21 | AQ40: =IF(AP40<0,"Not Due",IF(AP40<366,"Less than 1 year",IF(AP40<731,"1-2 years",IF(AP40<1096,"2-3 years","More than 3 years")))) -> Not Due
A41: GE India Industrial Pvt Ltd - GEITC | B41: GR16 | C41: 2070201000 | D41: Trade Accounts Payable-Subledge | E41: BK INFRASYS PRIVATE LIMITED A39017 | F41: Non-IBS | G41: Domestic | I41: Opex | J41: 122/2025-26 | K41: 100066515 | L41: 46077 | M41: INR | N41: 37973.76 | O41: 1 | P41: =N41*O41 -> 37973.76 | Q41: 1 | R41: =N41*Q41 -> 37973.76 | S41: =R41-P41 -> 0 | T41: Small | U41: =$U$1-AH41 -> -10 | V41: 0 | W41: 0 | X41: 0 | Y41: 0 | Z41: 0 | AA41: 0 | AB41: 0 | AC41: =R41 -> 37973.76 | AD41: 38981682 | AE41: Not Due | AF41: 88119 | AG41: 46119 | AH41: 46122 | AK41: INR | AL41: 1 | AM41: =N41*AL41 -> 37973.76 | AN41: =R41-AM41 -> 0 | AO41: =AM41 -> 37973.76 | AP41: =$AP$19-AH41 -> -10 | AQ41: =IF(AP41<0,"Not Due",IF(AP41<366,"Less than 1 year",IF(AP41<731,"1-2 years",IF(AP41<1096,"2-3 years","More than 3 years")))) -> Not Due
A42: GE India Industrial Pvt Ltd - GEITC | B42: GR16 | C42: 2070201000 | D42: Trade Accounts Payable-Subledge | E42: S.S. Manpower Services Pvt LTD A37638 | F42: Non-IBS | G42: Domestic | I42: Opex | J42: SSMS/2025-26/353 | K42: 100068772 | L42: 46085 | M42: INR | N42: 55726.2 | O42: 1 | P42: =N42*O42 -> 55726.2 | Q42: 1 | R42: =N42*Q42 -> 55726.2 | S42: =R42-P42 -> 0 | T42: Micro | U42: =$U$1-AH42 -> -18 | V42: 0 | W42: 0 | X42: 0 | Y42: 0 | Z42: 0 | AA42: 0 | AB42: 0 | AC42: =R42 -> 55726.2 | AD42: 38983036 | AE42: Not Due | AF42: 88279 | AG42: 46127 | AH42: 46130 | AK42: INR | AL42: 1 | AM42: =N42*AL42 -> 55726.2 | AN42: =R42-AM42 -> 0 | AO42: =AM42 -> 55726.2 | AP42: =$AP$19-AH42 -> -18 | AQ42: =IF(AP42<0,"Not Due",IF(AP42<366,"Less than 1 year",IF(AP42<731,"1-2 years",IF(AP42<1096,"2-3 years","More than 3 years")))) -> Not Due
A43: GE India Industrial Pvt Ltd - GEITC | B43: GR16 | C43: 2070201000 | D43: Trade Accounts Payable-Subledge | E43: Bethur Unique Engineering LLP A38791 | F43: Non-IBS | G43: Domestic | I43: Opex | J43: DS2025666 | K43: 100070364 | L43: 46076 | M43: INR | N43: 15660 | O43: 1 | P43: =N43*O43 -> 15660 | Q43: 1 | R43: =N43*Q43 -> 15660 | S43: =R43-P43 -> 0 | T43: Micro | U43: =$U$1-AH43 -> -9 | V43: 0 | W43: 0 | X43: 0 | Y43: 0 | Z43: 0 | AA43: 0 | AB43: 0 | AC43: =R43 -> 15660 | AD43: 38927080 | AE43: Not Due | AF43: 88092 | AG43: 46118 | AH43: 46121 | AK43: INR | AL43: 1 | AM43: =N43*AL43 -> 15660 | AN43: =R43-AM43 -> 0 | AO43: =AM43 -> 15660 | AP43: =$AP$19-AH43 -> -9 | AQ43: =IF(AP43<0,"Not Due",IF(AP43<366,"Less than 1 year",IF(AP43<731,"1-2 years",IF(AP43<1096,"2-3 years","More than 3 years")))) -> Not Due
A44: GE India Industrial Pvt Ltd - GEITC | B44: GR16 | C44: 2070201000 | D44: Trade Accounts Payable-Subledge | E44: Equipment Fabricators A37538 | F44: Non-IBS | G44: Domestic | I44: Opex | J44: EF435/2025-26 | K44: 100070689 | L44: 46078 | M44: INR | N44: 22263.06 | O44: 1 | P44: =N44*O44 -> 22263.06 | Q44: 1 | R44: =N44*Q44 -> 22263.06 | S44: =R44-P44 -> 0 | T44: Small | U44: =$U$1-AH44 -> -11 | V44: 0 | W44: 0 | X44: 0 | Y44: 0 | Z44: 0 | AA44: 0 | AB44: 0 | AC44: =R44 -> 22263.06 | AD44: 38956621 | AE44: Not Due | AF44: 88127 | AG44: 46120 | AH44: 46123 | AK44: INR | AL44: 1 | AM44: =N44*AL44 -> 22263.06 | AN44: =R44-AM44 -> 0 | AO44: =AM44 -> 22263.06 | AP44: =$AP$19-AH44 -> -11 | AQ44: =IF(AP44<0,"Not Due",IF(AP44<366,"Less than 1 year",IF(AP44<731,"1-2 years",IF(AP44<1096,"2-3 years","More than 3 years")))) -> Not Due
... A59: GE India Industrial Pvt Ltd - GEITC | B59: GR16 | C59: 2070201000 | D59: Trade Accounts Payable-Subledge | E59: Touchstone Enterprises Private Limited A37818 | F59: Non-IBS | G59: Domestic | I59: Opex | J59: TSG-23261 | K59: 100070475 | L59: 46070 | M59: INR | N59: 51577.71 | O59: 1 | P59: =N59*O59 -> 51577.71 | Q59: 1 | R59: =N59*Q59 -> 51577.71 | S59: =R59-P59 -> 0 | T59: Micro | U59: =$U$1-AH59 -> -3 | V59: 0 | W59: 0 | X59: 0 | Y59: 0 | Z59: 0 | AA59: 0 | AB59: 0 | AC59: =R59 -> 51577.71 | AD59: 38927196 | AE59: Not Due | AF59: 88020 | AG59: 46113 | AH59: 46115 | AK59: INR | AL59: 1 | AM59: =N59*AL59 -> 51577.71 | AN59: =R59-AM59 -> 0 | AO59: =AM59 -> 51577.71 | AP59: =$AP$19-AH59 -> -3 | AQ59: =IF(AP59<0,"Not Due",IF(AP59<366,"Less than 1 year",IF(AP59<731,"1-2 years",IF(AP59<1096,"2-3 years","More than 3 years")))) -> Not Due
A60: GE India Industrial Pvt Ltd - GEITC | B60: GR16 | C60: 2070201000 | D60: Trade Accounts Payable-Subledge | E60: 3D Z NATION | F60: Non-IBS | G60: Domestic | I60: Opex | J60: 202593 | K60: 100070870 | L60: 46069 | M60: INR | N60: 11318.4 | O60: 1 | P60: =N60*O60 -> 11318.4 | Q60: 1 | R60: =N60*Q60 -> 11318.4 | S60: =R60-P60 -> 0 | T60: Micro | U60: =$U$1-AH60 -> -2 | V60: 0 | W60: 0 | X60: 0 | Y60: 0 | Z60: 0 | AA60: 0 | AB60: 0 | AC60: =R60 -> 11318.4 | AD60: 38887950 | AE60: Not Due | AF60: 87983 | AG60: 46113 | AH60: 46114 | AK60: INR | AL60: 1 | AM60: =N60*AL60 -> 11318.4 | AN60: =R60-AM60 -> 0 | AO60: =AM60 -> 11318.4 | AP60: =$AP$19-AH60 -> -2 | AQ60: =IF(AP60<0,"Not Due",IF(AP60<366,"Less than 1 year",IF(AP60<731,"1-2 years",IF(AP60<1096,"2-3 years","More than 3 years")))) -> Not Due
A61: GE India Industrial Pvt Ltd - GEITC | B61: GR16 | C61: 2070201000 | D61: Trade Accounts Payable-Subledge | E61: Bethur Unique Engineering LLP A38791 | F61: Non-IBS | G61: Domestic | I61: Opex | J61: DS2025679 | K61: 100070968 | L61: 46080 | M61: INR | N61: 29232 | O61: 1 | P61: =N61*O61 -> 29232 | Q61: 1 | R61: =N61*Q61 -> 29232 | S61: =R61-P61 -> 0 | T61: Micro | U61: =$U$1-AH61 -> -13 | V61: 0 | W61: 0 | X61: 0 | Y61: 0 | Z61: 0 | AA61: 0 | AB61: 0 | AC61: =R61 -> 29232 | AD61: 38956812 | AE61: Not Due | AF61: 88180 | AG61: 46122 | AH61: 46125 | AK61: INR | AL61: 1 | AM61: =N61*AL61 -> 29232 | AN61: =R61-AM61 -> 0 | AO61: =AM61 -> 29232 | AP61: =$AP$19-AH61 -> -13 | AQ61: =IF(AP61<0,"Not Due",IF(AP61<366,"Less than 1 year",IF(AP61<731,"1-2 years",IF(AP61<1096,"2-3 years","More than 3 years")))) -> Not Due
A62: GE India Industrial Pvt Ltd - GEITC | B62: GR16 | C62: 2070201000 | D62: Trade Accounts Payable-Subledge | E62: Netsign Inc A37871 | F62: Non-IBS | G62: Domestic | I62: Opex | J62: 229/2025-26 | K62: 100070434 | L62: 46072 | M62: INR | N62: 4909.21 | O62: 1 | P62: =N62*O62 -> 4909.21 | Q62: 1 | R62: =N62*Q62 -> 4909.21 | S62: =R62-P62 -> 0 | T62: Micro | U62: =$U$1-AH62 -> -5 | V62: 0 | W62: 0 | X62: 0 | Y62: 0 | Z62: 0 | AA62: 0 | AB62: 0 | AC62: =R62 -> 4909.21 | AD62: 38938484 | AE62: Not Due | AF62: 88048 | AG62: 46114 | AH62: 46117 | AK62: INR | AL62: 1 | AM62: =N62*AL62 -> 4909.21 | AN62: =R62-AM62 -> 0 | AO62: =AM62 -> 4909.21 | AP62: =$AP$19-AH62 -> -5 | AQ62: =IF(AP62<0,"Not Due",IF(AP62<366,"Less than 1 year",IF(AP62<731,"1-2 years",IF(AP62<1096,"2-3 years","More than 3 years")))) -> Not Due
A63: GE India Industrial Pvt Ltd - GEITC | B63: GR16 | C63: 2070201000 | D63: Trade Accounts Payable-Subledge | E63: Shobha Electricals A37602 | F63: Non-IBS | G63: Domestic | I63: Capex | J63: SER/478/25-26 | K63: 100068781 | L63: 46093 | M63: INR | N63: 216000 | O63: 1 | P63: =N63*O63 -> 216000 | Q63: 1 | R63: =N63*Q63 -> 216000 | S63: =R63-P63 -> 0 | T63: Small | U63: =$U$1-AH63 -> -26 | V63: 0 | W63: 0 | X63: 0 | Y63: 0 | Z63: 0 | AA63: 0 | AB63: 0 | AC63: =R63 -> 216000 | AD63: 39028902 | AE63: Not Due | AF63: 88402 | AG63: 46135 | AH63: 46138 | AK63: INR | AL63: 1 | AM63: =N63*AL63 -> 216000 | AN63: =R63-AM63 -> 0 | AO63: =AM63 -> 216000 | AP63: =$AP$19-AH63 -> -26 | AQ63: =IF(AP63<0,"Not Due",IF(AP63<366,"Less than 1 year",IF(AP63<731,"1-2 years",IF(AP63<1096,"2-3 years","More than 3 years")))) -> Not Due
A64: GE India Industrial Pvt Ltd - GEITC | B64: GR16 | C64: 2070201000 | D64: Trade Accounts Payable-Subledge | E64: Bethur Unique Engineering LLP A38791 | F64: Non-IBS | G64: Domestic | I64: Opex | J64: DS2025691 | K64: 100070850 | L64: 46085 | M64: INR | N64: 15660 | O64: 1 | P64: =N64*O64 -> 15660 | Q64: 1 | R64: =N64*Q64 -> 15660 | S64: =R64-P64 -> 0 | T64: Micro | U64: =$U$1-AH64 -> -18 | V64: 0 | W64: 0 | X64: 0 | Y64: 0 | Z64: 0 | AA64: 0 | AB64: 0 | AC64: =R64 -> 15660 | AD64: 38965607 | AE64: Not Due | AF64: 88289 | AG64: 46127 | AH64: 46130 | AK64: INR | AL64: 1 | AM64: =N64*AL64 -> 15660 | AN64: =R64-AM64 -> 0 | AO64: =AM64 -> 15660 | AP64: =$AP$19-AH64 -> -18 | AQ64: =IF(AP64<0,"Not Due",IF(AP64<366,"Less than 1 year",IF(AP64<731,"1-2 years",IF(AP64<1096,"2-3 years","More than 3 years")))) -> Not Due
A65: GE India Industrial Pvt Ltd - GEITC | B65: GR16 | C65: 2070201000 | D65: Trade Accounts Payable-Subledge | E65: Bethur Unique Engineering LLP A38791 | F65: Non-IBS | G65: Domestic | I65: Opex | J65: DS2025653 | K65: 100069577 | L65: 46069 | M65: INR | N65: 14616 | O65: 1 | P65: =N65*O65 -> 14616 | Q65: 1 | R65: =N65*Q65 -> 14616 | S65: =R65-P65 -> 0 | T65: Micro | U65: =$U$1-AH65 -> -2 | V65: 0 | W65: 0 | X65: 0 | Y65: 0 | Z65: 0 | AA65: 0 | AB65: 0 | AC65: =R65 -> 14616 | AD65: 38887928 | AE65: Not Due | AF65: 88038 | AG65: 46113 | AH65: 46114 | AK65: INR | AL65: 1 | AM65: =N65*AL65 -> 14616 | AN65: =R65-AM65 -> 0 | AO65: =AM65 -> 14616 | AP65: =$AP$19-AH65 -> -2 | AQ65: =IF(AP65<0,"Not Due",IF(AP65<366,"Less than 1 year",IF(AP65<731,"1-2 years",IF(AP65<1096,"2-3 years","More than 3 years")))) -> Not Due
A66: GE India Industrial Pvt Ltd - GEITC | B66: GR16 | C66: 2070201000 | D66: Trade Accounts Payable-Subledge | E66: Harshini Industries A39087 | F66: Non-IBS | G66: Domestic | I66: Opex | J66: 777 | K66: 100070391 | L66: 46077 | M66: INR | N66: 6032 | O66: 1 | P66: =N66*O66 -> 6032 | Q66: 1 | R66: =N66*Q66 -> 6032 | S66: =R66-P66 -> 0 | T66: Micro | U66: =$U$1-AH66 -> -10 | V66: 0 | W66: 0 | X66: 0 | Y66: 0 | Z66: 0 | AA66: 0 | AB66: 0 | AC66: =R66 -> 6032 | AD66: 38938489 | AE66: Not Due | AF66: 88120 | AG66: 46119 | AH66: 46122 | AK66: INR | AL66: 1 | AM66: =N66*AL66 -> 6032 | AN66: =R66-AM66 -> 0 | AO66: =AM66 -> 6032 | AP66: =$AP$19-AH66 -> -10 | AQ66: =IF(AP66<0,"Not Due",IF(AP66<366,"Less than 1 year",IF(AP66<731,"1-2 years",IF(AP66<1096,"2-3 years","More than 3 years")))) -> Not Due
A67: GE India Industrial Pvt Ltd - GEITC | B67: GR16 | C67: 2070201000 | D67: Trade Accounts Payable-Subledge | E67: RCS Tech LLP A37688 | F67: Non-IBS | G67: Domestic | I67: Opex | J67: RCSL/2526/519 | K67: 100070739 | L67: 46083 | M67: INR | N67: 100465.92 | O67: 1 | P67: =N67*O67 -> 100465.92 | Q67: 1 | R67: =N67*Q67 -> 100465.92 | S67: =R67-P67 -> 0 | T67: Medium | U67: =$U$1-AH67 -> -16 | V67: 0 | W67: 0 | X67: 0 | Y67: 0 | Z67: 0 | AA67: 0 | AB67: 0 | AC67: =R67 -> 100465.92 | AD67: 38956841 | AE67: Not Due | AF67: 88205 | AG67: 46125 | AH67: 46128 | AK67: INR | AL67: 1 | AM67: =N67*AL67 -> 100465.92 | AN67: =R67-AM67 -> 0 | AO67: =AM67 -> 100465.92 | AP67: =$AP$19-AH67 -> -16 | AQ67: =IF(AP67<0,"Not Due",IF(AP67<366,"Less than 1 year",IF(AP67<731,"1-2 years",IF(AP67<1096,"2-3 years","More than 3 years")))) -> Not Due
A68: GE India Industrial Pvt Ltd - GEITC | B68: GR16 | C68: 2070201000 | D68: Trade Accounts Payable-Subledge | E68: A V Engineering Works A37650 | F68: Non-IBS | G68: Domestic | I68: Opex | J68: 672 | K68: 100071303 | L68: 46098 | M68: INR | N68: 20043 | O68: 1 | P68: =N68*O68 -> 20043 | Q68: 1 | R68: =N68*Q68 -> 20043 | S68: =R68-P68 -> 0 | T68: Micro | U68: =$U$1-AH68 -> -31 | V68: 0 | W68: 0 | X68: 0 | Y68: 0 | Z68: 0 | AA68: 0 | AB68: 0 | AC68: =R68 -> 20043 | AD68: 39036033 | AE68: Not Due | AF68: 88509 | AG68: 46143 | AH68: 46143 | AK68: INR | AL68: 1 | AM68: =N68*AL68 -> 20043 | AN68: =R68-AM68 -> 0 | AO68: =AM68 -> 20043 | AP68: =$AP$19-AH68 -> -31 | AQ68: =IF(AP68<0,"Not Due",IF(AP68<366,"Less than 1 year",IF(AP68<731,"1-2 years",IF(AP68<1096,"2-3 years","More than 3 years")))) -> Not Due
A69: GE India Industrial Pvt Ltd - GEITC | B69: GR16 | C69: 2070201000 | D69: Trade Accounts Payable-Subledge | E69: EVENFLOW EXPERIENCES PRIVATE LIMITED | F69: Non-IBS | G69: Domestic | I69: Opex | J69: EEPL/25-26/251 | K69: 100071369 | L69: 46101 | M69: INR | N69: 38280 | O69: 1 | P69: =N69*O69 -> 38280 | Q69: 1 | R69: =N69*Q69 -> 38280 | S69: =R69-P69 -> 0 | T69: Micro | U69: =$U$1-AH69 -> -34 | V69: 0 | W69: 0 | X69: 0 | Y69: 0 | Z69: 0 | AA69: 0 | AB69: 0 | AC69: =R69 -> 38280 | AD69: 39029842 | AE69: Not Due | AF69: 88475 | AG69: 46143 | AH69: 46146 | AK69: INR | AL69: 1 | AM69: =N69*AL69 -> 38280 | AN69: =R69-AM69 -> 0 | AO69: =AM69 -> 38280 | AP69: =$AP$19-AH69 -> -34 | AQ69: =IF(AP69<0,"Not Due",IF(AP69<366,"Less than 1 year",IF(AP69<731,"1-2 years",IF(AP69<1096,"2-3 years","More than 3 years")))) -> Not Due
A70: GE India Industrial Pvt Ltd - GEITC | B70: GR16 | C70: 2070201000 | D70: Trade Accounts Payable-Subledge | E70: S.S. Manpower Services Pvt LTD A37638 | F70: Non-IBS | G70: Domestic | I70: Opex | J70: SSMS/2025-26/351 | K70: 100065913 | L70: 46085 | M70: INR | N70: 43775.26 | O70: 1 | P70: =N70*O70 -> 43775.26 | Q70: 1 | R70: =N70*Q70 -> 43775.26 | S70: =R70-P70 -> 0 | T70: Micro | U70: =$U$1-AH70 -> -18 | V70: 0 | W70: 0 | X70: 0 | Y70: 0 | Z70: 0 | AA70: 0 | AB70: 0 | AC70: =R70 -> 43775.26 | AD70: 38981690 | AE70: Not Due | AF70: 88279 | AG70: 46127 | AH70: 46130 | AK70: INR | AL70: 1 | AM70: =N70*AL70 -> 43775.26 | AN70: =R70-AM70 -> 0 | AO70: =AM70 -> 43775.26 | AP70: =$AP$19-AH70 -> -18 | AQ70: =IF(AP70<0,"Not Due",IF(AP70<366,"Less than 1 year",IF(AP70<731,"1-2 years",IF(AP70<1096,"2-3 years","More than 3 years")))) -> Not Due
A71: GE India Industrial Pvt Ltd - GEITC | B71: GR16 | C71: 2070201000 | D71: Trade Accounts Payable-Subledge | E71: CHANDRODAYA ELECTRICALS A38327 | F71: Non-IBS | G71: Domestic | I71: Opex | J71: 139/2025-26 | K71: 100070901 | L71: 46084 | M71: INR | N71: 144875.12 | O71: 1 | P71: =N71*O71 -> 144875.12 | Q71: 1 | R71: =N71*Q71 -> 144875.12 | S71: =R71-P71 -> 0 | T71: Micro | U71: =$U$1-AH71 -> -17 | V71: 0 | W71: 0 | X71: 0 | Y71: 0 | Z71: 0 | AA71: 0 | AB71: 0 | AC71: =R71 -> 144875.12 | AD71: 38964797 | AE71: Not Due | AF71: 88257 | AG71: 46126 | AH71: 46129 | AK71: INR | AL71: 1 | AM71: =N71*AL71 -> 144875.12 | AN71: =R71-AM71 -> 0 | AO71: =AM71 -> 144875.12 | AP71: =$AP$19-AH71 -> -17 | AQ71: =IF(AP71<0,"Not Due",IF(AP71<366,"Less than 1 year",IF(AP71<731,"1-2 years",IF(AP71<1096,"2-3 years","More than 3 years")))) -> Not Due
A72: GE India Industrial Pvt Ltd - GEITC | B72: GR16 | C72: 2070201000 | D72: Trade Accounts Payable-Subledge | E72: Aaliaado A37863 | F72: Non-IBS | G72: Domestic | I72: Opex | J72: A/25-26/85 | K72: 100070881 | L72: 46086 | M72: INR | N72: 72444.55 | O72: 1 | P72: =N72*O72 -> 72444.55 | Q72: 1 | R72: =N72*Q72 -> 72444.55 | S72: =R72-P72 -> 0 | T72: Micro | U72: =$U$1-AH72 -> -19 | V72: 0 | W72: 0 | X72: 0 | Y72: 0 | Z72: 0 | AA72: 0 | AB72: 0 | AC72: =R72 -> 72444.55 | AD72: 38987424 | AE72: Not Due | AF72: 88514 | AG72: 46143 | AH72: 46131 | AK72: INR | AL72: 1 | AM72: =N72*AL72 -> 72444.55 | AN72: =R72-AM72 -> 0 | AO72: =AM72 -> 72444.55 | AP72: =$AP$19-AH72 -> -19 | AQ72: =IF(AP72<0,"Not Due",IF(AP72<366,"Less than 1 year",IF(AP72<731,"1-2 years",IF(AP72<1096,"2-3 years","More than 3 years")))) -> Not Due
A73: GE India Industrial Pvt Ltd - GEITC | B73: GR16 | C73: 2070201000 | D73: Trade Accounts Payable-Subledge | E73: Shobha Electricals A37602 | F73: Non-IBS | G73: Domestic | I73: Opex | J73: SER/451/25-26 | K73: 100066239 | L73: 46083 | M73: INR | N73: 83409.9 | O73: 1 | P73: =N73*O73 -> 83409.9 | Q73: 1 | R73: =N73*Q73 -> 83409.9 | S73: =R73-P73 -> 0 | T73: Small | U73: =$U$1-AH73 -> -16 | V73: 0 | W73: 0 | X73: 0 | Y73: 0 | Z73: 0 | AA73: 0 | AB73: 0 | AC73: =R73 -> 83409.9 | AD73: 39008019 | AE73: Not Due | AF73: 88201 | AG73: 46125 | AH73: 46128 | AK73: INR | AL73: 1 | AM73: =N73*AL73 -> 83409.9 | AN73: =R73-AM73 -> 0 | AO73: =AM73 -> 83409.9 | AP73: =$AP$19-AH73 -> -16 | AQ73: =IF(AP73<0,"Not Due",IF(AP73<366,"Less than 1 year",IF(AP73<731,"1-2 years",IF(AP73<1096,"2-3 years","More than 3 years")))) -> Not Due
A74: GE India Industrial Pvt Ltd - GEITC | B74: GR16 | C74: 2070201000 | D74: Trade Accounts Payable-Subledge | E74: BNB Security and Automation Solutions (P) Ltd A37563 | F74: Non-IBS | G74: Domestic | I74: Opex | J74: TI/25-26/3182 | K74: 100069080 | L74: 46093 | M74: INR | N74: 141810 | O74: 1 | P74: =N74*O74 -> 141810 | Q74: 1 | R74: =N74*Q74 -> 141810 | S74: =R74-P74 -> 0 | T74: Medium | U74: =$U$1-AH74 -> -26 | V74: 0 | W74: 0 | X74: 0 | Y74: 0 | Z74: 0 | AA74: 0 | AB74: 0 | AC74: =R74 -> 141810 | AD74: 39037138 | AE74: Not Due | AF74: 88401 | AG74: 46135 | AH74: 46138 | AK74: INR | AL74: 1 | AM74: =N74*AL74 -> 141810 | AN74: =R74-AM74 -> 0 | AO74: =AM74 -> 141810 | AP74: =$AP$19-AH74 -> -26 | AQ74: =IF(AP74<0,"Not Due",IF(AP74<366,"Less than 1 year",IF(AP74<731,"1-2 years",IF(AP74<1096,"2-3 years","More than 3 years")))) -> Not Due
A75: GE India Industrial Pvt Ltd - GEITC | B75: GR16 | C75: 2070201000 | D75: Trade Accounts Payable-Subledge | E75: Dwija Foods Private Limited A38747 | F75: Non-IBS | G75: Domestic | I75: Opex | J75: B-C-25-26-0382 | K75: 100070292 | L75: 46081 | M75: INR | N75: 210952.88 | O75: 1 | P75: =N75*O75 -> 210952.88 | Q75: 1 | R75: =N75*Q75 -> 210952.88 | S75: =R75-P75 -> 0 | T75: Micro | U75: =$U$1-AH75 -> -14 | V75: 0 | W75: 0 | X75: 0 | Y75: 0 | Z75: 0 | AA75: 0 | AB75: 0 | AC75: =R75 -> 210952.88 | AD75: 38959864 | AE75: Not Due | AF75: 88222 | AG75: 46125 | AH75: 46126 | AK75: INR | AL75: 1 | AM75: =N75*AL75 -> 210952.88 | AN75: =R75-AM75 -> 0 | AO75: =AM75 -> 210952.88 | AP75: =$AP$19-AH75 -> -14 | AQ75: =IF(AP75<0,"Not Due",IF(AP75<366,"Less than 1 year",IF(AP75<731,"1-2 years",IF(AP75<1096,"2-3 years","More than 3 years")))) -> Not Due
A76: GE India Industrial Pvt Ltd - GEITC | B76: GR16 | C76: 2070201000 | D76: Trade Accounts Payable-Subledge | E76: Bethur Unique Engineering LLP A38791 | F76: Non-IBS | G76: Domestic | I76: Opex | J76: DS2025688 | K76: 100070364 | L76: 46083 | M76: INR | N76: 28188 | O76: 1 | P76: =N76*O76 -> 28188 | Q76: 1 | R76: =N76*Q76 -> 28188 | S76: =R76-P76 -> 0 | T76: Micro | U76: =$U$1-AH76 -> -16 | V76: 0 | W76: 0 | X76: 0 | Y76: 0 | Z76: 0 | AA76: 0 | AB76: 0 | AC76: =R76 -> 28188 | AD76: 38956588 | AE76: Not Due | AF76: 88224 | AG76: 46125 | AH76: 46128 | AK76: INR | AL76: 1 | AM76: =N76*AL76 -> 28188 | AN76: =R76-AM76 -> 0 | AO76: =AM76 -> 28188 | AP76: =$AP$19-AH76 -> -16 | AQ76: =IF(AP76<0,"Not Due",IF(AP76<366,"Less than 1 year",IF(AP76<731,"1-2 years",IF(AP76<1096,"2-3 years","More than 3 years")))) -> Not Due
A77: GE India Industrial Pvt Ltd - GEITC | B77: GR16 | C77: 2070201000 | D77: Trade Accounts Payable-Subledge | E77: Shobha Electricals A37602 | F77: Non-IBS | G77: Domestic | I77: Capex | J77: SER/449/25-26 | K77: 100070441 | L77: 46083 | M77: INR | N77: 36540 | O77: 1 | P77: =N77*O77 -> 36540 | Q77: 1 | R77: =N77*Q77 -> 36540 | S77: =R77-P77 -> 0 | T77: Small | U77: =$U$1-AH77 -> -16 | V77: 0 | W77: 0 | X77: 0 | Y77: 0 | Z77: 0 | AA77: 0 | AB77: 0 | AC77: =R77 -> 36540 | AD77: 38976338 | AE77: Not Due | AF77: 88201 | AG77: 46125 | AH77: 46128 | AK77: INR | AL77: 1 | AM77: =N77*AL77 -> 36540 | AN77: =R77-AM77 -> 0 | AO77: =AM77 -> 36540 | AP77: =$AP$19-AH77 -> -16 | AQ77: =IF(AP77<0,"Not Due",IF(AP77<366,"Less than 1 year",IF(AP77<731,"1-2 years",IF(AP77<1096,"2-3 years","More than 3 years")))) -> Not Due
A78: GE India Industrial Pvt Ltd - GEITC | B78: GR16 | C78: 2070201000 | D78: Trade Accounts Payable-Subledge | E78: Adarsh Solutions Private Limited A37489 | F78: Non-IBS | G78: Domestic | I78: Opex | J78: AS26MAR612 | K78: 100065980 | L78: 46087 | M78: INR | N78: 50583.96 | O78: 1 | P78: =N78*O78 -> 50583.96 | Q78: 1 | R78: =N78*Q78 -> 50583.96 | S78: =R78-P78 -> 0 | T78: Micro | U78: =$U$1-AH78 -> -20 | V78: 0 | W78: 0 | X78: 0 | Y78: 0 | Z78: 0 | AA78: 0 | AB78: 0 | AC78: =R78 -> 50583.96 | AD78: 38998928 | AE78: Not Due | AF78: 88310 | AG78: 46129 | AH78: 46132 | AK78: INR | AL78: 1 | AM78: =N78*AL78 -> 50583.96 | AN78: =R78-AM78 -> 0 | AO78: =AM78 -> 50583.96 | AP78: =$AP$19-AH78 -> -20 | AQ78: =IF(AP78<0,"Not Due",IF(AP78<366,"Less than 1 year",IF(AP78<731,"1-2 years",IF(AP78<1096,"2-3 years","More than 3 years")))) -> Not Due
A79: GE India Industrial Pvt Ltd - GEITC | B79: GR16 | C79: 2070201000 | D79: Trade Accounts Payable-Subledge | E79: Chemix Specialty Gases and Equipment A37836 | F79: Non-IBS | G79: Domestic | I79: Opex | J79: CH/2025-26/3463 | K79: 100071031 | L79: 46087 | M79: INR | N79: 19394.55 | O79: 1 | P79: =N79*O79 -> 19394.55 | Q79: 1 | R79: =N79*Q79 -> 19394.55 | S79: =R79-P79 -> 0 | T79: Small | U79: =$U$1-AH79 -> -5 | V79: 0 | W79: 0 | X79: 0 | Y79: 0 | Z79: 0 | AA79: 0 | AB79: 0 | AC79: =R79 -> 19394.55 | AD79: 38987440 | AE79: Not Due | AF79: 88046 | AG79: 46114 | AH79: 46117 | AK79: INR | AL79: 1 | AM79: =N79*AL79 -> 19394.55 | AN79: =R79-AM79 -> 0 | AO79: =AM79 -> 19394.55 | AP79: =$AP$19-AH79 -> -5 | AQ79: =IF(AP79<0,"Not Due",IF(AP79<366,"Less than 1 year",IF(AP79<731,"1-2 years",IF(AP79<1096,"2-3 years","More than 3 years")))) -> Not Due
A80: GE India Industrial Pvt Ltd - GEITC | B80: GR16 | C80: 2070201000 | D80: Trade Accounts Payable-Subledge | E80: The Zuri Whitefield Bangalore A38985 | F80: Non-IBS | G80: Domestic | I80: Opex | J80: 10012794 | K80: 100071242 | L80: 46094 | M80: INR | N80: 11542 | O80: 1 | P80: =N80*O80 -> 11542 | Q80: 1 | R80: =N80*Q80 -> 11542 | S80: =R80-P80 -> 0 | T80: Small | U80: =$U$1-AH80 -> -12 | V80: 0 | W80: 0 | X80: 0 | Y80: 0 | Z80: 0 | AA80: 0 | AB80: 0 | AC80: =R80 -> 11542 | AD80: 39036059 | AE80: Not Due | AF80: 88170 | AG80: 46121 | AH80: 46124 | AK80: INR | AL80: 1 | AM80: =N80*AL80 -> 11542 | AN80: =R80-AM80 -> 0 | AO80: =AM80 -> 11542 | AP80: =$AP$19-AH80 -> -12 | AQ80: =IF(AP80<0,"Not Due",IF(AP80<366,"Less than 1 year",IF(AP80<731,"1-2 years",IF(AP80<1096,"2-3 years","More than 3 years")))) -> Not Due
A81: GE India Industrial Pvt Ltd - GEITC | B81: GR16 | C81: 2070201000 | D81: Trade Accounts Payable-Subledge | E81: WORKPLACE OPTIONS INDIA PRIVATE LIMITED | F81: Non-IBS | G81: Domestic | I81: Opex | J81: 63/26-IN | K81: 100069627 | L81: 46091 | M81: INR | N81: 87307.2 | O81: 1 | P81: =N81*O81 -> 87307.2 | Q81: 1 | R81: =N81*Q81 -> 87307.2 | S81: =R81-P81 -> 0 | T81: Small | U81: =$U$1-AH81 -> -24 | V81: 0 | W81: 0 | X81: 0 | Y81: 0 | Z81: 0 | AA81: 0 | AB81: 0 | AC81: =R81 -> 87307.2 | AD81: 39017987 | AE81: Not Due | AF81: 88378 | AG81: 46133 | AH81: 46136 | AK81: INR | AL81: 1 | AM81: =N81*AL81 -> 87307.2 | AN81: =R81-AM81 -> 0 | AO81: =AM81 -> 87307.2 | AP81: =$AP$19-AH81 -> -24 | AQ81: =IF(AP81<0,"Not Due",IF(AP81<366,"Less than 1 year",IF(AP81<731,"1-2 years",IF(AP81<1096,"2-3 years","More than 3 years")))) -> Not Due
A82: GE India Industrial Pvt Ltd - GEITC | B82: GR16 | C82: 2070201000 | D82: Trade Accounts Payable-Subledge | E82: World Of Opportunities For Women LLP A38514 | F82: Non-IBS | G82: Domestic | I82: Opex | J82: INV-C-202526155 | K82: 100070571 | L82: 46086 | M82: INR | N82: 127657.08 | O82: 1 | P82: =N82*O82 -> 127657.08 | Q82: 1 | R82: =N82*Q82 -> 127657.08 | S82: =R82-P82 -> 0 | T82: Micro | U82: =$U$1-AH82 -> -4 | V82: 0 | W82: 0 | X82: 0 | Y82: 0 | Z82: 0 | AA82: 0 | AB82: 0 | AC82: =R82 -> 127657.08 | AD82: 38988095 | AE82: Not Due | AF82: 88035 | AG82: 46113 | AH82: 46116 | AK82: INR | AL82: 1 | AM82: =N82*AL82 -> 127657.08 | AN82: =R82-AM82 -> 0 | AO82: =AM82 -> 127657.08 | AP82: =$AP$19-AH82 -> -4 | AQ82: =IF(AP82<0,"Not Due",IF(AP82<366,"Less than 1 year",IF(AP82<731,"1-2 years",IF(AP82<1096,"2-3 years","More than 3 years")))) -> Not Due
A83: GE India Industrial Pvt Ltd - GEITC | B83: GR16 | C83: 2070201000 | D83: Trade Accounts Payable-Subledge | E83: Bethur Unique Engineering LLP A38791 | F83: Non-IBS | G83: Domestic | I83: Opex | J83: DS2025709 | K83: 100071159 | L83: 46091 | M83: INR | N83: 6264 | O83: 1 | P83: =N83*O83 -> 6264 | Q83: 1 | R83: =N83*Q83 -> 6264 | S83: =R83-P83 -> 0 | T83: Micro | U83: =$U$1-AH83 -> -24 | V83: 0 | W83: 0 | X83: 0 | Y83: 0 | Z83: 0 | AA83: 0 | AB83: 0 | AC83: =R83 -> 6264 | AD83: 38993163 | AE83: Not Due | AF83: 88363 | AG83: 46133 | AH83: 46136 | AK83: INR | AL83: 1 | AM83: =N83*AL83 -> 6264 | AN83: =R83-AM83 -> 0 | AO83: =AM83 -> 6264 | AP83: =$AP$19-AH83 -> -24 | AQ83: =IF(AP83<0,"Not Due",IF(AP83<366,"Less than 1 year",IF(AP83<731,"1-2 years",IF(AP83<1096,"2-3 years","More than 3 years")))) -> Not Due
A84: GE India Industrial Pvt Ltd - GEITC | B84: GR16 | C84: 2070201000 | D84: Trade Accounts Payable-Subledge | E84: RCS Tech LLP A37688 | F84: Non-IBS | G84: Domestic | I84: Opex | J84: RCSL/2526/520 | K84: 100070734 | L84: 46083 | M84: INR | N84: 276886.08 | O84: 1 | P84: =N84*O84 -> 276886.08 | Q84: 1 | R84: =N84*Q84 -> 276886.08 | S84: =R84-P84 -> 0 | T84: Medium | U84: =$U$1-AH84 -> -16 | V84: 0 | W84: 0 | X84: 0 | Y84: 0 | Z84: 0 | AA84: 0 | AB84: 0 | AC84: =R84 -> 276886.08 | AD84: 38964841 | AE84: Not Due | AF84: 88205 | AG84: 46125 | AH84: 46128 | AK84: INR | AL84: 1 | AM84: =N84*AL84 -> 276886.08 | AN84: =R84-AM84 -> 0 | AO84: =AM84 -> 276886.08 | AP84: =$AP$19-AH84 -> -16 | AQ84: =IF(AP84<0,"Not Due",IF(AP84<366,"Less than 1 year",IF(AP84<731,"1-2 years",IF(AP84<1096,"2-3 years","More than 3 years")))) -> Not Due
A85: GE India Industrial Pvt Ltd - GEITC | B85: GR16 | C85: 2070201000 | D85: Trade Accounts Payable-Subledge | E85: BRILYANT IT SOLUTIONS PRIVATE LIMITED A36745 | F85: Non-IBS | G85: Domestic | I85: Opex | J85: BITS25-26S6531 | K85: 100070409 | L85: 46069 | M85: INR | N85: 4463.69 | O85: 1 | P85: =N85*O85 -> 4463.69 | Q85: 1 | R85: =N85*Q85 -> 4463.69 | S85: =R85-P85 -> 0 | T85: Small | U85: =$U$1-AH85 -> -2 | V85: 0 | W85: 0 | X85: 0 | Y85: 0 | Z85: 0 | AA85: 0 | AB85: 0 | AC85: =R85 -> 4463.69 | AD85: 38888599 | AE85: Not Due | AF85: 87995 | AG85: 46113 | AH85: 46114 | AK85: INR | AL85: 1 | AM85: =N85*AL85 -> 4463.69 | AN85: =R85-AM85 -> 0 | AO85: =AM85 -> 4463.69 | AP85: =$AP$19-AH85 -> -2 | AQ85: =IF(AP85<0,"Not Due",IF(AP85<366,"Less than 1 year",IF(AP85<731,"1-2 years",IF(AP85<1096,"2-3 years","More than 3 years")))) -> Not Due
A86: GE India Industrial Pvt Ltd - GEITC | B86: GR16 | C86: 2070201000 | D86: Trade Accounts Payable-Subledge | E86: Altair Engineering India Pvt LTD A37670 | F86: Non-IBS | G86: Domestic | I86: Opex | J86: INVALKA-04578 | K86: 100066402 | L86: 46097 | M86: INR | N86: 1987200 | O86: 1 | P86: =N86*O86 -> 1987200 | Q86: 1 | R86: =N86*Q86 -> 1987200 | S86: =R86-P86 -> 0 | T86: Medium | U86: =$U$1-AH86 -> -15 | V86: 0 | W86: 0 | X86: 0 | Y86: 0 | Z86: 0 | AA86: 0 | AB86: 0 | AC86: =R86 -> 1987200 | AD86: 39036073 | AE86: Not Due | AF86: 88204 | AG86: 46125 | AH86: 46127 | AK86: INR | AL86: 1 | AM86: =N86*AL86 -> 1987200 | AN86: =R86-AM86 -> 0 | AO86: =AM86 -> 1987200 | AP86: =$AP$19-AH86 -> -15 | AQ86: =IF(AP86<0,"Not Due",IF(AP86<366,"Less than 1 year",IF(AP86<731,"1-2 years",IF(AP86<1096,"2-3 years","More than 3 years")))) -> Not Due
A87: GE India Industrial Pvt Ltd - GEITC | B87: GR16 | C87: 2070201000 | D87: Trade Accounts Payable-Subledge | E87: Scientific Research Instruments Company Private Limited A39031 | F87: Non-IBS | G87: Domestic | I87: Opex | J87: 2526/1186 | K87: 100071064 | L87: 46084 | M87: INR | N87: 146267.94 | O87: 1 | P87: =N87*O87 -> 146267.94 | Q87: 1 | R87: =N87*Q87 -> 146267.94 | S87: =R87-P87 -> 0 | T87: Small | U87: =$U$1-AH87 -> -2 | V87: 0 | W87: 0 | X87: 0 | Y87: 0 | Z87: 0 | AA87: 0 | AB87: 0 | AC87: =R87 -> 146267.94 | AD87: 38956872 | AE87: Not Due | AF87: 88071 | AG87: 46115 | AH87: 46114 | AK87: INR | AL87: 1 | AM87: =N87*AL87 -> 146267.94 | AN87: =R87-AM87 -> 0 | AO87: =AM87 -> 146267.94 | AP87: =$AP$19-AH87 -> -2 | AQ87: =IF(AP87<0,"Not Due",IF(AP87<366,"Less than 1 year",IF(AP87<731,"1-2 years",IF(AP87<1096,"2-3 years","More than 3 years")))) -> Not Due
A88: GE India Industrial Pvt Ltd - GEITC | B88: GR16 | C88: 2070201000 | D88: Trade Accounts Payable-Subledge | E88: Bethur Unique Engineering LLP A38791 | F88: Non-IBS | G88: Domestic | I88: Opex | J88: DS2025678 | K88: 100070364 | L88: 46078 | M88: INR | N88: 15660 | O88: 1 | P88: =N88*O88 -> 15660 | Q88: 1 | R88: =N88*Q88 -> 15660 | S88: =R88-P88 -> 0 | T88: Micro | U88: =$U$1-AH88 -> -11 | V88: 0 | W88: 0 | X88: 0 | Y88: 0 | Z88: 0 | AA88: 0 | AB88: 0 | AC88: =R88 -> 15660 | AD88: 38938702 | AE88: Not Due | AF88: 88142 | AG88: 46120 | AH88: 46123 | AK88: INR | AL88: 1 | AM88: =N88*AL88 -> 15660 | AN88: =R88-AM88 -> 0 | AO88: =AM88 -> 15660 | AP88: =$AP$19-AH88 -> -11 | AQ88: =IF(AP88<0,"Not Due",IF(AP88<366,"Less than 1 year",IF(AP88<731,"1-2 years",IF(AP88<1096,"2-3 years","More than 3 years")))) -> Not Due
A89: GE India Industrial Pvt Ltd - GEITC | B89: GR16 | C89: 2070201000 | D89: Trade Accounts Payable-Subledge | E89: Alpha Lab Solutions A38403 | F89: Non-IBS | G89: Domestic | I89: Capex | J89: 136/2025-26 | K89: 100070909 | L89: 46085 | M89: INR | N89: 62397.99 | O89: 1 | P89: =N89*O89 -> 62397.99 | Q89: 1 | R89: =N89*Q89 -> 62397.99 | S89: =R89-P89 -> 0 | T89: Micro | U89: =$U$1-AH89 -> -18 | V89: 0 | W89: 0 | X89: 0 | Y89: 0 | Z89: 0 | AA89: 0 | AB89: 0 | AC89: =R89 -> 62397.99 | AD89: 39006962 | AE89: Not Due | AF89: 88285 | AG89: 46127 | AH89: 46130 | AK89: INR | AL89: 1 | AM89: =N89*AL89 -> 62397.99 | AN89: =R89-AM89 -> 0 | AO89: =AM89 -> 62397.99 | AP89: =$AP$19-AH89 -> -18 | AQ89: =IF(AP89<0,"Not Due",IF(AP89<366,"Less than 1 year",IF(AP89<731,"1-2 years",IF(AP89<1096,"2-3 years","More than 3 years")))) -> Not Due
A90: GE India Industrial Pvt Ltd - GEITC | B90: GR16 | C90: 2070201000 | D90: Trade Accounts Payable-Subledge | E90: Subhaash Electrical Enterprises A37682 | F90: Non-IBS | G90: Domestic | I90: Opex | J90: 228-2025--26 | K90: 100070745 | L90: 46084 | M90: INR | N90: 145526.92 | O90: 1 | P90: =N90*O90 -> 145526.92 | Q90: 1 | R90: =N90*Q90 -> 145526.92 | S90: =R90-P90 -> 0 | T90: Micro | U90: =$U$1-AH90 -> -2 | V90: 0 | W90: 0 | X90: 0 | Y90: 0 | Z90: 0 | AA90: 0 | AB90: 0 | AC90: =R90 -> 145526.92 | AD90: 38956880 | AE90: Not Due | AF90: 88015 | AG90: 46113 | AH90: 46114 | AK90: INR | AL90: 1 | AM90: =N90*AL90 -> 145526.92 | AN90: =R90-AM90 -> 0 | AO90: =AM90 -> 145526.92 | AP90: =$AP$19-AH90 -> -2 | AQ90: =IF(AP90<0,"Not Due",IF(AP90<366,"Less than 1 year",IF(AP90<731,"1-2 years",IF(AP90<1096,"2-3 years","More than 3 years")))) -> Not Due
A91: GE India Industrial Pvt Ltd - GEITC | B91: GR16 | C91: 2070201000 | D91: Trade Accounts Payable-Subledge | E91: Bharathi Engineering A37664 | F91: Non-IBS | G91: Domestic | I91: Opex | J91: 285/25-26 | K91: 100071158 | L91: 46092 | M91: INR | N91: 153875.47 | O91: 1 | P91: =N91*O91 -> 153875.47 | Q91: 1 | R91: =N91*Q91 -> 153875.47 | S91: =R91-P91 -> 0 | T91: Small | U91: =$U$1-AH91 -> -25 | V91: 0 | W91: 0 | X91: 0 | Y91: 0 | Z91: 0 | AA91: 0 | AB91: 0 | AC91: =R91 -> 153875.47 | AD91: 38993166 | AE91: Not Due | AF91: 88385 | AG91: 46134 | AH91: 46137 | AK91: INR | AL91: 1 | AM91: =N91*AL91 -> 153875.47 | AN91: =R91-AM91 -> 0 | AO91: =AM91 -> 153875.47 | AP91: =$AP$19-AH91 -> -25 | AQ91: =IF(AP91<0,"Not Due",IF(AP91<366,"Less than 1 year",IF(AP91<731,"1-2 years",IF(AP91<1096,"2-3 years","More than 3 years")))) -> Not Due
A92: GE India Industrial Pvt Ltd - GEITC | B92: GR16 | C92: 2070201000 | D92: Trade Accounts Payable-Subledge | E92: BK INFRASYS PRIVATE LIMITED A39017 | F92: Non-IBS | G92: Domestic | I92: Opex | J92: 123/2025-26 | K92: 100067756 | L92: 46077 | M92: INR | N92: 281300 | O92: 1 | P92: =N92*O92 -> 281300 | Q92: 1 | R92: =N92*Q92 -> 281300 | S92: =R92-P92 -> 0 | T92: Small | U92: =$U$1-AH92 -> -10 | V92: 0 | W92: 0 | X92: 0 | Y92: 0 | Z92: 0 | AA92: 0 | AB92: 0 | AC92: =R92 -> 281300 | AD92: 38965406 | AE92: Not Due | AF92: 88119 | AG92: 46119 | AH92: 46122 | AK92: INR | AL92: 1 | AM92: =N92*AL92 -> 281300 | AN92: =R92-AM92 -> 0 | AO92: =AM92 -> 281300 | AP92: =$AP$19-AH92 -> -10 | AQ92: =IF(AP92<0,"Not Due",IF(AP92<366,"Less than 1 year",IF(AP92<731,"1-2 years",IF(AP92<1096,"2-3 years","More than 3 years")))) -> Not Due
... A97: GE India Industrial Pvt Ltd - GEITC | B97: GR16 | C97: 2070201000 | D97: Trade Accounts Payable-Subledge | E97: Bethur Unique Engineering LLP A38791 | F97: Non-IBS | G97: Domestic | I97: Opex | J97: DS2025696 | K97: 100069577 | L97: 46085 | M97: INR | N97: 25056 | O97: 1 | P97: =N97*O97 -> 25056 | Q97: 1 | R97: =N97*Q97 -> 25056 | S97: =R97-P97 -> 0 | T97: Micro | U97: =$U$1-AH97 -> -18 | V97: 0 | W97: 0 | X97: 0 | Y97: 0 | Z97: 0 | AA97: 0 | AB97: 0 | AC97: =R97 -> 25056 | AD97: 38960446 | AE97: Not Due | AF97: 88289 | AG97: 46127 | AH97: 46130 | AK97: INR | AL97: 1 | AM97: =N97*AL97 -> 25056 | AN97: =R97-AM97 -> 0 | AO97: =AM97 -> 25056 | AP97: =$AP$19-AH97 -> -18 | AQ97: =IF(AP97<0,"Not Due",IF(AP97<366,"Less than 1 year",IF(AP97<731,"1-2 years",IF(AP97<1096,"2-3 years","More than 3 years")))) -> Not Due
A98: GE India Industrial Pvt Ltd - GEITC | B98: GR16 | C98: 2070201000 | D98: Trade Accounts Payable-Subledge | E98: Anjanadri Water Supply A38222 | F98: Non-IBS | G98: Domestic | I98: Opex | J98: 360 | K98: 100070440 | L98: 46083 | M98: INR | N98: 157252.59 | O98: 1 | P98: =N98*O98 -> 157252.59 | Q98: 1 | R98: =N98*Q98 -> 157252.59 | S98: =R98-P98 -> 0 | T98: Micro | U98: =$U$1-AH98 -> -1 | V98: 0 | W98: 0 | X98: 0 | Y98: 0 | Z98: 0 | AA98: 0 | AB98: 0 | AC98: =R98 -> 157252.59 | AD98: 38976065 | AE98: Not Due | AF98: 88028 | AG98: 46113 | AH98: 46113 | AK98: INR | AL98: 1 | AM98: =N98*AL98 -> 157252.59 | AO98: =AM98 -> 157252.59 | AP98: =$AP$19-AH98 -> -1 | AQ98: =IF(AP98<0,"Not Due",IF(AP98<366,"Less than 1 year",IF(AP98<731,"1-2 years",IF(AP98<1096,"2-3 years","More than 3 years")))) -> Not Due
A99: GE India Industrial Pvt Ltd - GEITC | B99: GR16 | C99: 2070201000 | D99: Trade Accounts Payable-Subledge | E99: Labsupplies India Pvt Ltd A38991 | F99: Non-IBS | G99: Domestic | I99: Opex | J99: LS-25-26-10254 | K99: 100071130 | L99: 46092 | M99: INR | N99: 5037.73 | O99: 1 | P99: =N99*O99 -> 5037.73 | Q99: 1 | R99: =N99*Q99 -> 5037.73 | S99: =R99-P99 -> 0 | T99: Small | U99: =$U$1-AH99 -> -10 | V99: 0 | W99: 0 | X99: 0 | Y99: 0 | Z99: 0 | AA99: 0 | AB99: 0 | AC99: =R99 -> 5037.73 | AD99: 39017900 | AE99: Not Due | AF99: 88118 | AG99: 46119 | AH99: 46122 | AK99: INR | AL99: 1 | AM99: =N99*AL99 -> 5037.73 | AO99: =AM99 -> 5037.73 | AP99: =$AP$19-AH99 -> -10 | AQ99: =IF(AP99<0,"Not Due",IF(AP99<366,"Less than 1 year",IF(AP99<731,"1-2 years",IF(AP99<1096,"2-3 years","More than 3 years")))) -> Not Due
A100: GE India Industrial Pvt Ltd - GEITC | B100: GR16 | C100: 2070201000 | D100: Trade Accounts Payable-Subledge | E100: Vamtech Energy Solutions Private Limited A37608 | F100: Non-IBS | G100: Domestic | I100: Opex | J100: J-3383 | K100: 100069277 | L100: 46083 | M100: INR | N100: 108000 | O100: 1 | P100: =N100*O100 -> 108000 | Q100: 1 | R100: =N100*Q100 -> 108000 | S100: =R100-P100 -> 0 | T100: Micro | U100: =$U$1-AH100 -> -16 | V100: 0 | W100: 0 | X100: 0 | Y100: 0 | Z100: 0 | AA100: 0 | AB100: 0 | AC100: =R100 -> 108000 | AD100: 38965683 | AE100: Not Due | AF100: 88202 | AG100: 46125 | AH100: 46128 | AK100: INR | AL100: 1 | AM100: =N100*AL100 -> 108000 | AO100: =AM100 -> 108000 | AP100: =$AP$19-AH100 -> -16 | AQ100: =IF(AP100<0,"Not Due",IF(AP100<366,"Less than 1 year",IF(AP100<731,"1-2 years",IF(AP100<1096,"2-3 years","More than 3 years")))) -> Not Due
A101: GE India Industrial Pvt Ltd - GEITC | B101: GR16 | C101: 2070201000 | D101: Trade Accounts Payable-Subledge | E101: Bethur Unique Engineering LLP A38791 | F101: Non-IBS | G101: Domestic | I101: Opex | J101: DS2025704 | K101: 100070836 | L101: 46090 | M101: INR | N101: 15190.1 | O101: 1 | P101: =N101*O101 -> 15190.1 | Q101: 1 | R101: =N101*Q101 -> 15190.1 | S101: =R101-P101 -> 0 | T101: Micro | U101: =$U$1-AH101 -> -23 | V101: 0 | W101: 0 | X101: 0 | Y101: 0 | Z101: 0 | AA101: 0 | AB101: 0 | AC101: =R101 -> 15190.1 | AD101: 38993871 | AE101: Not Due | AF101: 88347 | AG101: 46132 | AH101: 46135 | AK101: INR | AL101: 1 | AM101: =N101*AL101 -> 15190.1 | AO101: =AM101 -> 15190.1 | AP101: =$AP$19-AH101 -> -23 | AQ101: =IF(AP101<0,"Not Due",IF(AP101<366,"Less than 1 year",IF(AP101<731,"1-2 years",IF(AP101<1096,"2-3 years","More than 3 years")))) -> Not Due
A102: GE India Industrial Pvt Ltd - GEITC | B102: GR16 | C102: 2070201000 | D102: Trade Accounts Payable-Subledge | E102: Growell Precisions A38999 | F102: Non-IBS | G102: Domestic | I102: Opex | J102: 121/25-26 | K102: 100071067 | L102: 46085 | M102: INR | N102: 10886.6 | O102: 1 | P102: =N102*O102 -> 10886.6 | Q102: 1 | R102: =N102*Q102 -> 10886.6 | S102: =R102-P102 -> 0 | T102: Micro | U102: =$U$1-AH102 -> -18 | V102: 0 | W102: 0 | X102: 0 | Y102: 0 | Z102: 0 | AA102: 0 | AB102: 0 | AC102: =R102 -> 10886.6 | AD102: 38976335 | AE102: Not Due | AF102: 88290 | AG102: 46127 | AH102: 46130 | AK102: INR | AL102: 1 | AM102: =N102*AL102 -> 10886.6 | AO102: =AM102 -> 10886.6 | AP102: =$AP$19-AH102 -> -18 | AQ102: =IF(AP102<0,"Not Due",IF(AP102<366,"Less than 1 year",IF(AP102<731,"1-2 years",IF(AP102<1096,"2-3 years","More than 3 years")))) -> Not Due
A103: GE India Industrial Pvt Ltd - GEITC | B103: GR16 | C103: 2070201000 | D103: Trade Accounts Payable-Subledge | E103: Pro Team Solutions Private Limited A37469 | F103: Non-IBS | G103: Domestic | I103: Opex | J103: PTSB/25-26/4071 | K103: 100066541 | L103: 46082 | M103: INR | N103: 87435 | O103: 1 | P103: =N103*O103 -> 87435 | Q103: 1 | R103: =N103*Q103 -> 87435 | S103: =R103-P103 -> 0 | T103: Small | U103: =$U$1-AH103 -> -15 | V103: 0 | W103: 0 | X103: 0 | Y103: 0 | Z103: 0 | AA103: 0 | AB103: 0 | AC103: =R103 -> 87435 | AD103: 38964832 | AE103: Not Due | AF103: 88194 | AG103: 46125 | AH103: 46127 | AK103: INR | AL103: 1 | AM103: =N103*AL103 -> 87435 | AO103: =AM103 -> 87435 | AP103: =$AP$19-AH103 -> -15 | AQ103: =IF(AP103<0,"Not Due",IF(AP103<366,"Less than 1 year",IF(AP103<731,"1-2 years",IF(AP103<1096,"2-3 years","More than 3 years")))) -> Not Due
A104: GE India Industrial Pvt Ltd - GEITC | B104: GR16 | C104: 2070201000 | D104: Trade Accounts Payable-Subledge | E104: S.S. Manpower Services Pvt LTD A37638 | F104: Non-IBS | G104: Domestic | I104: Opex | J104: SSMS/2025-26/362 | K104: 100070744 | L104: 46085 | M104: INR | N104: 2817915.3 | O104: 1 | P104: =N104*O104 -> 2817915.3 | Q104: 1 | R104: =N104*Q104 -> 2817915.3 | S104: =R104-P104 -> 0 | T104: Micro | U104: =$U$1-AH104 -> -18 | V104: 0 | W104: 0 | X104: 0 | Y104: 0 | Z104: 0 | AA104: 0 | AB104: 0 | AC104: =R104 -> 2817915.3 | AD104: 38982883 | AE104: Not Due | AF104: 88279 | AG104: 46127 | AH104: 46130 | AK104: INR | AL104: 1 | AM104: =N104*AL104 -> 2817915.3 | AO104: =AM104 -> 2817915.3 | AP104: =$AP$19-AH104 -> -18 | AQ104: =IF(AP104<0,"Not Due",IF(AP104<366,"Less than 1 year",IF(AP104<731,"1-2 years",IF(AP104<1096,"2-3 years","More than 3 years")))) -> Not Due
A105: GE India Industrial Pvt Ltd - GEITC | B105: GR16 | C105: 2070201000 | D105: Trade Accounts Payable-Subledge | E105: S.S. Manpower Services Pvt LTD A37638 | F105: Non-IBS | G105: Domestic | I105: Opex | J105: SSMS/2025-26/356 | K105: 100070833 | L105: 46085 | M105: INR | N105: 186577.16 | O105: 1 | P105: =N105*O105 -> 186577.16 | Q105: 1 | R105: =N105*Q105 -> 186577.16 | S105: =R105-P105 -> 0 | T105: Micro | U105: =$U$1-AH105 -> -18 | V105: 0 | W105: 0 | X105: 0 | Y105: 0 | Z105: 0 | AA105: 0 | AB105: 0 | AC105: =R105 -> 186577.16 | AD105: 38982998 | AE105: Not Due | AF105: 88279 | AG105: 46127 | AH105: 46130 | AK105: INR | AL105: 1 | AM105: =N105*AL105 -> 186577.16 | AO105: =AM105 -> 186577.16 | AP105: =$AP$19-AH105 -> -18 | AQ105: =IF(AP105<0,"Not Due",IF(AP105<366,"Less than 1 year",IF(AP105<731,"1-2 years",IF(AP105<1096,"2-3 years","More than 3 years")))) -> Not Due
A106: GE India Industrial Pvt Ltd - GEITC | B106: GR16 | C106: 2070201000 | D106: Trade Accounts Payable-Subledge | E106: Adarsh Solutions Private Limited A37489 | F106: Non-IBS | G106: Domestic | I106: Opex | J106: AS26FEB577 | K106: 100070912 | L106: 46073 | M106: INR | N106: 56854.44 | O106: 1 | P106: =N106*O106 -> 56854.44 | Q106: 1 | R106: =N106*Q106 -> 56854.44 | S106: =R106-P106 -> 0 | T106: Micro | U106: =$U$1-AH106 -> -6 | V106: 0 | W106: 0 | X106: 0 | Y106: 0 | Z106: 0 | AA106: 0 | AB106: 0 | AC106: =R106 -> 56854.44 | AD106: 38927625 | AE106: Not Due | AF106: 88056 | AG106: 46115 | AH106: 46118 | AK106: INR | AL106: 1 | AM106: =N106*AL106 -> 56854.44 | AO106: =AM106 -> 56854.44 | AP106: =$AP$19-AH106 -> -6 | AQ106: =IF(AP106<0,"Not Due",IF(AP106<366,"Less than 1 year",IF(AP106<731,"1-2 years",IF(AP106<1096,"2-3 years","More than 3 years")))) -> Not Due
A107: GE India Industrial Pvt Ltd - GEITC | B107: GR16 | C107: 2070201000 | D107: Trade Accounts Payable-Subledge | E107: Ambassador Tours And Travels Llp A37868 | F107: Non-IBS | G107: Domestic | I107: Opex | J107: 3073/25-26 | K107: 100068520 | L107: 46072 | M107: INR | N107: 16220.96 | O107: 1 | P107: =N107*O107 -> 16220.96 | Q107: 1 | R107: =N107*Q107 -> 16220.96 | S107: =R107-P107 -> 0 | T107: Medium | U107: =$U$1-AH107 -> -5 | V107: 0 | W107: 0 | X107: 0 | Y107: 0 | Z107: 0 | AA107: 0 | AB107: 0 | AC107: =R107 -> 16220.96 | AD107: 38938527 | AE107: Not Due | AF107: 88047 | AG107: 46114 | AH107: 46117 | AK107: INR | AL107: 1 | AM107: =N107*AL107 -> 16220.96 | AO107: =AM107 -> 16220.96 | AP107: =$AP$19-AH107 -> -5 | AQ107: =IF(AP107<0,"Not Due",IF(AP107<366,"Less than 1 year",IF(AP107<731,"1-2 years",IF(AP107<1096,"2-3 years","More than 3 years")))) -> Not Due
A108: GE India Industrial Pvt Ltd - GEITC | B108: GR16 | C108: 2070201000 | D108: Trade Accounts Payable-Subledge | E108: Bethur Unique Engineering LLP A38791 | F108: Non-IBS | G108: Domestic | I108: Opex | J108: DS2025687 | K108: 100070376 | L108: 46083 | M108: INR | N108: 4176 | O108: 1 | P108: =N108*O108 -> 4176 | Q108: 1 | R108: =N108*Q108 -> 4176 | S108: =R108-P108 -> 0 | T108: Micro | U108: =$U$1-AH108 -> -16 | V108: 0 | W108: 0 | X108: 0 | Y108: 0 | Z108: 0 | AA108: 0 | AB108: 0 | AC108: =R108 -> 4176 | AD108: 38948599 | AE108: Not Due | AF108: 88224 | AG108: 46125 | AH108: 46128 | AK108: INR | AL108: 1 | AM108: =N108*AL108 -> 4176 | AO108: =AM108 -> 4176 | AP108: =$AP$19-AH108 -> -16 | AQ108: =IF(AP108<0,"Not Due",IF(AP108<366,"Less than 1 year",IF(AP108<731,"1-2 years",IF(AP108<1096,"2-3 years","More than 3 years")))) -> Not Due
A109: GE India Industrial Pvt Ltd - GEITC | B109: GR16 | C109: 2070201000 | D109: Trade Accounts Payable-Subledge | E109: Bethur Unique Engineering LLP A38791 | F109: Non-IBS | G109: Domestic | I109: Opex | J109: DS2025650 | K109: 100070404 | L109: 46069 | M109: INR | N109: 44566.2 | O109: 1 | P109: =N109*O109 -> 44566.2 | Q109: 1 | R109: =N109*Q109 -> 44566.2 | S109: =R109-P109 -> 0 | T109: Micro | U109: =$U$1-AH109 -> -2 | V109: 0 | W109: 0 | X109: 0 | Y109: 0 | Z109: 0 | AA109: 0 | AB109: 0 | AC109: =R109 -> 44566.2 | AD109: 38887948 | AE109: Not Due | AF109: 88038 | AG109: 46113 | AH109: 46114 | AK109: INR | AL109: 1 | AM109: =N109*AL109 -> 44566.2 | AO109: =AM109 -> 44566.2 | AP109: =$AP$19-AH109 -> -2 | AQ109: =IF(AP109<0,"Not Due",IF(AP109<366,"Less than 1 year",IF(AP109<731,"1-2 years",IF(AP109<1096,"2-3 years","More than 3 years")))) -> Not Due
A110: GE India Industrial Pvt Ltd - GEITC | B110: GR16 | C110: 2070201000 | D110: Trade Accounts Payable-Subledge | E110: PC Process Pvt Ltd A37404 | F110: Non-IBS | G110: Domestic | I110: Opex | J110: 7436/25-26 | K110: 100071146 | L110: 46092 | M110: INR | N110: 30923.77 | O110: 1 | P110: =N110*O110 -> 30923.77 | Q110: 1 | R110: =N110*Q110 -> 30923.77 | S110: =R110-P110 -> 0 | T110: Small | U110: =$U$1-AH110 -> -10 | V110: 0 | W110: 0 | X110: 0 | Y110: 0 | Z110: 0 | AA110: 0 | AB110: 0 | AC110: =R110 -> 30923.77 | AD110: 39018465 | AE110: Not Due | AF110: 88109 | AG110: 46119 | AH110: 46122 | AK110: INR | AL110: 1 | AM110: =N110*AL110 -> 30923.77 | AO110: =AM110 -> 30923.77 | AP110: =$AP$19-AH110 -> -10 | AQ110: =IF(AP110<0,"Not Due",IF(AP110<366,"Less than 1 year",IF(AP110<731,"1-2 years",IF(AP110<1096,"2-3 years","More than 3 years")))) -> Not Due
A111: GE India Industrial Pvt Ltd - GEITC | B111: GR16 | C111: 2070201000 | D111: Trade Accounts Payable-Subledge | E111: Fillip Innovative Solutions Private Limited A38508 | F111: Non-IBS | G111: Domestic | I111: Capex | J111: FISPL/25-26/0248 | K111: 100070919 | L111: 46091 | M111: INR | N111: 15080 | O111: 1 | P111: =N111*O111 -> 15080 | Q111: 1 | R111: =N111*Q111 -> 15080 | S111: =R111-P111 -> 0 | T111: Small | U111: =$U$1-AH111 -> -24 | V111: 0 | W111: 0 | X111: 0 | Y111: 0 | Z111: 0 | AA111: 0 | AB111: 0 | AC111: =R111 -> 15080 | AD111: 39008047 | AE111: Not Due | AF111: 88362 | AG111: 46133 | AH111: 46136 | AK111: INR | AL111: 1 | AM111: =N111*AL111 -> 15080 | AO111: =AM111 -> 15080 | AP111: =$AP$19-AH111 -> -24 | AQ111: =IF(AP111<0,"Not Due",IF(AP111<366,"Less than 1 year",IF(AP111<731,"1-2 years",IF(AP111<1096,"2-3 years","More than 3 years")))) -> Not Due
A112: GE India Industrial Pvt Ltd - GEITC | B112: GR16 | C112: 2070201000 | D112: Trade Accounts Payable-Subledge | E112: Perfect Point A38190 | F112: Non-IBS | G112: Domestic | I112: Opex | J112: 67142 | K112: 100070002 | L112: 46072 | M112: INR | N112: 21824.4 | O112: 1 | P112: =N112*O112 -> 21824.4 | Q112: 1 | R112: =N112*Q112 -> 21824.4 | S112: =R112-P112 -> 0 | T112: Small | U112: =$U$1-AH112 -> -5 | V112: 0 | W112: 0 | X112: 0 | Y112: 0 | Z112: 0 | AA112: 0 | AB112: 0 | AC112: =R112 -> 21824.4 | AD112: 38932754 | AE112: Not Due | AF112: 88049 | AG112: 46114 | AH112: 46117 | AK112: INR | AL112: 1 | AM112: =N112*AL112 -> 21824.4 | AO112: =AM112 -> 21824.4 | AP112: =$AP$19-AH112 -> -5 | AQ112: =IF(AP112<0,"Not Due",IF(AP112<366,"Less than 1 year",IF(AP112<731,"1-2 years",IF(AP112<1096,"2-3 years","More than 3 years")))) -> Not Due
A113: GE India Industrial Pvt Ltd - GEITC | B113: GR16 | C113: 2070201000 | D113: Trade Accounts Payable-Subledge | E113: Shobha Electricals A37602 | F113: Non-IBS | G113: Domestic | I113: Opex | J113: SER/445/25-26 | K113: 100069197 | L113: 46083 | M113: INR | N113: 31900 | O113: 1 | P113: =N113*O113 -> 31900 | Q113: 1 | R113: =N113*Q113 -> 31900 | S113: =R113-P113 -> 0 | T113: Small | U113: =$U$1-AH113 -> -16 | V113: 0 | W113: 0 | X113: 0 | Y113: 0 | Z113: 0 | AA113: 0 | AB113: 0 | AC113: =R113 -> 31900 | AD113: 38976176 | AE113: Not Due | AF113: 88201 | AG113: 46125 | AH113: 46128 | AK113: INR | AL113: 1 | AM113: =N113*AL113 -> 31900 | AO113: =AM113 -> 31900 | AP113: =$AP$19-AH113 -> -16 | AQ113: =IF(AP113<0,"Not Due",IF(AP113<366,"Less than 1 year",IF(AP113<731,"1-2 years",IF(AP113<1096,"2-3 years","More than 3 years")))) -> Not Due
A114: GE India Industrial Pvt Ltd - GEITC | B114: GR16 | C114: 2070201000 | D114: Trade Accounts Payable-Subledge | E114: Eta Engineers Bangalore Private Limited A37548 | F114: Non-IBS | G114: Domestic | I114: Capex | J114: 338/HO/2025-26 | K114: 100070140 | L114: 46073 | M114: INR | N114: 40136 | O114: 1 | P114: =N114*O114 -> 40136 | Q114: 1 | R114: =N114*Q114 -> 40136 | S114: =R114-P114 -> 0 | T114: Small | U114: =$U$1-AH114 -> -6 | V114: 0 | W114: 0 | X114: 0 | Y114: 0 | Z114: 0 | AA114: 0 | AB114: 0 | AC114: =R114 -> 40136 | AD114: 38984813 | AE114: Not Due | AF114: 88061 | AG114: 46115 | AH114: 46118 | AK114: INR | AL114: 1 | AM114: =N114*AL114 -> 40136 | AO114: =AM114 -> 40136 | AP114: =$AP$19-AH114 -> -6 | AQ114: =IF(AP114<0,"Not Due",IF(AP114<366,"Less than 1 year",IF(AP114<731,"1-2 years",IF(AP114<1096,"2-3 years","More than 3 years")))) -> Not Due
A115: GE India Industrial Pvt Ltd - GEITC | B115: GR16 | C115: 2070201000 | D115: Trade Accounts Payable-Subledge | E115: D SQUARE ELECTROPLATING MACHINES PRIVATE LIMITED A38682 | F115: Non-IBS | G115: Domestic | I115: Opex | J115: 1548/BLR/2025-26 | K115: 100069451 | L115: 46008 | M115: INR | N115: 11600 | O115: 1 | P115: =N115*O115 -> 11600 | Q115: 1 | R115: =N115*Q115 -> 11600 | S115: =R115-P115 -> 0 | T115: Micro | U115: =$U$1-AH115 -> -6 | V115: 0 | W115: 0 | X115: 0 | Y115: 0 | Z115: 0 | AA115: 0 | AB115: 0 | AC115: =R115 -> 11600 | AD115: 38932763 | AE115: Not Due | AF115: 88067 | AG115: 46115 | AH115: 46118 | AK115: INR | AL115: 1 | AM115: =N115*AL115 -> 11600 | AO115: =AM115 -> 11600 | AP115: =$AP$19-AH115 -> -6 | AQ115: =IF(AP115<0,"Not Due",IF(AP115<366,"Less than 1 year",IF(AP115<731,"1-2 years",IF(AP115<1096,"2-3 years","More than 3 years")))) -> Not Due
A116: GE India Industrial Pvt Ltd - GEITC | B116: GR16 | C116: 2070201000 | D116: Trade Accounts Payable-Subledge | E116: Ramesh Sign Graphics A37581 | F116: Non-IBS | G116: Domestic | I116: Opex | J116: 7240/25-26 | K116: 100060364 | L116: 46095 | M116: INR | N116: 2845.92 | O116: 1 | P116: =N116*O116 -> 2845.92 | Q116: 1 | R116: =N116*Q116 -> 2845.92 | S116: =R116-P116 -> 0 | T116: Micro | U116: =$U$1-AH116 -> -28 | V116: 0 | W116: 0 | X116: 0 | Y116: 0 | Z116: 0 | AA116: 0 | AB116: 0 | AC116: =R116 -> 2845.92 | AD116: 39023182 | AE116: Not Due | AF116: 88462 | AG116: 46136 | AH116: 46140 | AK116: INR | AL116: 1 | AM116: =N116*AL116 -> 2845.92 | AO116: =AM116 -> 2845.92 | AP116: =$AP$19-AH116 -> -28 | AQ116: =IF(AP116<0,"Not Due",IF(AP116<366,"Less than 1 year",IF(AP116<731,"1-2 years",IF(AP116<1096,"2-3 years","More than 3 years")))) -> Not Due
A117: GE India Industrial Pvt Ltd - GEITC | B117: GR16 | C117: 2070201000 | D117: Trade Accounts Payable-Subledge | E117: Vinolya Services Pvt Ltd. A38997 | F117: Non-IBS | G117: Domestic | I117: Opex | J117: 13645/25 | K117: 100066427 | L117: 46082 | M117: INR | N117: 71133.56 | O117: 1 | P117: =N117*O117 -> 71133.56 | Q117: 1 | R117: =N117*Q117 -> 71133.56 | S117: =R117-P117 -> 0 | T117: Small | U117: =$U$1-AH117 -> -15 | V117: 0 | W117: 0 | X117: 0 | Y117: 0 | Z117: 0 | AA117: 0 | AB117: 0 | AC117: =R117 -> 71133.56 | AD117: 38956566 | AE117: Not Due | AF117: 88226 | AG117: 46125 | AH117: 46127 | AK117: INR | AL117: 1 | AM117: =N117*AL117 -> 71133.56 | AO117: =AM117 -> 71133.56 | AP117: =$AP$19-AH117 -> -15 | AQ117: =IF(AP117<0,"Not Due",IF(AP117<366,"Less than 1 year",IF(AP117<731,"1-2 years",IF(AP117<1096,"2-3 years","More than 3 years")))) -> Not Due
A118: GE India Industrial Pvt Ltd - GEITC | B118: GR16 | C118: 2070201000 | D118: Trade Accounts Payable-Subledge | E118: Netsign Inc A37871 | F118: Non-IBS | G118: Domestic | I118: Opex | J118: 237/2025-26 | K118: 100070482 | L118: 46080 | M118: INR | N118: 8758 | O118: 1 | P118: =N118*O118 -> 8758 | Q118: 1 | R118: =N118*Q118 -> 8758 | S118: =R118-P118 -> 0 | T118: Micro | U118: =$U$1-AH118 -> -13 | V118: 0 | W118: 0 | X118: 0 | Y118: 0 | Z118: 0 | AA118: 0 | AB118: 0 | AC118: =R118 -> 8758 | AD118: 38960436 | AE118: Not Due | AF118: 88175 | AG118: 46122 | AH118: 46125 | AK118: INR | AL118: 1 | AM118: =N118*AL118 -> 8758 | AO118: =AM118 -> 8758 | AP118: =$AP$19-AH118 -> -13 | AQ118: =IF(AP118<0,"Not Due",IF(AP118<366,"Less than 1 year",IF(AP118<731,"1-2 years",IF(AP118<1096,"2-3 years","More than 3 years")))) -> Not Due
A119: GE India Industrial Pvt Ltd - GEITC | B119: GR16 | C119: 2070201000 | D119: Trade Accounts Payable-Subledge | E119: Eta Engineers Bangalore Private Limited A37548 | F119: Non-IBS | G119: Domestic | I119: Opex | J119: 340/HO/2025-26 | K119: 100069955 | L119: 46078 | M119: INR | N119: 49010 | O119: 1 | P119: =N119*O119 -> 49010 | Q119: 1 | R119: =N119*Q119 -> 49010 | S119: =R119-P119 -> 0 | T119: Small | U119: =$U$1-AH119 -> -11 | V119: 0 | W119: 0 | X119: 0 | Y119: 0 | Z119: 0 | AA119: 0 | AB119: 0 | AC119: =R119 -> 49010 | AD119: 38945214 | AE119: Not Due | AF119: 88128 | AG119: 46120 | AH119: 46123 | AK119: INR | AL119: 1 | AM119: =N119*AL119 -> 49010 | AO119: =AM119 -> 49010 | AP119: =$AP$19-AH119 -> -11 | AQ119: =IF(AP119<0,"Not Due",IF(AP119<366,"Less than 1 year",IF(AP119<731,"1-2 years",IF(AP119<1096,"2-3 years","More than 3 years")))) -> Not Due
A120: GE India Industrial Pvt Ltd - GEITC | B120: GR16 | C120: 2070201000 | D120: Trade Accounts Payable-Subledge | E120: Equipment Fabricators A37538 | F120: Non-IBS | G120: Domestic | I120: Capex | J120: EF448/2025-26 | K120: 100070931 | L120: 46085 | M120: INR | N120: 112452.44 | O120: 1 | P120: =N120*O120 -> 112452.44 | Q120: 1 | R120: =N120*Q120 -> 112452.44 | S120: =R120-P120 -> 0 | T120: Small | U120: =$U$1-AH120 -> -18 | V120: 0 | W120: 0 | X120: 0 | Y120: 0 | Z120: 0 | AA120: 0 | AB120: 0 | AC120: =R120 -> 112452.44 | AD120: 38988346 | AE120: Not Due | AF120: 88273 | AG120: 46127 | AH120: 46130 | AK120: INR | AL120: 1 | AM120: =N120*AL120 -> 112452.44 | AO120: =AM120 -> 112452.44 | AP120: =$AP$19-AH120 -> -18 | AQ120: =IF(AP120<0,"Not Due",IF(AP120<366,"Less than 1 year",IF(AP120<731,"1-2 years",IF(AP120<1096,"2-3 years","More than 3 years")))) -> Not Due
A121: GE India Industrial Pvt Ltd - GEITC | B121: GR16 | C121: 2070201000 | D121: Trade Accounts Payable-Subledge | E121: Shobha Electricals A37602 | F121: Non-IBS | G121: Domestic | I121: Opex | J121: SUP/323/25-26 | K121: 100069482 | L121: 46084 | M121: INR | N121: 61161.12 | O121: 1 | P121: =N121*O121 -> 61161.12 | Q121: 1 | R121: =N121*Q121 -> 61161.12 | S121: =R121-P121 -> 0 | T121: Small | U121: =$U$1-AH121 -> -17 | V121: 0 | W121: 0 | X121: 0 | Y121: 0 | Z121: 0 | AA121: 0 | AB121: 0 | AC121: =R121 -> 61161.12 | AD121: 39014805 | AE121: Not Due | AF121: 88265 | AG121: 46126 | AH121: 46129 | AK121: INR | AL121: 1 | AM121: =N121*AL121 -> 61161.12 | AO121: =AM121 -> 61161.12 | AP121: =$AP$19-AH121 -> -17 | AQ121: =IF(AP121<0,"Not Due",IF(AP121<366,"Less than 1 year",IF(AP121<731,"1-2 years",IF(AP121<1096,"2-3 years","More than 3 years")))) -> Not Due
A122: GE India Industrial Pvt Ltd - GEITC | B122: GR16 | C122: 2070201000 | D122: Trade Accounts Payable-Subledge | E122: World Of Opportunities For Women LLP A38514 | F122: Non-IBS | G122: Domestic | I122: Opex | J122: INV-C-202526154 | K122: 100070618 | L122: 46086 | M122: INR | N122: 106920 | O122: 1 | P122: =N122*O122 -> 106920 | Q122: 1 | R122: =N122*Q122 -> 106920 | S122: =R122-P122 -> 0 | T122: Micro | U122: =$U$1-AH122 -> -4 | V122: 0 | W122: 0 | X122: 0 | Y122: 0 | Z122: 0 | AA122: 0 | AB122: 0 | AC122: =R122 -> 106920 | AD122: 38988476 | AE122: Not Due | AF122: 88035 | AG122: 46113 | AH122: 46116 | AK122: INR | AL122: 1 | AM122: =N122*AL122 -> 106920 | AO122: =AM122 -> 106920 | AP122: =$AP$19-AH122 -> -4 | AQ122: =IF(AP122<0,"Not Due",IF(AP122<366,"Less than 1 year",IF(AP122<731,"1-2 years",IF(AP122<1096,"2-3 years","More than 3 years")))) -> Not Due
...

Sheet SSS Accrual Non MSME
A1: =Memo!A1 -> 0 | Y1: 46112
A2: =Memo!A2 -> 0
A3: =Memo!A3 -> 0
A5: Work Done
A6: 1. ET has obtained the schedule for SSS Accrual (Non-MSME).
A7: 2. ET has verified the exchange rate considered for closing payable amount.
A8: 3. ET has recomputed the ageing of invoices payable from due date.
A9: 4. ET has checked the computation of due date and performed 3 way match on sample basis.
A11: Summary
A13: Particulars | B13: Amount
A14: Payable Amount | B14: =$AK$19 -> 1.5423263e+08
A15: Subsequently Paid | B15: =$AM$19 -> 1.536038e+08
A16: Subsequently Paid % | B16: =B15/B14 -> 0.99592281
A18: SSS Accrual Schedule - Non MSME | AI18: DHS Testing
N19: =SUM(N20:N5300) -> 1.5423263e+08 | AA19: =SUM(AA21:AA226) -> 17001164 | AB19: =SUM(AB21:AB226) -> 1985.5 | AC19: =SUM(AC21:AC226) -> 0 | AD19: =SUM(AD21:AD226) -> 0 | AE19: =SUM(AE21:AE226) -> 418599.18 | AF19: =SUM(AF21:AF226) -> 0 | AG19: =SUM(AG21:AG226) -> 1.3681088e+08 | AK19: =SUM(AK20:AK530) -> 1.5423263e+08 | AL19: =SUM(AL20:AL530) -> 0 | AM19: =SUM(AM20:AM530) -> 1.536038e+08 | AN19: 46112
A20: VENDOR_NAME | B20: LINE_DESC | C20: PO_NUM | D20: COST CENTER | E20: CURRENCY_CODE | F20: Entered Net | G20: MOR Rate | H20: RBI Rate | I20: Functional Amount in INR | J20: Amount as per RBI rate | K20: FX Impact | L20: TDS | M20: Net Amount In INR | N20: Net Amount as Per RBI | O20: Opex/Capex | P20: MSMED | Q20: Supplier# | R20: PO Description | S20: Invoice# | T20: Invoice accounted date | U20: Invoice date | V20: Subsequent payment Doc # | W20: Date of subsequent payment | X20: Remarks | Y20: Due Date | Z20: Ageing | AA20: 0-30 days | AB20: 30-60 days | AC20: 60- 90 days | AD20: 90-180 days | AE20: 180- 365 days | AF20: > 365 days | AG20: Not Due | AI20: Currency | AJ20: Exchange Rate | AK20: Amount in INR | AL20: Difference | AM20: Subsequently Paid | AN20: No. of Days | AO20: Ageing Bracket
A21: NETZSCH GERATEBAU GMBH | B21: Project#271209,Task#1001,INV#,Barcode#,Po#100070970,PoLine#2,VendorName-NETZSCH GERATEBAU GMBH,Desc-Supply of sample crucible - Al2O3 for DSC instrume,PT#2712091001 | C21: 100070970 | D21: GRAS01 | E21: EUR | F21: 1170 | G21: 108.38462 | H21: 109.0064 | I21: =F21*G21 -> 126810.01 | J21: =F21*H21 -> 127537.49 | K21: =J21-I21 -> 727.47726 | L21: 0 | M21: =I21-L21 -> 126810.01 | N21: =J21-L21 -> 127537.49 | O21: Opex | P21: Non-MSME | Q21: A39046 | R21: Supply of sample crucible - Al2O3 for DSC instrument. Size: outer bottom Ø 6.8 mm, 85 µl . | S21: 14298263 | U21: 46099 | V21: Adjusted against advance | X21: Adjusted against advance | Y21: 46125 | Z21: =$Y$1-Y21 -> -13 | AA21: 0 | AB21: 0 | AC21: 0 | AD21: 0 | AE21: 0 | AF21: 0 | AG21: 127537.49 | AI21: =E21 -> EUR | AJ21: 109.0064 | AK21: =F21*AJ21-L21 -> 127537.49 | AL21: =N21-AK21 -> 0 | AM21: =N21 -> 127537.49 | AN21: =$AN$19-Y21 -> -13 | AO21: =IF(AN21<0,"Not Due",IF(AN21<366,"Less than 1 year",IF(AN21<731,"1-2 years",IF(AN21<1096,"2-3 years","More than 3 years")))) -> Not Due
A22: NATIONAL PHARMA CENTRE A38146 | B22: Project#116889,Task#3203,INV#,Barcode#,Po#100071269,PoLine#1,VendorName-NATIONAL PHARMA CENTRE A38146,Desc-Supply of Medicines- Details as per annexure,PT#1168893203 | C22: 100071269 | D22: GC6889 | E22: INR | F22: 23417.18 | G22: 1 | H22: 1 | I22: =F22*G22 -> 23417.18 | J22: =F22*H22 -> 23417.18 | K22: =J22-I22 -> 0 | L22: 23 | M22: =I22-L22 -> 23394.18 | N22: =J22-L22 -> 23394.18 | O22: Opex | P22: Non-MSME | Q22: A38146 | R22: Supply of Medicines- Details as per annexure | S22: NAT00262 | T22: 46125 | U22: 46099 | V22: 88388 | W22: 46134 | Y22: 46129 | Z22: =$Y$1-Y22 -> -17 | AA22: 0 | AB22: 0 | AC22: 0 | AD22: 0 | AE22: 0 | AF22: 0 | AG22: 23394.18 | AI22: =E22 -> INR | AJ22: 1 | AK22: =F22*AJ22-L22 -> 23394.18 | AL22: =N22-AK22 -> 0 | AM22: =N22 -> 23394.18 | AN22: =$AN$19-Y22 -> -17 | AO22: =IF(AN22<0,"Not Due",IF(AN22<366,"Less than 1 year",IF(AN22<731,"1-2 years",IF(AN22<1096,"2-3 years","More than 3 years")))) -> Not Due
A23: INFINITI POWER PRIVATE LIMITED A37094 | B23: Project#117399,Task#3006,INV#,Barcode#,Po#100070904,PoLine#2,VendorName-INFINITI POWER PRIVATE LIMITED A37094,Desc-Supply of IT materials towards Network related wor,PT#1173993006 | C23: 100070904 | D23: GC7399 | E23: INR | F23: 48126 | G23: 1 | H23: 1 | I23: =F23*G23 -> 48126 | J23: =F23*H23 -> 48126 | K23: =J23-I23 -> 0 | L23: 48 | M23: =I23-L23 -> 48078 | N23: =J23-L23 -> 48078 | O23: Opex | P23: Non-MSME | Q23: A37094 | R23: Supply and installation of IT materials for Upgradation of meeting room / cabin in JFWTC. Details as per annexure. | S23: 252900478 | T23: 46083 | U23: 46076 | V23: 88089 | W23: 46118 | Y23: 46121 | Z23: =$Y$1-Y23 -> -9 | AA23: 0 | AB23: 0 | AC23: 0 | AD23: 0 | AE23: 0 | AF23: 0 | AG23: 48078 | AI23: =E23 -> INR | AJ23: 1 | AK23: =F23*AJ23-L23 -> 48078 | AL23: =N23-AK23 -> 0 | AN23: =$AN$19-Y23 -> -9 | AO23: =IF(AN23<0,"Not Due",IF(AN23<366,"Less than 1 year",IF(AN23<731,"1-2 years",IF(AN23<1096,"2-3 years","More than 3 years")))) -> Not Due
A24: INFINITI POWER PRIVATE LIMITED A37094 | B24: Project#117399,Task#3006,INV#,Barcode#,Po#100070904,PoLine#3,VendorName-INFINITI POWER PRIVATE LIMITED A37094,Desc-Supply of IT materials towards Network related wor,PT#1173993006 | C24: 100070904 | D24: GC7399 | E24: INR | F24: 1839 | G24: 1 | H24: 1 | I24: =F24*G24 -> 1839 | J24: =F24*H24 -> 1839 | K24: =J24-I24 -> 0 | L24: 2 | M24: =I24-L24 -> 1837 | N24: =J24-L24 -> 1837 | O24: Opex | P24: Non-MSME | Q24: A37094 | R24: Supply and installation of IT materials for Upgradation of meeting room / cabin in JFWTC. Details as per annexure. | S24: 252900478 | T24: 46083 | U24: 46076 | V24: 88089 | W24: 46118 | Y24: 46121 | Z24: =$Y$1-Y24 -> -9 | AA24: 0 | AB24: 0 | AC24: 0 | AD24: 0 | AE24: 0 | AF24: 0 | AG24: 1837 | AI24: =E24 -> INR | AJ24: 1 | AK24: =F24*AJ24-L24 -> 1837 | AL24: =N24-AK24 -> 0 | AN24: =$AN$19-Y24 -> -9 | AO24: =IF(AN24<0,"Not Due",IF(AN24<366,"Less than 1 year",IF(AN24<731,"1-2 years",IF(AN24<1096,"2-3 years","More than 3 years")))) -> Not Due
A25: FLOWLINE ENGINEERS A37751 | B25: Project#117399,Task#3202,INV#,Barcode#,Po#100071308,PoLine#1,VendorName-FLOWLINE ENGINEERS A37751,Desc-Transportation charges,PT#1173993202 | C25: 100071308 | D25: GC7399 | E25: INR | F25: 1500 | G25: 1 | H25: 1 | I25: =F25*G25 -> 1500 | J25: =F25*H25 -> 1500 | K25: =J25-I25 -> 0 | L25: 2 | M25: =I25-L25 -> 1498 | N25: =J25-L25 -> 1498 | O25: Opex | P25: Non-MSME | Q25: A37751 | R25: Supply of FLAB0270 ( Ph Booster Chemical). Minimum Packing: 20 Kgs. Qty: 260 Kgs. | S25: 20253593 | T25: 46114 | U25: 46105 | V25: 88579 | W25: 46147 | Y25: 46150 | Z25: =$Y$1-Y25 -> -38 | AA25: 0 | AB25: 0 | AC25: 0 | AD25: 0 | AE25: 0 | AF25: 0 | AG25: 1498 | AI25: =E25 -> INR | AJ25: 1 | AK25: =F25*AJ25-L25 -> 1498 | AL25: =N25-AK25 -> 0 | AN25: =$AN$19-Y25 -> -38 | AO25: =IF(AN25<0,"Not Due",IF(AN25<366,"Less than 1 year",IF(AN25<731,"1-2 years",IF(AN25<1096,"2-3 years","More than 3 years")))) -> Not Due
A26: FLOWLINE ENGINEERS A37751 | B26: Project#117399,Task#3202,INV#,Barcode#,Po#100071308,PoLine#2,VendorName-FLOWLINE ENGINEERS A37751,Desc-Supply of FLAB0270 ( Ph Booster Chemical). Minimum,PT#1173993202 | C26: 100071308 | D26: GC7399 | E26: INR | F26: 50700 | G26: 1 | H26: 1 | I26: =F26*G26 -> 50700 | J26: =F26*H26 -> 50700 | K26: =J26-I26 -> 0 | L26: 51 | M26: =I26-L26 -> 50649 | N26: =J26-L26 -> 50649 | O26: Opex | P26: Non-MSME | Q26: A37751 | R26: Supply of FLAB0270 ( Ph Booster Chemical). Minimum Packing: 20 Kgs. Qty: 260 Kgs. | S26: 20253593 | T26: 46114 | U26: 46105 | V26: 88579 | W26: 46147 | Y26: 46150 | Z26: =$Y$1-Y26 -> -38 | AA26: 0 | AB26: 0 | AC26: 0 | AD26: 0 | AE26: 0 | AF26: 0 | AG26: 50649 | AI26: =E26 -> INR | AJ26: 1 | AK26: =F26*AJ26-L26 -> 50649 | AL26: =N26-AK26 -> 0 | AN26: =$AN$19-Y26 -> -38 | AO26: =IF(AN26<0,"Not Due",IF(AN26<366,"Less than 1 year",IF(AN26<731,"1-2 years",IF(AN26<1096,"2-3 years","More than 3 years")))) -> Not Due
A27: V.R.ASSOCIATES A38920 | B27: Project#117399,Task#4202,INV#,Barcode#,Po#100065841,PoLine#1,VendorName-V.R.ASSOCIATES A38920,Desc-Open PO towards supply of raw water through tanker,PT#1173994202 | C27: 100065841 | D27: GC7399 | E27: INR | F27: 65607 | G27: 1 | H27: 1 | I27: =F27*G27 -> 65607 | J27: =F27*H27 -> 65607 | K27: =J27-I27 -> 0 | L27: 66 | M27: =I27-L27 -> 65541 | N27: =J27-L27 -> 65541 | O27: Opex | P27: Non-MSME | Q27: A38920 | R27: Open PO towards supply of raw water through tankers from Mar 2025 to Feb 2026 at JFWTC, Bangalore. Billing to be done at actual quantity supplied. Refer annexure for details. | S27: 1168/25 | T27: 46113 | U27: 46083 | V27: 88129 | W27: 46120 | Y27: 46113 | Z27: =$Y$1-Y27 -> -1 | AA27: 0 | AB27: 0 | AC27: 0 | AD27: 0 | AE27: 0 | AF27: 0 | AG27: 65541 | AI27: =E27 -> INR | AJ27: 1 | AK27: =F27*AJ27-L27 -> 65541 | AL27: =N27-AK27 -> 0 | AM27: =N27 -> 65541 | AN27: =$AN$19-Y27 -> -1 | AO27: =IF(AN27<0,"Not Due",IF(AN27<366,"Less than 1 year",IF(AN27<731,"1-2 years",IF(AN27<1096,"2-3 years","More than 3 years")))) -> Not Due
A28: V.R.ASSOCIATES A38920 | B28: Project#117399,Task#4202,INV#,Barcode#,Po#100065841,PoLine#2,VendorName-V.R.ASSOCIATES A38920,Desc-Amendment: Open PO towards supply of raw water thr,PT#1173994202 | C28: 100065841 | D28: GC7399 | E28: INR | F28: 200000 | G28: 1 | H28: 1 | I28: =F28*G28 -> 200000 | J28: =F28*H28 -> 200000 | K28: =J28-I28 -> 0 | L28: 200 | M28: =I28-L28 -> 199800 | N28: =J28-L28 -> 199800 | O28: Opex | P28: Non-MSME | Q28: A38920 | R28: Open PO towards supply of raw water through tankers from Mar 2025 to Feb 2026 at JFWTC, Bangalore. Billing to be done at actual quantity supplied. Refer annexure for details. | S28: 1168/25 | T28: 46113 | U28: 46083 | V28: 88129 | W28: 46120 | Y28: 46113 | Z28: =$Y$1-Y28 -> -1 | AA28: 0 | AB28: 0 | AC28: 0 | AD28: 0 | AE28: 0 | AF28: 0 | AG28: 199800 | AI28: =E28 -> INR | AJ28: 1 | AK28: =F28*AJ28-L28 -> 199800 | AL28: =N28-AK28 -> 0 | AM28: =N28 -> 199800 | AN28: =$AN$19-Y28 -> -1 | AO28: =IF(AN28<0,"Not Due",IF(AN28<366,"Less than 1 year",IF(AN28<731,"1-2 years",IF(AN28<1096,"2-3 years","More than 3 years")))) -> Not Due
A29: V.R.ASSOCIATES A38920 | B29: Project#117399,Task#4202,INV#,Barcode#,Po#100065841,PoLine#3,VendorName-V.R.ASSOCIATES A38920,Desc-Amendment: Open PO towards supply of raw water thr,PT#1173994202 | C29: 100065841 | D29: GC7399 | E29: INR | F29: 100000 | G29: 1 | H29: 1 | I29: =F29*G29 -> 100000 | J29: =F29*H29 -> 100000 | K29: =J29-I29 -> 0 | L29: 100 | M29: =I29-L29 -> 99900 | N29: =J29-L29 -> 99900 | O29: Opex | P29: Non-MSME | Q29: A38920 | R29: Open PO towards supply of raw water through tankers from Mar 2025 to Feb 2026 at JFWTC, Bangalore. Billing to be done at actual quantity supplied. Refer annexure for details. | S29: 1168/25 | T29: 46113 | U29: 46083 | V29: 88129 | W29: 46120 | Y29: 46113 | Z29: =$Y$1-Y29 -> -1 | AA29: 0 | AB29: 0 | AC29: 0 | AD29: 0 | AE29: 0 | AF29: 0 | AG29: 99900 | AI29: =E29 -> INR | AJ29: 1 | AK29: =F29*AJ29-L29 -> 99900 | AL29: =N29-AK29 -> 0 | AN29: =$AN$19-Y29 -> -1 | AO29: =IF(AN29<0,"Not Due",IF(AN29<366,"Less than 1 year",IF(AN29<731,"1-2 years",IF(AN29<1096,"2-3 years","More than 3 years")))) -> Not Due
A30: V.R.ASSOCIATES A38920 | B30: Project#117399,Task#4202,INV#,Barcode#,Po#100070452,PoLine#1,VendorName-V.R.ASSOCIATES A38920,Desc-Open PO towards supply of raw water through tanker,PT#1173994202 | C30: 100070452 | D30: GC7399 | E30: INR | F30: 365607 | G30: 1 | H30: 1 | I30: =F30*G30 -> 365607 | J30: =F30*H30 -> 365607 | K30: =J30-I30 -> 0 | L30: 366 | M30: =I30-L30 -> 365241 | N30: =J30-L30 -> 365241 | O30: Opex | P30: Non-MSME | Q30: A38920 | R30: Open PO towards supply of raw water through tankers from Mar 2026 to Feb 2027 at JFWTC, Bangalore. Billing to be done at actual quantity supplied. Refer annexure for details. | S30: 1168/25 | T30: 46113 | U30: 46083 | V30: 88129 | W30: 46120 | Y30: 46113 | Z30: =$Y$1-Y30 -> -1 | AA30: 0 | AB30: 0 | AC30: 0 | AD30: 0 | AE30: 0 | AF30: 0 | AG30: 365241 | AI30: =E30 -> INR | AJ30: 1 | AK30: =F30*AJ30-L30 -> 365241 | AL30: =N30-AK30 -> 0 | AN30: =$AN$19-Y30 -> -1 | AO30: =IF(AN30<0,"Not Due",IF(AN30<366,"Less than 1 year",IF(AN30<731,"1-2 years",IF(AN30<1096,"2-3 years","More than 3 years")))) -> Not Due
A31: INFINITI POWER PRIVATE LIMITED A37094 | B31: Project#117699,Task#5506,INV#,Barcode#,Po#100071161,PoLine#1,VendorName-INFINITI POWER PRIVATE LIMITED A37094,Desc-Supply of materials for Pioneer and Pathfinder IDF,PT#1176995506 | C31: 100071161 | D31: GC7699 | E31: INR | F31: 95644 | G31: 1 | H31: 1 | I31: =F31*G31 -> 95644 | J31: =F31*H31 -> 95644 | K31: =J31-I31 -> 0 | L31: 96 | M31: =I31-L31 -> 95548 | N31: =J31-L31 -> 95548 | O31: Opex | P31: Non-MSME | Q31: A37094 | R31: Supply and Installation of materials for Pioneer and Pathfinder IDF raiser cable jack panel solution work- Details as per annexure | S31: 252900508 | T31: 46104 | U31: 46098 | V31: 88490 | W31: 46143 | Y31: 46143 | Z31: =$Y$1-Y31 -> -31 | AA31: 0 | AB31: 0 | AC31: 0 | AD31: 0 | AE31: 0 | AF31: 0 | AG31: 95548 | AI31: =E31 -> INR | AJ31: 1 | AK31: =F31*AJ31-L31 -> 95548 | AL31: =N31-AK31 -> 0 | AM31: =N31 -> 95548 | AN31: =$AN$19-Y31 -> -31 | AO31: =IF(AN31<0,"Not Due",IF(AN31<366,"Less than 1 year",IF(AN31<731,"1-2 years",IF(AN31<1096,"2-3 years","More than 3 years")))) -> Not Due
A32: INFINITI POWER PRIVATE LIMITED A37094 | B32: Project#117699,Task#5506,INV#,Barcode#,Po#100071167,PoLine#1,VendorName-INFINITI POWER PRIVATE LIMITED A37094,Desc-Supply of IT Network rack materials at Gate2 (Visi,PT#1176995506 | C32: 100071167 | D32: GC7699 | E32: INR | F32: 3216 | G32: 1 | H32: 1 | I32: =F32*G32 -> 3216 | J32: =F32*H32 -> 3216 | K32: =J32-I32 -> 0 | L32: 3 | M32: =I32-L32 -> 3213 | N32: =J32-L32 -> 3213 | O32: Opex | P32: Non-MSME | Q32: A37094 | R32: Supply and installation of IT Network rack materials at Gate2 (Visitor Gate) JFWTC. Details as per annexure. | S32: 252900519 | T32: 46119 | U32: 46105 | V32: 88570 | W32: 46147 | Y32: 46150 | Z32: =$Y$1-Y32 -> -38 | AA32: 0 | AB32: 0 | AC32: 0 | AD32: 0 | AE32: 0 | AF32: 0 | AG32: 3213 | AI32: =E32 -> INR | AJ32: 1 | AK32: =F32*AJ32-L32 -> 3213 | AL32: =N32-AK32 -> 0 | AM32: =N32 -> 3213 | AN32: =$AN$19-Y32 -> -38 | AO32: =IF(AN32<0,"Not Due",IF(AN32<366,"Less than 1 year",IF(AN32<731,"1-2 years",IF(AN32<1096,"2-3 years","More than 3 years")))) -> Not Due
A33: SR TECHTRONICS A39006 | B33: Project#119410,Task#3200,INV#,Barcode#,Po#100070367,PoLine#1,VendorName-SR TECHTRONICS A39006,Desc-Supply of spring Φ0.1*0.65*0.45*4000mm Material- ,PT#1194103200 | C33: 100070367 | D33: GC9410 | E33: INR | F33: 108000 | G33: 1 | H33: 1 | I33: =F33*G33 -> 108000 | J33: =F33*H33 -> 108000 | K33: =J33-I33 -> 0 | L33: 108 | M33: =I33-L33 -> 107892 | N33: =J33-L33 -> 107892 | O33: Opex | P33: Non-MSME | Q33: A39006 | R33: Supply of spring Φ0.1*0.65*0.45*4000mm Material- SUS304 Surface treatment-primary colors. | S33: SRT-CI/A/1114 | T33: 46119 | U33: 46099 | V33: 88532 | W33: 46143 | Y33: 46144 | Z33: =$Y$1-Y33 -> -32 | AA33: 0 | AB33: 0 | AC33: 0 | AD33: 0 | AE33: 0 | AF33: 0 | AG33: 107892 | AI33: =E33 -> INR | AJ33: 1 | AK33: =F33*AJ33-L33 -> 107892 | AL33: =N33-AK33 -> 0 | AM33: =N33 -> 107892 | AN33: =$AN$19-Y33 -> -32 | AO33: =IF(AN33<0,"Not Due",IF(AN33<366,"Less than 1 year",IF(AN33<731,"1-2 years",IF(AN33<1096,"2-3 years","More than 3 years")))) -> Not Due
A34: UNITRON INSTRUMENTATION TECHNOLOGY PVT. LTD. A37912 | B34: Project#119410,Task#3200,INV#,Barcode#,Po#100070681,PoLine#1,VendorName-UNITRON INSTRUMENTATION TECHNOLOGY PVT. LTD. A37912,Desc-Laboratory supplies and fixtures - WHEEL GUARD FOR,PT#1194103200 | C34: 100070681 | D34: GC9410 | E34: INR | F34: 65400 | G34: 1 | H34: 1 | I34: =F34*G34 -> 65400 | J34: =F34*H34 -> 65400 | K34: =J34-I34 -> 0 | L34: 65 | M34: =I34-L34 -> 65335 | N34: =J34-L34 -> 65335 | O34: Opex | P34: Non-MSME | Q34: A37912 | R34: Laboratory supplies and fixtures - WHEEL GUARD FOR MECATOME T210 Cutting Machine | S34: 635/2025-26 | T34: 46114 | U34: 46104 | V34: 88468 | W34: 46136 | Y34: 46134 | Z34: =$Y$1-Y34 -> -22 | AA34: 0 | AB34: 0 | AC34: 0 | AD34: 0 | AE34: 0 | AF34: 0 | AG34: 65335 | AI34: =E34 -> INR | AJ34: 1 | AK34: =F34*AJ34-L34 -> 65335 | AL34: =N34-AK34 -> 0 | AM34: =N34 -> 65335 | AN34: =$AN$19-Y34 -> -22 | AO34: =IF(AN34<0,"Not Due",IF(AN34<366,"Less than 1 year",IF(AN34<731,"1-2 years",IF(AN34<1096,"2-3 years","More than 3 years")))) -> Not Due
A35: MISUMI INDIA PRIVATE LIMITED A38891 | B35: Project#119410,Task#3200,INV#,Barcode#,Po#100070754,PoLine#1,VendorName-MISUMI INDIA PRIVATE LIMITED A38891,Desc-C-HTBN120S3M-60, Timing Belt,PT#1194103200 | C35: 100070754 | D35: GC9410 | E35: INR | F35: 3340 | G35: 1 | H35: 1 | I35: =F35*G35 -> 3340 | J35: =F35*H35 -> 3340 | K35: =J35-I35 -> 0 | L35: 3 | M35: =I35-L35 -> 3337 | N35: =J35-L35 -> 3337 | O35: Opex | P35: Non-MSME | Q35: A38891 | R35: C-HTBN126S3M-60 Timing Belt | S35: ID325084330 | T35: 46114 | U35: 46097 | V35: 88390 | W35: 46134 | Y35: 46127 | Z35: =$Y$1-Y35 -> -15 | AA35: 0 | AB35: 0 | AC35: 0 | AD35: 0 | AE35: 0 | AF35: 0 | AG35: 3337 | AI35: =E35 -> INR | AJ35: 1 | AK35: =F35*AJ35-L35 -> 3337 | AL35: =N35-AK35 -> 0 | AM35: =N35 -> 3337 | AN35: =$AN$19-Y35 -> -15 | AO35: =IF(AN35<0,"Not Due",IF(AN35<366,"Less than 1 year",IF(AN35<731,"1-2 years",IF(AN35<1096,"2-3 years","More than 3 years")))) -> Not Due
A36: MISUMI INDIA PRIVATE LIMITED A38891 | B36: Project#119410,Task#3200,INV#,Barcode#,Po#100070754,PoLine#2,VendorName-MISUMI INDIA PRIVATE LIMITED A38891,Desc-C-HTBN123S3M-60, Timing Belt,PT#1194103200 | C36: 100070754 | D36: GC9410 | E36: INR | F36: 3030 | G36: 1 | H36: 1 | I36: =F36*G36 -> 3030 | J36: =F36*H36 -> 3030 | K36: =J36-I36 -> 0 | L36: 3 | M36: =I36-L36 -> 3027 | N36: =J36-L36 -> 3027 | O36: Opex | P36: Non-MSME | Q36: A38891 | R36: C-HTBN126S3M-60 Timing Belt | S36: ID325084330 | T36: 46114 | U36: 46097 | V36: 88390 | W36: 46134 | Y36: 46127 | Z36: =$Y$1-Y36 -> -15 | AA36: 0 | AB36: 0 | AC36: 0 | AD36: 0 | AE36: 0 | AF36: 0 | AG36: 3027 | AI36: =E36 -> INR | AJ36: 1 | AK36: =F36*AJ36-L36 -> 3027 | AL36: =N36-AK36 -> 0 | AM36: =N36 -> 3027 | AN36: =$AN$19-Y36 -> -15 | AO36: =IF(AN36<0,"Not Due",IF(AN36<366,"Less than 1 year",IF(AN36<731,"1-2 years",IF(AN36<1096,"2-3 years","More than 3 years")))) -> Not Due
A37: MISUMI INDIA PRIVATE LIMITED A38891 | B37: Project#119410,Task#3200,INV#,Barcode#,Po#100070754,PoLine#3,VendorName-MISUMI INDIA PRIVATE LIMITED A38891,Desc-C-HTBN126S3M-60, Timing Belt,PT#1194103200 | C37: 100070754 | D37: GC9410 | E37: INR | F37: 1320.8 | G37: 1 | H37: 1 | I37: =F37*G37 -> 1320.8 | J37: =F37*H37 -> 1320.8 | K37: =J37-I37 -> 0 | L37: 1 | M37: =I37-L37 -> 1319.8 | N37: =J37-L37 -> 1319.8 | O37: Opex | P37: Non-MSME | Q37: A38891 | R37: C-HTBN126S3M-60 Timing Belt | S37: ID325084330 | T37: 46114 | U37: 46097 | V37: 88390 | W37: 46134 | Y37: 46127 | Z37: =$Y$1-Y37 -> -15 | AA37: 0 | AB37: 0 | AC37: 0 | AD37: 0 | AE37: 0 | AF37: 0 | AG37: 1319.8 | AI37: =E37 -> INR | AJ37: 1 | AK37: =F37*AJ37-L37 -> 1319.8 | AL37: =N37-AK37 -> 0 | AM37: =N37 -> 1319.8 | AN37: =$AN$19-Y37 -> -15 | AO37: =IF(AN37<0,"Not Due",IF(AN37<366,"Less than 1 year",IF(AN37<731,"1-2 years",IF(AN37<1096,"2-3 years","More than 3 years")))) -> Not Due
A38: MISUMI INDIA PRIVATE LIMITED A38891 | B38: Project#119410,Task#3200,INV#,Barcode#,Po#100070754,PoLine#5,VendorName-MISUMI INDIA PRIVATE LIMITED A38891,Desc-HTPA15S3M060-A-H4, Timing Pulley,PT#1194103200 | C38: 100070754 | D38: GC9410 | E38: INR | F38: 6181.9 | G38: 1 | H38: 1 | I38: =F38*G38 -> 6181.9 | J38: =F38*H38 -> 6181.9 | K38: =J38-I38 -> 0 | L38: 6 | M38: =I38-L38 -> 6175.9 | N38: =J38-L38 -> 6175.9 | O38: Opex | P38: Non-MSME | Q38: A38891 | R38: C-HTBN126S3M-60 Timing Belt | S38: ID325084330 | T38: 46114 | U38: 46097 | V38: 88390 | W38: 46134 | Y38: 46127 | Z38: =$Y$1-Y38 -> -15 | AA38: 0 | AB38: 0 | AC38: 0 | AD38: 0 | AE38: 0 | AF38: 0 | AG38: 6175.9 | AI38: =E38 -> INR | AJ38: 1 | AK38: =F38*AJ38-L38 -> 6175.9 | AL38: =N38-AK38 -> 0 | AM38: =N38 -> 6175.9 | AN38: =$AN$19-Y38 -> -15 | AO38: =IF(AN38<0,"Not Due",IF(AN38<366,"Less than 1 year",IF(AN38<731,"1-2 years",IF(AN38<1096,"2-3 years","More than 3 years")))) -> Not Due
A39: INDO-MIM LIMITED | B39: Project#119410,Task#3200,INV#,Barcode#,Po#100070932,PoLine#1,VendorName-INDO-MIM LIMITED,Desc-Supply of 4013796-746B, WOBBLE WASHER 2X, 17-4 PH ,PT#1194103200 | C39: 100070932 | D39: GC9410 | E39: INR | F39: 264798.31 | G39: 1 | H39: 1 | I39: =F39*G39 -> 264798.31 | J39: =F39*H39 -> 264798.31 | K39: =J39-I39 -> 0 | L39: 265 | M39: =I39-L39 -> 264533.31 | N39: =J39-L39 -> 264533.31 | O39: Opex | P39: Non-MSME | Q39: A38418 | R39: Supply of 4013796-746B, WOBBLE WASHER 2X, 17-4 PH material, 600 Quantity | S39: D-D2867/2526 | T39: 46114 | U39: 46102 | V39: 88315 | W39: 46129 | Y39: 46132 | Z39: =$Y$1-Y39 -> -20 | AA39: 0 | AB39: 0 | AC39: 0 | AD39: 0 | AE39: 0 | AF39: 0 | AG39: 264533.31 | AI39: =E39 -> INR | AJ39: 1 | AK39: =F39*AJ39-L39 -> 264533.31 | AL39: =N39-AK39 -> 0 | AM39: =N39 -> 264533.31 | AN39: =$AN$19-Y39 -> -20 | AO39: =IF(AN39<0,"Not Due",IF(AN39<366,"Less than 1 year",IF(AN39<731,"1-2 years",IF(AN39<1096,"2-3 years","More than 3 years")))) -> Not Due
A40: INDO-MIM LIMITED | B40: Project#119410,Task#3200,INV#,Barcode#,Po#100070932,PoLine#2,VendorName-INDO-MIM LIMITED,Desc-Supply of 4013796-747B, SEGMENT DIVIDER 2X, 17-4 ,PT#1194103200 | C40: 100070932 | D40: GC9410 | E40: INR | F40: 355000 | G40: 1 | H40: 1 | I40: =F40*G40 -> 355000 | J40: =F40*H40 -> 355000 | K40: =J40-I40 -> 0 | L40: 355 | M40: =I40-L40 -> 354645 | N40: =J40-L40 -> 354645 | O40: Opex | P40: Non-MSME | Q40: A38418 | R40: Supply of 4013796-746B, WOBBLE WASHER 2X, 17-4 PH material, 600 Quantity | S40: D-D2867/2526 | T40: 46114 | U40: 46102 | V40: 88315 | W40: 46129 | Y40: 46132 | Z40: =$Y$1-Y40 -> -20 | AA40: 0 | AB40: 0 | AC40: 0 | AD40: 0 | AE40: 0 | AF40: 0 | AG40: 354645 | AI40: =E40 -> INR | AJ40: 1 | AK40: =F40*AJ40-L40 -> 354645 | AL40: =N40-AK40 -> 0 | AM40: =N40 -> 354645 | AN40: =$AN$19-Y40 -> -20 | AO40: =IF(AN40<0,"Not Due",IF(AN40<366,"Less than 1 year",IF(AN40<731,"1-2 years",IF(AN40<1096,"2-3 years","More than 3 years")))) -> Not Due
A41: MISUMI INDIA PRIVATE LIMITED A38891 | B41: Project#119410,Task#3200,INV#,Barcode#,Po#100070964,PoLine#2,VendorName-MISUMI INDIA PRIVATE LIMITED A38891,Desc-C-HTBN123S3M-60 BELT(MISUMI),PT#1194103200 | C41: 100070964 | D41: GC9410 | E41: INR | F41: 1515 | G41: 1 | H41: 1 | I41: =F41*G41 -> 1515 | J41: =F41*H41 -> 1515 | K41: =J41-I41 -> 0 | L41: 2 | M41: =I41-L41 -> 1513 | N41: =J41-L41 -> 1513 | O41: Opex | P41: Non-MSME | Q41: A38891 | R41: C-HTBN126S3M-60ECONOMY_BELT(MISUMI) | S41: ID325084332 | T41: 46125 | U41: 46097 | V41: 88399 | W41: 46135 | Y41: 46127 | Z41: =$Y$1-Y41 -> -15 | AA41: 0 | AB41: 0 | AC41: 0 | AD41: 0 | AE41: 0 | AF41: 0 | AG41: 1513 | AI41: =E41 -> INR | AJ41: 1 | AK41: =F41*AJ41-L41 -> 1513 | AL41: =N41-AK41 -> 0 | AM41: =N41 -> 1513 | AN41: =$AN$19-Y41 -> -15 | AO41: =IF(AN41<0,"Not Due",IF(AN41<366,"Less than 1 year",IF(AN41<731,"1-2 years",IF(AN41<1096,"2-3 years","More than 3 years")))) -> Not Due
A42: MISUMI INDIA PRIVATE LIMITED A38891 | B42: Project#119410,Task#3200,INV#,Barcode#,Po#100070964,PoLine#4,VendorName-MISUMI INDIA PRIVATE LIMITED A38891,Desc-C-HTBN129S3M-60 BELT(MISUMI),PT#1194103200 | C42: 100070964 | D42: GC9410 | E42: INR | F42: 2121 | G42: 1 | H42: 1 | I42: =F42*G42 -> 2121 | J42: =F42*H42 -> 2121 | K42: =J42-I42 -> 0 | L42: 2 | M42: =I42-L42 -> 2119 | N42: =J42-L42 -> 2119 | O42: Opex | P42: Non-MSME | Q42: A38891 | R42: C-HTBN126S3M-60ECONOMY_BELT(MISUMI) | S42: ID325084332 | T42: 46125 | U42: 46097 | V42: 88399 | W42: 46135 | Y42: 46127 | Z42: =$Y$1-Y42 -> -15 | AA42: 0 | AB42: 0 | AC42: 0 | AD42: 0 | AE42: 0 | AF42: 0 | AG42: 2119 | AI42: =E42 -> INR | AJ42: 1 | AK42: =F42*AJ42-L42 -> 2119 | AL42: =N42-AK42 -> 0 | AM42: =N42 -> 2119 | AN42: =$AN$19-Y42 -> -15 | AO42: =IF(AN42<0,"Not Due",IF(AN42<366,"Less than 1 year",IF(AN42<731,"1-2 years",IF(AN42<1096,"2-3 years","More than 3 years")))) -> Not Due
A43: MISUMI INDIA PRIVATE LIMITED A38891 | B43: Project#119410,Task#3200,INV#,Barcode#,Po#100070964,PoLine#6,VendorName-MISUMI INDIA PRIVATE LIMITED A38891,Desc-HTPA15S3M060-A-H4 HIGH TORQUE TIMING PULLEY(MISUMI,PT#1194103200 | C43: 100070964 | D43: GC9410 | E43: INR | F43: 6181.9 | G43: 1 | H43: 1 | I43: =F43*G43 -> 6181.9 | J43: =F43*H43 -> 6181.9 | K43: =J43-I43 -> 0 | L43: 6 | M43: =I43-L43 -> 6175.9 | N43: =J43-L43 -> 6175.9 | O43: Opex | P43: Non-MSME | Q43: A38891 | R43: C-HTBN126S3M-60ECONOMY_BELT(MISUMI) | S43: ID325084332 | T43: 46125 | U43: 46097 | V43: 88399 | W43: 46135 | Y43: 46127 | Z43: =$Y$1-Y43 -> -15 | AA43: 0 | AB43: 0 | AC43: 0 | AD43: 0 | AE43: 0 | AF43: 0 | AG43: 6175.9 | AI43: =E43 -> INR | AJ43: 1 | AK43: =F43*AJ43-L43 -> 6175.9 | AL43: =N43-AK43 -> 0 | AM43: =N43 -> 6175.9 | AN43: =$AN$19-Y43 -> -15 | AO43: =IF(AN43<0,"Not Due",IF(AN43<366,"Less than 1 year",IF(AN43<731,"1-2 years",IF(AN43<1096,"2-3 years","More than 3 years")))) -> Not Due
A44: MISUMI INDIA PRIVATE LIMITED A38891 | B44: Project#119410,Task#3200,INV#,Barcode#,Po#100071238,PoLine#1,VendorName-MISUMI INDIA PRIVATE LIMITED A38891,Desc-C-HTPA32S3M060-A-P8 ECONOMIC TIMING PULLEY(MISUMI),PT#1194103200 | C44: 100071238 | D44: GC9410 | E44: INR | F44: 2536.8 | G44: 1 | H44: 1 | I44: =F44*G44 -> 2536.8 | J44: =F44*H44 -> 2536.8 | K44: =J44-I44 -> 0 | L44: 3 | M44: =I44-L44 -> 2533.8 | N44: =J44-L44 -> 2533.8 | O44: Opex | P44: Non-MSME | Q44: A38891 | R44: C-HTPA32S3M060-A-P8ECONOMIC TIMING PULLEY(MISUMI) | S44: ID325084834 | T44: 46114 | U44: 46098 | V44: 88390 | W44: 46134 | Y44: 46128 | Z44: =$Y$1-Y44 -> -16 | AA44: 0 | AB44: 0 | AC44: 0 | AD44: 0 | AE44: 0 | AF44: 0 | AG44: 2533.8 | AI44: =E44 -> INR | AJ44: 1 | AK44: =F44*AJ44-L44 -> 2533.8 | AL44: =N44-AK44 -> 0 | AM44: =N44 -> 2533.8 | AN44: =$AN$19-Y44 -> -16 | AO44: =IF(AN44<0,"Not Due",IF(AN44<366,"Less than 1 year",IF(AN44<731,"1-2 years",IF(AN44<1096,"2-3 years","More than 3 years")))) -> Not Due
A45: ELEMENT14 INDIA PRIVATE LIMITED A36095 | B45: Project#271164,Task#1007,INV#,Barcode#,Po#100070381,PoLine#1,VendorName-ELEMENT14 INDIA PRIVATE LIMITED A36095,Desc-EMI GASKET, RECTANGLE, 113DB. Manufacturer part no,PT#2711641007 | C45: 100070381 | D45: GRAS01 | E45: INR | F45: 2468.38 | G45: 1 | H45: 1 | I45: =F45*G45 -> 2468.38 | J45: =F45*H45 -> 2468.38 | K45: =J45-I45 -> 0 | L45: 2 | M45: =I45-L45 -> 2466.38 | N45: =J45-L45 -> 2466.38 | O45: Opex | P45: Non-MSME | Q45: A36095 | R45: FINGER GUARD; Fan Guard TypePlastic; Manufacturer part no MC33018 | S45: 1054301 | T45: 46105 | U45: 46097 | V45: 88239 | W45: 46125 | Y45: 46127 | Z45: =$Y$1-Y45 -> -15 | AA45: 0 | AB45: 0 | AC45: 0 | AD45: 0 | AE45: 0 | AF45: 0 | AG45: 2466.38 | AI45: =E45 -> INR | AJ45: 1 | AK45: =F45*AJ45-L45 -> 2466.38 | AL45: =N45-AK45 -> 0 | AM45: =N45 -> 2466.38 | AN45: =$AN$19-Y45 -> -15 | AO45: =IF(AN45<0,"Not Due",IF(AN45<366,"Less than 1 year",IF(AN45<731,"1-2 years",IF(AN45<1096,"2-3 years","More than 3 years")))) -> Not Due
A46: BANGALORE FLUID SYSTEM COMPONENTS PRIVATE LIMITED A37680 | B46: Project#271164,Task#1007,INV#,Barcode#,Po#100071145,PoLine#1,VendorName-BANGALORE FLUID SYSTEM COMPONENTS PRIVATE LIMITED A37680,Desc-Freight Charges,PT#2711641007 | C46: 100071145 | D46: GRAS01 | E46: INR | F46: 5000 | G46: 1 | H46: 1 | I46: =F46*G46 -> 5000 | J46: =F46*H46 -> 5000 | K46: =J46-I46 -> 0 | L46: 5 | M46: =I46-L46 -> 4995 | N46: =J46-L46 -> 4995 | O46: Opex | P46: Non-MSME | Q46: A37680 | R46: Transportation Charges | S46: 10025183 | T46: 46094 | U46: 46091 | V46: 88302 | W46: 46128 | Y46: 46121 | Z46: =$Y$1-Y46 -> -9 | AA46: 0 | AB46: 0 | AC46: 0 | AD46: 0 | AE46: 0 | AF46: 0 | AG46: 4995 | AI46: =E46 -> INR | AJ46: 1 | AK46: =F46*AJ46-L46 -> 4995 | AL46: =N46-AK46 -> 0 | AM46: =N46 -> 4995 | AN46: =$AN$19-Y46 -> -9 | AO46: =IF(AN46<0,"Not Due",IF(AN46<366,"Less than 1 year",IF(AN46<731,"1-2 years",IF(AN46<1096,"2-3 years","More than 3 years")))) -> Not Due
A47: BANGALORE FLUID SYSTEM COMPONENTS PRIVATE LIMITED A37680 | B47: Project#271164,Task#1007,INV#,Barcode#,Po#100071145,PoLine#10,VendorName-BANGALORE FLUID SYSTEM COMPONENTS PRIVATE LIMITED A37680,Desc-THT-3R60-9.53-1.24 SS Tubing 3/8ODx0.049WT (SS-T,PT#2711641007 | C47: 100071145 | D47: GRAS01 | E47: INR | F47: 9541.8 | G47: 1 | H47: 1 | I47: =F47*G47 -> 9541.8 | J47: =F47*H47 -> 9541.8 | K47: =J47-I47 -> 0 | L47: 10 | M47: =I47-L47 -> 9531.8 | N47: =J47-L47 -> 9531.8 | O47: Opex | P47: Non-MSME | Q47: A37680 | R47: Transportation Charges | S47: 10025183 | T47: 46094 | U47: 46091 | V47: 88302 | W47: 46128 | Y47: 46121 | Z47: =$Y$1-Y47 -> -9 | AA47: 0 | AB47: 0 | AC47: 0 | AD47: 0 | AE47: 0 | AF47: 0 | AG47: 9531.8 | AI47: =E47 -> INR | AJ47: 1 | AK47: =F47*AJ47-L47 -> 9531.8 | AL47: =N47-AK47 -> 0 | AM47: =N47 -> 9531.8 | AN47: =$AN$19-Y47 -> -9 | AO47: =IF(AN47<0,"Not Due",IF(AN47<366,"Less than 1 year",IF(AN47<731,"1-2 years",IF(AN47<1096,"2-3 years","More than 3 years")))) -> Not Due
A48: BANGALORE FLUID SYSTEM COMPONENTS PRIVATE LIMITED A37680 | B48: Project#271164,Task#1007,INV#,Barcode#,Po#100071145,PoLine#11,VendorName-BANGALORE FLUID SYSTEM COMPONENTS PRIVATE LIMITED A37680,Desc-Transportation Charges,PT#2711641007 | C48: 100071145 | D48: GRAS01 | E48: INR | F48: 1000 | G48: 1 | H48: 1 | I48: =F48*G48 -> 1000 | J48: =F48*H48 -> 1000 | K48: =J48-I48 -> 0 | L48: 1 | M48: =I48-L48 -> 999 | N48: =J48-L48 -> 999 | O48: Opex | P48: Non-MSME | Q48: A37680 | R48: Transportation Charges | S48: 10025183 | T48: 46094 | U48: 46091 | V48: 88302 | W48: 46128 | Y48: 46121 | Z48: =$Y$1-Y48 -> -9 | AA48: 0 | AB48: 0 | AC48: 0 | AD48: 0 | AE48: 0 | AF48: 0 | AG48: 999 | AI48: =E48 -> INR | AJ48: 1 | AK48: =F48*AJ48-L48 -> 999 | AL48: =N48-AK48 -> 0 | AM48: =N48 -> 999 | AN48: =$AN$19-Y48 -> -9 | AO48: =IF(AN48<0,"Not Due",IF(AN48<366,"Less than 1 year",IF(AN48<731,"1-2 years",IF(AN48<1096,"2-3 years","More than 3 years")))) -> Not Due
A49: BANGALORE FLUID SYSTEM COMPONENTS PRIVATE LIMITED A37680 | B49: Project#271164,Task#1007,INV#,Barcode#,Po#100071145,PoLine#2,VendorName-BANGALORE FLUID SYSTEM COMPONENTS PRIVATE LIMITED A37680,Desc-SS-4-RS-2V Stainless Steel Gasket for 1/4 in. ISO ,PT#2711641007 | C49: 100071145 | D49: GRAS01 | E49: INR | F49: 10305 | G49: 1 | H49: 1 | I49: =F49*G49 -> 10305 | J49: =F49*H49 -> 10305 | K49: =J49-I49 -> 0 | L49: 10 | M49: =I49-L49 -> 10295 | N49: =J49-L49 -> 10295 | O49: Opex | P49: Non-MSME | Q49: A37680 | R49: Transportation Charges | S49: 10025183 | T49: 46094 | U49: 46091 | V49: 88302 | W49: 46128 | Y49: 46121 | Z49: =$Y$1-Y49 -> -9 | AA49: 0 | AB49: 0 | AC49: 0 | AD49: 0 | AE49: 0 | AF49: 0 | AG49: 10295 | AI49: =E49 -> INR | AJ49: 1 | AK49: =F49*AJ49-L49 -> 10295 | AL49: =N49-AK49 -> 0 | AM49: =N49 -> 10295 | AN49: =$AN$19-Y49 -> -9 | AO49: =IF(AN49<0,"Not Due",IF(AN49<366,"Less than 1 year",IF(AN49<731,"1-2 years",IF(AN49<1096,"2-3 years","More than 3 years")))) -> Not Due
A50: BANGALORE FLUID SYSTEM COMPONENTS PRIVATE LIMITED A37680 | B50: Project#271164,Task#1007,INV#,Barcode#,Po#100071145,PoLine#6,VendorName-BANGALORE FLUID SYSTEM COMPONENTS PRIVATE LIMITED A37680,Desc-SS-600-61 Stainless Steel Swagelok Fitting, Bulkhe,PT#2711641007 | C50: 100071145 | D50: GRAS01 | E50: INR | F50: 6606 | G50: 1 | H50: 1 | I50: =F50*G50 -> 6606 | J50: =F50*H50 -> 6606 | K50: =J50-I50 -> 0 | L50: 7 | M50: =I50-L50 -> 6599 | N50: =J50-L50 -> 6599 | O50: Opex | P50: Non-MSME | Q50: A37680 | R50: Transportation Charges | S50: 10025183 | T50: 46094 | U50: 46091 | V50: 88302 | W50: 46128 | Y50: 46121 | Z50: =$Y$1-Y50 -> -9 | AA50: 0 | AB50: 0 | AC50: 0 | AD50: 0 | AE50: 0 | AF50: 0 | AG50: 6599 | AI50: =E50 -> INR | AJ50: 1 | AK50: =F50*AJ50-L50 -> 6599 | AL50: =N50-AK50 -> 0 | AN50: =$AN$19-Y50 -> -9 | AO50: =IF(AN50<0,"Not Due",IF(AN50<366,"Less than 1 year",IF(AN50<731,"1-2 years",IF(AN50<1096,"2-3 years","More than 3 years")))) -> Not Due
A51: BANGALORE FLUID SYSTEM COMPONENTS PRIVATE LIMITED A37680 | B51: Project#271164,Task#1007,INV#,Barcode#,Po#100071145,PoLine#8,VendorName-BANGALORE FLUID SYSTEM COMPONENTS PRIVATE LIMITED A37680,Desc-SS-600-SET 316 Stainless Steel Ferrule Set (1 Fron,PT#2711641007 | C51: 100071145 | D51: GRAS01 | E51: INR | F51: 6498 | G51: 1 | H51: 1 | I51: =F51*G51 -> 6498 | J51: =F51*H51 -> 6498 | K51: =J51-I51 -> 0 | L51: 6 | M51: =I51-L51 -> 6492 | N51: =J51-L51 -> 6492 | O51: Opex | P51: Non-MSME | Q51: A37680 | R51: Transportation Charges | S51: 10025183 | T51: 46094 | U51: 46091 | V51: 88302 | W51: 46128 | Y51: 46121 | Z51: =$Y$1-Y51 -> -9 | AA51: 0 | AB51: 0 | AC51: 0 | AD51: 0 | AE51: 0 | AF51: 0 | AG51: 6492 | AI51: =E51 -> INR | AJ51: 1 | AK51: =F51*AJ51-L51 -> 6492 | AL51: =N51-AK51 -> 0 | AN51: =$AN$19-Y51 -> -9 | AO51: =IF(AN51<0,"Not Due",IF(AN51<366,"Less than 1 year",IF(AN51<731,"1-2 years",IF(AN51<1096,"2-3 years","More than 3 years")))) -> Not Due
A52: SR TECHTRONICS A39006 | B52: Project#271280,Task#1002,INV#,Barcode#,Po#100070994,PoLine#1,VendorName-SR TECHTRONICS A39006,Desc-Supply of Lighting-Led (reel 100nos).,PT#2712801002 | C52: 100070994 | D52: GRAS07 | E52: INR | F52: 48590 | G52: 1 | H52: 1 | I52: =F52*G52 -> 48590 | J52: =F52*H52 -> 48590 | K52: =J52-I52 -> 0 | L52: 49 | M52: =I52-L52 -> 48541 | N52: =J52-L52 -> 48541 | O52: Opex | P52: Non-MSME | Q52: A39006 | R52: Supply of Lens (Edmund)- 33646 and Lens (Edmund) - 89410. INR 29380 per Lens. | S52: SRT-CI/A/1109 | T52: 46114 | U52: 46098 | V52: 88532 | W52: 46143 | Y52: 46143 | Z52: =$Y$1-Y52 -> -31 | AA52: 0 | AB52: 0 | AC52: 0 | AD52: 0 | AE52: 0 | AF52: 0 | AG52: 48541 | AI52: =E52 -> INR | AJ52: 1 | AK52: =F52*AJ52-L52 -> 48541 | AL52: =N52-AK52 -> 0 | AN52: =$AN$19-Y52 -> -31 | AO52: =IF(AN52<0,"Not Due",IF(AN52<366,"Less than 1 year",IF(AN52<731,"1-2 years",IF(AN52<1096,"2-3 years","More than 3 years")))) -> Not Due
A53: ELEMENT14 INDIA PRIVATE LIMITED A36095 | B53: Project#271298,Task#1001,INV#,Barcode#,Po#100070809,PoLine#1,VendorName-ELEMENT14 INDIA PRIVATE LIMITED A36095,Desc-C0805C104J5RALTU,PT#2712981001 | C53: 100070809 | D53: GRAS07 | E53: INR | F53: 1987.5 | G53: 1 | H53: 1 | I53: =F53*G53 -> 1987.5 | J53: =F53*H53 -> 1987.5 | K53: =J53-I53 -> 0 | L53: 2 | M53: =I53-L53 -> 1985.5 | N53: =J53-L53 -> 1985.5 | O53: Opex | P53: Non-MSME | Q53: A36095 | R53: CRCW0402100KFKED | S53: 1040173 | U53: 46050 | V53: 87955 | W53: 46107 | Y53: 46080 | Z53: =$Y$1-Y53 -> 32 | AA53: 0 | AB53: 1985.5 | AC53: 0 | AD53: 0 | AE53: 0 | AF53: 0 | AI53: =E53 -> INR | AJ53: 1 | AK53: =F53*AJ53-L53 -> 1985.5 | AL53: =N53-AK53 -> 0 | AM53: =N53 -> 1985.5 | AN53: =$AN$19-Y53 -> 32 | AO53: =IF(AN53<0,"Not Due",IF(AN53<366,"Less than 1 year",IF(AN53<731,"1-2 years",IF(AN53<1096,"2-3 years","More than 3 years")))) -> Less than 1 year
A54: BHORUKA SPECIALTY GASES PRIVATE LIMITED A38716 | B54: Project#271432,Task#8001,INV#,Barcode#,Po#100071255,PoLine#1,VendorName-BHORUKA SPECIALTY GASES PRIVATE LIMITED A38716,Desc-Supply of Nitrogen Gas, Purity: 99.9997%. SL : 12 ,PT#2714328001 | C54: 100071255 | D54: GRAS01 | E54: INR | F54: 2000 | G54: 1 | H54: 1 | I54: =F54*G54 -> 2000 | J54: =F54*H54 -> 2000 | K54: =J54-I54 -> 0 | L54: 2 | M54: =I54-L54 -> 1998 | N54: =J54-L54 -> 1998 | O54: Opex | P54: Non-MSME | Q54: A38716 | R54: Supply of Nitrogen Gas, Purity: 99.9997%. SL : 12 Months, FP : 140 Kg/Cm2 Gas Volume: 7 M3 Cylinder water capacity: 47 liters Carbon Steel Cylinder. | S54: 410043806 | T54: 46119 | U54: 46104 | V54: 88346 | W54: 46132 | Y54: 46134 | Z54: =$Y$1-Y54 -> -22 | AA54: 0 | AB54: 0 | AC54: 0 | AD54: 0 | AE54: 0 | AF54: 0 | AG54: 1998 | AI54: =E54 -> INR | AJ54: 1 | AK54: =F54*AJ54-L54 -> 1998 | AL54: =N54-AK54 -> 0 | AM54: =N54 -> 1998 | AN54: =$AN$19-Y54 -> -22 | AO54: =IF(AN54<0,"Not Due",IF(AN54<366,"Less than 1 year",IF(AN54<731,"1-2 years",IF(AN54<1096,"2-3 years","More than 3 years")))) -> Not Due
A55: SR TECHTRONICS A39006 | B55: Project#271540,Task#1001,INV#,Barcode#,Po#100070994,PoLine#2,VendorName-SR TECHTRONICS A39006,Desc-Supply of Lens (Edmund)- 33646 and Lens (Edmund) -,PT#2715401001 | C55: 100070994 | D55: GRAS11 | E55: INR | F55: 58760 | G55: 1 | H55: 1 | I55: =F55*G55 -> 58760 | J55: =F55*H55 -> 58760 | K55: =J55-I55 -> 0 | L55: 59 | M55: =I55-L55 -> 58701 | N55: =J55-L55 -> 58701 | O55: Opex | P55: Non-MSME | Q55: A39006 | R55: Supply of Lens (Edmund)- 33646 and Lens (Edmund) - 89410. INR 29380 per Lens. | S55: SRT-CI/A/1109 | T55: 46114 | U55: 46098 | V55: 88532 | W55: 46143 | Y55: 46143 | Z55: =$Y$1-Y55 -> -31 | AA55: 0 | AB55: 0 | AC55: 0 | AD55: 0 | AE55: 0 | AF55: 0 | AG55: 58701 | AI55: =E55 -> INR | AJ55: 1 | AK55: =F55*AJ55-L55 -> 58701 | AL55: =N55-AK55 -> 0 | AM55: =N55 -> 58701 | AN55: =$AN$19-Y55 -> -31 | AO55: =IF(AN55<0,"Not Due",IF(AN55<366,"Less than 1 year",IF(AN55<731,"1-2 years",IF(AN55<1096,"2-3 years","More than 3 years")))) -> Not Due
A56: SR TECHTRONICS A39006 | B56: Project#271545,Task#1001,INV#,Barcode#,Po#100071196,PoLine#1,VendorName-SR TECHTRONICS A39006,Desc-Electrical equipment and components and supplies,PT#2715451001 | C56: 100071196 | D56: GRAS08 | E56: INR | F56: 79100 | G56: 1 | H56: 1 | I56: =F56*G56 -> 79100 | J56: =F56*H56 -> 79100 | K56: =J56-I56 -> 0 | L56: 79 | M56: =I56-L56 -> 79021 | N56: =J56-L56 -> 79021 | O56: Opex | P56: Non-MSME | Q56: A39006 | R56: Electrical equipment and components and supplies | S56: SRT-CI/A/1110 | T56: 46114 | U56: 46098 | V56: 88532 | W56: 46143 | Y56: 46143 | Z56: =$Y$1-Y56 -> -31 | AA56: 0 | AB56: 0 | AC56: 0 | AD56: 0 | AE56: 0 | AF56: 0 | AG56: 79021 | AI56: =E56 -> INR | AJ56: 1 | AK56: =F56*AJ56-L56 -> 79021 | AL56: =N56-AK56 -> 0 | AM56: =N56 -> 79021 | AN56: =$AN$19-Y56 -> -31 | AO56: =IF(AN56<0,"Not Due",IF(AN56<366,"Less than 1 year",IF(AN56<731,"1-2 years",IF(AN56<1096,"2-3 years","More than 3 years")))) -> Not Due
A57: DESOCON TECHNOLOGIES PRIVATE LIMITED A43758 | B57: Project#271545,Task#1001,INV#,Barcode#,Po#100071407,PoLine#1,VendorName-DESOCON TECHNOLOGIES PRIVATE LIMITED A43758,Desc-Planetary Gearbox: PNSR60 15 Gear Ratio: 15:1,PT#2715451001 | C57: 100071407 | D57: GRAS08 | E57: INR | F57: 80550 | G57: 1 | H57: 1 | I57: =F57*G57 -> 80550 | J57: =F57*H57 -> 80550 | K57: =J57-I57 -> 0 | L57: 81 | M57: =I57-L57 -> 80469 | N57: =J57-L57 -> 80469 | O57: Opex | P57: Non-MSME | Q57: A43758 | R57: Planetary Gearbox PNSR6015 Gear Ratio 151 | S57: DTPL/55/25-26 | T57: 46113 | U57: 46105 | V57: 88590 | W57: 46147 | Y57: 46150 | Z57: =$Y$1-Y57 -> -38 | AA57: 0 | AB57: 0 | AC57: 0 | AD57: 0 | AE57: 0 | AF57: 0 | AG57: 80469 | AI57: =E57 -> INR | AJ57: 1 | AK57: =F57*AJ57-L57 -> 80469 | AL57: =N57-AK57 -> 0 | AM57: =N57 -> 80469 | AN57: =$AN$19-Y57 -> -38 | AO57: =IF(AN57<0,"Not Due",IF(AN57<366,"Less than 1 year",IF(AN57<731,"1-2 years",IF(AN57<1096,"2-3 years","More than 3 years")))) -> Not Due
A58: ELEMENT14 INDIA PRIVATE LIMITED A36095 | B58: Project#271562,Task#1001,INV#,Barcode#,Po#100071322,PoLine#1,VendorName-ELEMENT14 INDIA PRIVATE LIMITED A36095,Desc-Supply of Electrical switches and accessories. Det,PT#2715621001 | C58: 100071322 | D58: GRAS01 | E58: INR | F58: 112820.6 | G58: 1 | H58: 1 | I58: =F58*G58 -> 112820.6 | J58: =F58*H58 -> 112820.6 | K58: =J58-I58 -> 0 | L58: 113 | M58: =I58-L58 -> 112707.6 | N58: =J58-L58 -> 112707.6 | O58: Opex | P58: Non-MSME | Q58: A36095 | R58: Supply of Electrical switches and accessories. Details as per annexure. | S58: 1056561 | T58: 46119 | U58: 46105 | X58: Not Due | Y58: 46225 | Z58: =$Y$1-Y58 -> -113 | AA58: 0 | AB58: 0 | AC58: 0 | AD58: 0 | AE58: 0 | AF58: 0 | AG58: 112707.6 | AI58: =E58 -> INR | AJ58: 1 | AK58: =F58*AJ58-L58 -> 112707.6 | AL58: =N58-AK58 -> 0 | AM58: =N58 -> 112707.6 | AN58: =$AN$19-Y58 -> -113 | AO58: =IF(AN58<0,"Not Due",IF(AN58<366,"Less than 1 year",IF(AN58<731,"1-2 years",IF(AN58<1096,"2-3 years","More than 3 years")))) -> Not Due
A59: INNOV CONTROLS TECHNOLOGY (I) PVT. LTD. A37769 | B59: Project#271740,Task#0001,INV#,Barcode#,Po#100071135,PoLine#1,VendorName-INNOV CONTROLS TECHNOLOGY (I) PVT. LTD. A37769,Desc-Supply of 6W Metal Ceiling Speaker LBD606. BOSCH.,PT#2717400001 | C59: 100071135 | D59: GC7399 | E59: INR | F59: 2570 | G59: 1 | H59: 1 | I59: =F59*G59 -> 2570 | J59: =F59*H59 -> 2570 | K59: =J59-I59 -> 0 | L59: 3 | M59: =I59-L59 -> 2567 | N59: =J59-L59 -> 2567 | O59: Capex | P59: Non-MSME | Q59: A37769 | R59: Supply of FAPA device for command center room. | S59: IC25/180 | T59: 46113 | U59: 46101 | V59: 88512 | W59: 46143 | Y59: 46146 | Z59: =$Y$1-Y59 -> -34 | AA59: 0 | AB59: 0 | AC59: 0 | AD59: 0 | AE59: 0 | AF59: 0 | AG59: 2567 | AI59: =E59 -> INR | AJ59: 1 | AK59: =F59*AJ59-L59 -> 2567 | AL59: =N59-AK59 -> 0 | AM59: =N59 -> 2567 | AN59: =$AN$19-Y59 -> -34 | AO59: =IF(AN59<0,"Not Due",IF(AN59<366,"Less than 1 year",IF(AN59<731,"1-2 years",IF(AN59<1096,"2-3 years","More than 3 years")))) -> Not Due
A60: INNOV CONTROLS TECHNOLOGY (I) PVT. LTD. A37769 | B60: Project#271740,Task#0001,INV#,Barcode#,Po#100071135,PoLine#2,VendorName-INNOV CONTROLS TECHNOLOGY (I) PVT. LTD. A37769,Desc-Supply of HOOTER_G1AVRF Conventional Wall Horn/St,PT#2717400001 | C60: 100071135 | D60: GC7399 | E60: INR | F60: 3255 | G60: 1 | H60: 1 | I60: =F60*G60 -> 3255 | J60: =F60*H60 -> 3255 | K60: =J60-I60 -> 0 | L60: 3 | M60: =I60-L60 -> 3252 | N60: =J60-L60 -> 3252 | O60: Capex | P60: Non-MSME | Q60: A37769 | R60: Supply of FAPA device for command center room. | S60: IC25/180 | T60: 46113 | U60: 46101 | V60: 88512 | W60: 46143 | Y60: 46146 | Z60: =$Y$1-Y60 -> -34 | AA60: 0 | AB60: 0 | AC60: 0 | AD60: 0 | AE60: 0 | AF60: 0 | AG60: 3252 | AI60: =E60 -> INR | AJ60: 1 | AK60: =F60*AJ60-L60 -> 3252 | AL60: =N60-AK60 -> 0 | AM60: =N60 -> 3252 | AN60: =$AN$19-Y60 -> -34 | AO60: =IF(AN60<0,"Not Due",IF(AN60<366,"Less than 1 year",IF(AN60<731,"1-2 years",IF(AN60<1096,"2-3 years","More than 3 years")))) -> Not Due
A61: INNOV CONTROLS TECHNOLOGY (I) PVT. LTD. A37769 | B61: Project#271740,Task#0001,INV#,Barcode#,Po#100071135,PoLine#3,VendorName-INNOV CONTROLS TECHNOLOGY (I) PVT. LTD. A37769,Desc-Supply of Manual Call Point,PT#2717400001 | C61: 100071135 | D61: GC7399 | E61: INR | F61: 10800 | G61: 1 | H61: 1 | I61: =F61*G61 -> 10800 | J61: =F61*H61 -> 10800 | K61: =J61-I61 -> 0 | L61: 11 | M61: =I61-L61 -> 10789 | N61: =J61-L61 -> 10789 | O61: Capex | P61: Non-MSME | Q61: A37769 | R61: Supply of FAPA device for command center room. | S61: IC25/180 | T61: 46113 | U61: 46101 | V61: 88512 | W61: 46143 | Y61: 46146 | Z61: =$Y$1-Y61 -> -34 | AA61: 0 | AB61: 0 | AC61: 0 | AD61: 0 | AE61: 0 | AF61: 0 | AG61: 10789 | AI61: =E61 -> INR | AJ61: 1 | AK61: =F61*AJ61-L61 -> 10789 | AL61: =N61-AK61 -> 0 | AM61: =N61 -> 10789 | AN61: =$AN$19-Y61 -> -34 | AO61: =IF(AN61<0,"Not Due",IF(AN61<366,"Less than 1 year",IF(AN61<731,"1-2 years",IF(AN61<1096,"2-3 years","More than 3 years")))) -> Not Due
A62: INNOV CONTROLS TECHNOLOGY (I) PVT. LTD. A37769 | B62: Project#271740,Task#0001,INV#,Barcode#,Po#100071135,PoLine#4,VendorName-INNOV CONTROLS TECHNOLOGY (I) PVT. LTD. A37769,Desc-Supply of Smoke Detector. Brand - JCI.,PT#2717400001 | C62: 100071135 | D62: GC7399 | E62: INR | F62: 109200 | G62: 1 | H62: 1 | I62: =F62*G62 -> 109200 | J62: =F62*H62 -> 109200 | K62: =J62-I62 -> 0 | L62: 109 | M62: =I62-L62 -> 109091 | N62: =J62-L62 -> 109091 | O62: Capex | P62: Non-MSME | Q62: A37769 | R62: Supply of FAPA device for command center room. | S62: IC25/180 | T62: 46113 | U62: 46101 | V62: 88512 | W62: 46143 | Y62: 46146 | Z62: =$Y$1-Y62 -> -34 | AA62: 0 | AB62: 0 | AC62: 0 | AD62: 0 | AE62: 0 | AF62: 0 | AG62: 109091 | AI62: =E62 -> INR | AJ62: 1 | AK62: =F62*AJ62-L62 -> 109091 | AL62: =N62-AK62 -> 0 | AM62: =N62 -> 109091 | AN62: =$AN$19-Y62 -> -34 | AO62: =IF(AN62<0,"Not Due",IF(AN62<366,"Less than 1 year",IF(AN62<731,"1-2 years",IF(AN62<1096,"2-3 years","More than 3 years")))) -> Not Due
