Workbook

Sheet Summary
B3: ROU
B4: Opening Balance | C4: ='Rent Alpha Detail'!G7 -> 40015641
B5: Modification | C5: ='Rent Alpha Detail'!K17 -> 4521159.3
B6: Amortization | C6: =-'Rent Alpha Detail'!I7 -> -35727324
B7: Closing Balance | C7: =C4+C5+C6 -> 8809477

Sheet Rent Alpha Detail
A1: Current year Schedule (Modification of lease Liabilities)
K2: Opening Balnce | L2: Add :Interest | M2: Less:Repayment | N2: => Closing Liability
B3: Particulars | G3: 2024-25 (Actual) | H3: 2024-25 Should have been | I3: 2025-26 (Mar 2026) | K3: =H17 -> 32215701 | L3: =N3+M3-K3 -> 2835219 | M3: =I10 -> 33093224 | N3: =I17 -> 1957695.8
G5: >> Actual ROU >> | H5: >> Revised ROU >>
A6: 0.08 | B6: ROU | H6: =40015641.3303417-H16 -> 44536801 | I6: =H7 -> 44536801
B7: Depreciation | G7: =H24 -> 40015641 | H7: =H6 -> 44536801 | I7: =SUM('Rent Alpha'!BH43:BQ43) -> 35727324
B8: ROU -Closing balance | G8: =G25 -> 40015641 | I8: =I6-I7 -> 8809477
B9: Lease Liablity
B10: Repayment | G10: =G27 -> 45528432 | I10: =SUM('Rent Alpha'!BH33:BQ33) -> 33093224
B11: Interest | G11: =G28 -> -3153040.5 | I11: =SUM('Rent Alpha'!BH37:BQ37)-I10 -> -2835219 | J11: >>>Interest = Closing Liability + Repayment - Opening Balance
G12: =G29 -> 27694542 | H12: =SUM('Rent Alpha'!BH37:BT37) -> 32215701 | I12: =H12-I10-I11 -> 1957695.8
B13: P&L Impact | G13: =G30 -> -2359750.1 | I13: =I6-SUM(I10:I11) -> 14278795
H16: =G17-H17 -> -4521159.3 | J16: Differnce in Opening ROU has been added to ROU
B17: Balance Lease Liablity | D17: =C9-D10-D11 -> 0 | E17: =D17-E10-E11 -> 0 | F17: =F34 -> 70069933 | G17: =F17-G10-G11 -> 27694542 | H17: =H12 -> 32215701 | I17: =H17-I10-I11 -> 1957695.8 | J17: ROU DR | K17: =-H16 -> 4521159.3
G18: >> Actual Liability >> | H18: >> Revised Liability >> | J18: To Lease Liability | K18: =H16 -> -4521159.3
A20: Till last Year (actual)
B21: Particulars | C21: Total Value | D21: 2021-22 | E21: 2022-23 | F21: 2023-24 | G21: 2024-25 | H21: 2025-26
A23: 0.08 | B23: ROU | C23: 2.0018784e+08 | J23: =SUM('Rent Alpha'!BH33:BT33) -> 35265406 | K23: Repayment as per CY
B24: Depreciation | C24: 2.0018784e+08 | D24: 40015641 | E24: 40015641 | F24: 40125273 | G24: 40015641 | H24: 40015641 | J24: =H27 -> 30263410 | K24: Repayment as per LY
D25: 1.601722e+08 | E25: 1.2015656e+08 | F25: 80031283 | G25: 40015641 | H25: 0 | J25: =J23-J24 -> 5001995.8 | K25: Increase in LL
B26: Lease Liablity | C26: 2.0018784e+08 | J26: =AVERAGE('Rent Alpha'!BH35:BT35) -> 0.9102482
B27: Repayment | C27: 210204955 | D27: 43356249 | E27: 45528432 | F27: 45528432 | G27: 45528432 | H27: 30263410 | J27: =J25*J26 -> 4553057.7 | K27: INCREASE IN LL pv
B28: Interest | C28: -10017116 | D28: -548600.4 | E28: -1441074.7 | F28: -2305532.7 | G28: -3153040.5 | H28: -2568868.1
D29: 1.5738019e+08 | E29: 1.1329283e+08 | F29: 70069933 | G29: 27694542 | H29: 7.4505806e-09 | J29: =J25-'Rent Alpha'!BT33 -> 2829814.4
B30: P&L Impact | D30: -2792007.3 | E30: -4071716 | F30: -3097626.1 | G30: -2359750.1 | H30: 12321099
B34: Balance Lease Liablity | D34: 1.5738019e+08 | E34: 1.1329283e+08 | F34: 70069933 | G34: 27694542 | H34: 7.4505806e-09

Sheet Rent Alpha
K2: 0.25 | N2: =K2+0.25 -> 0.5 | Q2: =N2+0.25 -> 0.75 | T2: =Q2+0.25 -> 1 | W2: =T2+0.25 -> 1.25 | Z2: =W2+0.25 -> 1.5 | AC2: =Z2+0.25 -> 1.75 | AF2: =AC2+0.25 -> 2 | AI2: =AF2+0.25 -> 2.25 | AL2: =AI2+0.25 -> 2.5 | AO2: =AL2+0.25 -> 2.75 | AR2: =AO2+0.25 -> 3 | AU2: =AR2+0.25 -> 3.25 | AX2: =AU2+0.25 -> 3.5 | BA2: =AX2+0.25 -> 3.75 | BD2: =BA2+0.25 -> 4 | BH2: =BD2+0.25 -> 4.25 | BK2: =BH2+0.25 -> 4.5 | BN2: =BK2+0.25 -> 4.75 | BQ2: =BN2+0.25 -> 5 | BT2: =BQ2+0.25 -> 5.25
A3: Agreement Number | B3: From | C3: To | D3: Rental | E3: Period | F3: Total Rental | I3: 44287 | J3: 44317 | K3: 44348 | L3: 44378 | M3: 44409 | N3: 44440 | O3: 44470 | P3: 44501 | Q3: 44531 | R3: 44562 | S3: 44593 | T3: 44621 | U3: 44652 | V3: 44682 | W3: 44713 | X3: 44743 | Y3: 44774 | Z3: 44805 | AA3: 44835 | AB3: 44866 | AC3: 44896 | AD3: 44927 | AE3: 44958 | AF3: 44986 | AG3: 45017 | AH3: 45047 | AI3: 45078 | AJ3: 45108 | AK3: 45139 | AL3: 45170 | AM3: 45200 | AN3: 45231 | AO3: 45261 | AP3: 45292 | AQ3: 45323 | AR3: 45352 | AS3: 45383 | AT3: 45413 | AU3: 45444 | AV3: 45474 | AW3: 45505 | AX3: 45536 | AY3: 45566 | AZ3: 45597 | BA3: 45627 | BB3: 45658 | BC3: 45689 | BD3: 45717 | BF3: 45748 | BG3: 45778 | BH3: 45809 | BI3: 45839 | BJ3: 45870 | BK3: 45901 | BL3: 45931 | BM3: 45962 | BN3: 45992 | BO3: 46023 | BP3: 46054 | BQ3: 46082 | BR3: 46113 | BS3: 46143 | BT3: 46174
A5: GEI/0005 | B5: 44287 | C5: 45930 | D5: 1421039 | E5: 18 | F5: =D5*E5 -> 25578702 | G5: =SUM(F5:F6) -> 25626070 | K5: =D5 -> 1421039 | N5: =K5 -> 1421039 | Q5: =N5 -> 1421039 | T5: =Q5 -> 1421039 | W5: =T5 -> 1421039 | Z5: =W5 -> 1421039 | AC5: =Z5 -> 1421039 | AF5: =AC5 -> 1421039 | AI5: =AF5 -> 1421039 | AL5: =AI5 -> 1421039 | AO5: =AL5 -> 1421039 | AR5: =AO5 -> 1421039 | AU5: =AR5 -> 1421039 | AX5: =AU5 -> 1421039 | BA5: =AX5 -> 1421039 | BD5: =BA5 -> 1421039 | BH5: =BD5 -> 1421039 | BK5: =BH5 -> 1421039 | BN5: =F6 -> 47368
A6: GEI/0005 | B6: 45931 | C6: 46022 | D6: 47368 | E6: 1 | F6: =D6*E6 -> 47368
A8: GEI/0006 | B8: 44287 | C8: 45930 | D8: 1136831 | E8: 18 | F8: =D8*E8 -> 20462958 | G8: =SUM(F8:F9) -> 20660279 | K8: =D8 -> 1136831 | N8: =K8 -> 1136831 | Q8: =N8 -> 1136831 | T8: =Q8 -> 1136831 | W8: =T8 -> 1136831 | Z8: =W8 -> 1136831 | AC8: =Z8 -> 1136831 | AF8: =AC8 -> 1136831 | AI8: =AF8 -> 1136831 | AL8: =AI8 -> 1136831 | AO8: =AL8 -> 1136831 | AR8: =AO8 -> 1136831 | AU8: =AR8 -> 1136831 | AX8: =AU8 -> 1136831 | BA8: =AX8 -> 1136831 | BD8: =BA8 -> 1136831 | BH8: =BD8 -> 1136831 | BK8: =BH8 -> 1136831 | BN8: =F9 -> 197321
A9: GEI/0006 | B9: 45931 | C9: 46022 | D9: 197321 | E9: 1 | F9: =D9*E9 -> 197321
A11: GEI/0007 | B11: 44287 | C11: 45930 | D11: 2273662 | E11: 18 | F11: =D11*E11 -> 40925916 | G11: =SUM(F11:F12) -> 41566196 | K11: =D11 -> 2273662 | N11: =K11 -> 2273662 | Q11: =N11 -> 2273662 | T11: =Q11 -> 2273662 | W11: =T11 -> 2273662 | Z11: =W11 -> 2273662 | AC11: =Z11 -> 2273662 | AF11: =AC11 -> 2273662 | AI11: =AF11 -> 2273662 | AL11: =AI11 -> 2273662 | AO11: =AL11 -> 2273662 | AR11: =AO11 -> 2273662 | AU11: =AR11 -> 2273662 | AX11: =AU11 -> 2273662 | BA11: =AX11 -> 2273662 | BD11: =BA11 -> 2273662 | BH11: =BD11 -> 2273662 | BK11: =BH11 -> 2273662 | BN11: =F12 -> 640280
A12: GEI/0007 | B12: 45931 | C12: 46022 | D12: 640280 | E12: 1 | F12: =D12*E12 -> 640280
A14: GEI/0008 | B14: 44287 | C14: 45930 | D14: 1421039 | E14: 18 | F14: =D14*E14 -> 25578702 | G14: =SUM(F14:F15) -> 26194486 | K14: =D14 -> 1421039 | N14: =K14 -> 1421039 | Q14: =N14 -> 1421039 | T14: =Q14 -> 1421039 | W14: =T14 -> 1421039 | Z14: =W14 -> 1421039 | AC14: =Z14 -> 1421039 | AF14: =AC14 -> 1421039 | AI14: =AF14 -> 1421039 | AL14: =AI14 -> 1421039 | AO14: =AL14 -> 1421039 | AR14: =AO14 -> 1421039 | AU14: =AR14 -> 1421039 | AX14: =AU14 -> 1421039 | BA14: =AX14 -> 1421039 | BD14: =BA14 -> 1421039 | BH14: =BD14 -> 1421039 | BK14: =BH14 -> 1421039 | BN14: =F15 -> 615784
A15: GEI/0008 | B15: 45931 | C15: 46022 | D15: 615784 | E15: 1 | F15: =D15*E15 -> 615784
A17: GEI/0009 | B17: 44287 | C17: 45930 | D17: 852623 | E17: 18 | F17: =D17*E17 -> 15347214 | G17: =SUM(F17:F18) -> 15713618 | K17: =D17 -> 852623 | N17: =K17 -> 852623 | Q17: =N17 -> 852623 | T17: =Q17 -> 852623 | W17: =T17 -> 852623 | Z17: =W17 -> 852623 | AC17: =Z17 -> 852623 | AF17: =AC17 -> 852623 | AI17: =AF17 -> 852623 | AL17: =AI17 -> 852623 | AO17: =AL17 -> 852623 | AR17: =AO17 -> 852623 | AU17: =AR17 -> 852623 | AX17: =AU17 -> 852623 | BA17: =AX17 -> 852623 | BD17: =BA17 -> 852623 | BH17: =BD17 -> 852623 | BK17: =BH17 -> 852623 | BN17: =F18 -> 366404
A18: GEI/0009 | B18: 45931 | C18: 46022 | D18: 366404 | E18: 1 | F18: =D18*E18 -> 366404
A20: GEI/0010 | B20: 44378 | C20: 46022 | D20: 1379649 | E20: 19 | F20: =D20*E20 -> 26213331 | G20: =SUM(F20:F21) -> 27501004 | K20: =D20 -> 1379649 | N20: =K20 -> 1379649 | Q20: =N20 -> 1379649 | T20: =Q20 -> 1379649 | W20: =T20 -> 1379649 | Z20: =W20 -> 1379649 | AC20: =Z20 -> 1379649 | AF20: =AC20 -> 1379649 | AI20: =AF20 -> 1379649 | AL20: =AI20 -> 1379649 | AO20: =AL20 -> 1379649 | AR20: =AO20 -> 1379649 | AU20: =AR20 -> 1379649 | AX20: =AU20 -> 1379649 | BA20: =AX20 -> 1379649 | BD20: =BA20 -> 1379649 | BH20: =BD20 -> 1379649 | BK20: =BH20 -> 1379649 | BN20: 1379649.5 | BQ20: =F21 -> 1287673
A21: GEI/0010 | B21: 46023 | C21: 46106 | D21: 1287673 | E21: 1 | F21: =D21*E21 -> 1287673
A23: GEI/0011 | B23: 44470 | C23: 46112 | D23: 965755 | E23: 19 | F23: =D23*E23 -> 18349345 | G23: =SUM(F23:F24) -> 18778569 | K23: 536530 | N23: =D23 -> 965755 | Q23: =D23 -> 965755 | T23: =Q23 -> 965755 | W23: =T23 -> 965755 | Z23: =W23 -> 965755 | AC23: =Z23 -> 965755 | AF23: =AC23 -> 965755 | AI23: =AF23 -> 965755 | AL23: =AI23 -> 965755 | AO23: =AL23 -> 965755 | AR23: =AO23 -> 965755 | AU23: =AR23 -> 965755 | AX23: =AU23 -> 965755 | BA23: =AX23 -> 965755 | BD23: =BA23 -> 965755 | BH23: =BD23 -> 965755 | BK23: =BH23 -> 965755 | BN23: 965755 | BQ23: 965754.63 | BT23: 429224.28
A24: GEI/0011 | B24: 46113 | C24: 46191 | D24: 429224 | E24: 1 | F24: =D24*E24 -> 429224
A26: GEI/0012 | B26: 44470 | C26: 46112 | D26: 689825 | E26: 19 | F26: =D26*E26 -> 13106675 | G26: =SUM(F26:F27) -> 13704523 | K26: 91977 | N26: =D26 -> 689825 | Q26: =D26 -> 689825 | T26: =Q26 -> 689825 | W26: =T26 -> 689825 | Z26: =W26 -> 689825 | AC26: =Z26 -> 689825 | AF26: =AC26 -> 689825 | AI26: =AF26 -> 689825 | AL26: =AI26 -> 689825 | AO26: =AL26 -> 689825 | AR26: =AO26 -> 689825 | AU26: =AR26 -> 689825 | AX26: =AU26 -> 689825 | BA26: =AX26 -> 689825 | BD26: =BA26 -> 689825 | BH26: =BD26 -> 689825 | BK26: =BH26 -> 689825 | BN26: =BK26 -> 689825 | BQ26: 689824.74 | BT26: 597848.11
A27: GEI/0012 | B27: 46113 | C27: 46153 | D27: 597848 | E27: 1 | F27: =D27*E27 -> 597848
A29: GEI/0013 | B29: 44470 | C29: 46112 | D29: 1241685 | E29: 19 | F29: =D29*E29 -> 23592015 | G29: =SUM(F29:F30) -> 24737124 | K29: 96575 | N29: =D29 -> 1241685 | Q29: =D29 -> 1241685 | T29: =Q29 -> 1241685 | W29: =T29 -> 1241685 | Z29: =W29 -> 1241685 | AC29: =Z29 -> 1241685 | AF29: =AC29 -> 1241685 | AI29: =AF29 -> 1241685 | AL29: =AI29 -> 1241685 | AO29: =AL29 -> 1241685 | AR29: =AO29 -> 1241685 | AU29: =AR29 -> 1241685 | AX29: =AU29 -> 1241685 | BA29: =AX29 -> 1241685 | BD29: =BA29 -> 1241685 | BH29: =BD29 -> 1241685 | BK29: =BH29 -> 1241685 | BN29: =BK29 -> 1241685 | BQ29: 1241684.5 | BT29: 1145109.1
A30: GEI/0013 | B30: 46113 | C30: 46196 | D30: 1145109 | E30: 1 | F30: =D30*E30 -> 1145109
D33: Total repayments | F33: =SUM(F4:F32) -> 214481869 | G33: =SUM(G4:G32) -> 214481869 | I33: =SUM(I4:I32) -> 0 | J33: =SUM(J4:J32) -> 0 | K33: =SUM(K4:K32) -> 9209925 | L33: =SUM(L4:L32) -> 0 | M33: =SUM(M4:M32) -> 0 | N33: =SUM(N4:N32) -> 11382108 | O33: =SUM(O4:O32) -> 0 | P33: =SUM(P4:P32) -> 0 | ... BD33: =SUM(BD4:BD32) -> 11382108 | BF33: =SUM(BF4:BF32) -> 0 | BG33: =SUM(BG4:BG32) -> 0 | BH33: =SUM(BH4:BH32) -> 11382108 | BI33: =SUM(BI4:BI32) -> 0 | BJ33: =SUM(BJ4:BJ32) -> 0 | BK33: =SUM(BK4:BK32) -> 11382108 | BL33: =SUM(BL4:BL32) -> 0 | BM33: =SUM(BM4:BM32) -> 0 | ... BT33: =SUM(BT4:BT32) -> 2172181.5
D35: Discounting factor | H35: 0.08 | K35: =1/(1+$H$35/4)^K2 -> 0.99506158 | N35: =1/(1+$H$35/4)^N2 -> 0.99014754 | Q35: =1/(1+$H$35/4)^Q2 -> 0.98525778 | T35: =1/(1+$H$35/4)^T2 -> 0.98039216 | W35: =1/(1+$H$35/4)^W2 -> 0.97555057 | Z35: =1/(1+$H$35/4)^Z2 -> 0.97073289 | AC35: =1/(1+$H$35/4)^AC2 -> 0.965939 | AF35: =1/(1+$H$35/4)^AF2 -> 0.96116878 | AI35: =1/(1+$H$35/4)^AI2 -> 0.95642212 | AL35: =1/(1+$H$35/4)^AL2 -> 0.95169891 | AO35: =1/(1+$H$35/4)^AO2 -> 0.94699902 | AR35: =1/(1+$H$35/4)^AR2 -> 0.94232233 | AU35: =1/(1+$H$35/4)^AU2 -> 0.93766875 | AX35: =1/(1+$H$35/4)^AX2 -> 0.93303814 | BA35: =1/(1+$H$35/4)^BA2 -> 0.92843041 | BD35: =1/(1+$H$35/4)^BD2 -> 0.92384543 | BH35: =1/(1+$H$35/4)^BH2 -> 0.91928309 | BK35: =1/(1+$H$35/4)^BK2 -> 0.91474328 | BN35: =1/(1+$H$35/4)^BN2 -> 0.91022589 | BQ35: =1/(1+$H$35/4)^BQ2 -> 0.90573081 | BT35: =1/(1+$H$35/4)^BT2 -> 0.90125793
D37: Present value of Lease Liability | F37: =SUM(K37:BQ37) -> 2.027513e+08 | H37: 0.08 | K37: =K33*K35 -> 9164442.5 | N37: =N33*N35 -> 11269966 | Q37: =Q33*Q35 -> 11214310 | T37: =T33*T35 -> 11158929 | W37: =W33*W35 -> 11103822 | Z37: =Z33*Z35 -> 11048987 | AC37: =AC33*AC35 -> 10994422 | AF37: =AF33*AF35 -> 10940127 | AI37: =AI33*AI35 -> 10886100 | AL37: =AL33*AL35 -> 10832340 | AO37: =AO33*AO35 -> 10778845 | AR37: =AR33*AR35 -> 10725615 | AU37: =AU33*AU35 -> 10672647 | AX37: =AX33*AX35 -> 10619941 | BA37: =BA33*BA35 -> 10567495 | BD37: =BD33*BD35 -> 10515308 | BH37: =BH33*BH35 -> 10463379 | BK37: =BK33*BK35 -> 10411707 | BN37: =BN33*BN35 -> 5592492.9 | BQ37: =BQ33*BQ35 -> 3790426.3 | BT37: =BT33*BT35 -> 1957695.8
AC38: =AC37/3 -> 3664807.3 | AD38: =AC37-AC38 -> 7329614.7 | AF38: =AF37 -> 10940127 | AI38: =AI37 -> 10886100 | AL38: =AL37 -> 10832340 | AO38: =AO37/3 -> 3592948.4
D39: No of days in Qtr | K39: =30+31+30 -> 91 | N39: =31+31+30 -> 92 | Q39: =31+30+31 -> 92 | T39: =31+28+31 -> 90 | W39: =30+31+30 -> 91 | Z39: =31+31+30 -> 92 | AC39: =31+30+31 -> 92 | AF39: =31+28+31 -> 90 | AI39: =30+31+30 -> 91 | AL39: =31+31+30 -> 92 | AO39: =31+30+31 -> 92 | AR39: =31+29+31 -> 91 | AU39: =30+31+30 -> 91 | AX39: =31+31+30 -> 92 | BA39: =31+30+31 -> 92 | BD39: =31+28+31 -> 90 | BH39: =30+31+30 -> 91 | BK39: =31+31+30 -> 92 | BN39: =31+30+31 -> 92 | BQ39: =31+28+31 -> 90 | BT39: =31+28+31 -> 90
D40: Revised Opening ROU | F40: ='Rent Alpha Detail'!H6 -> 44536801 | BH40: =$F$40/BH39 -> 489415.39 | BK40: =$F$40/BK39 -> 484095.66 | BN40: =$F$40/BN39 -> 484095.66 | BQ40: =$F$40/BQ39 -> 494853.34 | BT40: =$F$40/BT39 -> 494853.34
F41: 44536801 | K41: =K39*#REF! -> #REF! | N41: =N39*#REF! -> #REF! | Q41: =Q39*#REF! -> #REF! | T41: =T39*#REF! -> #REF! | W41: =W39*#REF! -> #REF! | Z41: =Z39*#REF! -> #REF! | AC41: =AC39*#REF! -> #REF! | AF41: =AF39*#REF! -> #REF! | AI41: =AI39*#REF! -> #REF! | AL41: =AL39*#REF! -> #REF! | AO41: =AO39*#REF! -> #REF! | AR41: =AR39*#REF! -> #REF! | AU41: =AU39*#REF! -> #REF! | AX41: =AX39*#REF! -> #REF! | BA41: =BA39*#REF! -> #REF! | BD41: =BD39*#REF! -> #REF! | BH41: =BH39*#REF! -> #REF! | BK41: =BK39*#REF! -> #REF! | BN41: =BN39*#REF! -> #REF! | BQ41: =BQ39*#REF! -> #REF! | BT41: =BT39*#REF! -> #REF!
D42: Total Days left | F42: =SUM(BH39:BT39) -> 455 | AC42: =AC41/AC39*31 -> #REF!
D43: Depreciation per Qtr | F43: =F40/F42 -> 97883.078 | BH43: =$F$43*BH39 -> 8907360.1 | BK43: =$F$43*BK39 -> 9005243.2 | BN43: =$F$43*BN39 -> 9005243.2 | BQ43: =$F$43*BQ39 -> 8809477 | BT43: =$F$43*BT39 -> 8809477
