Workbook

Sheet Scope
A2: Purpose
A3: To verify lease liability and ROU as at March 31, 2026
A5: Work Done
A7: Assertion | B7: Procedures | C7: Reference
A8: Valuation and Allocation | B8: ET performed the recomputation of new leases started as well as leases terminated during the year on samples extracted using MUS | C8: << Refer tab testing >>
B9: ET verified the depreciation of ROU assets and verified that the same has been computed on the basis of the lease period. | C9: << Refer tab testing >>
B10: ET verified the finance cost on the lease liabilities | C10: << Refer tab testing >>
A11: Existence | B11: ET obtained the executed agreement from the client of the new leases added during the year. | C11: << Refer tab testing >>
B12: ET verified the lease deeds of the leasehold lands and verified whether the same are registered in the name of the Company. | C12: << Refer WP B. CARO Workbook GEIIPL 2026>>
B13: ET obtained the physical verification certificates from the management and analysed the coverage of the physical verification. | C13: << Refer WP B. CARO Workbook GEIIPL 2026>>
A14: Completeness | B14: ET obtained the schedule of rental expenses and verified that they are not to be accounted for as lease. | C14: << Refer workspace Rent >>
A15: Accuracy | B15: ET has verified the lease start date, end date, monthly payment amount as per the agreement. | C15: << Refer tab testing >>
B16: ET performed the recomputation of the lease liability and ROU to ensure the accuracy of the IPE. | C16: << Refer tab testing >>
B17: ET has verified the discount rate used for discounting from the GSEC rates which have been used by the Company. | C17: << Refer tab additions summary >>
A18: Presentation and Disclosure | B18: ET has also reconciled the values appearing in the balance sheet and verified the notes to account with the balance as per Schedule. | C18: << Refer tab Notes to Account >>
B19: ET has ensured that the notes to account are in accordance with the requirements of Ind AS 116. | C19: << Refer tab Notes to Account >>
A22: Observation
A23: None
A26: Conclusion
A27: No material misstatements identified

Sheet Notes to Account
A1: =Scope!#REF! -> #REF!
A2: =Scope!#REF! -> #REF!
A3: =Scope!#REF! -> #REF!
A5: Purpose
A6: To verify the amounts disclosed in notes to account as on March 31, 2026
A8: Note 4.4. Right-of-use assets | F8: (Amount in Rs. Lakhs)
I9: << As per Schedule >> | T9: << Difference >>
A10: Particulars | B10: Buildings | C10: Vehicles | D10: Equipments | E10: IT Equipments | F10: Land | G10: Total | I10: Buildings | J10: Vehicles | K10: Equipments | L10: IT Equipments | M10: Land | N10: Total | T10: Buildings | U10: Vehicles | V10: Equipments | W10: IT Equipments | X10: Land | Y10: Total
A11: Balance at April 1, 2024 | B11: 739.33623 | C11: 1640.8464 | D11: 1145.9376 | E11: 3608.8915 | F11: 6159.4388 | G11: =SUM(B11:F11) -> 13294.451 | I11: 739.33623 | J11: 1640.8464 | K11: 1145.9376 | L11: 3608.8915 | M11: 6159.4388 | N11: =SUM(I11:M11) -> 13294.451 | O11: << Verified from PY Financial Statements >> | T11: =B11-I11 -> 0 | U11: =C11-J11 -> 0 | V11: =D11-K11 -> 0 | W11: =E11-L11 -> 0 | X11: =F11-M11 -> 0 | Y11: =G11-N11 -> 0
A12: Additions/ modifications during the year | B12: 22 | C12: 863 | D12: 27 | E12: 5924 | F12: 0 | G12: =SUM(B12:F12) -> 6836 | I12: 22 | J12: 863 | K12: 27 | L12: 5924 | M12: 0 | N12: =SUM(I12:M12) -> 6836 | O12: << Verified from PY Financial Statements >> | T12: =B12-I12 -> 0 | U12: =C12-J12 -> 0 | V12: =D12-K12 -> 0 | W12: =E12-L12 -> 0 | X12: =F12-M12 -> 0 | Y12: =G12-N12 -> 0
A13: Depreciation expense | B13: -448 | C13: -766 | D13: -352 | E13: -2943 | F13: -74 | G13: =SUM(B13:F13) -> -4583 | I13: -448 | J13: -766 | K13: -352 | L13: -2943 | M13: -74 | N13: =SUM(I13:M13) -> -4583 | O13: << Verified from PY Financial Statements >> | T13: =B13-I13 -> 0 | U13: =C13-J13 -> 0 | V13: =D13-K13 -> 0 | W13: =E13-L13 -> 0 | X13: =F13-M13 -> 0 | Y13: =G13-N13 -> 0
A14: Disposal/Adjustment during the year | B14: 2 | C14: -149 | D14: 0 | E14: 8 | F14: 0 | G14: =SUM(B14:F14) -> -139 | I14: 2 | J14: -149 | K14: 0 | L14: 8 | M14: 0 | N14: =SUM(I14:M14) -> -139 | O14: << Verified from PY Financial Statements >> | T14: =B14-I14 -> 0 | U14: =C14-J14 -> 0 | V14: =D14-K14 -> 0 | W14: =E14-L14 -> 0 | X14: =F14-M14 -> 0 | Y14: =G14-N14 -> 0
A15: Transferred of Assets under demerger | B15: -113 | C15: -648 | D15: 0 | E15: -163 | F15: 0 | G15: =SUM(B15:F15) -> -924 | I15: -113 | J15: -648 | K15: 0 | L15: -163 | M15: 0 | N15: =SUM(I15:M15) -> -924 | O15: << Verified from PY Financial Statements >> | T15: =B15-I15 -> 0 | U15: =C15-J15 -> 0 | V15: =D15-K15 -> 0 | W15: =E15-L15 -> 0 | X15: =F15-M15 -> 0 | Y15: =G15-N15 -> 0
A16: Transferred to Assets held for sale | B16: 0 | C16: -26 | D16: 0 | E16: 0 | F16: 0 | G16: =SUM(B16:F16) -> -26 | I16: 0 | J16: -26 | K16: 0 | L16: 0 | M16: 0 | N16: =SUM(I16:M16) -> -26 | O16: << Verified from PY Financial Statements >> | T16: =B16-I16 -> 0 | U16: =C16-J16 -> 0 | V16: =D16-K16 -> 0 | W16: =E16-L16 -> 0 | X16: =F16-M16 -> 0 | Y16: =G16-N16 -> 0
A17: Balance as at 31 March 2025 | B17: =SUM(B11:B16) -> 202.33623 | C17: =SUM(C11:C16) -> 914.8464 | D17: =SUM(D11:D16) -> 820.93765 | E17: =SUM(E11:E16) -> 6434.8915 | F17: =SUM(F11:F16) -> 6085.4388 | G17: =SUM(G11:G16) -> 14458.451 | I17: =SUM(I11:I16) -> 202.33623 | J17: =SUM(J11:J16) -> 914.8464 | K17: =SUM(K11:K16) -> 820.93765 | L17: =SUM(L11:L16) -> 6434.8915 | M17: =SUM(M11:M16) -> 6085.4388 | N17: =SUM(N11:N16) -> 14458.451 | O17: << Verified from PY Financial Statements >> | T17: =SUM(T11:T16) -> 0 | U17: =SUM(U11:U16) -> 0 | V17: =SUM(V11:V16) -> 0 | W17: =SUM(W11:W16) -> 0 | X17: =SUM(X11:X16) -> 0 | Y17: =SUM(Y11:Y16) -> 0
A19: Balance at April 1, 2025 | B19: =B17 -> 202.33623 | C19: =C17 -> 914.8464 | D19: =D17 -> 820.93765 | E19: =E17 -> 6434.8915 | F19: =F17 -> 6085.4388 | G19: =SUM(B19:F19) -> 14458.451 | I19: =I17 -> 202.33623 | J19: =J17 -> 914.8464 | K19: =K17 -> 820.93765 | L19: =L17 -> 6434.8915 | M19: =M17 -> 6085.4388 | N19: =N17 -> 14458.451 | O19: << Refer Link >> | T19: =B19-I19 -> 0 | U19: =C19-J19 -> 0 | V19: =D19-K19 -> 0 | W19: =E19-L19 -> 0 | X19: =F19-M19 -> 0 | Y19: =Y17 -> 0
A20: Additions/ modifications during the year | B20: 1867 | C20: 1225 | D20: 0 | E20: 5755 | F20: 0 | G20: =SUM(B20:F20) -> 8847 | I20: =Summary!C14 -> 0 | J20: =Summary!C15 -> 3248 | K20: =Summary!C16 -> 45 | L20: =Summary!C17 -> 61 | M20: 0 | N20: =SUM(I20:M20) -> 3354 | O20: << Refer Link >> | T20: =B20-I20 -> 1867 | U20: =C20-J20 -> -2023 | V20: =D20-K20 -> -45 | W20: =E20-L20 -> 5694 | X20: =F20-M20 -> 0 | Y20: =SUM(T20:X20) -> 5493
A21: Depreciation expense | B21: -340 | C21: -623 | D21: -400 | E21: -4330 | F21: -74 | G21: =SUM(B21:F21) -> -5767 | I21: =-Summary!E14 -> -394 | J21: =-Summary!E15 -> -911 | K21: =-Summary!E16 -> -357 | L21: =-Summary!$E$17 -> -4280 | M21: =M13 -> -74 | N21: =SUM(I21:M21) -> -6016 | O21: << Refer Link >> | T21: =B21-I21 -> 54 | U21: =C21-J21 -> 288 | V21: =D21-K21 -> -43 | W21: =E21-L21 -> -50 | X21: =F21-M21 -> 0 | Y21: =SUM(T21:X21) -> 249
A22: Disposal/Adjustment during the year | B22: -202 | C22: -137 | D22: -21 | E22: 0 | F22: 0 | G22: =SUM(B22:F22) -> -360 | I22: =-Summary!D14 -> 0 | J22: =-Summary!D15 -> 25 | K22: =-Summary!D16 -> 0 | L22: 0 | M22: 0 | N22: =SUM(I22:M22) -> 25 | O22: << Refer Link >> | T22: =B22-I22 -> -202 | U22: =C22-J22 -> -162 | V22: =D22-K22 -> -21 | W22: =E22-L22 -> 0 | X22: =F22-M22 -> 0 | Y22: =SUM(T22:X22) -> -385
A23: Balance as at 31 March 2026 | B23: =SUM(B19:B22) -> 1527.3362 | C23: =SUM(C19:C22) -> 1379.8464 | D23: =SUM(D19:D22) -> 399.93765 | E23: =SUM(E19:E22) -> 7859.8915 | F23: =SUM(F19:F22) -> 6011.4388 | G23: =SUM(G19:G22) -> 17178.451 | I23: =SUM(I19:I22) -> -191.66377 | J23: =SUM(J19:J22) -> 3276.8464 | K23: =Summary!F16 -> 88 | L23: =Summary!F17 -> 3573 | M23: =SUM(M19:M22) -> 6011.4388 | N23: =SUM(N19:N22) -> 11821.451 | O23: << Refer Link >> | T23: =B23-I23 -> 1719 | U23: =C23-J23 -> -1897 | V23: =D23-K23 -> 311.93765 | W23: =E23-L23 -> 4286.8915 | X23: =F23-M23 -> 0 | Y23: =G23-N23 -> 5357
N24: 0
A26: Note 4.5. Lease liabilities
T27: << Difference >>
A28: Particulars | B28: Buildings | C28: Vehicles | D28: Equipments | E28: IT Equipments | F28: Land | G28: Total | I28: Buildings | J28: Vehicles | K28: Equipments | L28: IT Equipments | M28: Land | N28: Total | T28: Buildings | U28: Vehicles | V28: Equipments | W28: IT Equipments | X28: Land | Y28: Total
A29: Balance as at 1 April 2024 | B29: 793.35015 | C29: 1604.4515 | D29: 1132 | E29: 3370.5952 | F29: 0 | G29: =SUM(B29:F29) -> 6900.3969 | I29: 793.35015 | J29: 1604.4515 | K29: 1132 | L29: 3370.5952 | M29: 0 | N29: =SUM(I29:M29) -> 6900.3969 | O29: << Verified from PY Financial Statements >> | T29: =B29-I29 -> 0 | U29: =C29-J29 -> 0 | V29: =D29-K29 -> 0 | W29: =E29-L29 -> 0 | X29: =F29-M29 -> 0 | Y29: =SUM(T29:X29) -> 0
A30: Additions/ modifications during the year | B30: 22 | C30: 854 | D30: 27 | E30: 5932 | F30: 0 | G30: =SUM(B30:F30) -> 6835 | I30: 22 | J30: 854 | K30: 27 | L30: 5932 | M30: 0 | N30: =SUM(I30:M30) -> 6835 | O30: << Verified from PY Financial Statements >> | T30: =B30-I30 -> 0 | U30: =C30-J30 -> 0 | V30: =D30-K30 -> 0 | W30: =E30-L30 -> 0 | X30: =F30-M30 -> 0 | Y30: =G30-N30 -> 0
A31: Accrual of finance cost | B31: 22 | C31: 101 | D31: 24 | E31: 493 | F31: 0 | G31: =SUM(B31:F31) -> 640 | I31: 22 | J31: 101 | K31: 24 | L31: 493 | M31: 0 | N31: =SUM(I31:M31) -> 640 | O31: << Verified from PY Financial Statements >> | T31: =B31-I31 -> 0 | U31: =C31-J31 -> 0 | V31: =D31-K31 -> 0 | W31: =E31-L31 -> 0 | X31: =F31-M31 -> 0 | Y31: =G31-N31 -> 0
A32: Payments | B32: -509 | C32: -818 | D32: -462 | E32: -3321 | F32: 0 | G32: =SUM(B32:F32) -> -5110 | I32: -509 | J32: -818 | K32: -462 | L32: -3321 | M32: 0 | N32: =SUM(I32:M32) -> -5110 | O32: << Verified from PY Financial Statements >> | T32: =B32-I32 -> 0 | U32: =C32-J32 -> 0 | V32: =D32-K32 -> 0 | W32: =E32-L32 -> 0 | X32: =F32-M32 -> 0 | Y32: =G32-N32 -> 0
A33: Adjustment on account of demerger | B33: 0 | C33: -154 | D33: 0 | E33: 0 | F33: 0 | G33: =SUM(B33:F33) -> -154 | I33: 0 | J33: -154 | K33: 0 | L33: 0 | M33: 0 | N33: =SUM(I33:M33) -> -154 | O33: << Verified from PY Financial Statements >> | T33: =B33-I33 -> 0 | U33: =C33-J33 -> 0 | V33: =D33-K33 -> 0 | W33: =E33-L33 -> 0 | X33: =F33-M33 -> 0 | Y33: =G33-N33 -> 0
A34: Adjustment for termination of leases | B34: -135 | C34: -663 | D34: 0 | E34: -151 | F34: 0 | G34: =SUM(B34:F34) -> -949 | I34: -135 | J34: -663 | K34: 0 | L34: -151 | M34: 0 | N34: =SUM(I34:M34) -> -949 | O34: << Verified from PY Financial Statements >> | T34: =B34-I34 -> 0 | U34: =C34-J34 -> 0 | V34: =D34-K34 -> 0 | W34: =E34-L34 -> 0 | X34: =F34-M34 -> 0 | Y34: =G34-N34 -> 0
A35: Transferred to Assets held for sale | B35: 0 | C35: -27 | D35: 0 | E35: 0 | F35: 0 | G35: =SUM(B35:F35) -> -27 | I35: 0 | J35: -27 | K35: 0 | L35: 0 | M35: 0 | N35: =SUM(I35:M35) -> -27 | O35: << Verified from PY Financial Statements >> | T35: =B35-I35 -> 0 | U35: =C35-J35 -> 0 | V35: =D35-K35 -> 0 | W35: =E35-L35 -> 0 | X35: =F35-M35 -> 0 | Y35: =G35-N35 -> 0
A36: Balance as at 31 March 2025 | B36: =SUM(B29:B35) -> 193.35015 | C36: =SUM(C29:C35) -> 897.45153 | D36: =SUM(D29:D35) -> 721 | E36: =SUM(E29:E35) -> 6323.5952 | F36: =SUM(F29:F35) -> 0 | G36: =SUM(G29:G35) -> 8135.3969 | I36: =SUM(I29:I35) -> 193.35015 | J36: =SUM(J29:J35) -> 897.45153 | K36: =SUM(K29:K35) -> 721 | L36: =SUM(L29:L35) -> 6323.5952 | M36: =SUM(M29:M35) -> 0 | N36: =SUM(N29:N35) -> 8135.3969 | O36: << Verified from PY Financial Statements >> | T36: =SUM(T29:T35) -> 0 | U36: =SUM(U29:U35) -> 0 | V36: =SUM(V29:V35) -> 0 | W36: =SUM(W29:W35) -> 0 | X36: =SUM(X29:X35) -> 0 | Y36: =SUM(Y29:Y35) -> 0
A37: Current | B37: 177 | C37: 406 | D37: 433 | E37: 3099 | F37: 0 | G37: =SUM(B37:F37) -> 4115 | I37: 177 | J37: 406 | K37: 433 | L37: 3099 | M37: 0 | N37: =SUM(I37:M37) -> 4115 | O37: << Verified from PY Financial Statements >> | T37: =B37-I37 -> 0 | U37: =C37-J37 -> 0 | V37: =D37-K37 -> 0 | W37: =E37-L37 -> 0 | X37: =F37-M37 -> 0 | Y37: =SUM(T37:X37) -> 0
A38: Non-current | B38: 16 | C38: 491 | D38: 288 | E38: 3225 | F38: 0 | G38: =SUM(B38:F38) -> 4020 | I38: 16 | J38: 491 | K38: 288 | L38: 3225 | M38: 0 | N38: =SUM(I38:M38) -> 4020 | O38: << Verified from PY Financial Statements >> | T38: =B38-I38 -> 0 | U38: =C38-J38 -> 0 | V38: =D38-K38 -> 0 | W38: =E38-L38 -> 0 | X38: =F38-M38 -> 0 | Y38: =SUM(T38:X38) -> 0
A40: Balance as at 1 April 2025 | B40: =B36 -> 193.35015 | C40: =C36 -> 897.45153 | D40: =D36 -> 721 | E40: =E36 -> 6323.5952 | F40: 0 | G40: =SUM(B40:F40) -> 8135.3969 | I40: =I36 -> 193.35015 | J40: =J36 -> 897.45153 | K40: =K36 -> 721 | L40: =L36 -> 6323.5952 | M40: 0 | N40: =SUM(I40:M40) -> 8135.3969 | O40: << Refer Link >> | T40: =B40-I40 -> 0 | U40: =C40-J40 -> 0 | V40: =D40-K40 -> 0 | W40: =E40-L40 -> 0 | X40: =F40-M40 -> 0 | Y40: =G40-N40 -> 0
A41: Additions/ modifications during the year | B41: =B20 -> 1867 | C41: =C20 -> 1225 | D41: 0 | E41: =E20 -> 5755 | F41: 0 | G41: =SUM(B41:F41) -> 8847 | I41: =Summary!H14 -> 0 | J41: =J20 -> 3248 | K41: =K20 -> 45 | L41: =Summary!H17 -> 61 | M41: =M20 -> 0 | N41: =SUM(I41:M41) -> 3354 | O41: << Refer Link >> | T41: =B41-I41 -> 1867 | U41: =C41-J41 -> -2023 | V41: =D41-K41 -> -45 | W41: =E41-L41 -> 5694 | X41: =F41-M41 -> 0 | Y41: =G41-N41 -> 5493
A42: Accrual of finance cost | B42: 123 | C42: 112 | D42: 32 | E42: 586 | F42: 0 | G42: =SUM(B42:F42) -> 853 | I42: =Summary!I14 -> 109 | J42: =Summary!I15 -> 202 | K42: =Summary!I16 -> 28 | L42: =Summary!I17 -> 406 | M42: 0 | N42: =SUM(I42:M42) -> 745 | O42: << Refer Link >> | T42: =B42-I42 -> 14 | U42: =C42-J42 -> -90 | V42: =D42-K42 -> 4 | W42: =E42-L42 -> 180 | X42: =F42-M42 -> 0 | Y42: =G42-N42 -> 108
A43: Payments | B43: -331 | C43: -693 | D43: -455 | E43: -4704 | F43: 0 | G43: =SUM(B43:F43) -> -6183 | I43: =-Summary!J14 -> -458 | J43: =-Summary!J15 -> -1040 | K43: =-Summary!J16 -> -331 | L43: =-Summary!J17 -> -4703 | M43: 0 | N43: =SUM(I43:M43) -> -6532 | O43: << Refer Link >> | T43: =B43-I43 -> 127 | U43: =C43-J43 -> 347 | V43: =D43-K43 -> -124 | W43: =E43-L43 -> -1 | X43: =F43-M43 -> 0 | Y43: =G43-N43 -> 349
A44: Adjustment for termination of leases | B44: -199 | C44: -134 | D44: -21 | E44: =-2 -> -2 | F44: 0 | G44: =SUM(B44:F44) -> -356 | I44: =-Summary!K14 -> 0 | J44: =-Summary!K15 -> 24 | K44: =-Summary!K16 -> 0 | L44: =-Summary!K17 -> 0 | M44: =-Summary!K18 -> 0 | N44: =SUM(I44:M44) -> 24 | O44: << Refer Link >> | T44: =B44-I44 -> -199 | U44: =C44-J44 -> -158 | V44: =D44-K44 -> -21 | W44: =E44-L44 -> -2 | X44: =F44-M44 -> 0 | Y44: =G44-N44 -> -380
A45: Balance as at 31 March 2026 | B45: =SUM(B40:B44) -> 1653.3502 | C45: =SUM(C40:C44) -> 1407.4515 | D45: =SUM(D40:D44) -> 277 | E45: =SUM(E40:E44) -> 7958.5952 | F45: =SUM(F40:F44) -> 0 | G45: =SUM(G40:G44) -> 11296.397 | I45: =SUM(I40:I44) -> -155.64985 | J45: =SUM(J40:J44) -> 3331.4515 | K45: =SUM(K40:K44) -> 463 | L45: =SUM(L40:L44) -> 2087.5952 | M45: =SUM(M40:M44) -> 0 | N45: =SUM(N40:N44) -> 5726.3969 | T45: =B45-I45 -> 1809 | U45: =C45-J45 -> -1924 | V45: =D45-K45 -> -186 | W45: =E45-L45 -> 5871 | X45: =F45-M45 -> 0 | Y45: =G45-N45 -> 5570
A46: Current | B46: 349 | C46: 558.56223 | D46: 277 | E46: 4256 | F46: 0 | G46: =SUM(B46:F46) -> 5440.5622 | I46: =Summary!M14 -> 442 | J46: =Summary!M15 -> 961 | K46: =Summary!M16 -> 20 | L46: =Summary!M17 -> 2245 | M46: =Summary!M18 -> 0 | N46: =SUM(I46:M46) -> 3668 | T46: =B46-I46 -> -93 | U46: =C46-J46 -> -402.43777 | V46: =D46-K46 -> 257 | W46: =E46-L46 -> 2011 | X46: =F46-M46 -> 0 | Y46: =SUM(T46:X46) -> 1772.5622
A47: Non-current | B47: 1304.3502 | C47: 848.88931 | D47: 0 | E47: 3703 | F47: 0 | G47: =SUM(B47:F47) -> 5856.2395 | I47: =Summary!N14 -> 863 | J47: =Summary!N15 -> 2946 | K47: =Summary!N16 -> 0 | L47: =Summary!N17 -> 1411 | M47: =Summary!N18 -> 0 | N47: =SUM(I47:M47) -> 5220 | T47: =B47-I47 -> 441.35015 | U47: =C47-J47 -> -2097.1107 | V47: =D47-K47 -> 0 | W47: =E47-L47 -> 2292 | X47: =F47-M47 -> 0 | Y47: =SUM(T47:X47) -> 636.23947
A49: Note:
A50: (i) Lease hold land includes land amounting to INR 6,816 lakhs (previous year 6,816 lakhs) representing land leased from Maharashtra Industrial Development Corporation taken on 17 September 2012 for an initial period of 95 years.
A52: Amounts recognized in statement of profit and loss
A54: Particulars | D54: For the year ended 31 March 2025 | E54: For the year ended 31 March 2024
A55: Depreciation on right of use assets | D55: =-G21 -> 5767 | E55: =-N13 -> 4583 | F55: << Refer Link >>
A56: Interest on lease liabilities | D56: =G42 -> 853 | E56: =G31 -> 640 | F56: << Refer Link >>
A57: Expense relating to low value assets | D57: 7125 | E57: 9637 | F57: << Refer Rent Expense >>
A58: Total | D58: =SUM(D55:D57) -> 13745 | E58: =SUM(E55:E57) -> 14860
A60: The details of contractual maturities of lease liabilities as at March 31, 2025 on an undiscounted basis are as follows:
A61: Particulars | D61: As at 31 March 2025 | E61: As at 31 March 2024
A62: Less than one year | D62: =Summary!M19 -> 3668 | E62: 5069 | F62: << Refer Link >>
A63: One to five years | D63: =Summary!N19 -> 5220 | E63: 5380 | F63: << Refer Link >>
A65: Total | D65: =SUM(D62:D64) -> 8888 | E65: =SUM(E62:E64) -> 10449
A67: The details of principal and interest repayment for the year ended March 31, 2025 are as follows:
A68: Particulars | D68: For the year ended 31 March 2024 | E68: For the year ended 31 March 2023
A69: Principal repayments | D69: =-G43-G42 -> 5330 | E69: =-(G32+E70) -> 4470 | F69: << Refer Link >>
A70: Interest expense | D70: =G42 -> 853 | E70: =G31 -> 640 | F70: << Refer Link >>
A71: Total | D71: =SUM(D69:D70) -> 6183 | E71: 4100

Sheet Summary
A1: =Scope!#REF! -> #REF!
A2: =Scope!#REF! -> #REF!
A3: =Scope!#REF! -> #REF!
A6: =Scope!A2 -> Purpose
A7: To document the summary of ROU Assets and Lease Liability
A10: Summary
B12: Right of Use Assets | G12: Lease Liability
A13: Particulars | B13: Net Block as at April 1, 2025 | C13: Addition | D13: Disposals | E13: Amortisation during FY 2025-26 | F13: Net Block as at March 31, 2026 | G13: Opening Balance | H13: Addition | I13: Interest | J13: Repayment | K13: Deletions/ Adjustment | L13: Closing Balance | M13: Sum of ST | N13: Sum of LT
A14: Building Lease | B14: =ROUND(SUMIF('Details 25-26'!$D:$D,$A14,'Details 25-26'!I:I)/10^5,0) -> 1527 | C14: =ROUND(SUMIF('Details 25-26'!$D:$D,$A14,'Details 25-26'!J:J)/10^5,0) -> 0 | D14: =ROUND(SUMIF('Details 25-26'!$D:$D,$A14,'Details 25-26'!K:K)/10^5,0) -> 0 | E14: =ROUND(SUMIF('Details 25-26'!$D:$D,$A14,'Details 25-26'!L:L)/10^5,0) -> 394 | F14: =B14+C14-D14-E14 -> 1133 | G14: =ROUND(SUMIF('Details 25-26'!$D:$D,$A14,'Details 25-26'!N:N)/10^5,0) -> 1653 | H14: =ROUND(SUMIF('Details 25-26'!$D:$D,$A14,'Details 25-26'!O:O)/10^5,0) -> 0 | I14: =ROUND(SUMIF('Details 25-26'!$D:$D,$A14,'Details 25-26'!P:P)/10^5,0) -> 109 | J14: =ROUND(SUMIF('Details 25-26'!$D:$D,$A14,'Details 25-26'!Q:Q)/10^5,0) -> 458 | K14: =ROUND(SUMIF('Details 25-26'!$D:$D,$A14,'Details 25-26'!R:R)/10^5,0) -> 0 | L14: =G14+H14+I14-J14-K14 -> 1304 | M14: =ROUND(SUMIF('Details 25-26'!$D:$D,$A14,'Details 25-26'!T:T)/10^5,0) -> 442 | N14: =ROUND(SUMIF('Details 25-26'!$D:$D,$A14,'Details 25-26'!U:U)/10^5,0) -> 863
A15: Vehicle Lease | B15: =ROUND(SUMIF('Details 25-26'!$D:$D,$A15,'Details 25-26'!I:I)/10^5,0) -> 1436 | C15: =ROUND(SUMIF('Details 25-26'!$D:$D,$A15,'Details 25-26'!J:J)/10^5,0) -> 3248 | D15: =ROUND(SUMIF('Details 25-26'!$D:$D,$A15,'Details 25-26'!K:K)/10^5,0) -> -25 | E15: =ROUND(SUMIF('Details 25-26'!$D:$D,$A15,'Details 25-26'!L:L)/10^5,0) -> 911 | F15: =B15+C15-D15-E15 -> 3798 | G15: =ROUND(SUMIF('Details 25-26'!$D:$D,$A15,'Details 25-26'!N:N)/10^5,0) -> 1474 | H15: =ROUND(SUMIF('Details 25-26'!$D:$D,$A15,'Details 25-26'!O:O)/10^5,0) -> 3248 | I15: =ROUND(SUMIF('Details 25-26'!$D:$D,$A15,'Details 25-26'!P:P)/10^5,0) -> 202 | J15: =ROUND(SUMIF('Details 25-26'!$D:$D,$A15,'Details 25-26'!Q:Q)/10^5,0) -> 1040 | K15: =ROUND(SUMIF('Details 25-26'!$D:$D,$A15,'Details 25-26'!R:R)/10^5,0) -> -24 | L15: =G15+H15+I15-J15-K15 -> 3908 | M15: =ROUND(SUMIF('Details 25-26'!$D:$D,$A15,'Details 25-26'!T:T)/10^5,0) -> 961 | N15: =ROUND(SUMIF('Details 25-26'!$D:$D,$A15,'Details 25-26'!U:U)/10^5,0) -> 2946
A16: Equipment Lease | B16: =ROUND(SUMIF('Details 25-26'!$D:$D,$A16,'Details 25-26'!I:I)/10^5,0) -> 400 | C16: =ROUND(SUMIF('Details 25-26'!$D:$D,$A16,'Details 25-26'!J:J)/10^5,0) -> 45 | D16: =ROUND(SUMIF('Details 25-26'!$D:$D,$A16,'Details 25-26'!K:K)/10^5,0) -> 0 | E16: =ROUND(SUMIF('Details 25-26'!$D:$D,$A16,'Details 25-26'!L:L)/10^5,0) -> 357 | F16: =B16+C16-D16-E16 -> 88 | G16: =ROUND(SUMIF('Details 25-26'!$D:$D,$A16,'Details 25-26'!N:N)/10^5,0) -> 277 | H16: =ROUND(SUMIF('Details 25-26'!$D:$D,$A16,'Details 25-26'!O:O)/10^5,0) -> 45 | I16: =ROUND(SUMIF('Details 25-26'!$D:$D,$A16,'Details 25-26'!P:P)/10^5,0) -> 28 | J16: =ROUND(SUMIF('Details 25-26'!$D:$D,$A16,'Details 25-26'!Q:Q)/10^5,0) -> 331 | K16: =ROUND(SUMIF('Details 25-26'!$D:$D,$A16,'Details 25-26'!R:R)/10^5,0) -> 0 | L16: =G16+H16+I16-J16-K16 -> 19 | M16: =ROUND(SUMIF('Details 25-26'!$D:$D,$A16,'Details 25-26'!T:T)/10^5,0) -> 20 | N16: =ROUND(SUMIF('Details 25-26'!$D:$D,$A16,'Details 25-26'!U:U)/10^5,0) -> 0
A17: IT Equipment Lease | B17: =ROUND(SUMIF('Details 25-26'!$D:$D,$A17,'Details 25-26'!I:I)/10^5,0) -> 7792 | C17: =ROUND(SUMIF('Details 25-26'!$D:$D,$A17,'Details 25-26'!J:J)/10^5,0) -> 61 | D17: =ROUND(SUMIF('Details 25-26'!$D:$D,$A17,'Details 25-26'!K:K)/10^5,0) -> 0 | E17: =ROUND(SUMIF('Details 25-26'!$D:$D,$A17,'Details 25-26'!L:L)/10^5,0) -> 4280 | F17: =B17+C17-D17-E17 -> 3573 | G17: =ROUND(SUMIF('Details 25-26'!$D:$D,$A17,'Details 25-26'!N:N)/10^5,0) -> 7893 | H17: =ROUND(SUMIF('Details 25-26'!$D:$D,$A17,'Details 25-26'!O:O)/10^5,0) -> 61 | I17: =ROUND(SUMIF('Details 25-26'!$D:$D,$A17,'Details 25-26'!P:P)/10^5,0) -> 406 | J17: =ROUND(SUMIF('Details 25-26'!$D:$D,$A17,'Details 25-26'!Q:Q)/10^5,0) -> 4703 | K17: =ROUND(SUMIF('Details 25-26'!$D:$D,$A17,'Details 25-26'!R:R)/10^5,0) -> 0 | L17: =G17+H17+I17-J17-K17 -> 3657 | M17: =ROUND(SUMIF('Details 25-26'!$D:$D,$A17,'Details 25-26'!T:T)/10^5,0) -> 2245 | N17: =ROUND(SUMIF('Details 25-26'!$D:$D,$A17,'Details 25-26'!U:U)/10^5,0) -> 1411
A18: Land | B18: 6085.4388 | C18: =ROUND(SUMIF('Details 25-26'!$D:$D,$A18,'Details 25-26'!J:J)/10^5,0) -> 0 | D18: =ROUND(SUMIF('Details 25-26'!$D:$D,$A18,'Details 25-26'!K:K)/10^5,0) -> 0 | E18: 74 | F18: =B18+C18-D18-E18 -> 6011.4388 | G18: 0 | H18: 0 | I18: 0 | J18: 0 | K18: 0 | L18: =G18+H18+I18-J18-K18 -> 0 | M18: =ROUND(SUMIF('Details 25-26'!$D:$D,$A18,'Details 25-26'!T:T)/10^5,0) -> 0 | N18: =ROUND(SUMIF('Details 25-26'!$D:$D,$A18,'Details 25-26'!U:U)/10^5,0) -> 0
A19: Grand Total | B19: =SUM(B14:B17) -> 11155 | C19: =SUM(C14:C17) -> 3354 | D19: =SUM(D14:D17) -> -25 | E19: =SUM(E14:E17) -> 5942 | F19: =SUM(F14:F17) -> 8592 | G19: =SUM(G14:G17) -> 11297 | H19: =SUM(H14:H17) -> 3354 | I19: =SUM(I14:I17) -> 745 | ... N19: =SUM(N14:N17) -> 5220

Sheet Testing
A1: =Scope!#REF! -> #REF!
A2: =Scope!#REF! -> #REF!
A3: =Scope!#REF! -> #REF!
A6: =Scope!A2 -> Purpose
A7: To document the summary of samples recomputed by ET.
A10: Lease ID | B10: Division | C10: Lease Type | D10: Lessor details | E10: Amount | F10: Testing Reference
A11: 64797 | B11: ITC | C11: IT Equipment Lease | D11: Hewlett-Packard Financial Services (India) Private Limited | E11: =_xlfn.XLOOKUP(A11,'Details 25-26'!B:B,'Details 25-26'!I:I) -> 18576235 | F11: ="<< Refer tab "&A11&" >>" -> << Refer tab 64797 >>
A12: 64806 | B12: ITC | C12: IT Equipment Lease | D12: Hewlett-Packard Financial Services (India) Private Limited | E12: =_xlfn.XLOOKUP(A12,'Details 25-26'!B:B,'Details 25-26'!I:I) -> 2.5323583e+08 | F12: ="<< Refer tab "&A12&" >>" -> << Refer tab 64806 >>
A13: 64807 | B13: ITC | C13: IT Equipment Lease | D13: Hewlett-Packard Financial Services (India) Private Limited | E13: =_xlfn.XLOOKUP(A13,'Details 25-26'!B:B,'Details 25-26'!I:I) -> 31042989 | F13: ="<< Refer tab "&A13&" >>" -> << Refer tab 64807 >>
A14: 64418 | B14: OCL | C14: Building Lease | D14: Workprovince Technology Private Limited | E14: =_xlfn.XLOOKUP(A14,'Details 25-26'!B:B,'Details 25-26'!I:I) -> 41405813 | F14: ="<< Refer tab "&A14&" -1"&" >>" -> << Refer tab 64418 -1 >>
A15: 64418 | B15: OCL | C15: Building Lease | D15: Workprovince Technology Private Limited | E15: =_xlfn.XLOOKUP(A15,'Details 25-26'!B:B,'Details 25-26'!I:I) -> 41405813 | F15: ="<< Refer tab "&A15&" -2"&" >>" -> << Refer tab 64418 -2 >>
A16: 59308 | B16: MMF | C16: IT Equipment Lease | D16: Cisco Systems Capital India Private Limited | E16: =_xlfn.XLOOKUP(A16,'Details 25-26'!B:B,'Details 25-26'!I:I) -> 16941688 | F16: ="<< Refer tab "&A16&" >>" -> << Refer tab 59308 >>
A17: 66353 | B17: MMF | C17: Vehicle Lease | D17: Shree Gajanan Corporation India Private Limited | E17: ='Details 25-26'!J27 -> 1.4217495e+08 | F17: ="<< Refer tab "&A17&" >>" -> << Refer tab 66353 >>
A18: 66354 | B18: MMF | C18: Vehicle Lease | D18: Shree Gajanan Corporation India Private Limited | E18: ='Details 25-26'!J28 -> 18970811 | F18: ="<< Refer tab "&A18&" >>" -> << Refer tab 66354 >>
A19: 53818 | B19: ITC | C19: IT Equipment Lease | D19: STT Telemedia Global Data Centre | E19: =_xlfn.XLOOKUP(A19,'Details 25-26'!B:B,'Details 25-26'!I:I) -> 42114950 | F19: ="<< Refer tab "&A19&" >>" -> << Refer tab 53818 >>
A20: 59268 | B20: ITC | C20: IT Equipment Lease | D20: Hewlett-Packard Financial Services (India) Private Limited | E20: =_xlfn.XLOOKUP(A20,'Details 25-26'!B:B,'Details 25-26'!I:I) -> 32928959 | F20: ="<< Refer tab "&A20&" >>" -> << Refer tab 59268 >>
A21: 60756 | B21: ITC | C21: IT Equipment Lease | D21: Hewlett-Packard Financial Services (India) Private Limited | E21: =_xlfn.XLOOKUP(A21,'Details 25-26'!B:B,'Details 25-26'!I:I) -> 26034322 | F21: ="<< Refer tab "&A21&" >>" -> << Refer tab 60756 >>
A22: 62007 | B22: ITC | C22: IT Equipment Lease | D22: Hewlett-Packard Financial Services (India) Private Limited | E22: =_xlfn.XLOOKUP(A22,'Details 25-26'!B:B,'Details 25-26'!I:I) -> 22626429 | F22: ="<< Refer tab "&A22&" >>" -> << Refer tab 62007 >>
A23: 64753 | B23: ITC | C23: IT Equipment Lease | D23: Cisco Systems Capital India Private Limited | E23: =_xlfn.XLOOKUP(A23,'Details 25-26'!B:B,'Details 25-26'!I:I) -> 19027935 | F23: ="<< Refer tab "&A23&" >>" -> << Refer tab 64753 >>
A24: 64754 | B24: ITC | C24: IT Equipment Lease | D24: Cisco Systems Capital India Private Limited | E24: =_xlfn.XLOOKUP(A24,'Details 25-26'!B:B,'Details 25-26'!I:I) -> 18680628 | F24: ="<< Refer tab "&A24&" >>" -> << Refer tab 64754 >>
A25: 64802 | B25: ITC | C25: IT Equipment Lease | D25: Hewlett-Packard Financial Services (India) Private Limited | E25: =_xlfn.XLOOKUP(A25,'Details 25-26'!B:B,'Details 25-26'!I:I) -> 28252051 | F25: ="<< Refer tab "&A25&" >>" -> << Refer tab 64802 >>
A26: 65449 | B26: ITC | C26: IT Equipment Lease | D26: Cisco Systems Capital India Private Limited | E26: =_xlfn.XLOOKUP(A26,'Details 25-26'!B:B,'Details 25-26'!I:I) -> 1.2309448e+08 | F26: ="<< Refer tab "&A26&" >>" -> << Refer tab 65449 >>
A27: 56754 | B27: ITC | C27: IT Equipment Lease | D27: Orix Leasing And Financial Services India Limited A37848 | E27: =_xlfn.XLOOKUP(A27,'Details 25-26'!B:B,'Details 25-26'!I:I) -> 987857.38 | F27: ="<< Refer tab "&A27&" >>" -> << Refer tab 56754 >>
A28: 57772 | B28: ITC | C28: IT Equipment Lease | D28: Hewlett-Packard Financial Services (India) Private Limited | E28: =_xlfn.XLOOKUP(A28,'Details 25-26'!B:B,'Details 25-26'!I:I) -> 5036147.2 | F28: ="<< Refer tab "&A28&" >>" -> << Refer tab 57772 >>
A29: 60014 | B29: ITC | C29: IT Equipment Lease | D29: Hewlett-Packard Financial Services (India) Private Limited | E29: =_xlfn.XLOOKUP(A29,'Details 25-26'!B:B,'Details 25-26'!I:I) -> 46481791 | F29: ="<< Refer tab "&A29&" >>" -> << Refer tab 60014 >>
A30: 62561 | B30: ITC | C30: IT Equipment Lease | D30: Hewlett-Packard Financial Services (India) Private Limited | E30: =_xlfn.XLOOKUP(A30,'Details 25-26'!B:B,'Details 25-26'!I:I) -> 83277964 | F30: ="<< Refer tab "&A30&" >>" -> << Refer tab 62561 >>
A31: 63100 | B31: ITC | C31: IT Equipment Lease | D31: Hewlett-Packard Financial Services (India) Private Limited | E31: =_xlfn.XLOOKUP(A31,'Details 25-26'!B:B,'Details 25-26'!I:I) -> 10884953 | F31: ="<< Refer tab "&A31&" >>" -> << Refer tab 63100 >>
A32: Rent Alpha Private Limited | B32: WIND | C32: Equipment Lease | D32: Rent Alpha Private Limited | E32: =_xlfn.XLOOKUP(A32,'Details 25-26'!B:B,'Details 25-26'!I:I) -> 40015641 | F32: ="<< Refer tab "&A32&" >>" -> << Refer tab Rent Alpha Private Limited >>

Sheet Vehicle Policy Analysis
A1: =Testing!A1 -> #REF!
A2: =Testing!A2 -> #REF!
A3: =Testing!A3 -> #REF!
A5: Work Done
A6: ET has obtained vehicle policy and performed an analysis of the same.
A8: Area | B8: Key Provision
A9: Objective | B9: Provides eligible employees with a company car lease for business and reasonable personal use.
A10: Coverage | B10: Applicable to permanent employees in LPB and SPB bands in India with a local employment contract.
A11: Eligibility Limits | B11: Vehicle value eligibility ranges from ₹14 lakh to ₹32 lakh depending on employee band and lease tenure.
A12: Lease | B12: Employees can opt for a 3, 4, or 5-year lease. Once selected, tenure cannot be changed.
A13: Fuel & Maintenance Benefit | B13: Annual reimbursement capped at ₹2 lakh (LPB- Lead Professional Band) and ₹2.5 lakh (SPB- Senior Professional Band) against supporting bills
A14: Cost Allocation | B14: Company bears insurance cost during lease tenure; employee bears lease rentals, road tax, registration charges, fines, and other applicable taxes.
A15: End of | B15: Employee is responsible for closing the lease, obtaining NDC, and purchasing the vehicle from the leasing company at lease expiry.
A16: Employee Obligations | B16: Employee must maintain the vehicle, comply with traffic laws, and bear uninsured losses, damages, and penalties.
A17: Key Restriction | B17: Vehicle usage should not exceed 15,000 km per year on average; excess usage charges may apply.

Sheet Details 25-26
A1: =Scope!#REF! -> #REF!
A2: =Scope!#REF! -> #REF!
A3: =Scope!#REF! -> #REF!
A5: Purpose
A6: To document the schedule for ROU Assets and Lease Liability.
H8: =SUBTOTAL(9,H11:H2529) -> 11676309 | I8: =SUBTOTAL(9,I11:I2529) -> 1.1156086e+09 | J8: =SUBTOTAL(9,J11:J2529) -> 3.353532e+08 | K8: =SUBTOTAL(9,K11:K2529) -> -2542050.4 | L8: =SUBTOTAL(9,L11:L2529) -> 5.9424369e+08 | M8: =SUBTOTAL(9,M11:M2529) -> 8.5926012e+08 | N8: =SUBTOTAL(9,N11:N2529) -> 1.1296833e+09 | O8: =SUBTOTAL(9,O11:O2529) -> 3.353532e+08 | ... U8: =SUBTOTAL(9,U11:U2529) -> 5.2197959e+08
I9: ROU | N9: Lease Liability
A10: S.No | B10: System Lease ID | C10: Division | D10: Lease Template | E10: Discount Rate | F10: Commencement Date | G10: Expiration Date | H10: Monthly Payments | I10: Opening Balance as on April'25 | J10: Addition during FY 2025-26 | K10: Deletions/ Adjustment during FY 2025-26 | L10: Amortisation during FY 2025-26 | M10: Closing Balance | N10: Opening Balance | O10: Addition during the year | P10: Interest | Q10: Repayment | R10: Deletion during the year | S10: Closing Balance | T10: ST | U10: LT
A11: 1 | B11: 60272 | C11: MMF | D11: Vehicle Lease | E11: 4.4375 | F11: 44986 | G11: 46124 | H11: 35593.85 | I11: 659457.49 | J11: 0 | K11: -37247.4 | L11: 400867.72 | M11: =I11+J11-K11-L11 -> 295837.17 | N11: 687503.51 | O11: 0 | P11: 36500.42 | Q11: 433959.16 | R11: -37247.4 | S11: =N11+O11+P11-Q11-R11 -> 327292.17 | T11: 327291.7 | U11: 0
A12: =A11+1 -> 2 | B12: 61193 | C12: MMF | D12: Vehicle Lease | E12: 4.698 | F12: 45047 | G12: 46498 | H12: 27611.88 | I12: 615109.1 | J12: 0 | K12: -11137.05 | L12: 296354.24 | M12: =I12+J12-K12-L12 -> 329891.91 | N12: 633798.3 | O12: 0 | P12: 38432.04 | Q12: 333162.8 | R12: -11137.05 | S12: =N12+O12+P12-Q12-R12 -> 350204.59 | T12: 322137.84 | U12: 28066.94
A13: =A12+1 -> 3 | B13: 61200 | C13: MMF | D13: Vehicle Lease | E13: 4.698 | F13: 45047 | G13: 46498 | H13: 17701.46 | I13: 394335.25 | J13: 0 | K13: -4031.03 | L13: 189242.56 | M13: =I13+J13-K13-L13 -> 209123.72 | N13: 406316.69 | O13: 0 | P13: 24564.61 | Q13: 212811.96 | R13: -4031.03 | S13: =N13+O13+P13-Q13-R13 -> 222100.37 | T13: 204300.02 | U13: 17800.07
A14: =A13+1 -> 4 | B14: 61205 | C14: MMF | D14: Vehicle Lease | E14: 4.698 | F14: 45047 | G14: 46507 | H14: 33574.42 | I14: 766842.83 | J14: 0 | K14: -25.97 | L14: 361349.76 | M14: =I14+J14-K14-L14 -> 405519.04 | N14: 801230.71 | O14: 0 | P14: 48785.27 | Q14: 409744.72 | R14: -25.97 | S14: =N14+O14+P14-Q14-R14 -> 440297.23 | T14: 405009.89 | U14: 35287.34
A15: =A14+1 -> 5 | B15: 61209 | C15: MMF | D15: Vehicle Lease | E15: 4.698 | F15: 45047 | G15: 46507 | H15: 25441.09 | I15: 581076.73 | J15: 0 | K15: 18603.13 | L15: 269431.72 | M15: =I15+J15-K15-L15 -> 293041.88 | N15: 607134.72 | O15: 0 | P15: 36527.14 | Q15: 305857.36 | R15: 18603.13 | S15: =N15+O15+P15-Q15-R15 -> 319201.37 | T15: 293618.84 | U15: 25582.16
A16: =A15+1 -> 6 | B16: 62974 | C16: MMF | D16: Vehicle Lease | E16: 4.8266 | F16: 45170 | G16: 46668 | H16: 21973.84 | I16: 564437.74 | J16: 0 | K16: -3900.01 | L16: 235793.36 | M16: =I16+J16-K16-L16 -> 332544.39 | N16: 583119.97 | O16: 0 | P16: 34499.16 | Q16: 264241.76 | R16: -3900.01 | S16: =N16+O16+P16-Q16-R16 -> 357277.38 | T16: 248119.12 | U16: 109157.99
A17: =A16+1 -> 7 | B17: 62980 | C17: MMF | D17: Vehicle Lease | E17: 4.8266 | F17: 45169 | G17: 46629 | H17: 24788.47 | I17: 642481.88 | J17: 0 | K17: -29982.71 | L17: 267290.72 | M17: =I17+J17-K17-L17 -> 405173.87 | N17: 657812.3 | O17: 0 | P17: 39499.4 | Q17: 303280.6 | R17: -29982.71 | S17: =N17+O17+P17-Q17-R17 -> 424013.81 | T17: 294465.38 | U17: 129547.65
A18: =A17+1 -> 8 | B18: 59308 | C18: MMF | D18: IT Equipment Lease | E18: 5.1215 | F18: 44926 | G18: 46691 | H18: 606609.11 | I18: 16941688 | J18: 0 | K18: 0 | L18: 6558072.7 | M18: =I18+J18-K18-L18 -> 10383615 | N18: 17653948 | O18: 0 | P18: 720542.53 | Q18: 7279309.3 | R18: 0 | S18: =N18+O18+P18-Q18-R18 -> 11095181 | T18: 6902672.2 | U18: 4192508.5
A19: =A18+1 -> 9 | B19: 64733 | C19: MMF | D19: Vehicle Lease | E19: 7.4689 | F19: 45422 | G19: 47247 | H19: 48438.24 | I19: 1999679.8 | J19: 0 | K19: 146835.18 | L19: 501057.8 | M19: =I19+J19-K19-L19 -> 1351786.8 | N19: 2052968 | O19: 0 | P19: 138138.14 | Q19: 593044.52 | R19: 0 | S19: =N19+O19+P19-Q19-R19 -> 1598061.6 | T19: 580776 | U19: 1017285.6
A20: =A19+1 -> 10 | B20: 64752 | C20: MMF | D20: Vehicle Lease | E20: 7.4689 | F20: 45422 | G20: 46516 | H20: 26324.8 | I20: 598499.66 | J20: 0 | K20: 480173.86 | L20: 118325.8 | M20: =I20+J20-K20-L20 -> 0 | N20: 611508.89 | O20: 0 | P20: 16790.59 | Q20: 131624 | R20: 496675.48 | S20: =N20+O20+P20-Q20-R20 -> 0 | T20: 0 | U20: 0
A21: =A20+1 -> 11 | B21: 65270 | C21: MMF | D21: Vehicle Lease | E21: 7.3028 | F21: 45536 | G21: 45897 | H21: 38401.24 | I21: 183631 | J21: 0 | K21: 0 | L21: 183631.27 | M21: =I21+J21-K21-L21 -> -0.27 | N21: 189697 | O21: 0 | P21: 2308.83 | Q21: 192006.2 | R21: 0 | S21: =N21+O21+P21-Q21-R21 -> -0.37 | T21: 0 | U21: 0
A22: =A21+1 -> 12 | B22: 65366 | C22: MMF | D22: Vehicle Lease | E22: 7.8173 | F22: 45549 | G22: 47374 | H22: 25782.09 | I22: 1144676.2 | J22: 0 | K22: -75042.02 | L22: 263677.04 | M22: =I22+J22-K22-L22 -> 956041.18 | N22: 1159883.2 | O22: 0 | P22: 82456.16 | Q22: 314979 | R22: -75042.02 | S22: =N22+O22+P22-Q22-R22 -> 1002402.4 | T22: 259083 | U22: 743319.44
A23: =A22+1 -> 13 | B23: 65884 | C23: MMF | D23: Vehicle Lease | E23: 7.3469 | F23: 45795 | G23: 47620 | H23: 37122.22 | I23: 0 | J23: 1870722.9 | K23: -57608.42 | L23: 330171.13 | M23: =I23+J23-K23-L23 -> 1598160.2 | N23: 0 | O23: 1870722.9 | P23: 115987.3 | Q23: 411009.7 | R23: -57608.42 | S23: =N23+O23+P23-Q23-R23 -> 1633308.9 | T23: 347797.83 | U23: 1285511.1
... A28: =A27+1 -> 18 | B28: 66354 | C28: MMF | D28: Vehicle Lease | E28: 7.6675 | F28: 45992 | G28: 48182 | H28: 285165 | I28: 0 | J28: 18970811 | K28: 0 | L28: 1053933.9 | M28: =I28+J28-K28-L28 -> 17916877 | N28: 0 | O28: 18970811 | P28: 471191.95 | Q28: 1140660 | R28: 0 | S28: =N28+O28+P28-Q28-R28 -> 18301343 | T28: 2113849.9 | U28: 16187493
A29: =A28+1 -> 19 | B29: 52815 | C29: OCL | D29: Vehicle Lease | E29: 1.3148 | F29: 44470 | G29: 45899 | H29: 28583.98 | I29: 123356.37 | J29: =0 -> 0 | K29: =0 -> 0 | L29: 123356.37 | M29: =I29+J29-K29-L29 -> 0 | N29: 113295.64 | O29: =0 -> 0 | P29: 29624.26 | Q29: 142919.9 | R29: =0 -> 0 | S29: =N29+O29+P29-Q29-R29 -> 0 | T29: 0 | U29: 0
A30: =A29+1 -> 20 | B30: 57761 | C30: OCL | D30: Vehicle Lease | E30: 7.3531 | F30: 44707 | G30: 46167 | H30: 23776.33 | I30: 282820.91 | J30: =0 -> 0 | K30: -23641.5 | L30: 262102.68 | M30: =I30+J30-K30-L30 -> 44359.73 | N30: 298045.98 | O30: =0 -> 0 | P30: 11625.07 | Q30: 285708.84 | R30: -23641.5 | S30: =N30+O30+P30-Q30-R30 -> 47603.71 | T30: 0 | U30: 47603.71
A31: =A30+1 -> 21 | B31: 57765 | C31: OCL | D31: Vehicle Lease | E31: 7.3531 | F31: 44774 | G31: 46187 | H31: 35265.05 | I31: 441634.41 | J31: =0 -> 0 | K31: -42182.7 | L31: 392014.96 | M31: =I31+J31-K31-L31 -> 91802.15 | N31: 474634.59 | O31: =0 -> 0 | P31: 19820.94 | Q31: 427559.16 | R31: -42182.7 | S31: =N31+O31+P31-Q31-R31 -> 109079.07 | T31: 0 | U31: 109079.07
A32: =A31+1 -> 22 | B32: 57774 | C32: OCL | D32: Vehicle Lease | E32: 7.3531 | F32: 44774 | G32: 46203 | H32: 19340.58 | I32: 256260.26 | J32: =0 -> 0 | K32: -19273.25 | L32: 211690.4 | M32: =I32+J32-K32-L32 -> 63843.11 | N32: 278060.64 | O32: =0 -> 0 | P32: 12165.61 | Q32: 232466.08 | R32: -19273.25 | S32: =N32+O32+P32-Q32-R32 -> 77033.42 | T32: 0 | U32: 77033.42
A33: =A32+1 -> 23 | B33: 58553 | C33: OCL | D33: Vehicle Lease | E33: 7.1163 | F33: 44805 | G33: 45900 | H33: 23422.29 | I33: 114477.31 | J33: =0 -> 0 | K33: =0 -> 0 | L33: 114477.31 | M33: =I33+J33-K33-L33 -> 0 | N33: 115738.75 | O33: =0 -> 0 | P33: 1372.7 | Q33: 117111.45 | R33: =0 -> 0 | S33: =N33+O33+P33-Q33-R33 -> 0 | T33: 0 | U33: 0
A34: =A33+1 -> 24 | B34: 64306 | C34: OCL | D34: Vehicle Lease | E34: 7.62 | F34: 45289 | G34: 46749 | H34: 114408.86 | I34: 4210036.7 | J34: =0 -> 0 | K34: -401941.95 | L34: 1547732.5 | M34: =I34+J34-K34-L34 -> 3064246.1 | N34: 4288565.9 | O34: =0 -> 0 | P34: 262955.68 | Q34: 1735287.8 | R34: -401941.95 | S34: =N34+O34+P34-Q34-R34 -> 3218175.7 | T34: 1797207.7 | U34: 1420968.1
A35: =A34+1 -> 25 | B35: 64418 | C35: OCL | D35: Building Lease | E35: 7.57 | F35: 45606 | G35: 47163 | H35: 960825 | I35: 41405813 | J35: =0 -> 0 | K35: =0 -> 0 | L35: 10685371 | M35: =I35+J35-K35-L35 -> 30720442 | N35: 41816461 | O35: =0 -> 0 | P35: 2793767.7 | Q35: 11610541 | R35: =0 -> 0 | S35: =N35+O35+P35-Q35-R35 -> 32999688 | T35: 11170343 | U35: 21829345
A36: =A35+1 -> 26 | B36: 64418 | C36: OCL | D36: Building Lease | E36: 7.485 | F36: 45336 | G36: 47162 | H36: 2700000 | I36: 1.1132711e+08 | J36: =0 -> 0 | K36: =0 -> 0 | L36: 28751660 | M36: =I36+J36-K36-L36 -> 82575451 | N36: 1.2350436e+08 | O36: =0 -> 0 | P36: 8154950.2 | Q36: 34237688 | R36: =0 -> 0 | S36: =N36+O36+P36-Q36-R36 -> 97421626 | T36: 32988176 | U36: 64433450
A37: =A36+1 -> 27 | B37: 64719 | C37: OCL | D37: Vehicle Lease | E37: 7.64 | F37: 45403 | G37: 46863 | H37: 26474.88 | I37: 839425.41 | J37: =0 -> 0 | K37: -67549.42 | L37: 284146.56 | M37: =I37+J37-K37-L37 -> 622828.27 | N37: 854720.1 | O37: =0 -> 0 | P37: 55831.75 | Q37: 324531.12 | R37: -67549.42 | S37: =N37+O37+P37-Q37-R37 -> 653570.15 | T37: 318475.82 | U37: 335094.33
A38: =A37+1 -> 28 | B38: 64729 | C38: OCL | D38: Vehicle Lease | E38: 7.81 | F38: 45431 | G38: 47256 | H38: 29270.46 | I38: 1205959.2 | J38: =0 -> 0 | K38: 1132989.6 | L38: 72969.57 | M38: =I38+J38-K38-L38 -> 0 | N38: 1232556.6 | O38: =0 -> 0 | P38: 23084.82 | Q38: 87811.38 | R38: 1167830.1 | S38: =N38+O38+P38-Q38-R38 -> 0 | T38: 0 | U38: 0
A39: =A38+1 -> 29 | B39: 64761 | C39: OCL | D39: Vehicle Lease | E39: 7.64 | F39: 45464 | G39: 46924 | H39: 40099.87 | I39: 1340776.5 | J39: =0 -> 0 | K39: 1340776.5 | L39: 0 | M39: =I39+J39-K39-L39 -> 0 | N39: 1358201.9 | O39: =0 -> 0 | P39: =0 -> 0 | Q39: =0 -> 0 | R39: 1358201.9 | S39: =N39+O39+P39-Q39-R39 -> 0 | T39: 0 | U39: 0
A40: =A39+1 -> 30 | B40: 65689 | C40: OCL | D40: Vehicle Lease | E40: 7.24 | F40: 45700 | G40: 46794 | H40: 45726.35 | I40: 1418224.7 | J40: =0 -> 0 | K40: -124717.34 | L40: 513938.64 | M40: =I40+J40-K40-L40 -> 1029003.4 | N40: 1410213.4 | O40: =0 -> 0 | P40: 86410.67 | Q40: 562416.56 | R40: -124717.34 | S40: =N40+O40+P40-Q40-R40 -> 1058924.9 | T40: 563913.45 | U40: 495011.45
A41: =A40+1 -> 31 | B41: 65816 | C41: OCL | D41: Vehicle Lease | E41: 7.14 | F41: 45778 | G41: 47165 | H41: 48893.45 | I41: 0 | J41: 1955486.9 | K41: =0 -> 0 | L41: 455639.82 | M41: =I41+J41-K41-L41 -> 1499847 | N41: 0 | O41: 1955486.9 | P41: 108320.04 | Q41: 513985.95 | R41: =0 -> 0 | S41: =N41+O41+P41-Q41-R41 -> 1549821 | T41: 522711.82 | U41: 1027109.1
A42: =A41+1 -> 32 | B42: 66078 | C42: OCL | D42: Vehicle Lease | E42: 7.02 | F42: 45898 | G42: 47358 | H42: 50494.14 | I42: 0 | J42: 2147091.2 | K42: =0 -> 0 | L42: 306113.35 | M42: =I42+J42-K42-L42 -> 1840977.8 | N42: 0 | O42: 2147091.2 | P42: 87740.27 | Q42: 388149.08 | R42: =0 -> 0 | S42: =N42+O42+P42-Q42-R42 -> 1846682.4 | T42: 522288.42 | U42: 1324393.9
A43: =A42+1 -> 33 | B43: 65910 | C43: OCL | D43: Vehicle Lease | E43: 7.35 | F43: 45800 | G43: 47625 | H43: 19680.52 | I43: 0 | J43: 999816.3 | K43: =0 -> 0 | L43: 164600.73 | M43: =I43+J43-K43-L43 -> 835215.57 | N43: 0 | O43: 999816.3 | P43: 58585.36 | Q43: 207763.65 | R43: =0 -> 0 | S43: =N43+O43+P43-Q43-R43 -> 850638.01 | T43: 191364.23 | U43: 659273.78
A44: =A43+1 -> 34 | B44: 65969 | C44: OCL | D44: Vehicle Lease | E44: 6.89 | F44: 45817 | G44: 46912 | H44: 47586.61 | I44: 0 | J44: 1574931.1 | K44: =0 -> 0 | L44: 406651.64 | M44: =I44+J44-K44-L44 -> 1168279.5 | N44: 0 | O44: 1574931.1 | P44: 73454.08 | Q44: 454472.86 | R44: =0 -> 0 | S44: =N44+O44+P44-Q44-R44 -> 1193912.3 | T44: 534775.05 | U44: 659137.28
A45: =A44+1 -> 35 | B45: 66253 | C45: OCL | D45: Vehicle Lease | E45: 6.78 | F45: 45998 | G45: 47093 | H45: 21397.47 | I45: 0 | J45: 699202.72 | K45: =0 -> 0 | L45: 73930.05 | M45: =I45+J45-K45-L45 -> 625272.67 | N45: 0 | O45: 699202.72 | P45: 14715.34 | Q45: 85589.88 | R45: =0 -> 0 | S45: =N45+O45+P45-Q45-R45 -> 628328.18 | T45: 234027.46 | U45: 394300.72
A46: =A45+1 -> 36 | B46: 65789 | C46: OCL | D46: Vehicle Lease | E46: 7.35 | F46: 45778 | G46: 47603 | H46: 35457.73 | I46: 0 | J46: 1775760.5 | K46: =0 -> 0 | L46: 314639.77 | M46: =I46+J46-K46-L46 -> 1461120.7 | N46: 0 | O46: 1775760.5 | P46: 104950.87 | Q46: 374437.28 | R46: =0 -> 0 | S46: =N46+O46+P46-Q46-R46 -> 1506274.1 | T46: 346885.33 | U46: 1159388.7
A47: =A46+1 -> 37 | B47: 65966 | C47: OCL | D47: Vehicle Lease | E47: 7.02 | F47: 45839 | G47: 47256 | H47: 93899.58 | I47: 0 | J47: 1333812.7 | K47: =0 -> 0 | L47: 248201.85 | M47: =I47+J47-K47-L47 -> 1085610.9 | N47: 0 | O47: 1333812.7 | P47: 58888.93 | Q47: 271551.66 | R47: =0 -> 0 | S47: =N47+O47+P47-Q47-R47 -> 1121150 | T47: 329467.48 | U47: 791682.51
A48: =A47+1 -> 38 | B48: 66393 | C48: OCL | D48: Vehicle Lease | E48: 7.38 | F48: 46068 | G48: 47893 | H48: 141501 | I48: =0 -> 0 | J48: 2375178.6 | K48: =0 -> 0 | L48: 59379.47 | M48: =I48+J48-K48-L48 -> 2315799.2 | N48: =0 -> 0 | O48: 2375178.6 | P48: 28427.88 | Q48: 94334 | R48: =0 -> 0 | S48: =N48+O48+P48-Q48-R48 -> 2309272.5 | T48: 436283.71 | U48: 1872988.8
A49: =A48+1 -> 39 | B49: 53818 | C49: ITC | D49: IT Equipment Lease | E49: 7.906689 | F49: 44562 | G49: 46387 | I49: 42114950 | J49: 0 | K49: 0 | L49: 24065686 | M49: =I49+J49-K49-L49 -> 18049264 | N49: 46322667 | O49: 0 | P49: 2374434.6 | Q49: 28060000 | R49: 0 | S49: =N49+O49+P49-Q49-R49 -> 20637101 | T49: 20637101 | U49: 0
A50: =A49+1 -> 40 | B50: 54238 | C50: ITC | D50: Vehicle Lease | E50: 0 | F50: 44593 | G50: 45902 | I50: 130548.61 | J50: 0 | K50: 0 | L50: 130548.61 | M50: =I50+J50-K50-L50 -> 0 | N50: 141722.14 | O50: 0 | P50: 1804.21 | Q50: 143526.35 | R50: 0 | S50: =N50+O50+P50-Q50-R50 -> 0 | T50: 0 | U50: 0
A51: =A50+1 -> 41 | B51: 54245 | C51: ITC | D51: Vehicle Lease | E51: 0 | F51: 44593 | G51: 45926 | I51: 137060.45 | J51: 0 | K51: 0 | L51: 137060.45 | M51: =I51+J51-K51-L51 -> 0 | N51: 130828.67 | O51: 0 | P51: 1665.53 | Q51: 132494.2 | R51: 0 | S51: =N51+O51+P51-Q51-R51 -> 0 | T51: 0 | U51: 0
A52: =A51+1 -> 42 | B52: 54263 | C52: ITC | D52: Vehicle Lease | E52: 7.638546 | F52: 44593 | G52: 46006 | I52: 212405.93 | J52: 0 | K52: 0 | L52: 212405.93 | M52: =I52+J52-K52-L52 -> 0 | N52: 222208.94 | O52: 0 | P52: 4966.1 | Q52: 227175.04 | R52: 0 | S52: =N52+O52+P52-Q52-R52 -> 0 | T52: 0 | U52: 0
A53: =A52+1 -> 43 | B53: 55765 | C53: ITC | D53: Vehicle Lease | E53: 7.6385 | F53: 44682 | G53: 46139 | I53: 465981.14 | J53: 0 | K53: -45396.02 | L53: 470528.8 | M53: =I53+J53-K53-L53 -> 40848.36 | N53: 486283.82 | O53: 0 | P53: 18258.28 | Q53: 507074.96 | R53: -45396.02 | S53: =N53+O53+P53-Q53-R53 -> 42863.16 | T53: 42863.16 | U53: 0
A54: =A53+1 -> 44 | B54: 55768 | C54: ITC | D54: Vehicle Lease | E54: 7.6385 | F54: 44682 | G54: 46138 | I54: 382780.61 | J54: 0 | K54: -37357.25 | L54: 387702.04 | M54: =I54+J54-K54-L54 -> 32435.82 | N54: 400217.88 | O54: 0 | P54: 15026.73 | Q54: 417325.8 | R54: -37357.25 | S54: =N54+O54+P54-Q54-R54 -> 35276.06 | T54: 35276.06 | U54: 0
A55: =A54+1 -> 45 | B55: 55771 | C55: ITC | D55: Vehicle Lease | E55: 7.638546 | F55: 44682 | G55: 46137 | I55: 461956.17 | J55: 0 | K55: 0 | L55: 431959.08 | M55: =I55+J55-K55-L55 -> 29997.09 | N55: 483921.89 | O55: 0 | P55: 17066.35 | Q55: 500988.24 | R55: 0 | S55: =N55+O55+P55-Q55-R55 -> -5.8207661e-11 | T55: 0 | U55: 0
A56: =A55+1 -> 46 | B56: 55775 | C56: ITC | D56: Vehicle Lease | E56: 7.6385 | F56: 44682 | G56: 46137 | I56: 221785.84 | J56: 0 | K56: -21943.82 | L56: 225544.56 | M56: =I56+J56-K56-L56 -> 18185.1 | N56: 232331.65 | O56: 0 | P56: 8726.48 | Q56: 242471.6 | R56: -21943.82 | S56: =N56+O56+P56-Q56-R56 -> 20530.35 | T56: 20530.35 | U56: 0
A57: =A56+1 -> 47 | B57: 55778 | C57: ITC | D57: Vehicle Lease | E57: 7.6385 | F57: 44682 | G57: 46140 | I57: 329883.61 | J57: 0 | K57: -32069.55 | L57: 332079.92 | M57: =I57+J57-K57-L57 -> 29873.24 | N57: 343605.42 | O57: 0 | P57: 12901.11 | Q57: 358290.64 | R57: -32069.55 | S57: =N57+O57+P57-Q57-R57 -> 30285.44 | T57: 30285.44 | U57: 0
A58: =A57+1 -> 48 | B58: 56135 | C58: ITC | D58: Vehicle Lease | E58: 7.638546 | F58: 44713 | G58: 46159 | I58: 641834.33 | J58: 0 | K58: 0 | L58: 568481.76 | M58: =I58+J58-K58-L58 -> 73352.57 | N58: 685507.77 | O58: 0 | P58: 26400.95 | Q58: 657146.52 | R58: 0 | S58: =N58+O58+P58-Q58-R58 -> 54762.2 | T58: 54762.2 | U58: 0
A59: =A58+1 -> 49 | B59: 56143 | C59: ITC | D59: Vehicle Lease | E59: 7.6385 | F59: 44713 | G59: 46154 | I59: 374359.83 | J59: 0 | K59: -35321.76 | L59: 361797.64 | M59: =I59+J59-K59-L59 -> 47883.95 | N59: 403291.12 | O59: 0 | P59: 16395.31 | Q59: 389390 | R59: -35321.76 | S59: =N59+O59+P59-Q59-R59 -> 65618.19 | T59: 65618.19 | U59: 0
A60: =A59+1 -> 50 | B60: 56148 | C60: ITC | D60: Vehicle Lease | E60: 7.6385 | F60: 44713 | G60: 46146 | I60: 425701.4 | J60: 0 | K60: -40752.52 | L60: 420875.04 | M60: =I60+J60-K60-L60 -> 45578.88 | N60: 465093.53 | O60: 0 | P60: 18908.09 | Q60: 449074.24 | R60: -40752.52 | S60: =N60+O60+P60-Q60-R60 -> 75679.9 | T60: 75679.9 | U60: 0
... A309: =A308+1 -> 299 | B309: 66275 | C309: ITC | D309: Vehicle Lease | E309: 7.2 | F309: 46015 | G309: 47840 | I309: 0 | J309: 2126297 | K309: 0 | L309: 115460.2 | M309: =I309+J309-K309-L309 -> 2010836.8 | N309: 0 | O309: 2126297 | P309: 48951.23 | Q309: 168205.84 | R309: 0 | S309: =N309+O309+P309-Q309-R309 -> 2007042.4 | T309: 375372.09 | U309: 1631670.4
A310: =A309+1 -> 300 | B310: Rent Alpha Private Limited | C310: WIND | D310: Equipment Lease | E310: - | F310: 44287 | G310: 46203 | H310: 3794036 | I310: 40015641 | J310: 4521159.3 | K310: 0 | L310: 35727324 | M310: =I310+J310-K310-L310 -> 8809477 | N310: 27694542 | O310: 4521159.3 | P310: 2835219 | Q310: 33093224 | R310: 0 | S310: =N310+O310+P310-Q310-R310 -> 1957695.9 | T310: 1957695.9 | U310: 0

Sheet Rate impact
A1: =Scope!#REF! -> #REF!
A2: =Scope!#REF! -> #REF!
A3: =Scope!#REF! -> #REF!
A6: Purpose
A7: To compute the amount of unadjusted difference due to low discount rate considered by the company.
A10: Particulars | B10: As per schedule | C10: As per DHS | D10: Difference
A11: ROU | B11: =SUM(K19) -> 12654747 | C11: =AB20 -> 11320748 | D11: =B11-C11 -> 1333998.7 | E11: <<Imm>>
A12: Difference in Interest (Calculated on the basis of 7% rate on difference in ROU computed for average months completed i.e. 37 months) | D12: =(D11*0.07/12)*37 -> 287921.4 | E12: <<Imm>>
A13: Difference in Depreciation charged till date | D13: =J19-AA20 -> 1405932.5 | E13: <<Imm>>
A16: Obervation
A17: ET observed that the difference due to low rates is not material.
H19: =SUM(H21:H30) -> 21288785 | I19: =SUM(I21:I30) -> 8701759.2 | J19: =SUM(J21:J30) -> 28568120 | K19: =SUM(K21:K30) -> 12654747 | L19: =SUM(L22:L29) -> 2271132 | M19: =SUM(M22:M29) -> 0 | N19: =SUM(N22:N29) -> 718221.84 | O19: =SUM(O22:O29) -> 10932960 | P19: =SUM(P22:P29) -> 0 | Q19: =SUM(Q22:Q29) -> 0 | R19: =SUM(R22:R29) -> 4612238.7
H20: ROU | L20: Lease Liability | Z20: 46112 | AA20: =SUM(AA22:AA30) -> 27162188 | AB20: =SUM(AB22:AB30) -> 11320748 | AD20: =SUM(AD22:AD30) -> 1333998.7
A21: System Lease ID | B21: Division | C21: Lease Template | D21: Discount Rate | E21: Commencement Date | F21: Expiration Date | G21: Monthly Payments | H21: Opening Balance as on April'25 | I21: Amortisation during FY 2025-26 | J21: Amortisation till FY 2025-26 | K21: Closing Balance | L21: Opening Balance | M21: Addition during the year | N21: Interest | O21: Repayment | P21: Deletion during the year | Q21: Transfer due to Demerger | R21: Closing Balance | T21: Discount Rate | U21: Commencement Date | V21: Expiration Date | W21: Monthly Payments | X21: Period | Y21: ROU | Z21: Months till March 31, 2026 | AA21: Depreciation till March 31, 2026 | AB21: Closing balance as on March 31, 2026 | AD21: Difference in Closing balance of ROU
A22: 60272 | B22: MMF | C22: Vehicle Lease | D22: 4.4375 | E22: 44986 | F22: 46124 | G22: 35593.85 | H22: 659457.49 | I22: 400867.72 | J22: 1231917.8 | K22: 295837.17 | L22: 295837.17 | M22: 0 | N22: 42150.98 | O22: 343007.76 | P22: 0 | Q22: 0 | R22: 437035.74 | T22: 0.07 | U22: =E22 -> 44986 | V22: =F22 -> 46124 | W22: =G22 -> 35593.85 | X22: =(V22-U22)/30 -> 37.933333 | Y22: =-PV((T22/12),X22,W22) -> 1208099.3 | Z22: =($Z$20-U22)/30 -> 37.533333 | AA22: =Y22/X22*Z22 -> 1195360.1 | AB22: =Y22-AA22 -> 12739.184 | AD22: =K22-AB22 -> 283097.99
A23: 61193 | B23: MMF | C23: Vehicle Lease | D23: 4.698 | E23: 45047 | F23: 46498 | G23: 27611.88 | H23: 615109.1 | I23: 296354.24 | J23: 877429.61 | K23: 329891.91 | L23: 329891.91 | M23: 0 | N23: 44359.84 | O23: 319561.92 | P23: 0 | Q23: 0 | R23: 479173.68 | T23: 0.07 | U23: =E23 -> 45047 | V23: =F23 -> 46498 | W23: =G23 -> 27611.88 | X23: =ROUNDDOWN((V23-U23)/30,0) -> 48 | Y23: =-PV((T23/12),X23,W23) -> 1153077.7 | Z23: =($Z$20-U23)/30 -> 35.5 | AA23: =Y23/X23*Z23 -> 852797.03 | AB23: =Y23-AA23 -> 300280.64 | AD23: =K23-AB23 -> 29611.267
A24: 61200 | B24: MMF | C24: Vehicle Lease | D24: 4.698 | E24: 45047 | F24: 46498 | G24: 17701.46 | H24: 394335.25 | I24: 189242.56 | J24: 561758.99 | K24: 209123.72 | L24: 209123.72 | M24: 0 | N24: 330921.15 | O24: 6122556 | P24: 0 | Q24: 0 | R24: 1520641.7 | T24: 0.07 | U24: =E24 -> 45047 | V24: =F24 -> 46498 | W24: =G24 -> 17701.46 | X24: =ROUNDDOWN((V24-U24)/30,0) -> 48 | Y24: =-PV((T24/12),X24,W24) -> 739216.53 | Z24: =($Z$20-U24)/30 -> 35.5 | AA24: =Y24/X24*Z24 -> 546712.23 | AB24: =Y24-AA24 -> 192504.31 | AD24: =K24-AB24 -> 16619.414
A25: 61205 | B25: MMF | C25: Vehicle Lease | D25: 4.698 | E25: 45047 | F25: 46507 | G25: 33574.42 | H25: 766842.83 | I25: 361349.76 | J25: 1077069.9 | K25: 405519.04 | L25: 405519.04 | M25: 0 | N25: 105245.3 | O25: 1806060.6 | P25: 0 | Q25: 0 | R25: 596332.41 | T25: 0.07 | U25: =E25 -> 45047 | V25: =F25 -> 46507 | W25: =G25 -> 33574.42 | X25: =ROUNDDOWN((V25-U25)/30,0) -> 48 | Y25: =-PV((T25/12),X25,W25) -> 1402074.5 | Z25: =($Z$20-U25)/30 -> 35.5 | AA25: =Y25/X25*Z25 -> 1036951 | AB25: =Y25-AA25 -> 365123.58 | AD25: =K25-AB25 -> 40395.462
A26: 61209 | B26: MMF | C26: Vehicle Lease | D26: 4.698 | E26: 45047 | F26: 46507 | G26: 25441.09 | H26: 581076.73 | I26: 269431.72 | J26: 811770.25 | K26: 293041.88 | L26: 293041.88 | M26: 0 | N26: 78646.48 | O26: 1121136 | P26: 0 | Q26: 0 | R26: 551778.15 | T26: 0.07 | U26: =E26 -> 45047 | V26: =F26 -> 46507 | W26: =G26 -> 25441.09 | X26: =ROUNDDOWN((V26-U26)/30,0) -> 48 | Y26: =-PV((T26/12),X26,W26) -> 1062425 | Z26: =($Z$20-U26)/30 -> 35.5 | AA26: =Y26/X26*Z26 -> 785751.85 | AB26: =Y26-AA26 -> 276673.19 | AD26: =K26-AB26 -> 16368.692
A27: 62974 | B27: MMF | C27: Vehicle Lease | D27: 4.8266 | E27: 45170 | F27: 46668 | G27: 21973.84 | H27: 564437.74 | I27: 235793.36 | J27: 619092.34 | K27: 332544.39 | L27: 332544.39 | M27: 0 | N27: 38504.13 | O27: 506430.6 | P27: 0 | Q27: 0 | R27: 289870.84 | T27: 0.07 | U27: =E27 -> 45170 | V27: =F27 -> 46668 | W27: =G27 -> 21973.84 | X27: =ROUNDDOWN((V27-U27)/30,0) -> 49 | Y27: =-PV((T27/12),X27,W27) -> 934156.58 | Z27: =($Z$20-U27)/30 -> 31.4 | AA27: =Y27/X27*Z27 -> 598622.79 | AB27: =Y27-AA27 -> 335533.79 | AD27: =K27-AB27 -> -2989.401
A28: 62980 | B28: MMF | C28: Vehicle Lease | D28: 4.8266 | E28: 45169 | F28: 46629 | G28: 24788.47 | H28: 642481.88 | I28: 267290.72 | J28: 694610.17 | K28: 405173.87 | L28: 405173.87 | M28: 0 | N28: 37651.37 | O28: 379600.92 | P28: 0 | Q28: 0 | R28: 337168.91 | T28: 0.07 | U28: =E28 -> 45169 | V28: =F28 -> 46629 | W28: =G28 -> 24788.47 | X28: =ROUNDDOWN((V28-U28)/30,0) -> 48 | Y28: =-PV((T28/12),X28,W28) -> 1035171.5 | Z28: =($Z$20-U28)/30 -> 31.433333 | AA28: =Y28/X28*Z28 -> 677893.56 | AB28: =Y28-AA28 -> 357277.94 | AD28: =K28-AB28 -> 47895.929
A29: 52815 | B29: OCL | C29: Vehicle Lease | D29: 1.3148 | E29: 44470 | F29: 45899 | G29: 28583.98 | H29: 123356.37 | I29: 123356.37 | J29: 1180349.3 | K29: 0 | L29: 0 | M29: 0 | N29: 40742.59 | O29: 334606.56 | P29: 0 | Q29: 0 | R29: 400237.36 | T29: 0.07 | U29: =E29 -> 44470 | V29: =F29 -> 45899 | W29: =G29 -> 28583.98 | X29: =ROUNDDOWN((V29-U29)/30,0) -> 47 | Y29: =-PV((T29/12),X29,W29) -> 1172051.9 | Z29: 47 | AA29: =Y29/X29*Z29 -> 1172051.9 | AB29: =Y29-AA29 -> 0 | AD29: =K29-AB29 -> 0
A30: 59308 | B30: MMF | C30: IT Equipment Lease | D30: 5.1215 | E30: 44926 | F30: 46691 | G30: 606609.11 | H30: 16941688 | I30: 6558072.7 | J30: 21514122 | K30: 10383615 | T30: 0.07 | U30: =E30 -> 44926 | V30: =F30 -> 46691 | W30: =G30 -> 606609.11 | X30: =ROUNDDOWN((V30-U30)/30,0) -> 58 | Y30: =-PV((T30/12),X30,W30) -> 29776663 | Z30: =($Z$20-U30)/30 -> 39.533333 | AA30: =Y30/X30*Z30 -> 20296047 | AB30: =Y30-AA30 -> 9480615.7 | AD30: =K30-AB30 -> 902999.4
Z32: =AVERAGE(Z22:Z30) -> 36.544444

Sheet MMF-59308
A1: ='ITC- 59268'!A1 -> #REF!
A2: ='ITC- 59268'!A2 -> #REF!
A3: ='ITC- 59268'!A3 -> #REF!
A6: =[3]Scope!A6 -> Purpose
A7: To verify the lease working of the sample selected
A10: Summary
B11: << Link >> | C11: << As per agreement >> | D11: << As per agreement >> | E11: << Link >> | F11: << Link >> | G11: << Link >> | H11: << Link >> | I11: << Link >> | J11: << Link >>
A12: Particulars | B12: Discount Rate | C12: Commencement Date | D12: Expiration Date | E12: Addition during FY 2025-26 | F12: Amortisation during FY 2025-26 | G12: Closing Balance | H12: Interest | I12: Repayment | J12: Closing Balance | K12: ST | L12: LT
A13: As per Lease Report | B13: 0.051215 | C13: 44926 | D13: 46691 | E13: 0 | F13: 6558072.7 | G13: 10383615 | H13: 720542.53 | I13: 7279309.3 | J13: 11095181 | K13: 6902672.2 | L13: 4192508.5
A14: As per DHS Working | B14: 0.051215 | C14: 44926 | D14: 46691 | E14: 0 | F14: =SUM(C52:C63) -> 6436214.8 | G14: =D63 -> 9654322.2 | H14: =SUM(F52:F63) -> 720542.53 | I14: =-SUM(G52:G63) -> 7279309.3 | J14: =H63 -> 10488572 | K14: =H63-H76 -> 7493977 | L14: =J14-K14 -> 2994594.6
A15: Difference | B15: =B13-B14 -> 0 | C15: =C13-C14 -> 0 | D15: =D13-D14 -> 0 | E15: =E13-E14 -> 0 | F15: =F13-F14 -> 121857.92 | G15: =G13-G14 -> 729292.88 | H15: =H13-H14 -> 8.6452463e-05 | I15: =I13-I14 -> 0 | ... L15: =L13-L14 -> 1197913.9
A18: Monthly Rent | B18: 606609.11 | C18: << As per agreement >>
A19: Monthly discount rate | B19: =B14/12 -> 0.0042679167 | C19: << Link >>
A20: No of Months | B20: =ROUND(((D14-C14)/30.5),0) -> 58 | C20: << Formula >>
A21: PV of rent payments | B21: =-PV(B19,B20,B18) -> 31108372 | C21: << Formula >>
A23: Month | B23: Opening WDV | C23: Dep | D23: Closing WDV | E23: Opening Liability | F23: Interest | G23: Repayment | H23: Closing Lease Liability
A24: 44896 | B24: =$B$21 -> 31108372 | C24: =$B$21/$B$20 -> 536351.23 | D24: =B24-C24 -> 30572020 | E24: =$B$21 -> 31108372 | F24: =E24*$B$19 -> 132767.94 | G24: =-$B$18 -> -606609.11 | H24: =SUM(E24:G24) -> 30634530
A25: 44927 | B25: =D24 -> 30572020 | C25: =$B$21/$B$20 -> 536351.23 | D25: =B25-C25 -> 30035669 | E25: =H24 -> 30634530 | F25: =E25*$B$19 -> 130745.62 | G25: =-$B$18 -> -606609.11 | H25: =SUM(E25:G25) -> 30158667
A26: 44958 | B26: =D25 -> 30035669 | C26: =$B$21/$B$20 -> 536351.23 | D26: =B26-C26 -> 29499318 | E26: =H25 -> 30158667 | F26: =E26*$B$19 -> 128714.68 | G26: =-$B$18 -> -606609.11 | H26: =SUM(E26:G26) -> 29680772
A27: 44986 | B27: =D26 -> 29499318 | C27: =$B$21/$B$20 -> 536351.23 | D27: =B27-C27 -> 28962967 | E27: =H26 -> 29680772 | F27: =E27*$B$19 -> 126675.06 | G27: =-$B$18 -> -606609.11 | H27: =SUM(E27:G27) -> 29200838
A28: 45017 | B28: =D27 -> 28962967 | C28: =$B$21/$B$20 -> 536351.23 | D28: =B28-C28 -> 28426615 | E28: =H27 -> 29200838 | F28: =E28*$B$19 -> 124626.74 | G28: =-$B$18 -> -606609.11 | H28: =SUM(E28:G28) -> 28718856
A29: 45047 | B29: =D28 -> 28426615 | C29: =$B$21/$B$20 -> 536351.23 | D29: =B29-C29 -> 27890264 | E29: =H28 -> 28718856 | F29: =E29*$B$19 -> 122569.68 | G29: =-$B$18 -> -606609.11 | H29: =SUM(E29:G29) -> 28234817
A30: 45078 | B30: =D29 -> 27890264 | C30: =$B$21/$B$20 -> 536351.23 | D30: =B30-C30 -> 27353913 | E30: =H29 -> 28234817 | F30: =E30*$B$19 -> 120503.84 | G30: =-$B$18 -> -606609.11 | H30: =SUM(E30:G30) -> 27748711
A31: 45108 | B31: =D30 -> 27353913 | C31: =$B$21/$B$20 -> 536351.23 | D31: =B31-C31 -> 26817562 | E31: =H30 -> 27748711 | F31: =E31*$B$19 -> 118429.19 | G31: =-$B$18 -> -606609.11 | H31: =SUM(E31:G31) -> 27260531
A32: 45139 | B32: =D31 -> 26817562 | C32: =$B$21/$B$20 -> 536351.23 | D32: =B32-C32 -> 26281210 | E32: =H31 -> 27260531 | F32: =E32*$B$19 -> 116345.68 | G32: =-$B$18 -> -606609.11 | H32: =SUM(E32:G32) -> 26770268
A33: 45170 | B33: =D32 -> 26281210 | C33: =$B$21/$B$20 -> 536351.23 | D33: =B33-C33 -> 25744859 | E33: =H32 -> 26770268 | F33: =E33*$B$19 -> 114253.27 | G33: =-$B$18 -> -606609.11 | H33: =SUM(E33:G33) -> 26277912
A34: 45200 | B34: =D33 -> 25744859 | C34: =$B$21/$B$20 -> 536351.23 | D34: =B34-C34 -> 25208508 | E34: =H33 -> 26277912 | F34: =E34*$B$19 -> 112151.94 | G34: =-$B$18 -> -606609.11 | H34: =SUM(E34:G34) -> 25783455
A35: 45231 | B35: =D34 -> 25208508 | C35: =$B$21/$B$20 -> 536351.23 | D35: =B35-C35 -> 24672157 | E35: =H34 -> 25783455 | F35: =E35*$B$19 -> 110041.64 | G35: =-$B$18 -> -606609.11 | H35: =SUM(E35:G35) -> 25286888
A36: 45261 | B36: =D35 -> 24672157 | C36: =$B$21/$B$20 -> 536351.23 | D36: =B36-C36 -> 24135806 | E36: =H35 -> 25286888 | F36: =E36*$B$19 -> 107922.33 | G36: =-$B$18 -> -606609.11 | H36: =SUM(E36:G36) -> 24788201
... A81: 46631 | B81: =D80 -> 536351.23 | C81: =$B$21/$B$20 -> 536351.23 | D81: =B81-C81 -> -1.8393621e-08 | E81: =H80 -> 604031.16 | F81: =E81*$B$19 -> 2577.9546 | G81: =-$B$18 -> -606609.11 | H81: =SUM(E81:G81) -> -1.0760268e-06

Sheet MMF-66353
A6: Purpose
A7: To verify the lease working of the sample selected
A10: Summary
A12: Particulars | B12: Discount Rate | C12: Commencement Date | D12: Expiration Date | E12: Addition during FY 2025-26 | F12: Amortisation during FY 2025-26 | G12: Closing WDV | H12: Interest | I12: Repayment | J12: Closing Balance | K12: ST | L12: LT
A13: As per Lease Report | B13: 0.076675 | C13: 45992 | D13: 48182 | E13: 1.4217495e+08 | F13: 7898608.4 | G13: 134276343 | H13: 3542368.2 | I13: 7860320 | J13: 1.37857e+08 | K13: 13633962 | L13: 1.2422304e+08
A14: As per DHS Working | B14: 0.076675 | C14: 45992 | D14: 48182 | E14: =B20 -> 1.4217498e+08 | F14: =SUM(C25:C28) -> 7898609.9 | G14: =D28 -> 1.3427637e+08 | H14: =SUM(G25:G28) -> 3542366.1 | I14: =-SUM(F25:F28) -> 7860320 | J14: =H28 -> 1.3785702e+08 | K14: =H29-H41 -> 13721084 | L14: =H41 -> 1.2303915e+08
A15: Difference | B15: =B13-B14 -> 0 | C15: =C13-C14 -> 0 | D15: =D13-D14 -> 0 | E15: =E13-E14 -> -25.959899 | F15: =F13-F14 -> -1.4533277 | G15: =G13-G14 -> -24.506571 | H15: =H13-H14 -> 2.1198117 | I15: =I13-I14 -> 0 | ... L15: =L13-L14 -> 1183884.8
A17: Net EMI - Months 1-36 (GST benefit available) | B17: 1965080 | C17: << As per agreement - net of GST credit >>
A18: Monthly discount rate | B18: =B14/12 -> 0.0063895833 | C18: << Link >>
A19: No of Months | B19: =6*12 -> 72 | C19: << As per Agreement >>
A20: PV of rent payments | B20: =-PV(B18,36,B17,,1)-PV(B18,36,B21,,1)/(1+B18)^36 -> 1.4217498e+08 | C20: << Formula >>
A21: Gross EMI - Months 37-72 (GST benefit not available) | B21: 3069120 | C21: << As per agreement - gross, no GST credit >>
B23: Right of Use Asset | E23: Lease Liability
A24: From | B24: Opening WDV | C24: Depreciation | D24: Closing WDV | E24: Opening Liability | F24: Repayment | G24: Interest | H24: Closing Lease Liability
A25: 45992 | B25: =B20 -> 1.4217498e+08 | C25: =$B$20/$B$19 -> 1974652.5 | D25: =B25-C25 -> 1.4020032e+08 | E25: =B25 -> 1.4217498e+08 | F25: =-$B$17 -> -1965080 | G25: =(E25+F25)*$B$18 -> 895882.82 | H25: =E25+F25+G25 -> 1.4110578e+08
A26: 46023 | B26: =D25 -> 1.4020032e+08 | C26: =$B$20/$B$19 -> 1974652.5 | D26: =B26-C26 -> 1.3822567e+08 | E26: =H25 -> 1.4110578e+08 | F26: =-$B$17 -> -1965080 | G26: =(E26+F26)*$B$18 -> 889051.1 | H26: =E26+F26+G26 -> 1.4002975e+08
A27: 46054 | B27: =D26 -> 1.3822567e+08 | C27: =$B$20/$B$19 -> 1974652.5 | D27: =B27-C27 -> 1.3625102e+08 | E27: =H26 -> 1.4002975e+08 | F27: =-$B$17 -> -1965080 | G27: =(E27+F27)*$B$18 -> 882175.72 | H27: =E27+F27+G27 -> 1.3894685e+08
A28: 46082 | B28: =D27 -> 1.3625102e+08 | C28: =$B$20/$B$19 -> 1974652.5 | D28: =B28-C28 -> 1.3427637e+08 | E28: =H27 -> 1.3894685e+08 | F28: =-$B$17 -> -1965080 | G28: =(E28+F28)*$B$18 -> 875256.42 | H28: =E28+F28+G28 -> 1.3785702e+08
A29: 46113 | B29: =D28 -> 1.3427637e+08 | C29: =$B$20/$B$19 -> 1974652.5 | D29: =B29-C29 -> 1.3230172e+08 | E29: =H28 -> 1.3785702e+08 | F29: =-$B$17 -> -1965080 | G29: =(E29+F29)*$B$18 -> 868292.9 | H29: =E29+F29+G29 -> 1.3676024e+08
A30: 46143 | B30: =D29 -> 1.3230172e+08 | C30: =$B$20/$B$19 -> 1974652.5 | D30: =B30-C30 -> 1.3032706e+08 | E30: =H29 -> 1.3676024e+08 | F30: =-$B$17 -> -1965080 | G30: =(E30+F30)*$B$18 -> 861284.88 | H30: =E30+F30+G30 -> 1.3565644e+08
A31: 46174 | B31: =D30 -> 1.3032706e+08 | C31: =$B$20/$B$19 -> 1974652.5 | D31: =B31-C31 -> 1.2835241e+08 | E31: =H30 -> 1.3565644e+08 | F31: =-$B$17 -> -1965080 | G31: =(E31+F31)*$B$18 -> 854232.09 | H31: =E31+F31+G31 -> 1.3454559e+08
A32: 46204 | B32: =D31 -> 1.2835241e+08 | C32: =$B$20/$B$19 -> 1974652.5 | D32: =B32-C32 -> 1.2637776e+08 | E32: =H31 -> 1.3454559e+08 | F32: =-$B$17 -> -1965080 | G32: =(E32+F32)*$B$18 -> 847134.24 | H32: =E32+F32+G32 -> 1.3342765e+08
A33: 46235 | B33: =D32 -> 1.2637776e+08 | C33: =$B$20/$B$19 -> 1974652.5 | D33: =B33-C33 -> 1.2440311e+08 | E33: =H32 -> 1.3342765e+08 | F33: =-$B$17 -> -1965080 | G33: =(E33+F33)*$B$18 -> 839991.03 | H33: =E33+F33+G33 -> 1.3230256e+08
A34: 46266 | B34: =D33 -> 1.2440311e+08 | C34: =$B$20/$B$19 -> 1974652.5 | D34: =B34-C34 -> 1.2242845e+08 | E34: =H33 -> 1.3230256e+08 | F34: =-$B$17 -> -1965080 | G34: =(E34+F34)*$B$18 -> 832802.18 | H34: =E34+F34+G34 -> 1.3117028e+08
A35: 46296 | B35: =D34 -> 1.2242845e+08 | C35: =$B$20/$B$19 -> 1974652.5 | D35: =B35-C35 -> 1.204538e+08 | E35: =H34 -> 1.3117028e+08 | F35: =-$B$17 -> -1965080 | G35: =(E35+F35)*$B$18 -> 825567.4 | H35: =E35+F35+G35 -> 1.3003077e+08
A36: 46327 | B36: =D35 -> 1.204538e+08 | C36: =$B$20/$B$19 -> 1974652.5 | D36: =B36-C36 -> 1.1847915e+08 | E36: =H35 -> 1.3003077e+08 | F36: =-$B$17 -> -1965080 | G36: =(E36+F36)*$B$18 -> 818286.39 | H36: =E36+F36+G36 -> 1.2888397e+08
A37: 46357 | B37: =D36 -> 1.1847915e+08 | C37: =$B$20/$B$19 -> 1974652.5 | D37: =B37-C37 -> 1.165045e+08 | E37: =H36 -> 1.2888397e+08 | F37: =-$B$17 -> -1965080 | G37: =(E37+F37)*$B$18 -> 810958.85 | H37: =E37+F37+G37 -> 1.2772985e+08
... A60: 47058 | B60: =D59 -> 73062141 | C60: =$B$20/$B$19 -> 1974652.5 | D60: =B60-C60 -> 71087489 | E60: =H59 -> 1.003873e+08 | F60: =-$B$17 -> -1965080 | G60: =(E60+F60)*$B$18 -> 628876.96 | H60: =E60+F60+G60 -> 99051094
A61: 47088 | B61: =D60 -> 71087489 | C61: =$B$20/$B$19 -> 1974652.5 | D61: =B61-C61 -> 69112836 | E61: =H60 -> 99051094 | F61: =-$B$21 -> -3069120 | G61: =(E61+F61)*$B$18 -> 613284.82 | H61: =E61+F61+G61 -> 96595259
A62: 47119 | B62: =D61 -> 69112836 | C62: =$B$20/$B$19 -> 1974652.5 | D62: =B62-C62 -> 67138184 | E62: =H61 -> 96595259 | F62: =-$B$21 -> -3069120 | G62: =(E62+F62)*$B$18 -> 597593.06 | H62: =E62+F62+G62 -> 94123732
A63: 47150 | B63: =D62 -> 67138184 | C63: =$B$20/$B$19 -> 1974652.5 | D63: =B63-C63 -> 65163531 | E63: =H62 -> 94123732 | F63: =-$B$21 -> -3069120 | G63: =(E63+F63)*$B$18 -> 581801.03 | H63: =E63+F63+G63 -> 91636413
A64: 47178 | B64: =D63 -> 65163531 | C64: =$B$20/$B$19 -> 1974652.5 | D64: =B64-C64 -> 63188879 | E64: =H63 -> 91636413 | F64: =-$B$21 -> -3069120 | G64: =(E64+F64)*$B$18 -> 565908.1 | H64: =E64+F64+G64 -> 89133201
A65: 47209 | B65: =D64 -> 63188879 | C65: =$B$20/$B$19 -> 1974652.5 | D65: =B65-C65 -> 61214226 | E65: =H64 -> 89133201 | F65: =-$B$21 -> -3069120 | G65: =(E65+F65)*$B$18 -> 549913.62 | H65: =E65+F65+G65 -> 86613995
A66: 47239 | B66: =D65 -> 61214226 | C66: =$B$20/$B$19 -> 1974652.5 | D66: =B66-C66 -> 59239574 | E66: =H65 -> 86613995 | F66: =-$B$21 -> -3069120 | G66: =(E66+F66)*$B$18 -> 533816.94 | H66: =E66+F66+G66 -> 84078691
A67: 47270 | B67: =D66 -> 59239574 | C67: =$B$20/$B$19 -> 1974652.5 | D67: =B67-C67 -> 57264921 | E67: =H66 -> 84078691 | F67: =-$B$21 -> -3069120 | G67: =(E67+F67)*$B$18 -> 517617.41 | H67: =E67+F67+G67 -> 81527189
A68: 47300 | B68: =D67 -> 57264921 | C68: =$B$20/$B$19 -> 1974652.5 | D68: =B68-C68 -> 55290269 | E68: =H67 -> 81527189 | F68: =-$B$21 -> -3069120 | G68: =(E68+F68)*$B$18 -> 501314.37 | H68: =E68+F68+G68 -> 78959383
A69: 47331 | B69: =D68 -> 55290269 | C69: =$B$20/$B$19 -> 1974652.5 | D69: =B69-C69 -> 53315617 | E69: =H68 -> 78959383 | F69: =-$B$21 -> -3069120 | G69: =(E69+F69)*$B$18 -> 484907.16 | H69: =E69+F69+G69 -> 76375170
A70: 47362 | B70: =D69 -> 53315617 | C70: =$B$20/$B$19 -> 1974652.5 | D70: =B70-C70 -> 51340964 | E70: =H69 -> 76375170 | F70: =-$B$21 -> -3069120 | G70: =(E70+F70)*$B$18 -> 468395.12 | H70: =E70+F70+G70 -> 73774446
A71: 47392 | B71: =D70 -> 51340964 | C71: =$B$20/$B$19 -> 1974652.5 | D71: =B71-C71 -> 49366312 | E71: =H70 -> 73774446 | F71: =-$B$21 -> -3069120 | G71: =(E71+F71)*$B$18 -> 451777.57 | H71: =E71+F71+G71 -> 71157103
A72: 47423 | B72: =D71 -> 49366312 | C72: =$B$20/$B$19 -> 1974652.5 | D72: =B72-C72 -> 47391659 | E72: =H71 -> 71157103 | F72: =-$B$21 -> -3069120 | G72: =(E72+F72)*$B$18 -> 435053.84 | H72: =E72+F72+G72 -> 68523037
... A96: 48153 | B96: =D95 -> 1974652.5 | C96: =$B$20/$B$19 -> 1974652.5 | D96: =B96-C96 -> -1.8021092e-07 | E96: =H95 -> 3069120 | F96: =-$B$21 -> -3069120 | G96: =(E96+F96)*$B$18 -> 1.9941007e-08 | H96: =E96+F96+G96 -> 3.140803e-06

Sheet MMF-66354
A3: Purpose
A4: To verify the lease working of the sample selected
A7: Summary
A9: Particulars | B9: Discount Rate | C9: Commencement Date | D9: Expiration Date | E9: Addition during FY 2025-26 | F9: Amortisation during FY 2025-26 | G9: Closing WDV | H9: Interest | I9: Repayment | J9: Closing Balance | K9: ST | L9: LT
A10: As per Lease Report | B10: 0.076675 | C10: 45992 | D10: 48182 | E10: 18970811 | F10: 1053933.9 | G10: 17916877 | H10: 471191.95 | I10: 1140660 | J10: 18301343 | K10: 2113849.9 | L10: 16187493
A11: As per DHS Working | B11: 0.076675 | C11: 45992 | D11: 48182 | E11: =B22 -> 18970814 | F11: =SUM(C22:C25) -> 1053934.1 | G11: =D25 -> 17916880 | H11: =SUM(G22:G25) -> 471191.67 | I11: =-SUM(F22:F25) -> 1140660 | J11: =H25 -> 18301346 | K11: =H25-H37 -> 2113850.7 | L11: =J11-K11 -> 16187495
A12: Difference | B12: =B10-B11 -> 0 | C12: =C10-C11 -> 0 | D12: =D10-D11 -> 0 | E12: =E10-E11 -> -3.3283131 | F12: =F10-F11 -> -0.20435073 | G12: =G10-G11 -> -3.1239623 | H12: =H10-H11 -> 0.27750748 | I12: =I10-I11 -> 0 | ... L12: =L10-L11 -> -2.2196463
A14: Net EMI - Months 1-36 (GST benefit available) | B14: 285165 | C14: << As per agreement - net of GST credit >>
A15: Monthly discount rate | B15: =B11/12 -> 0.0063895833 | C15: << Link >>
A16: No of Months | B16: =6*12 -> 72 | C16: << As per Agreement >>
A17: PV of rent payments | B17: =-PV(B15,36,B14,,1)-PV(B15,36,B18,,1)/(1+B15)^36 -> 18970814 | C17: << Formula >>
A18: Gross EMI - Months 37-72 (GST benefit not available) | B18: 380646 | C18: << As per agreement - gross, no GST credit >>
B20: Right of Use Asset | E20: Lease Liability
A21: From | B21: Opening WDV | C21: Depreciation | D21: Closing WDV | E21: Opening Liability | F21: Repayment | G21: Interest | H21: Closing Lease Liability
A22: 45992 | B22: =B17 -> 18970814 | C22: =$B$17/$B$16 -> 263483.53 | D22: =B22-C22 -> 18707331 | E22: =B22 -> 18970814 | F22: =-$B$14 -> -285165 | G22: =(E22+F22)*$B$15 -> 119393.51 | H22: =E22+F22+G22 -> 18805043
A23: 46023 | B23: =D22 -> 18707331 | C23: =$B$17/$B$16 -> 263483.53 | D23: =B23-C23 -> 18443847 | E23: =H22 -> 18805043 | F23: =-$B$14 -> -285165 | G23: =(E23+F23)*$B$15 -> 118334.3 | H23: =E23+F23+G23 -> 18638212
A24: 46054 | B24: =D23 -> 18443847 | C24: =$B$17/$B$16 -> 263483.53 | D24: =B24-C24 -> 18180364 | E24: =H23 -> 18638212 | F24: =-$B$14 -> -285165 | G24: =(E24+F24)*$B$15 -> 117268.32 | H24: =E24+F24+G24 -> 18470315
A25: 46082 | B25: =D24 -> 18180364 | C25: =$B$17/$B$16 -> 263483.53 | D25: =B25-C25 -> 17916880 | E25: =H24 -> 18470315 | F25: =-$B$14 -> -285165 | G25: =(E25+F25)*$B$15 -> 116195.53 | H25: =E25+F25+G25 -> 18301346
A26: 46113 | B26: =D25 -> 17916880 | C26: =$B$17/$B$16 -> 263483.53 | D26: =B26-C26 -> 17653397 | E26: =H25 -> 18301346 | F26: =-$B$14 -> -285165 | G26: =(E26+F26)*$B$15 -> 115115.89 | H26: =E26+F26+G26 -> 18131297
A27: 46143 | B27: =D26 -> 17653397 | C27: =$B$17/$B$16 -> 263483.53 | D27: =B27-C27 -> 17389913 | E27: =H26 -> 18131297 | F27: =-$B$14 -> -285165 | G27: =(E27+F27)*$B$15 -> 114029.35 | H27: =E27+F27+G27 -> 17960161
A28: 46174 | B28: =D27 -> 17389913 | C28: =$B$17/$B$16 -> 263483.53 | D28: =B28-C28 -> 17126430 | E28: =H27 -> 17960161 | F28: =-$B$14 -> -285165 | G28: =(E28+F28)*$B$15 -> 112935.86 | H28: =E28+F28+G28 -> 17787932
A29: 46204 | B29: =D28 -> 17126430 | C29: =$B$17/$B$16 -> 263483.53 | D29: =B29-C29 -> 16862946 | E29: =H28 -> 17787932 | F29: =-$B$14 -> -285165 | G29: =(E29+F29)*$B$15 -> 111835.39 | H29: =E29+F29+G29 -> 17614602
A30: 46235 | B30: =D29 -> 16862946 | C30: =$B$17/$B$16 -> 263483.53 | D30: =B30-C30 -> 16599462 | E30: =H29 -> 17614602 | F30: =-$B$14 -> -285165 | G30: =(E30+F30)*$B$15 -> 110727.88 | H30: =E30+F30+G30 -> 17440165
A31: 46266 | B31: =D30 -> 16599462 | C31: =$B$17/$B$16 -> 263483.53 | D31: =B31-C31 -> 16335979 | E31: =H30 -> 17440165 | F31: =-$B$14 -> -285165 | G31: =(E31+F31)*$B$15 -> 109613.3 | H31: =E31+F31+G31 -> 17264614
A32: 46296 | B32: =D31 -> 16335979 | C32: =$B$17/$B$16 -> 263483.53 | D32: =B32-C32 -> 16072495 | E32: =H31 -> 17264614 | F32: =-$B$14 -> -285165 | G32: =(E32+F32)*$B$15 -> 108491.6 | H32: =E32+F32+G32 -> 17087940
A33: 46327 | B33: =D32 -> 16072495 | C33: =$B$17/$B$16 -> 263483.53 | D33: =B33-C33 -> 15809012 | E33: =H32 -> 17087940 | F33: =-$B$14 -> -285165 | G33: =(E33+F33)*$B$15 -> 107362.73 | H33: =E33+F33+G33 -> 16910138
A34: 46357 | B34: =D33 -> 15809012 | C34: =$B$17/$B$16 -> 263483.53 | D34: =B34-C34 -> 15545528 | E34: =H33 -> 16910138 | F34: =-$B$14 -> -285165 | G34: =(E34+F34)*$B$15 -> 106226.65 | H34: =E34+F34+G34 -> 16731200
... A57: 47058 | B57: =D56 -> 9748890.7 | C57: =$B$17/$B$16 -> 263483.53 | D57: =B57-C57 -> 9485407.1 | E57: =H56 -> 12491929 | F57: =-$B$14 -> -285165 | G57: =(E57+F57)*$B$15 -> 77996.135 | H57: =E57+F57+G57 -> 12284760
A58: 47088 | B58: =D57 -> 9485407.1 | C58: =$B$17/$B$16 -> 263483.53 | D58: =B58-C58 -> 9221923.6 | E58: =H57 -> 12284760 | F58: =-$B$18 -> -380646 | G58: =(E58+F58)*$B$15 -> 76062.329 | H58: =E58+F58+G58 -> 11980176
A59: 47119 | B59: =D58 -> 9221923.6 | C59: =$B$17/$B$16 -> 263483.53 | D59: =B59-C59 -> 8958440.1 | E59: =H58 -> 11980176 | F59: =-$B$18 -> -380646 | G59: =(E59+F59)*$B$15 -> 74116.166 | H59: =E59+F59+G59 -> 11673647
A60: 47150 | B60: =D59 -> 8958440.1 | C60: =$B$17/$B$16 -> 263483.53 | D60: =B60-C60 -> 8694956.5 | E60: =H59 -> 11673647 | F60: =-$B$18 -> -380646 | G60: =(E60+F60)*$B$15 -> 72157.568 | H60: =E60+F60+G60 -> 11365158
A61: 47178 | B61: =D60 -> 8694956.5 | C61: =$B$17/$B$16 -> 263483.53 | D61: =B61-C61 -> 8431473 | E61: =H60 -> 11365158 | F61: =-$B$18 -> -380646 | G61: =(E61+F61)*$B$15 -> 70186.455 | H61: =E61+F61+G61 -> 11054699
A62: 47209 | B62: =D61 -> 8431473 | C62: =$B$17/$B$16 -> 263483.53 | D62: =B62-C62 -> 8167989.5 | E62: =H61 -> 11054699 | F62: =-$B$18 -> -380646 | G62: =(E62+F62)*$B$15 -> 68202.748 | H62: =E62+F62+G62 -> 10742255
A63: 47239 | B63: =D62 -> 8167989.5 | C63: =$B$17/$B$16 -> 263483.53 | D63: =B63-C63 -> 7904505.9 | E63: =H62 -> 10742255 | F63: =-$B$18 -> -380646 | G63: =(E63+F63)*$B$15 -> 66206.366 | H63: =E63+F63+G63 -> 10427816
A64: 47270 | B64: =D63 -> 7904505.9 | C64: =$B$17/$B$16 -> 263483.53 | D64: =B64-C64 -> 7641022.4 | E64: =H63 -> 10427816 | F64: =-$B$18 -> -380646 | G64: =(E64+F64)*$B$15 -> 64197.228 | H64: =E64+F64+G64 -> 10111367
A65: 47300 | B65: =D64 -> 7641022.4 | C65: =$B$17/$B$16 -> 263483.53 | D65: =B65-C65 -> 7377538.9 | E65: =H64 -> 10111367 | F65: =-$B$18 -> -380646 | G65: =(E65+F65)*$B$15 -> 62175.252 | H65: =E65+F65+G65 -> 9792896.1
A66: 47331 | B66: =D65 -> 7377538.9 | C66: =$B$17/$B$16 -> 263483.53 | D66: =B66-C66 -> 7114055.3 | E66: =H65 -> 9792896.1 | F66: =-$B$18 -> -380646 | G66: =(E66+F66)*$B$15 -> 60140.357 | H66: =E66+F66+G66 -> 9472390.5
A67: 47362 | B67: =D66 -> 7114055.3 | C67: =$B$17/$B$16 -> 263483.53 | D67: =B67-C67 -> 6850571.8 | E67: =H66 -> 9472390.5 | F67: =-$B$18 -> -380646 | G67: =(E67+F67)*$B$15 -> 58092.459 | H67: =E67+F67+G67 -> 9149837
A68: 47392 | B68: =D67 -> 6850571.8 | C68: =$B$17/$B$16 -> 263483.53 | D68: =B68-C68 -> 6587088.3 | E68: =H67 -> 9149837 | F68: =-$B$18 -> -380646 | G68: =(E68+F68)*$B$15 -> 56031.476 | H68: =E68+F68+G68 -> 8825222.4
A69: 47423 | B69: =D68 -> 6587088.3 | C69: =$B$17/$B$16 -> 263483.53 | D69: =B69-C69 -> 6323604.7 | E69: =H68 -> 8825222.4 | F69: =-$B$18 -> -380646 | G69: =(E69+F69)*$B$15 -> 53957.325 | H69: =E69+F69+G69 -> 8498533.8
... A93: 48153 | B93: =D92 -> 263483.53 | C93: =$B$17/$B$16 -> 263483.53 | D93: =B93-C93 -> -1.6647391e-08 | E93: =H92 -> 380646 | F93: =-$B$18 -> -380646 | G93: =(E93+F93)*$B$15 -> 2.569242e-09 | H93: =E93+F93+G93 -> 4.0466776e-07

Sheet ITC-57772
A1: Deloitte Haskins & Sells
A2: GE India Industrial Private Limited
A3: Audit for the year ended March 31, 2026
A6: Purpose
A7: To verify the lease working of the sample selected
A10: Summary
A12: Particulars | B12: Discount Rate | C12: Commencement Date | D12: Expiration Date | E12: Addition during FY 2025-26 | F12: Amortisation during FY 2025-26 | G12: Closing WDV | H12: Interest | I12: Repayment | J12: Closing Balance | K12: ST | L12: LT
A13: As per Lease Report | B13: 0.073532 | C13: 44805 | D13: 46022 | E13: 6063067.8 | F13: 11099215 | G13: 0 | H13: 91040.98 | I13: 13560139 | J13: 0 | K13: 0 | L13: 0
A14: As per DHS Working | B14: 0.073532 | C14: 44805 | D14: 46022 | E14: =B25 -> 6063067.8 | F14: =SUM(C60:C62)+SUM(C65:C68) -> 13258589 | G14: =D62+D68 -> 5.3085387e-08 | H14: =SUM(F60:F62)+SUM(F65:F68) -> 90494.209 | I14: =-G62-SUM(G65:G68) -> 13560139 | J14: =H62+H68 -> 1.648441e-07 | K14: =J14 -> 1.648441e-07 | L14: =J14-K14 -> 0
A15: Difference | B15: =B13-B14 -> 0 | C15: =C13-C14 -> 0 | D15: =D13-D14 -> 0 | E15: =E13-E14 -> 0 | F15: =F13-F14 -> -2159373.5 | G15: =G13-G14 -> -5.3085387e-08 | H15: =H13-H14 -> 546.77138 | I15: =I13-I14 -> 0 | ... L15: =L13-L14 -> 0
F16: Difference is due to mid life discount rate change by client, whereas I have recalculated as per one rate only
A17: Original Tranche (Sep-22 to Aug-25) - 12 quarterly payments in advance
A18: Quarterly Rent (In Advance) | B18: 7497070.8 | C18: << As per agreement >>
A19: Quarterly discount rate | B19: =B14/4 -> 0.018383 | C19: << Link >>
A20: No of Quarterly Payments | B20: 12 | C20: << Formula >>
A21: PV of rent payments (Annuity Due) | B21: =-PV(B19,B20,B18,,1) -> 81549235 | C21: << Formula >>
A23: Renewal Tranche (Sep-25 to Dec-25) - lump sum paid in full at commencement
A24: No of months - Renewal Term | B24: 4 | C24: << As per Renewal Agreement (Sep, Oct, Nov, Dec-25) >>
A25: PV of Renewal Payment | B25: 6063067.8 | C25: << Paid in full at commencement - no further discounting required >>
A27: Right of Use Asset & Lease Liability - Combined Schedule
A28: Month | B28: Opening WDV | C28: Dep | D28: Closing WDV | E28: Opening Liability | F28: Interest | G28: Repayment | H28: Closing Lease Liability
A29: 44805 | B29: =$B$21 -> 81549235 | C29: =$B$21/34 -> 2398506.9 | D29: =B29-C29 -> 79150728 | E29: =$B$21 -> 81549235 | F29: =(E29+G29)*((1+$B$19)^(1/3)-1) -> 451014.5 | G29: =-$B$18 -> -7497070.8 | H29: =E29+F29+G29 -> 74503179
A30: 44835 | B30: =D29 -> 79150728 | C30: =$B$21/34 -> 2398506.9 | D30: =B30-C30 -> 76752222 | E30: =H29 -> 74503179 | F30: =(E30+G30)*((1+$B$19)^(1/3)-1) -> 453761.4 | G30: 0 | H30: =E30+F30+G30 -> 74956940
A31: 44866 | B31: =D30 -> 76752222 | C31: =$B$21/34 -> 2398506.9 | D31: =B31-C31 -> 74353715 | E31: =H30 -> 74956940 | F31: =(E31+G31)*((1+$B$19)^(1/3)-1) -> 456525.04 | G31: 0 | H31: =E31+F31+G31 -> 75413466
A32: 44896 | B32: =D31 -> 74353715 | C32: =$B$21/34 -> 2398506.9 | D32: =B32-C32 -> 71955208 | E32: =H31 -> 75413466 | F32: =(E32+G32)*((1+$B$19)^(1/3)-1) -> 413644.61 | G32: =-$B$18 -> -7497070.8 | H32: =E32+F32+G32 -> 68330039
A33: 44927 | B33: =D32 -> 71955208 | C33: =$B$21/34 -> 2398506.9 | D33: =B33-C33 -> 69556701 | E33: =H32 -> 68330039 | F33: =(E33+G33)*((1+$B$19)^(1/3)-1) -> 416163.91 | G33: 0 | H33: =E33+F33+G33 -> 68746203
A34: 44958 | B34: =D33 -> 69556701 | C34: =$B$21/34 -> 2398506.9 | D34: =B34-C34 -> 67158194 | E34: =H33 -> 68746203 | F34: =(E34+G34)*((1+$B$19)^(1/3)-1) -> 418698.56 | G34: 0 | H34: =E34+F34+G34 -> 69164902
A35: 44986 | B35: =D34 -> 67158194 | C35: =$B$21/34 -> 2398506.9 | D35: =B35-C35 -> 64759687 | E35: =H34 -> 69164902 | F35: =(E35+G35)*((1+$B$19)^(1/3)-1) -> 375587.75 | G35: =-$B$18 -> -7497070.8 | H35: =E35+F35+G35 -> 62043419
A36: 45017 | B36: =D35 -> 64759687 | C36: =$B$21/34 -> 2398506.9 | D36: =B36-C36 -> 62361180 | E36: =H35 -> 62043419 | F36: =(E36+G36)*((1+$B$19)^(1/3)-1) -> 377875.27 | G36: 0 | H36: =E36+F36+G36 -> 62421294
A37: 45047 | B37: =D36 -> 62361180 | C37: =$B$21/34 -> 2398506.9 | D37: =B37-C37 -> 59962673 | E37: =H36 -> 62421294 | F37: =(E37+G37)*((1+$B$19)^(1/3)-1) -> 380176.72 | G37: 0 | H37: =E37+F37+G37 -> 62801471
A38: 45078 | B38: =D37 -> 59962673 | C38: =$B$21/34 -> 2398506.9 | D38: =B38-C38 -> 57564166 | E38: =H37 -> 62801471 | F38: =(E38+G38)*((1+$B$19)^(1/3)-1) -> 336831.29 | G38: =-$B$18 -> -7497070.8 | H38: =E38+F38+G38 -> 55641231
A39: 45108 | B39: =D38 -> 57564166 | C39: =$B$21/34 -> 2398506.9 | D39: =B39-C39 -> 55165659 | E39: =H38 -> 55641231 | F39: =(E39+G39)*((1+$B$19)^(1/3)-1) -> 338882.76 | G39: 0 | H39: =E39+F39+G39 -> 55980114
A40: 45139 | B40: =D39 -> 55165659 | C40: =$B$21/34 -> 2398506.9 | D40: =B40-C40 -> 52767152 | E40: =H39 -> 55980114 | F40: =(E40+G40)*((1+$B$19)^(1/3)-1) -> 340946.73 | G40: 0 | H40: =E40+F40+G40 -> 56321061
A41: 45170 | B41: =D40 -> 52767152 | C41: =$B$21/34 -> 2398506.9 | D41: =B41-C41 -> 50368645 | E41: =H40 -> 56321061 | F41: =(E41+G41)*((1+$B$19)^(1/3)-1) -> 297362.37 | G41: =-$B$18 -> -7497070.8 | H41: =E41+F41+G41 -> 49121352
A42: 45200 | B42: =D41 -> 50368645 | C42: =$B$21/34 -> 2398506.9 | D42: =B42-C42 -> 47970138 | E42: =H41 -> 49121352 | F42: =(E42+G42)*((1+$B$19)^(1/3)-1) -> 299173.46 | G42: 0 | H42: =E42+F42+G42 -> 49420526
A43: 45231 | B43: =D42 -> 47970138 | C43: =$B$21/34 -> 2398506.9 | D43: =B43-C43 -> 45571632 | E43: =H42 -> 49420526 | F43: =(E43+G43)*((1+$B$19)^(1/3)-1) -> 300995.57 | G43: 0 | H43: =E43+F43+G43 -> 49721521
A44: 45261 | B44: =D43 -> 45571632 | C44: =$B$21/34 -> 2398506.9 | D44: =B44-C44 -> 43173125 | E44: =H43 -> 49721521 | F44: =(E44+G44)*((1+$B$19)^(1/3)-1) -> 257167.9 | G44: =-$B$18 -> -7497070.8 | H44: =E44+F44+G44 -> 42481618
A45: 45292 | B45: =D44 -> 43173125 | C45: =$B$21/34 -> 2398506.9 | D45: =B45-C45 -> 40774618 | E45: =H44 -> 42481618 | F45: =(E45+G45)*((1+$B$19)^(1/3)-1) -> 258734.18 | G45: 0 | H45: =E45+F45+G45 -> 42740353
A46: 45323 | B46: =D45 -> 40774618 | C46: =$B$21/34 -> 2398506.9 | D46: =B46-C46 -> 38376111 | E46: =H45 -> 42740353 | F46: =(E46+G46)*((1+$B$19)^(1/3)-1) -> 260310 | G46: 0 | H46: =E46+F46+G46 -> 43000663
A47: 45352 | B47: =D46 -> 38376111 | C47: =$B$21/34 -> 2398506.9 | D47: =B47-C47 -> 35977604 | E47: =H46 -> 43000663 | F47: =(E47+G47)*((1+$B$19)^(1/3)-1) -> 216234.53 | G47: =-$B$18 -> -7497070.8 | H47: =E47+F47+G47 -> 35719826
A48: 45383 | B48: =D47 -> 35977604 | C48: =$B$21/34 -> 2398506.9 | D48: =B48-C48 -> 33579097 | E48: =H47 -> 35719826 | F48: =(E48+G48)*((1+$B$19)^(1/3)-1) -> 217551.5 | G48: 0 | H48: =E48+F48+G48 -> 35937378
A49: 45413 | B49: =D48 -> 33579097 | C49: =$B$21/34 -> 2398506.9 | D49: =B49-C49 -> 31180590 | E49: =H48 -> 35937378 | F49: =(E49+G49)*((1+$B$19)^(1/3)-1) -> 218876.5 | G49: 0 | H49: =E49+F49+G49 -> 36156254
A50: 45444 | B50: =D49 -> 31180590 | C50: =$B$21/34 -> 2398506.9 | D50: =B50-C50 -> 28782083 | E50: =H49 -> 36156254 | F50: =(E50+G50)*((1+$B$19)^(1/3)-1) -> 174548.68 | G50: =-$B$18 -> -7497070.8 | H50: =E50+F50+G50 -> 28833732
A51: 45474 | B51: =D50 -> 28782083 | C51: =$B$21/34 -> 2398506.9 | D51: =B51-C51 -> 26383576 | E51: =H50 -> 28833732 | F51: =(E51+G51)*((1+$B$19)^(1/3)-1) -> 175611.77 | G51: 0 | H51: =E51+F51+G51 -> 29009344
A52: 45505 | B52: =D51 -> 26383576 | C52: =$B$21/34 -> 2398506.9 | D52: =B52-C52 -> 23985069 | E52: =H51 -> 29009344 | F52: =(E52+G52)*((1+$B$19)^(1/3)-1) -> 176681.33 | G52: 0 | H52: =E52+F52+G52 -> 29186025
A53: 45536 | B53: =D52 -> 23985069 | C53: =$B$21/34 -> 2398506.9 | D53: =B53-C53 -> 21586562 | E53: =H52 -> 29186025 | F53: =(E53+G53)*((1+$B$19)^(1/3)-1) -> 132096.52 | G53: =-$B$18 -> -7497070.8 | H53: =E53+F53+G53 -> 21821051
A54: 45566 | B54: =D53 -> 21586562 | C54: =$B$21/34 -> 2398506.9 | D54: =B54-C54 -> 19188055 | E54: =H53 -> 21821051 | F54: =(E54+G54)*((1+$B$19)^(1/3)-1) -> 132901.05 | G54: 0 | H54: =E54+F54+G54 -> 21953952
A55: 45597 | B55: =D54 -> 19188055 | C55: =$B$21/34 -> 2398506.9 | D55: =B55-C55 -> 16789548 | E55: =H54 -> 21953952 | F55: =(E55+G55)*((1+$B$19)^(1/3)-1) -> 133710.48 | G55: 0 | H55: =E55+F55+G55 -> 22087663
A56: 45627 | B56: =D55 -> 16789548 | C56: =$B$21/34 -> 2398506.9 | D56: =B56-C56 -> 14391042 | E56: =H55 -> 22087663 | F56: =(E56+G56)*((1+$B$19)^(1/3)-1) -> 88863.959 | G56: =-$B$18 -> -7497070.8 | H56: =E56+F56+G56 -> 14679456
A57: 45658 | B57: =D56 -> 14391042 | C57: =$B$21/34 -> 2398506.9 | D57: =B57-C57 -> 11992535 | E57: =H56 -> 14679456 | F57: =(E57+G57)*((1+$B$19)^(1/3)-1) -> 89405.185 | G57: 0 | H57: =E57+F57+G57 -> 14768861
A58: 45689 | B58: =D57 -> 11992535 | C58: =$B$21/34 -> 2398506.9 | D58: =B58-C58 -> 9594027.7 | E58: =H57 -> 14768861 | F58: =(E58+G58)*((1+$B$19)^(1/3)-1) -> 89949.707 | G58: 0 | H58: =E58+F58+G58 -> 14858811
A59: 45717 | B59: =D58 -> 9594027.7 | C59: =$B$21/34 -> 2398506.9 | D59: =B59-C59 -> 7195520.8 | E59: =H58 -> 14858811 | F59: =(E59+G59)*((1+$B$19)^(1/3)-1) -> 44836.656 | G59: =-$B$18 -> -7497070.8 | H59: =E59+F59+G59 -> 7406576.6
A60: 45748 | B60: =D59 -> 7195520.8 | C60: =$B$21/34 -> 2398506.9 | D60: =B60-C60 -> 4797013.8 | E60: =H59 -> 7406576.6 | F60: =(E60+G60)*((1+$B$19)^(1/3)-1) -> 45109.734 | G60: 0 | H60: =E60+F60+G60 -> 7451686.3
A61: 45778 | B61: =D60 -> 4797013.8 | C61: =$B$21/34 -> 2398506.9 | D61: =B61-C61 -> 2398506.9 | E61: =H60 -> 7451686.3 | F61: =(E61+G61)*((1+$B$19)^(1/3)-1) -> 45384.475 | G61: 0 | H61: =E61+F61+G61 -> 7497070.8
A62: 45809 | B62: =D61 -> 2398506.9 | C62: =$B$21/34 -> 2398506.9 | D62: =B62-C62 -> 5.3085387e-08 | E62: =H61 -> 7497070.8 | F62: =(E62+G62)*((1+$B$19)^(1/3)-1) -> 9.9831029e-10 | G62: =-$B$18 -> -7497070.8 | H62: =E62+F62+G62 -> 1.648441e-07
A64: Jul'25 - Aug'25: No lease in force (original expired Jun-25, renewal commences Sep-25)
A65: 45901 | B65: =$B$25 -> 6063067.8 | C65: =$B$25/$B$24 -> 1515766.9 | D65: =B65-C65 -> 4547300.8 | E65: =$B$25 -> 6063067.8 | F65: 0 | G65: =-$B$25 -> -6063067.8 | H65: =E65+F65+G65 -> 0
A66: 45931 | B66: =D65 -> 4547300.8 | C66: =$B$25/$B$24 -> 1515766.9 | D66: =B66-C66 -> 3031533.9 | E66: =H65 -> 0 | F66: 0 | G66: 0 | H66: =E66+F66+G66 -> 0
A67: 45962 | B67: =D66 -> 3031533.9 | C67: =$B$25/$B$24 -> 1515766.9 | D67: =B67-C67 -> 1515766.9 | E67: =H66 -> 0 | F67: 0 | G67: 0 | H67: =E67+F67+G67 -> 0
A68: 45992 | B68: =D67 -> 1515766.9 | C68: =$B$25/$B$24 -> 1515766.9 | D68: =B68-C68 -> 0 | E68: =H67 -> 0 | F68: 0 | G68: 0 | H68: =E68+F68+G68 -> 0

Sheet ITC-56754
A1: =Scope!#REF! -> #REF!
A2: =Scope!#REF! -> #REF!
A3: =Scope!#REF! -> #REF!
A6: =Scope!A2 -> Purpose
A7: To verify the lease working of the sample selected
A10: Summary
A12: Particulars | B12: Discount Rate | C12: Commencement Date | D12: Expiration Date | E12: Addition during FY 2025-26 | F12: Amortisation during FY 2025-26 | G12: Closing WDV | H12: Interest | I12: Repayment | J12: Closing Balance | K12: ST | L12: LT
A13: As per Lease Report | B13: 0.07353162 | C13: 44621 | D13: 45777 | E13: 0 | F13: 987857.38 | G13: 0 | H13: 0.01 | I13: 991136.97 | J13: ='Details 25-26'!S256 -> 0 | K13: 0 | L13: 0
A14: As per DHS Working | B14: 0.07353162 | C14: 44621 | D14: 45777 | E14: 0 | F14: =SUM(C62) -> 887208.69 | G14: 0 | H14: =G62 -> -1.7669694e-09 | I14: =F62 -> -991137 | J14: 0 | K14: 0 | L14: 0
A15: Difference | B15: =B13-B14 -> 0 | C15: =C13-C14 -> 0 | D15: =D13-D14 -> 0 | E15: =E13-E14 -> 0 | F15: =F13-F14 -> 100648.69 | G15: =G13-G14 -> 0 | H15: =H13-H14 -> 0.010000002 | I15: =I13+I14 -> -0.03 | J15: =J13-J14 -> 0 | K15: =K13-K14 -> 0 | L15: =L13-L14 -> 0
A17: Monthly Rent (In Advance) | B17: 991137 | C17: << As per agreement >>
A18: Monthly discount rate | B18: =B14/12 -> 0.006127635 | C18: << Link >>
A19: No of Months | B19: =ROUND(((D14-C14)/30.5),0) -> 38 | C19: << Formula >>
A20: PV of rent payments | B20: =-PV(B18,B19,B17,,1) -> 33713930 | C20: << Formula >>
B23: Right of Use Asset | E23: Lease Liability
A24: From | B24: Opening WDV | C24: Depreciation | D24: Closing WDV | E24: Opening Liability | F24: Repayment | G24: Interest | H24: Closing Lease Liability
A25: 44621 | B25: =B20 -> 33713930 | C25: =$B$20/$B$19 -> 887208.69 | D25: =B25-C25 -> 32826722 | E25: =B25 -> 33713930 | F25: =-$B$17 -> -991137 | G25: =(E25+F25)*$B$18 -> 200513.33 | H25: =E25+F25+G25 -> 32923307
A26: 44652 | B26: =D25 -> 32826722 | C26: =$B$20/$B$19 -> 887208.69 | D26: =B26-C26 -> 31939513 | E26: =H25 -> 32923307 | F26: =-$B$17 -> -991137 | G26: =(E26+F26)*$B$18 -> 195668.68 | H26: =E26+F26+G26 -> 32127838
A27: 44682 | B27: =D26 -> 31939513 | C27: =$B$20/$B$19 -> 887208.69 | D27: =B27-C27 -> 31052304 | E27: =H26 -> 32127838 | F27: =-$B$17 -> -991137 | G27: =(E27+F27)*$B$18 -> 190794.34 | H27: =E27+F27+G27 -> 31327496
A28: 44713 | B28: =D27 -> 31052304 | C28: =$B$20/$B$19 -> 887208.69 | D28: =B28-C28 -> 30165095 | E28: =H27 -> 31327496 | F28: =-$B$17 -> -991137 | G28: =(E28+F28)*$B$18 -> 185890.13 | H28: =E28+F28+G28 -> 30522249
A29: 44743 | B29: =D28 -> 30165095 | C29: =$B$20/$B$19 -> 887208.69 | D29: =B29-C29 -> 29277887 | E29: =H28 -> 30522249 | F29: =-$B$17 -> -991137 | G29: =(E29+F29)*$B$18 -> 180955.87 | H29: =E29+F29+G29 -> 29712068
A30: 44774 | B30: =D29 -> 29277887 | C30: =$B$20/$B$19 -> 887208.69 | D30: =B30-C30 -> 28390678 | E30: =H29 -> 29712068 | F30: =-$B$17 -> -991137 | G30: =(E30+F30)*$B$18 -> 175991.38 | H30: =E30+F30+G30 -> 28896922
A31: 44805 | B31: =D30 -> 28390678 | C31: =$B$20/$B$19 -> 887208.69 | D31: =B31-C31 -> 27503469 | E31: =H30 -> 28896922 | F31: =-$B$17 -> -991137 | G31: =(E31+F31)*$B$18 -> 170996.46 | H31: =E31+F31+G31 -> 28076781
A32: 44835 | B32: =D31 -> 27503469 | C32: =$B$20/$B$19 -> 887208.69 | D32: =B32-C32 -> 26616261 | E32: =H31 -> 28076781 | F32: =-$B$17 -> -991137 | G32: =(E32+F32)*$B$18 -> 165970.94 | H32: =E32+F32+G32 -> 27251615
A33: 44866 | B33: =D32 -> 26616261 | C33: =$B$20/$B$19 -> 887208.69 | D33: =B33-C33 -> 25729052 | E33: =H32 -> 27251615 | F33: =-$B$17 -> -991137 | G33: =(E33+F33)*$B$18 -> 160914.63 | H33: =E33+F33+G33 -> 26421393
A34: 44896 | B34: =D33 -> 25729052 | C34: =$B$20/$B$19 -> 887208.69 | D34: =B34-C34 -> 24841843 | E34: =H33 -> 26421393 | F34: =-$B$17 -> -991137 | G34: =(E34+F34)*$B$18 -> 155827.33 | H34: =E34+F34+G34 -> 25586083
A35: 44927 | B35: =D34 -> 24841843 | C35: =$B$20/$B$19 -> 887208.69 | D35: =B35-C35 -> 23954635 | E35: =H34 -> 25586083 | F35: =-$B$17 -> -991137 | G35: =(E35+F35)*$B$18 -> 150708.85 | H35: =E35+F35+G35 -> 24745655
A36: 44958 | B36: =D35 -> 23954635 | C36: =$B$20/$B$19 -> 887208.69 | D36: =B36-C36 -> 23067426 | E36: =H35 -> 24745655 | F36: =-$B$17 -> -991137 | G36: =(E36+F36)*$B$18 -> 145559.02 | H36: =E36+F36+G36 -> 23900077
A37: 44986 | B37: =D36 -> 23067426 | C37: =$B$20/$B$19 -> 887208.69 | D37: =B37-C37 -> 22180217 | E37: =H36 -> 23900077 | F37: =-$B$17 -> -991137 | G37: =(E37+F37)*$B$18 -> 140377.62 | H37: =E37+F37+G37 -> 23049318
... A62: 45748 | B62: =D61 -> 887208.69 | C62: =$B$20/$B$19 -> 887208.69 | D62: =B62-C62 -> 2.6309863e-08 | E62: =H61 -> 991137 | F62: =-$B$17 -> -991137 | G62: =(E62+F62)*$B$18 -> -1.7669694e-09 | H62: =E62+F62+G62 -> -2.9012772e-07

Sheet ITC- 65449
A1: =Scope!#REF! -> #REF!
A2: =Scope!#REF! -> #REF!
A3: =Scope!#REF! -> #REF!
A6: =Scope!A2 -> Purpose
A7: To verify the lease working of the sample selected
A10: Summary
A12: Particulars | B12: Discount Rate | C12: Commencement Date | D12: Expiration Date | E12: Addition during FY 2025-26 | F12: Amortisation during FY 2025-26 | G12: Closing WDV | H12: Interest | I12: Repayment | J12: Closing Balance | K12: ST | L12: LT
A13: As per Lease Report | B13: 0.07485 | C13: 45617 | D13: 47442 | E13: 0 | F13: 26535337 | G13: 96559142 | H13: 8643126.1 | I13: 32090812 | J13: 1.052957e+08 | K13: 25264224 | L13: 80031471
A14: As per DHS Working | B14: =7.485% -> 0.07485 | C14: 45617 | D14: 47442 | E14: 0 | F14: =SUM(C30:C41) -> 26867744 | G14: =D41 -> 96276081 | H14: =SUM(G30:G41) -> 8349397.9 | I14: =-SUM(F42:F53) -> 32090812 | J14: =H41 -> 1.0121612e+08 | K14: =-(H54-H41) -> 27799847 | L14: =J14-K14 -> 73416269
A15: Difference | B15: =B13-B14 -> 0 | C15: =C13-C14 -> 0 | D15: =D13-D14 -> 0 | E15: =E13-E14 -> 0 | F15: =F13-F14 -> -332407.02 | G15: =G13-G14 -> 283060.34 | H15: =H13-H14 -> 293728.13 | I15: =I13-I14 -> 0 | ... L15: =L13-L14 -> 6615202.6
A17: Monthly Rent (In Advance) | B17: =8022703/3 -> 2674234.3 | C17: << As per agreement >>
A18: Monthly discount rate | B18: =B14/12 -> 0.0062375 | C18: << Link >>
A19: No of Months | B19: =ROUND(((D14-C14)/30.5),0) -> 60 | C19: << Formula >>
A20: PV of rent payments | B20: =-PV(B18,B19,B17,,1) -> 1.3433872e+08 | C20: << Formula >>
B23: Right of Use Asset | E23: Lease Liability
A24: From | B24: Opening WDV | C24: Depreciation | D24: Closing WDV | E24: Opening Liability | F24: Repayment | G24: Interest | H24: Closing Lease Liability
A25: Nov - 2024 | B25: =B20 -> 1.3433872e+08 | C25: =$B$20/$B$19 -> 2238978.6 | D25: =B25-C25 -> 1.3209974e+08 | E25: =B25 -> 1.3433872e+08 | F25: =-$B$17 -> -2674234.3 | G25: =(E25+F25)*$B$18 -> 821257.22 | H25: =E25+F25+G25 -> 1.3248574e+08
A26: Dec - 2024 | B26: =D25 -> 1.3209974e+08 | C26: =$B$20/$B$19 -> 2238978.6 | D26: =B26-C26 -> 1.2986076e+08 | E26: =H25 -> 1.3248574e+08 | F26: =-$B$17 -> -2674234.3 | G26: =(E26+F26)*$B$18 -> 809699.27 | H26: =E26+F26+G26 -> 1.3062121e+08
A27: Jan - 2025 | B27: =D26 -> 1.2986076e+08 | C27: =$B$20/$B$19 -> 2238978.6 | D27: =B27-C27 -> 1.2762178e+08 | E27: =H26 -> 1.3062121e+08 | F27: =-$B$17 -> -2674234.3 | G27: =(E27+F27)*$B$18 -> 798069.24 | H27: =E27+F27+G27 -> 1.2874504e+08
A28: Feb - 2025 | B28: =D27 -> 1.2762178e+08 | C28: =$B$20/$B$19 -> 2238978.6 | D28: =B28-C28 -> 1.253828e+08 | E28: =H27 -> 1.2874504e+08 | F28: =-$B$17 -> -2674234.3 | G28: =(E28+F28)*$B$18 -> 786366.66 | H28: =E28+F28+G28 -> 1.2685717e+08
A29: Mar - 2025 | B29: =D28 -> 1.253828e+08 | C29: =$B$20/$B$19 -> 2238978.6 | D29: =B29-C29 -> 1.2314382e+08 | E29: =H28 -> 1.2685717e+08 | F29: =-$B$17 -> -2674234.3 | G29: =(E29+F29)*$B$18 -> 774591.08 | H29: =E29+F29+G29 -> 1.2495753e+08
A30: Apr - 2025 | B30: =D29 -> 1.2314382e+08 | C30: =$B$20/$B$19 -> 2238978.6 | D30: =B30-C30 -> 1.2090485e+08 | E30: =H29 -> 1.2495753e+08 | F30: =-$B$17 -> -2674234.3 | G30: =(E30+F30)*$B$18 -> 762742.06 | H30: =E30+F30+G30 -> 1.2304604e+08
A31: May - 2025 | B31: =D30 -> 1.2090485e+08 | C31: =$B$20/$B$19 -> 2238978.6 | D31: =B31-C31 -> 1.1866587e+08 | E31: =H30 -> 1.2304604e+08 | F31: =-$B$17 -> -2674234.3 | G31: =(E31+F31)*$B$18 -> 750819.12 | H31: =E31+F31+G31 -> 1.2112262e+08
A32: Jun - 2025 | B32: =D31 -> 1.1866587e+08 | C32: =$B$20/$B$19 -> 2238978.6 | D32: =B32-C32 -> 1.1642689e+08 | E32: =H31 -> 1.2112262e+08 | F32: =-$B$17 -> -2674234.3 | G32: =(E32+F32)*$B$18 -> 738821.82 | H32: =E32+F32+G32 -> 1.1918721e+08
A33: Jul - 2025 | B33: =D32 -> 1.1642689e+08 | C33: =$B$20/$B$19 -> 2238978.6 | D33: =B33-C33 -> 1.1418791e+08 | E33: =H32 -> 1.1918721e+08 | F33: =-$B$17 -> -2674234.3 | G33: =(E33+F33)*$B$18 -> 726749.69 | H33: =E33+F33+G33 -> 1.1723973e+08
A34: Aug - 2025 | B34: =D33 -> 1.1418791e+08 | C34: =$B$20/$B$19 -> 2238978.6 | D34: =B34-C34 -> 1.1194893e+08 | E34: =H33 -> 1.1723973e+08 | F34: =-$B$17 -> -2674234.3 | G34: =(E34+F34)*$B$18 -> 714602.25 | H34: =E34+F34+G34 -> 1.1528009e+08
A35: Sep - 2025 | B35: =D34 -> 1.1194893e+08 | C35: =$B$20/$B$19 -> 2238978.6 | D35: =B35-C35 -> 1.0970995e+08 | E35: =H34 -> 1.1528009e+08 | F35: =-$B$17 -> -2674234.3 | G35: =(E35+F35)*$B$18 -> 702379.04 | H35: =E35+F35+G35 -> 1.1330824e+08
A36: Oct - 2025 | B36: =D35 -> 1.0970995e+08 | C36: =$B$20/$B$19 -> 2238978.6 | D36: =B36-C36 -> 1.0747097e+08 | E36: =H35 -> 1.1330824e+08 | F36: =-$B$17 -> -2674234.3 | G36: =(E36+F36)*$B$18 -> 690079.6 | H36: =E36+F36+G36 -> 1.1132408e+08
A37: Nov - 2025 | B37: =D36 -> 1.0747097e+08 | C37: =$B$20/$B$19 -> 2238978.6 | D37: =B37-C37 -> 1.05232e+08 | E37: =H36 -> 1.1132408e+08 | F37: =-$B$17 -> -2674234.3 | G37: =(E37+F37)*$B$18 -> 677703.43 | H37: =E37+F37+G37 -> 1.0932755e+08
... A84: Oct - 2029 | B84: =D83 -> 2238978.6 | C84: =$B$20/$B$19 -> 2238978.6 | D84: =B84-C84 -> 1.9464642e-07 | E84: =H83 -> 2674234.3 | F84: =-$B$17 -> -2674234.3 | G84: =(E84+F84)*$B$18 -> -1.5943142e-08 | H84: =E84+F84+G84 -> -2.5719579e-06

Sheet ITC-64802
A1: =Scope!#REF! -> #REF!
A2: =Scope!#REF! -> #REF!
A3: =Scope!#REF! -> #REF!
A6: =Scope!A2 -> Purpose
A7: To verify the lease working of the sample selected
A10: Summary
A12: Particulars | B12: Discount Rate | C12: Commencement Date | D12: Expiration Date | E12: Addition during FY 2025-26 | F12: Amortisation during FY 2025-26 | G12: Closing WDV | H12: Interest | I12: Repayment | J12: Closing Balance | K12: ST | L12: LT
A13: As per Lease Report | B13: 0.0764 | C13: 45292 | D13: 46053 | E13: 0 | F13: 28252051 | G13: 0 | H13: 852572.36 | I13: 30455813 | J13: 0 | K13: 0 | L13: 0
A14: As per DHS Working | B14: 0.0764 | C14: 45292 | D14: 46053 | E14: 0 | F14: =SUM(C40:C49) -> 28252051 | G14: =D49 -> -3.3527613e-08 | H14: =SUM(G40:G49) -> 852572.35 | I14: =-SUM(F40:F49) -> 30455813 | J14: =H49 -> 1.5605246e-07 | K14: 0 | L14: 0
A15: Difference | B15: =B13-B14 -> 0 | C15: =C13-C14 -> 0 | D15: =D13-D14 -> 0 | E15: =E13-E14 -> 0 | F15: =F13-F14 -> -0.055193707 | G15: =G13-G14 -> 3.3527613e-08 | H15: =H13-H14 -> 0.0081703876 | I15: =I13-I14 -> 0 | ... L15: =L13-L14 -> 0
A17: Monthly Rent (In Advance) | B17: 3045581.3 | C17: << As per agreement >>
A18: Monthly discount rate | B18: =B14/12 -> 0.0063666667 | C18: << Link >>
A19: No of Months | B19: =ROUND(((D14-C14)/30),0) -> 25 | C19: << Formula >>
A20: PV of rent payments | B20: =-PV(B18,B19,B17,,1) -> 70630128 | C20: << Formula >>
B23: Right of Use Asset | E23: Lease Liability
A24: From | B24: Opening WDV | C24: Depreciation | D24: Closing WDV | E24: Opening Liability | F24: Repayment | G24: Interest | H24: Closing Lease Liability
A25: Jan - 2024 | B25: =B20 -> 70630128 | C25: =$B$20/$B$19 -> 2825205.1 | D25: =B25-C25 -> 67804923 | E25: =B25 -> 70630128 | F25: =-$B$17 -> -3045581.3 | G25: =(E25+F25)*$B$18 -> 430288.28 | H25: =E25+F25+G25 -> 68014835
A26: Feb - 2024 | B26: =D25 -> 67804923 | C26: =$B$20/$B$19 -> 2825205.1 | D26: =B26-C26 -> 64979718 | E26: =H25 -> 68014835 | F26: =-$B$17 -> -3045581.3 | G26: =(E26+F26)*$B$18 -> 413637.58 | H26: =E26+F26+G26 -> 65382892
A27: Mar - 2024 | B27: =D26 -> 64979718 | C27: =$B$20/$B$19 -> 2825205.1 | D27: =B27-C27 -> 62154513 | E27: =H26 -> 65382892 | F27: =-$B$17 -> -3045581.3 | G27: =(E27+F27)*$B$18 -> 396880.88 | H27: =E27+F27+G27 -> 62734191
A28: Apr - 2024 | B28: =D27 -> 62154513 | C28: =$B$20/$B$19 -> 2825205.1 | D28: =B28-C28 -> 59329308 | E28: =H27 -> 62734191 | F28: =-$B$17 -> -3045581.3 | G28: =(E28+F28)*$B$18 -> 380017.48 | H28: =E28+F28+G28 -> 60068627
A29: May - 2024 | B29: =D28 -> 59329308 | C29: =$B$20/$B$19 -> 2825205.1 | D29: =B29-C29 -> 56504103 | E29: =H28 -> 60068627 | F29: =-$B$17 -> -3045581.3 | G29: =(E29+F29)*$B$18 -> 363046.73 | H29: =E29+F29+G29 -> 57386093
A30: Jun - 2024 | B30: =D29 -> 56504103 | C30: =$B$20/$B$19 -> 2825205.1 | D30: =B30-C30 -> 53678898 | E30: =H29 -> 57386093 | F30: =-$B$17 -> -3045581.3 | G30: =(E30+F30)*$B$18 -> 345967.92 | H30: =E30+F30+G30 -> 54686479
A31: Jul - 2024 | B31: =D30 -> 53678898 | C31: =$B$20/$B$19 -> 2825205.1 | D31: =B31-C31 -> 50853692 | E31: =H30 -> 54686479 | F31: =-$B$17 -> -3045581.3 | G31: =(E31+F31)*$B$18 -> 328780.38 | H31: =E31+F31+G31 -> 51969678
A32: Aug - 2024 | B32: =D31 -> 50853692 | C32: =$B$20/$B$19 -> 2825205.1 | D32: =B32-C32 -> 48028487 | E32: =H31 -> 51969678 | F32: =-$B$17 -> -3045581.3 | G32: =(E32+F32)*$B$18 -> 311483.42 | H32: =E32+F32+G32 -> 49235581
A33: Sep - 2024 | B33: =D32 -> 48028487 | C33: =$B$20/$B$19 -> 2825205.1 | D33: =B33-C33 -> 45203282 | E33: =H32 -> 49235581 | F33: =-$B$17 -> -3045581.3 | G33: =(E33+F33)*$B$18 -> 294076.33 | H33: =E33+F33+G33 -> 46484076
A34: Oct - 2024 | B34: =D33 -> 45203282 | C34: =$B$20/$B$19 -> 2825205.1 | D34: =B34-C34 -> 42378077 | E34: =H33 -> 46484076 | F34: =-$B$17 -> -3045581.3 | G34: =(E34+F34)*$B$18 -> 276558.41 | H34: =E34+F34+G34 -> 43715053
A35: Nov - 2024 | B35: =D34 -> 42378077 | C35: =$B$20/$B$19 -> 2825205.1 | D35: =B35-C35 -> 39552872 | E35: =H34 -> 43715053 | F35: =-$B$17 -> -3045581.3 | G35: =(E35+F35)*$B$18 -> 258928.97 | H35: =E35+F35+G35 -> 40928400
A36: Dec - 2024 | B36: =D35 -> 39552872 | C36: =$B$20/$B$19 -> 2825205.1 | D36: =B36-C36 -> 36727667 | E36: =H35 -> 40928400 | F36: =-$B$17 -> -3045581.3 | G36: =(E36+F36)*$B$18 -> 241187.28 | H36: =E36+F36+G36 -> 38124006
A37: Jan - 2025 | B37: =D36 -> 36727667 | C37: =$B$20/$B$19 -> 2825205.1 | D37: =B37-C37 -> 33902462 | E37: =H36 -> 38124006 | F37: =-$B$17 -> -3045581.3 | G37: =(E37+F37)*$B$18 -> 223332.64 | H37: =E37+F37+G37 -> 35301758
... A49: Jan - 2026 | B49: =D48 -> 2825205.1 | C49: =$B$20/$B$19 -> 2825205.1 | D49: =B49-C49 -> -3.3527613e-08 | E49: =H48 -> 3045581.3 | F49: =-$B$17 -> -3045581.3 | G49: =(E49+F49)*$B$18 -> 9.872485e-10 | H49: =E49+F49+G49 -> 1.5605246e-07

Sheet ITC-64753
A1: =Scope!#REF! -> #REF!
A2: =Scope!#REF! -> #REF!
A3: =Scope!#REF! -> #REF!
A6: =Scope!A2 -> Purpose
A7: To verify the lease working of the sample selected
A10: Summary
A12: Particulars | B12: Discount Rate | C12: Commencement Date | D12: Expiration Date | E12: Addition during FY 2025-26 | F12: Amortisation during FY 2025-26 | G12: Closing WDV | H12: Interest | I12: Repayment | J12: Closing Balance | K12: ST | L12: LT
A13: As per Lease Report | B13: 0.078173 | C13: 45434 | D13: 47259 | E13: 0 | F13: 4596358.3 | G13: 14431577 | H13: 1332980.8 | I13: 5531736 | J13: 15211259 | K13: 4539003.8 | L13: 10672255
A14: As per DHS Working | B14: 0.078173 | C14: 45434 | D14: 47259 | E14: 0 | F14: =SUM(C37:C48) -> 4596358.4 | G14: =D48 -> 13789075 | H14: =SUM(G37:G48) -> 1305628.4 | I14: =-SUM(F37:F48) -> 5531736 | J14: =H48 -> 14846370 | K14: =H48-H61 -> 4965599.9 | L14: =J14-K14 -> 9880770.4
A15: Difference | B15: =B13-B14 -> 0 | C15: =C13-C14 -> 0 | D15: =D13-D14 -> 0 | E15: =E13-E14 -> 0 | F15: =F13-F14 -> -0.055688853 | G15: =G13-G14 -> 642501.81 | H15: =H13-H14 -> 27352.433 | I15: =I13-I14 -> 0 | ... L15: =L13-L14 -> 791484.63
A17: Monthly Rent (In Advance) | B17: 460978 | C17: << As per agreement >>
A18: Monthly discount rate | B18: =B14/12 -> 0.0065144167 | C18: << Link >>
A19: No of Months | B19: =ROUND(((D14-C14)/30.5),0) -> 60 | C19: << Formula >>
A20: PV of rent payments | B20: =-PV(B18,B19,B17,,1) -> 22981792 | C20: << Formula >>
B23: Right of Use Asset | E23: Lease Liability
A24: From | B24: Opening WDV | C24: Depreciation | D24: Closing WDV | E24: Opening Liability | F24: Repayment | G24: Interest | H24: Closing Lease Liability
A25: May - 2024 | B25: =B20 -> 22981792 | C25: =$B$20/$B$19 -> 383029.86 | D25: =B25-C25 -> 22598762 | E25: =B25 -> 22981792 | F25: =-$B$17 -> -460978 | G25: =(E25+F25)*$B$18 -> 146709.97 | H25: =E25+F25+G25 -> 22667524
A26: Jun - 2024 | B26: =D25 -> 22598762 | C26: =$B$20/$B$19 -> 383029.86 | D26: =B26-C26 -> 22215732 | E26: =H25 -> 22667524 | F26: =-$B$17 -> -460978 | G26: =(E26+F26)*$B$18 -> 144662.69 | H26: =E26+F26+G26 -> 22351209
A27: Jul - 2024 | B27: =D26 -> 22215732 | C27: =$B$20/$B$19 -> 383029.86 | D27: =B27-C27 -> 21832702 | E27: =H26 -> 22351209 | F27: =-$B$17 -> -460978 | G27: =(E27+F27)*$B$18 -> 142602.08 | H27: =E27+F27+G27 -> 22032833
A28: Aug - 2024 | B28: =D27 -> 21832702 | C28: =$B$20/$B$19 -> 383029.86 | D28: =B28-C28 -> 21449672 | E28: =H27 -> 22032833 | F28: =-$B$17 -> -460978 | G28: =(E28+F28)*$B$18 -> 140528.05 | H28: =E28+F28+G28 -> 21712383
A29: Sep - 2024 | B29: =D28 -> 21449672 | C29: =$B$20/$B$19 -> 383029.86 | D29: =B29-C29 -> 21066643 | E29: =H28 -> 21712383 | F29: =-$B$17 -> -460978 | G29: =(E29+F29)*$B$18 -> 138440.5 | H29: =E29+F29+G29 -> 21389845
A30: Oct - 2024 | B30: =D29 -> 21066643 | C30: =$B$20/$B$19 -> 383029.86 | D30: =B30-C30 -> 20683613 | E30: =H29 -> 21389845 | F30: =-$B$17 -> -460978 | G30: =(E30+F30)*$B$18 -> 136339.36 | H30: =E30+F30+G30 -> 21065207
A31: Nov - 2024 | B31: =D30 -> 20683613 | C31: =$B$20/$B$19 -> 383029.86 | D31: =B31-C31 -> 20300583 | E31: =H30 -> 21065207 | F31: =-$B$17 -> -460978 | G31: =(E31+F31)*$B$18 -> 134224.53 | H31: =E31+F31+G31 -> 20738453
A32: Dec - 2024 | B32: =D31 -> 20300583 | C32: =$B$20/$B$19 -> 383029.86 | D32: =B32-C32 -> 19917553 | E32: =H31 -> 20738453 | F32: =-$B$17 -> -460978 | G32: =(E32+F32)*$B$18 -> 132095.92 | H32: =E32+F32+G32 -> 20409571
A33: Jan - 2025 | B33: =D32 -> 19917553 | C33: =$B$20/$B$19 -> 383029.86 | D33: =B33-C33 -> 19534523 | E33: =H32 -> 20409571 | F33: =-$B$17 -> -460978 | G33: =(E33+F33)*$B$18 -> 129953.45 | H33: =E33+F33+G33 -> 20078546
A34: Feb - 2025 | B34: =D33 -> 19534523 | C34: =$B$20/$B$19 -> 383029.86 | D34: =B34-C34 -> 19151493 | E34: =H33 -> 20078546 | F34: =-$B$17 -> -460978 | G34: =(E34+F34)*$B$18 -> 127797.01 | H34: =E34+F34+G34 -> 19745365
A35: Mar - 2025 | B35: =D34 -> 19151493 | C35: =$B$20/$B$19 -> 383029.86 | D35: =B35-C35 -> 18768463 | E35: =H34 -> 19745365 | F35: =-$B$17 -> -460978 | G35: =(E35+F35)*$B$18 -> 125626.53 | H35: =E35+F35+G35 -> 19410014
A36: Apr - 2025 | B36: =D35 -> 18768463 | C36: =$B$20/$B$19 -> 383029.86 | D36: =B36-C36 -> 18385434 | E36: =H35 -> 19410014 | F36: =-$B$17 -> -460978 | G36: =(E36+F36)*$B$18 -> 123441.92 | H36: =E36+F36+G36 -> 19072478
A37: May - 2025 | B37: =D36 -> 18385434 | C37: =$B$20/$B$19 -> 383029.86 | D37: =B37-C37 -> 18002404 | E37: =H36 -> 19072478 | F37: =-$B$17 -> -460978 | G37: =(E37+F37)*$B$18 -> 121243.07 | H37: =E37+F37+G37 -> 18732743
... A84: Apr - 2029 | B84: =D83 -> 383029.86 | C84: =$B$20/$B$19 -> 383029.86 | D84: =B84-C84 -> -7.9162419e-09 | E84: =H83 -> 460978 | F84: =-$B$17 -> -460978 | G84: =(E84+F84)*$B$18 -> -5.6271641e-10 | H84: =E84+F84+G84 -> -8.6942885e-08

Sheet ITC-64754
A1: =Scope!#REF! -> #REF!
A2: =Scope!#REF! -> #REF!
A3: =Scope!#REF! -> #REF!
A6: =Scope!A2 -> Purpose
A7: To verify the lease working of the sample selected
A10: Summary
A12: Particulars | B12: Discount Rate | C12: Commencement Date | D12: Expiration Date | E12: Addition during FY 2025-26 | F12: Amortisation during FY 2025-26 | G12: Closing WDV | H12: Interest | I12: Repayment | J12: Closing Balance | K12: ST | L12: LT
A13: As per Lease Report | B13: 0.078173 | C13: 45434 | D13: 47259 | F13: 4512463.3 | G13: 14168165 | H13: 1308650.6 | I13: 5430768 | J13: 14933615 | K13: 4456155.7 | L13: 10477460
A14: As per DHS Working | B14: 0.078173 | C14: 45434 | D14: 47259 | E14: 0 | F14: =SUM(C36:C47) -> 4512463.4 | G14: =D47 -> 13913429 | H14: =SUM(G36:G47) -> 1308650.6 | I14: =-SUM(F36:F47) -> 5430768 | J14: =H47 -> 14933615 | K14: =H47-H59 -> 4456155.7 | L14: =J14-K14 -> 10477460
A15: Difference | B15: =B13-B14 -> 0 | C15: =C13-C14 -> 0 | D15: =D13-D14 -> 0 | E15: =E13-E14 -> 0 | F15: =F13-F14 -> -0.033859078 | G15: =G13-G14 -> 254735.9 | H15: =H13-H14 -> -0.0080015003 | I15: =I13-I14 -> 0 | ... L15: =L13-L14 -> -0.0026046652
A17: Monthly Rent (In Advance) | B17: 452564 | C17: << As per agreement >>
A18: Monthly discount rate | B18: =B14/12 -> 0.0065144167 | C18: << Link >>
A19: No of Months | B19: =ROUND(((D14-C14)/30.5),0) -> 60 | C19: << Formula >>
A20: PV of rent payments | B20: =-PV(B18,B19,B17,,1) -> 22562317 | C20: << Formula >>
B23: Right of Use Asset | E23: Lease Liability
A24: From | B24: Opening WDV | C24: Depreciation | D24: Closing WDV | E24: Opening Liability | F24: Repayment | G24: Interest | H24: Closing Lease Liability
A25: May - 2024 | B25: =B20 -> 22562317 | C25: =$B$20/$B$19 -> 376038.61 | D25: =B25-C25 -> 22186278 | E25: =B25 -> 22562317 | F25: =-$B$17 -> -452564 | G25: =(E25+F25)*$B$18 -> 144032.14 | H25: =E25+F25+G25 -> 22253785
A26: Jun - 2024 | B26: =D25 -> 22186278 | C26: =$B$20/$B$19 -> 376038.61 | D26: =B26-C26 -> 21810240 | E26: =H25 -> 22253785 | F26: =-$B$17 -> -452564 | G26: =(E26+F26)*$B$18 -> 142022.24 | H26: =E26+F26+G26 -> 21943243
A27: Jul - 2024 | B27: =D26 -> 21810240 | C27: =$B$20/$B$19 -> 376038.61 | D27: =B27-C27 -> 21434201 | E27: =H26 -> 21943243 | F27: =-$B$17 -> -452564 | G27: =(E27+F27)*$B$18 -> 139999.24 | H27: =E27+F27+G27 -> 21630678
A28: Aug - 2024 | B28: =D27 -> 21434201 | C28: =$B$20/$B$19 -> 376038.61 | D28: =B28-C28 -> 21058162 | E28: =H27 -> 21630678 | F28: =-$B$17 -> -452564 | G28: =(E28+F28)*$B$18 -> 137963.06 | H28: =E28+F28+G28 -> 21316077
A29: Sep - 2024 | B29: =D28 -> 21058162 | C29: =$B$20/$B$19 -> 376038.61 | D29: =B29-C29 -> 20682124 | E29: =H28 -> 21316077 | F29: =-$B$17 -> -452564 | G29: =(E29+F29)*$B$18 -> 135913.62 | H29: =E29+F29+G29 -> 20999427
A30: Oct - 2024 | B30: =D29 -> 20682124 | C30: =$B$20/$B$19 -> 376038.61 | D30: =B30-C30 -> 20306085 | E30: =H29 -> 20999427 | F30: =-$B$17 -> -452564 | G30: =(E30+F30)*$B$18 -> 133850.83 | H30: =E30+F30+G30 -> 20680714
A31: Nov - 2024 | B31: =D30 -> 20306085 | C31: =$B$20/$B$19 -> 376038.61 | D31: =B31-C31 -> 19930046 | E31: =H30 -> 20680714 | F31: =-$B$17 -> -452564 | G31: =(E31+F31)*$B$18 -> 131774.6 | H31: =E31+F31+G31 -> 20359924
A32: Dec - 2024 | B32: =D31 -> 19930046 | C32: =$B$20/$B$19 -> 376038.61 | D32: =B32-C32 -> 19554008 | E32: =H31 -> 20359924 | F32: =-$B$17 -> -452564 | G32: =(E32+F32)*$B$18 -> 129684.84 | H32: =E32+F32+G32 -> 20037045
A33: Jan - 2025 | B33: =D32 -> 19554008 | C33: =$B$20/$B$19 -> 376038.61 | D33: =B33-C33 -> 19177969 | E33: =H32 -> 20037045 | F33: =-$B$17 -> -452564 | G33: =(E33+F33)*$B$18 -> 127581.47 | H33: =E33+F33+G33 -> 19712063
A34: Feb - 2025 | B34: =D33 -> 19177969 | C34: =$B$20/$B$19 -> 376038.61 | D34: =B34-C34 -> 18801931 | E34: =H33 -> 19712063 | F34: =-$B$17 -> -452564 | G34: =(E34+F34)*$B$18 -> 125464.4 | H34: =E34+F34+G34 -> 19384963
A35: Mar - 2025 | B35: =D34 -> 18801931 | C35: =$B$20/$B$19 -> 376038.61 | D35: =B35-C35 -> 18425892 | E35: =H34 -> 19384963 | F35: =-$B$17 -> -452564 | G35: =(E35+F35)*$B$18 -> 123333.54 | H35: =E35+F35+G35 -> 19055733
A36: Apr - 2025 | B36: =D35 -> 18425892 | C36: =$B$20/$B$19 -> 376038.61 | D36: =B36-C36 -> 18049853 | E36: =H35 -> 19055733 | F36: =-$B$17 -> -452564 | G36: =(E36+F36)*$B$18 -> 121188.79 | H36: =E36+F36+G36 -> 18724358
A37: May - 2025 | B37: =D36 -> 18049853 | C37: =$B$20/$B$19 -> 376038.61 | D37: =B37-C37 -> 17673815 | E37: =H36 -> 18724358 | F37: =-$B$17 -> -452564 | G37: =(E37+F37)*$B$18 -> 119030.08 | H37: =E37+F37+G37 -> 18390824
... A84: Apr - 2029 | B84: =D83 -> 376038.61 | C84: =$B$20/$B$19 -> 376038.61 | D84: =B84-C84 -> -2.0605512e-08 | E84: =H83 -> 452564 | F84: =-$B$17 -> -452564 | G84: =(E84+F84)*$B$18 -> -5.6688749e-10 | H84: =E84+F84+G84 -> -8.7587341e-08

Sheet ITC-62007
A1: =Scope!#REF! -> #REF!
A2: =Scope!#REF! -> #REF!
A3: =Scope!#REF! -> #REF!
A6: =Scope!A2 -> Purpose
A7: To verify the lease working of the sample selected
A10: Summary
A12: Particulars | B12: Discount Rate | C12: Commencement Date | D12: Expiration Date | E12: Addition during FY 2025-26 | F12: Amortisation during FY 2025-26 | G12: Closing WDV | H12: Interest | I12: Repayment | J12: Closing Balance | K12: ST | L12: LT
A13: As per Lease Report | B13: =7.737238% -> 0.07737238 | C13: 45108 | D13: 46203 | E13: 0 | F13: 18101143 | G13: 4525285.7 | H13: 940580.04 | I13: 20081652 | J13: 5020413 | K13: 5020413 | L13: 0
A14: As per DHS Working | B14: 0.07737238 | C14: 45108 | D14: 46203 | E14: 0 | F14: =SUM(C32:C35) -> 18112846 | G14: =D35 -> 4528211.4 | H14: =SUM(G32:G35) -> 934768.43 | I14: =SUM(F32:F35) -> -20081652 | J14: =H35 -> 5020413 | K14: =J14 -> 5020413 | L14: 0
A15: Difference | B15: =B13-B14 -> 0 | C15: =C13-C14 -> 0 | D15: =D13-D14 -> 0 | E15: =E13-E14 -> 0 | F15: =F13-F14 -> -11702.195 | G15: =G13-G14 -> -2925.7188 | H15: =H13-H14 -> 5811.6136 | I15: =I13+I14 -> 0 | J15: =J13-J14 -> 0.020000267 | K15: =K13-K14 -> 0.020000267 | L15: =L13-L14 -> 0
A17: Quarterly Rent (In Advance) | B17: 5020413 | C17: << As per agreement >>
A18: Quarterly discount rate | B18: =B14/4 -> 0.019343095 | C18: << Link >>
A19: No of Quarters | B19: =ROUND(((D14-C14)/30.5),0)/3 -> 12 | C19: << Formula >>
A20: PV of rent payments | B20: =-PV(B18,B19,B17,,1) -> 54338537 | C20: << Formula >>
B23: Right of Use Asset | E23: Lease Liability
A24: From | B24: Opening WDV | C24: Depreciation | D24: Closing WDV | E24: Opening Liability | F24: Repayment | G24: Interest | H24: Closing Lease Liability
A25: 45108 | B25: =B20 -> 54338537 | C25: =$B$20/$B$19 -> 4528211.4 | D25: =B25-C25 -> 49810325 | E25: =B25 -> 54338537 | F25: =-$B$17 -> -5020413 | G25: =(E25+F25)*$B$18 -> 953965.16 | H25: =E25+F25+G25 -> 50272089
A26: 45200 | B26: =D25 -> 49810325 | C26: =$B$20/$B$19 -> 4528211.4 | D26: =B26-C26 -> 45282114 | E26: =H25 -> 50272089 | F26: =-$B$17 -> -5020413 | G26: =(E26+F26)*$B$18 -> 875307.47 | H26: =E26+F26+G26 -> 46126984
A27: 45292 | B27: =D26 -> 45282114 | C27: =$B$20/$B$19 -> 4528211.4 | D27: =B27-C27 -> 40753903 | E27: =H26 -> 46126984 | F27: =-$B$17 -> -5020413 | G27: =(E27+F27)*$B$18 -> 795128.3 | H27: =E27+F27+G27 -> 41901699
A28: 45383 | B28: =D27 -> 40753903 | C28: =$B$20/$B$19 -> 4528211.4 | D28: =B28-C28 -> 36225691 | E28: =H27 -> 41901699 | F28: =-$B$17 -> -5020413 | G28: =(E28+F28)*$B$18 -> 713398.22 | H28: =E28+F28+G28 -> 37594684
A29: 45474 | B29: =D28 -> 36225691 | C29: =$B$20/$B$19 -> 4528211.4 | D29: =B29-C29 -> 31697480 | E29: =H28 -> 37594684 | F29: =-$B$17 -> -5020413 | G29: =(E29+F29)*$B$18 -> 630087.22 | H29: =E29+F29+G29 -> 33204358
A30: 45566 | B30: =D29 -> 31697480 | C30: =$B$20/$B$19 -> 4528211.4 | D30: =B30-C30 -> 27169268 | E30: =H29 -> 33204358 | F30: =-$B$17 -> -5020413 | G30: =(E30+F30)*$B$18 -> 545164.73 | H30: =E30+F30+G30 -> 28729110
A31: 45658 | B31: =D30 -> 27169268 | C31: =$B$20/$B$19 -> 4528211.4 | D31: =B31-C31 -> 22641057 | E31: =H30 -> 28729110 | F31: =-$B$17 -> -5020413 | G31: =(E31+F31)*$B$18 -> 458599.58 | H31: =E31+F31+G31 -> 24167297
A32: 45748 | B32: =D31 -> 22641057 | C32: =$B$20/$B$19 -> 4528211.4 | D32: =B32-C32 -> 18112846 | E32: =H31 -> 24167297 | F32: =-$B$17 -> -5020413 | G32: =(E32+F32)*$B$18 -> 370359.99 | H32: =E32+F32+G32 -> 19517244
A33: 45839 | B33: =D32 -> 18112846 | C33: =$B$20/$B$19 -> 4528211.4 | D33: =B33-C33 -> 13584634 | E33: =H32 -> 19517244 | F33: =-$B$17 -> -5020413 | G33: =(E33+F33)*$B$18 -> 280413.57 | H33: =E33+F33+G33 -> 14777244
A34: 45931 | B34: =D33 -> 13584634 | C34: =$B$20/$B$19 -> 4528211.4 | D34: =B34-C34 -> 9056422.8 | E34: =H33 -> 14777244 | F34: =-$B$17 -> -5020413 | G34: =(E34+F34)*$B$18 -> 188727.31 | H34: =E34+F34+G34 -> 9945558.4
A35: 46023 | B35: =D34 -> 9056422.8 | C35: =$B$20/$B$19 -> 4528211.4 | D35: =B35-C35 -> 4528211.4 | E35: =H34 -> 9945558.4 | F35: =-$B$17 -> -5020413 | G35: =(E35+F35)*$B$18 -> 95267.556 | H35: =E35+F35+G35 -> 5020413
A36: 46113 | B36: =D35 -> 4528211.4 | C36: =$B$20/$B$19 -> 4528211.4 | D36: =B36-C36 -> 1.4901161e-08 | E36: =H35 -> 5020413 | F36: =-$B$17 -> -5020413 | G36: =(E36+F36)*$B$18 -> -5.1702077e-09 | H36: =E36+F36+G36 -> -2.7245979e-07

Sheet ITC- 60756
A1: =Scope!#REF! -> #REF!
A2: =Scope!#REF! -> #REF!
A3: =Scope!#REF! -> #REF!
A6: =Scope!A2 -> Purpose
A7: To verify the lease working of the sample selected
A10: Summary
A12: Particulars | B12: Discount Rate | C12: Commencement Date | D12: Expiration Date | E12: Addition during FY 2025-26 | F12: Amortisation during FY 2025-26 | G12: Closing WDV | H12: Interest | I12: Repayment | J12: Closing Balance | K12: ST | L12: LT
A13: As per Lease Report | B13: 0.07638641 | C13: 45047 | D13: 46142 | E13: 0 | F13: 24031682 | G13: 2002640.1 | H13: 907404.52 | I13: 26626668 | J13: 0 | K13: 0 | L13: ='Details 25-26'!U86 -> 0
A14: As per DHS Working | B14: 0.07737238 | C14: 45047 | D14: 46142 | E14: 0 | F14: =(C32*1/3)+SUM(C33:C35)+(C36*2/3) -> 24016188 | G14: =D35*1/3 -> 2001349 | H14: =(G32*1/3)+SUM(G33:G35)+(G36*2/3) -> 912049.81 | I14: =(F32*1/3)+SUM(F33:F35)+(F36*2/3) -> -26626668 | J14: =H36 -> -3.5125478e-07 | K14: =J14 -> -3.5125478e-07 | L14: 0
A15: Difference | B15: =B13-B14 -> -0.00098597 | C15: =C13-C14 -> 0 | D15: =D13-D14 -> 0 | E15: =E13-E14 -> 0 | F15: =F13-F14 -> 15493.685 | G15: =G13-G14 -> 1291.1504 | H15: =H13-H14 -> -4645.2914 | I15: =I13+I14 -> 0 | J15: =J13-J14 -> 3.5125478e-07 | K15: =K13-K14 -> 3.5125478e-07 | L15: =L13-L14 -> 0
A17: Quarterly Rent (In Advance) | B17: 6656667 | C17: << As per agreement >>
A18: Quarterly discount rate | B18: =B14/4 -> 0.019343095 | C18: << Link >>
A19: No of Quarters | B19: =ROUND(((D14-C14)/30.5),0)/3 -> 12 | C19: << Formula >>
A20: PV of rent payments | B20: =-PV(B18,B19,B17,,1) -> 72048564 | C20: << Formula >>
B23: Right of Use Asset | E23: Lease Liability
A24: From | B24: Opening WDV | C24: Depreciation | D24: Closing WDV | E24: Opening Liability | F24: Repayment | G24: Interest | H24: Closing Lease Liability
A25: 45047 | B25: =B20 -> 72048564 | C25: =$B$20/$B$19 -> 6004047 | D25: =B25-C25 -> 66044517 | E25: =B25 -> 72048564 | F25: =-$B$17 -> -6656667 | G25: =(E25+F25)*$B$18 -> 1264881.7 | H25: =E25+F25+G25 -> 66656778
A26: 45139 | B26: =D25 -> 66044517 | C26: =$B$20/$B$19 -> 6004047 | D26: =B26-C26 -> 60040470 | E26: =H25 -> 66656778 | F26: =-$B$17 -> -6656667 | G26: =(E26+F26)*$B$18 -> 1160587.9 | H26: =E26+F26+G26 -> 61160699
A27: 45231 | B27: =D26 -> 60040470 | C27: =$B$20/$B$19 -> 6004047 | D27: =B27-C27 -> 54036423 | E27: =H26 -> 61160699 | F27: =-$B$17 -> -6656667 | G27: =(E27+F27)*$B$18 -> 1054276.7 | H27: =E27+F27+G27 -> 55558309
A28: 45323 | B28: =D27 -> 54036423 | C28: =$B$20/$B$19 -> 6004047 | D28: =B28-C28 -> 48032376 | E28: =H27 -> 55558309 | F28: =-$B$17 -> -6656667 | G28: =(E28+F28)*$B$18 -> 945909.1 | H28: =E28+F28+G28 -> 49847551
A29: 45778 | B29: =D28 -> 48032376 | C29: =$B$20/$B$19 -> 6004047 | D29: =B29-C29 -> 42028329 | E29: =H28 -> 49847551 | F29: =-$B$17 -> -6656667 | G29: =(E29+F29)*$B$18 -> 835445.37 | H29: =E29+F29+G29 -> 44026329
A30: 45870 | B30: =D29 -> 42028329 | C30: =$B$20/$B$19 -> 6004047 | D30: =B30-C30 -> 36024282 | E30: =H29 -> 44026329 | F30: =-$B$17 -> -6656667 | G30: =(E30+F30)*$B$18 -> 722844.93 | H30: =E30+F30+G30 -> 38092507
A31: 45962 | B31: =D30 -> 36024282 | C31: =$B$20/$B$19 -> 6004047 | D31: =B31-C31 -> 30020235 | E31: =H30 -> 38092507 | F31: =-$B$17 -> -6656667 | G31: =(E31+F31)*$B$18 -> 608066.44 | H31: =E31+F31+G31 -> 32043907
A32: 46054 | B32: =D31 -> 30020235 | C32: =$B$20/$B$19 -> 6004047 | D32: =B32-C32 -> 24016188 | E32: =H31 -> 32043907 | F32: =-$B$17 -> -6656667 | G32: =(E32+F32)*$B$18 -> 491067.79 | H32: =E32+F32+G32 -> 25878307
A33: 46143 | B33: =D32 -> 24016188 | C33: =$B$20/$B$19 -> 6004047 | D33: =B33-C33 -> 18012141 | E33: =H32 -> 25878307 | F33: =-$B$17 -> -6656667 | G33: =(E33+F33)*$B$18 -> 371806.02 | H33: =E33+F33+G33 -> 19593446
A34: 46235 | B34: =D33 -> 18012141 | C34: =$B$20/$B$19 -> 6004047 | D34: =B34-C34 -> 12008094 | E34: =H33 -> 19593446 | F34: =-$B$17 -> -6656667 | G34: =(E34+F34)*$B$18 -> 250237.35 | H34: =E34+F34+G34 -> 13187017
A35: 46327 | B35: =D34 -> 12008094 | C35: =$B$20/$B$19 -> 6004047 | D35: =B35-C35 -> 6004047 | E35: =H34 -> 13187017 | F35: =-$B$17 -> -6656667 | G35: =(E35+F35)*$B$18 -> 126317.18 | H35: =E35+F35+G35 -> 6656667
A36: 46419 | B36: =D35 -> 6004047 | C36: =$B$20/$B$19 -> 6004047 | D36: =B36-C36 -> 9.3132257e-09 | E36: =H35 -> 6656667 | F36: =-$B$17 -> -6656667 | G36: =(E36+F36)*$B$18 -> -6.6654246e-09 | H36: =E36+F36+G36 -> -3.5125478e-07

Sheet ITC- 59268
A1: =Scope!#REF! -> #REF!
A2: =Scope!#REF! -> #REF!
A3: =Scope!#REF! -> #REF!
A6: =Scope!A2 -> Purpose
A7: To verify the lease working of the sample selected
A10: Summary
A12: Particulars | B12: Discount Rate | C12: Commencement Date | D12: Expiration Date | E12: Addition during FY 2025-26 | F12: Amortisation during FY 2025-26 | G12: Closing WDV | H12: Interest | I12: Repayment | J12: Closing Balance | K12: ST | L12: LT
A13: As per Lease Report | B13: 0.07353162 | C13: 44896 | D13: 45991 | E13: 0 | F13: 32928959 | G13: 0 | H13: 575157.9 | I13: 27241594 | J13: 0 | K13: 0 | L13: ='Details 25-26'!U86 -> 0
A14: As per DHS Working | B14: 0.07353162 | C14: 44896 | D14: 45991 | E14: 0 | F14: =(C34*2/3)+C35+C36 -> 32924448 | G14: =D36*1/3 -> 0 | H14: =(G34*2/3)+G35+G36 -> 570737.88 | I14: =F35+F36 -> -27241594 | J14: =H36 -> -4.6663395e-07 | K14: =J14 -> -4.6663395e-07 | L14: 0
A15: Difference | B15: =B13-B14 -> 0 | C15: =C13-C14 -> 0 | D15: =D13-D14 -> 0 | E15: =E13-E14 -> 0 | F15: =F13-F14 -> 4511.0654 | G15: =G13-G14 -> 0 | H15: =H13-H14 -> 4420.0167 | I15: =I13+I14 -> 0 | J15: =J13-J14 -> 4.6663395e-07 | K15: =K13-K14 -> 4.6663395e-07 | L15: =L13-L14 -> 0
A17: Quarterly Rent (In Advance) | B17: 13620797 | C17: << As per agreement >>
A18: Quarterly discount rate | B18: =B14/4 -> 0.018382905 | C18: << Link >>
A19: No of Quarters | B19: =ROUND(((D14-C14)/30.5),0)/3 -> 12 | C19: << Formula >>
A20: PV of rent payments | B20: =-PV(B18,B19,B17,,1) -> 1.4816002e+08 | C20: << Formula >>
B23: Right of Use Asset | E23: Lease Liability
A24: From | B24: Opening WDV | C24: Depreciation | D24: Closing WDV | E24: Opening Liability | F24: Repayment | G24: Interest | H24: Closing Lease Liability
A25: 44896 | B25: =B20 -> 1.4816002e+08 | C25: =$B$20/$B$19 -> 12346668 | D25: =B25-C25 -> 1.3581335e+08 | E25: =B25 -> 1.4816002e+08 | F25: =-$B$17 -> -13620797 | G25: =(E25+F25)*$B$18 -> 2473221.7 | H25: =E25+F25+G25 -> 1.3701244e+08
A26: 44986 | B26: =D25 -> 1.3581335e+08 | C26: =$B$20/$B$19 -> 12346668 | D26: =B26-C26 -> 1.2346668e+08 | E26: =H25 -> 1.3701244e+08 | F26: =-$B$17 -> -13620797 | G26: =(E26+F26)*$B$18 -> 2268296.9 | H26: =E26+F26+G26 -> 1.2565994e+08
A27: 45078 | B27: =D26 -> 1.2346668e+08 | C27: =$B$20/$B$19 -> 12346668 | D27: =B27-C27 -> 1.1112001e+08 | E27: =H26 -> 1.2565994e+08 | F27: =-$B$17 -> -13620797 | G27: =(E27+F27)*$B$18 -> 2059604.9 | H27: =E27+F27+G27 -> 1.1409875e+08
A28: 45170 | B28: =D27 -> 1.1112001e+08 | C28: =$B$20/$B$19 -> 12346668 | D28: =B28-C28 -> 98773344 | E28: =H27 -> 1.1409875e+08 | F28: =-$B$17 -> -13620797 | G28: =(E28+F28)*$B$18 -> 1847076.6 | H28: =E28+F28+G28 -> 1.0232503e+08
A29: 45261 | B29: =D28 -> 98773344 | C29: =$B$20/$B$19 -> 12346668 | D29: =B29-C29 -> 86426676 | E29: =H28 -> 1.0232503e+08 | F29: =-$B$17 -> -13620797 | G29: =(E29+F29)*$B$18 -> 1630641.5 | H29: =E29+F29+G29 -> 90334873
A30: 45352 | B30: =D29 -> 86426676 | C30: =$B$20/$B$19 -> 12346668 | D30: =B30-C30 -> 74080008 | E30: =H29 -> 90334873 | F30: =-$B$17 -> -13620797 | G30: =(E30+F30)*$B$18 -> 1410227.6 | H30: =E30+F30+G30 -> 78124303
A31: 45444 | B31: =D30 -> 74080008 | C31: =$B$20/$B$19 -> 12346668 | D31: =B31-C31 -> 61733340 | E31: =H30 -> 78124303 | F31: =-$B$17 -> -13620797 | G31: =(E31+F31)*$B$18 -> 1185761.8 | H31: =E31+F31+G31 -> 65689268
A32: 45536 | B32: =D31 -> 61733340 | C32: =$B$20/$B$19 -> 12346668 | D32: =B32-C32 -> 49386672 | E32: =H31 -> 65689268 | F32: =-$B$17 -> -13620797 | G32: =(E32+F32)*$B$18 -> 957169.75 | H32: =E32+F32+G32 -> 53025641
A33: 45627 | B33: =D32 -> 49386672 | C33: =$B$20/$B$19 -> 12346668 | D33: =B33-C33 -> 37040004 | E33: =H32 -> 53025641 | F33: =-$B$17 -> -13620797 | G33: =(E33+F33)*$B$18 -> 724375.5 | H33: =E33+F33+G33 -> 40129219
A34: 45717 | B34: =D33 -> 37040004 | C34: =$B$20/$B$19 -> 12346668 | D34: =B34-C34 -> 24693336 | E34: =H33 -> 40129219 | F34: =-$B$17 -> -13620797 | G34: =(E34+F34)*$B$18 -> 487301.81 | H34: =E34+F34+G34 -> 26995724
A35: 45809 | B35: =D34 -> 24693336 | C35: =$B$20/$B$19 -> 12346668 | D35: =B35-C35 -> 12346668 | E35: =H34 -> 26995724 | F35: =-$B$17 -> -13620797 | G35: =(E35+F35)*$B$18 -> 245870.01 | H35: =E35+F35+G35 -> 13620797
A36: 45901 | B36: =D35 -> 12346668 | C36: =$B$20/$B$19 -> 12346668 | D36: =B36-C36 -> 0 | E36: =H35 -> 13620797 | F36: =-$B$17 -> -13620797 | G36: =(E36+F36)*$B$18 -> -8.4232439e-09 | H36: =E36+F36+G36 -> -4.6663395e-07

Sheet ITC- 53818
A1: =Scope!#REF! -> #REF!
A2: =Scope!#REF! -> #REF!
A3: =Scope!#REF! -> #REF!
A6: =Scope!A2 -> Purpose
A7: To verify the lease working of the sample selected
A10: Summary
A12: Particulars | B12: Discount Rate | C12: Commencement Date | D12: Expiration Date | E12: Addition during FY 2025-26 | F12: Amortisation during FY 2025-26 | G12: Closing WDV | H12: Interest | I12: Repayment | J12: Closing Balance | K12: ST | L12: LT
A13: As per Lease Report | B13: 0.07906689 | C13: 44562 | D13: 46387 | E13: 0 | F13: 24065686 | G13: 18049264 | H13: 2374434.6 | I13: 28060000 | J13: 20637101 | K13: 20637101 | L13: ='Details 25-26'!U86 -> 0
A14: As per DHS Working | B14: 0.07906689 | C14: 44562 | D14: 46387 | E14: 0 | F14: =SUM(C38:C41) -> 23447282 | G14: =D41 -> 17585461 | H14: =SUM(G38:G41) -> 2359717.5 | I14: =-SUM(F38:F41) -> 28060000 | J14: =H41 -> 20639708 | K14: =J14 -> 20639708 | L14: 0
A15: Difference | B15: =B13-B14 -> 0 | C15: =C13-C14 -> 0 | D15: =D13-D14 -> 0 | E15: =E13-E14 -> 0 | F15: =F13-F14 -> 618404.21 | G15: =G13-G14 -> 463803.06 | H15: =H13-H14 -> 14717.111 | I15: =I13-I14 -> 0 | ... L15: =L13-L14 -> 0
A17: Quarterly Rent (In Advance) | B17: 7015000 | C17: << As per agreement >>
A18: Quarterly discount rate | B18: =B14/4 -> 0.019766723 | C18: << Link >>
A19: No of Quarters | B19: =ROUND(((D14-C14)/30.5),0)/3 -> 20 | C19: << Formula >>
A20: PV of rent payments | B20: =-PV(B18,B19,B17,,1) -> 1.1723641e+08 | C20: << Formula >>
B23: Right of Use Asset | E23: Lease Liability
A24: From | B24: Opening WDV | C24: Depreciation | D24: Closing WDV | E24: Opening Liability | F24: Repayment | G24: Interest | H24: Closing Lease Liability
A25: 44562 | B25: =B20 -> 1.1723641e+08 | C25: =$B$20/$B$19 -> 5861820.4 | D25: =B25-C25 -> 1.1137459e+08 | E25: =B25 -> 1.1723641e+08 | F25: =-$B$17 -> -7015000 | G25: =(E25+F25)*$B$18 -> 2178716 | H25: =E25+F25+G25 -> 1.1240012e+08
A26: 44652 | B26: =D25 -> 1.1137459e+08 | C26: =$B$20/$B$19 -> 5861820.4 | D26: =B26-C26 -> 1.0551277e+08 | E26: =H25 -> 1.1240012e+08 | F26: =-$B$17 -> -7015000 | G26: =(E26+F26)*$B$18 -> 2083118.5 | H26: =E26+F26+G26 -> 1.0746824e+08
A27: 44743 | B27: =D26 -> 1.0551277e+08 | C27: =$B$20/$B$19 -> 5861820.4 | D27: =B27-C27 -> 99650947 | E27: =H26 -> 1.0746824e+08 | F27: =-$B$17 -> -7015000 | G27: =(E27+F27)*$B$18 -> 1985631.4 | H27: =E27+F27+G27 -> 1.0243887e+08
A28: 44835 | B28: =D27 -> 99650947 | C28: =$B$20/$B$19 -> 5861820.4 | D28: =B28-C28 -> 93789127 | E28: =H27 -> 1.0243887e+08 | F28: =-$B$17 -> -7015000 | G28: =(E28+F28)*$B$18 -> 1886217.3 | H28: =E28+F28+G28 -> 97310092
A29: 44927 | B29: =D28 -> 93789127 | C29: =$B$20/$B$19 -> 5861820.4 | D29: =B29-C29 -> 87927307 | E29: =H28 -> 97310092 | F29: =-$B$17 -> -7015000 | G29: =(E29+F29)*$B$18 -> 1784838 | H29: =E29+F29+G29 -> 92079930
A30: 45017 | B30: =D29 -> 87927307 | C30: =$B$20/$B$19 -> 5861820.4 | D30: =B30-C30 -> 82065486 | E30: =H29 -> 92079930 | F30: =-$B$17 -> -7015000 | G30: =(E30+F30)*$B$18 -> 1681454.9 | H30: =E30+F30+G30 -> 86746385
A31: 45108 | B31: =D30 -> 82065486 | C31: =$B$20/$B$19 -> 5861820.4 | D31: =B31-C31 -> 76203666 | E31: =H30 -> 86746385 | F31: =-$B$17 -> -7015000 | G31: =(E31+F31)*$B$18 -> 1576028.2 | H31: =E31+F31+G31 -> 81307413
A32: 45200 | B32: =D31 -> 76203666 | C32: =$B$20/$B$19 -> 5861820.4 | D32: =B32-C32 -> 70341845 | E32: =H31 -> 81307413 | F32: =-$B$17 -> -7015000 | G32: =(E32+F32)*$B$18 -> 1468517.5 | H32: =E32+F32+G32 -> 75760930
A33: 45292 | B33: =D32 -> 70341845 | C33: =$B$20/$B$19 -> 5861820.4 | D33: =B33-C33 -> 64480025 | E33: =H32 -> 75760930 | F33: =-$B$17 -> -7015000 | G33: =(E33+F33)*$B$18 -> 1358881.7 | H33: =E33+F33+G33 -> 70104812
A34: 45383 | B34: =D33 -> 64480025 | C34: =$B$20/$B$19 -> 5861820.4 | D34: =B34-C34 -> 58618204 | E34: =H33 -> 70104812 | F34: =-$B$17 -> -7015000 | G34: =(E34+F34)*$B$18 -> 1247078.8 | H34: =E34+F34+G34 -> 64336891
A35: 45474 | B35: =D34 -> 58618204 | C35: =$B$20/$B$19 -> 5861820.4 | D35: =B35-C35 -> 52756384 | E35: =H34 -> 64336891 | F35: =-$B$17 -> -7015000 | G35: =(E35+F35)*$B$18 -> 1133065.9 | H35: =E35+F35+G35 -> 58454957
A36: 45566 | B36: =D35 -> 52756384 | C36: =$B$20/$B$19 -> 5861820.4 | D36: =B36-C36 -> 46894564 | E36: =H35 -> 58454957 | F36: =-$B$17 -> -7015000 | G36: =(E36+F36)*$B$18 -> 1016799.4 | H36: =E36+F36+G36 -> 52456756
A37: 45658 | B37: =D36 -> 46894564 | C37: =$B$20/$B$19 -> 5861820.4 | D37: =B37-C37 -> 41032743 | E37: =H36 -> 52456756 | F37: =-$B$17 -> -7015000 | G37: =(E37+F37)*$B$18 -> 898234.59 | H37: =E37+F37+G37 -> 46339991
... A44: 46296 | B44: =D43 -> 5861820.4 | C44: =$B$20/$B$19 -> 5861820.4 | D44: =B44-C44 -> -2.4214387e-08 | E44: =H43 -> 7015000 | F44: =-$B$17 -> -7015000 | G44: =(E44+F44)*$B$18 -> -8.1552733e-09 | H44: =E44+F44+G44 -> -4.2073117e-07

Sheet Wind- Rent Alpha
A1: =Scope!#REF! -> #REF!
A2: =Scope!#REF! -> #REF!
A3: =Scope!#REF! -> #REF!
A6: =Scope!A2 -> Purpose
A7: To verify the lease working of the sample selected
A10: Summary
A12: Particulars | B12: Discount Rate | C12: Commencement Date | D12: Expiration Date | E12: Addition during FY 2025-26 | F12: Amortisation during FY 2025-26 | G12: Closing WDV | H12: Interest | I12: Repayment | J12: Closing Balance | K12: ST | L12: LT
A13: As per Lease Report | B13: 0.08 | C13: 44287 | D13: 46203 | E13: 0 | F13: 35727324 | G13: 8809477 | H13: 2835219 | I13: 33093224 | J13: 1957695.9 | K13: 1957695.9 | L13: 0
A14: As per DHS Working | C14: 44281 | D14: 46106 | E14: 0 | F14: =(D27*1/3)+SUM(D28:D30)+D31*2/3 -> 5518596 | G14: =E31+(D31*1/3) -> 11497075 | H14: =(H27*1/3)+SUM(H28:H30)+H31*2/3 -> 0 | I14: =-SUM(G28:G31) -> 5518596 | J14: =I31-(H31*1/3) -> 11037192 | K14: =J14-L14 -> 5518596 | L14: =I35-(H35/3) -> 5518596
A15: Difference | B15: =B13-B14 -> 0.08 | C15: =C13-C14 -> 6 | D15: =D13-D14 -> 97 | E15: =E13-E14 -> 0 | F15: =F13-F14 -> 30208728 | G15: =G13-G14 -> -2687598 | H15: =H13-H14 -> 2835219 | I15: =I13-I14 -> 27574628 | ... L15: =L13-L14 -> -5518596
A17: Quarterly Rent (In Advance) | B17: 1379649 | C17: << As per agreement >>
A18: Quarterly discount rate | B18: =B14/4 -> 0 | C18: << Link >>
A19: No of Quarters | B19: =60/4 -> 15 | C19: << Formula >>
A20: PV of rent payments | B20: =-PV(B18,B19,B17,,1) -> 20694735 | C20: << Formula >>
C23: Right of Use Asset | F23: Lease Liability
A24: From | B24: To | C24: Opening WDV | D24: Depreciation | E24: Closing WDV | F24: Opening Liability | G24: Repayment | H24: Interest | I24: Closing Lease Liability
A25: 45505 | B25: 45596 | C25: =B20 -> 20694735 | D25: =$B$20/$B$19 -> 1379649 | E25: =C25-D25 -> 19315086 | F25: =C25 -> 20694735 | G25: =-$B$17 -> -1379649 | H25: =(F25+G25)*$B$18 -> 0 | I25: =F25+G25+H25 -> 19315086
A26: 45597 | B26: 45688 | C26: =E25 -> 19315086 | D26: =$B$20/$B$19 -> 1379649 | E26: =C26-D26 -> 17935437 | F26: =I25 -> 19315086 | G26: =-$B$17 -> -1379649 | H26: =(F26+G26)*$B$18 -> 0 | I26: =F26+G26+H26 -> 17935437
A27: 45689 | B27: 45777 | C27: =E26 -> 17935437 | D27: =$B$20/$B$19 -> 1379649 | E27: =C27-D27 -> 16555788 | F27: =I26 -> 17935437 | G27: =-$B$17 -> -1379649 | H27: =(F27+G27)*$B$18 -> 0 | I27: =F27+G27+H27 -> 16555788
A28: 45778 | B28: 45869 | C28: =E27 -> 16555788 | D28: =$B$20/$B$19 -> 1379649 | E28: =C28-D28 -> 15176139 | F28: =I27 -> 16555788 | G28: =-$B$17 -> -1379649 | H28: =(F28+G28)*$B$18 -> 0 | I28: =F28+G28+H28 -> 15176139
A29: 45870 | B29: 45961 | C29: =E28 -> 15176139 | D29: =$B$20/$B$19 -> 1379649 | E29: =C29-D29 -> 13796490 | F29: =I28 -> 15176139 | G29: =-$B$17 -> -1379649 | H29: =(F29+G29)*$B$18 -> 0 | I29: =F29+G29+H29 -> 13796490
A30: 45962 | B30: 46053 | C30: =E29 -> 13796490 | D30: =$B$20/$B$19 -> 1379649 | E30: =C30-D30 -> 12416841 | F30: =I29 -> 13796490 | G30: =-$B$17 -> -1379649 | H30: =(F30+G30)*$B$18 -> 0 | I30: =F30+G30+H30 -> 12416841
A31: 46054 | B31: 46142 | C31: =E30 -> 12416841 | D31: =$B$20/$B$19 -> 1379649 | E31: =C31-D31 -> 11037192 | F31: =I30 -> 12416841 | G31: =-$B$17 -> -1379649 | H31: =(F31+G31)*$B$18 -> 0 | I31: =F31+G31+H31 -> 11037192
A32: 46143 | B32: 46234 | C32: =E31 -> 11037192 | D32: =$B$20/$B$19 -> 1379649 | E32: =C32-D32 -> 9657543 | F32: =I31 -> 11037192 | G32: =-$B$17 -> -1379649 | H32: =(F32+G32)*$B$18 -> 0 | I32: =F32+G32+H32 -> 9657543
A33: 46235 | B33: 46326 | C33: =E32 -> 9657543 | D33: =$B$20/$B$19 -> 1379649 | E33: =C33-D33 -> 8277894 | F33: =I32 -> 9657543 | G33: =-$B$17 -> -1379649 | H33: =(F33+G33)*$B$18 -> 0 | I33: =F33+G33+H33 -> 8277894
A34: 46327 | B34: 46418 | C34: =E33 -> 8277894 | D34: =$B$20/$B$19 -> 1379649 | E34: =C34-D34 -> 6898245 | F34: =I33 -> 8277894 | G34: =-$B$17 -> -1379649 | H34: =(F34+G34)*$B$18 -> 0 | I34: =F34+G34+H34 -> 6898245
A35: 46419 | B35: 46507 | C35: =E34 -> 6898245 | D35: =$B$20/$B$19 -> 1379649 | E35: =C35-D35 -> 5518596 | F35: =I34 -> 6898245 | G35: =-$B$17 -> -1379649 | H35: =(F35+G35)*$B$18 -> 0 | I35: =F35+G35+H35 -> 5518596
A36: 46508 | B36: 46599 | C36: =E35 -> 5518596 | D36: =$B$20/$B$19 -> 1379649 | E36: =C36-D36 -> 4138947 | F36: =I35 -> 5518596 | G36: =-$B$17 -> -1379649 | H36: =(F36+G36)*$B$18 -> 0 | I36: =F36+G36+H36 -> 4138947

Sheet OCL 64418-1
A6: =[4]Scope!A5 -> Purpose
A7: To verify the lease working of the sample selected
A10: Summary
A12: Particulars | B12: Discount Rate | C12: Commencement Date* | D12: Expiration Date | E12: Addition during FY 2025-26 | F12: Amortisation during FY 2025-26 | G12: Closing WDV | H12: Interest | I12: Repayment | J12: Closing Balance | K12: ST | L12: LT
A13: As per Lease Report | B13: 0.07485 | C13: 45383 | D13: 47162 | E13: 0 | F13: 28751660 | G13: 82575451 | H13: 8154950.2 | I13: 34237688 | J13: 97421626 | K13: 32988176 | L13: 64433450
A14: As per DHS Working | B14: ='G Sec 1 Apr'!C25/100 -> 0.072 | C14: 45383 | D14: 47162 | F14: =SUM(G37:G48) -> 30223485 | G14: =H48 -> 86458985 | H14: =SUM(K37:K48) -> 7865842.4 | I14: =SUM(J37:J48) -> -34237688 | J14: =L48 -> 97566640 | K14: =-(L61-L49) -> 30444758 | L14: =J14-K14 -> 67121883
A15: Difference | B15: =B13-B14 -> 0.00285 | C15: =C13-C14 -> 0 | D15: =D13-D14 -> 0 | E15: =E13-E14 -> 0 | F15: =F13-F14 -> -1471825.2 | G15: =G13-G14 -> -3883534.5 | H15: =H13-H14 -> 289107.87 | I15: =SUM(I13:I14) -> 0 | J15: =J13-J14 -> -145014.15 | K15: =K13-K14 -> 2543418.1 | L15: =L13-L14 -> -2688432.3
A16: *The ROU asset was created on 1 April 2024
A18: Monthly Rent | B18: 2700000 | C18: << As per agreement >>
A19: Monthly discount rate | B19: =B14/365 -> 0.00019726027 | C19: << Link >>
A20: No of Months | B20: =(D14-C14)/30.5 -> 58.327869 | C20: << Formula >>
A21: PV of rent payments | B21: =SUM(D25:D83) -> 1.4690595e+08 | C21: << Formula >>
A23: Calculation of PV of lease payments | F23: Right of Use Asset | I23: Lease Liability
A24: Date | B24: Cumulative Days | C24: Lease payments | D24: PV of Lease payments | F24: Opening Balance | G24: Depreciation | H24: Closing Balance | I24: Opening Liability | J24: Repayment | K24: Interest | L24: Closing Lease Liability
A25: 45383 | B25: 1 | C25: 2700000 | D25: =-PV($B$19,B25,,C25,1) -> 2699467.5 | F25: =B21 -> 1.4690595e+08 | G25: =$F$25/$B$20 -> 2518623.7 | H25: =F25-G25 -> 1.4438733e+08 | I25: =F25 -> 1.4690595e+08 | J25: =-C25 -> -2700000 | K25: =SUM(I25:J25)*$B$14/12 -> 865235.73 | L25: =SUM(I25:K25) -> 1.4507119e+08
A26: 45413 | B26: =A26-$A$25+1 -> 31 | C26: 2700000 | D26: =-PV($B$19,B26,,C26,1) -> 2683541.3 | F26: =H25 -> 1.4438733e+08 | G26: =$F$25/$B$20 -> 2518623.7 | H26: =F26-G26 -> 1.4186871e+08 | I26: =L25 -> 1.4507119e+08 | J26: =-C26 -> -2700000 | K26: =SUM(I26:J26)*$B$14/12 -> 854227.14 | L26: =SUM(I26:K26) -> 1.4322542e+08
A27: 45444 | B27: =A27-$A$25+1 -> 62 | C27: 2700000 | D27: =-PV($B$19,B27,,C27,1) -> 2667183 | F27: =H26 -> 1.4186871e+08 | G27: =$F$25/$B$20 -> 2518623.7 | H27: =F27-G27 -> 1.3935008e+08 | I27: =L26 -> 1.4322542e+08 | J27: =-C27 -> -2700000 | K27: =SUM(I27:J27)*$B$14/12 -> 843152.5 | L27: =SUM(I27:K27) -> 1.4136857e+08
A28: 45474 | B28: =A28-$A$25+1 -> 92 | C28: 2700000 | D28: =-PV($B$19,B28,,C28,1) -> 2651447.2 | F28: =H27 -> 1.3935008e+08 | G28: =$F$25/$B$20 -> 2518623.7 | H28: =F28-G28 -> 1.3683146e+08 | I28: =L27 -> 1.4136857e+08 | J28: =-C28 -> -2700000 | K28: =SUM(I28:J28)*$B$14/12 -> 832011.42 | L28: =SUM(I28:K28) -> 1.3950058e+08
A29: 45505 | B29: =A29-$A$25+1 -> 123 | C29: 2700000 | D29: =-PV($B$19,B29,,C29,1) -> 2635284.5 | F29: =H28 -> 1.3683146e+08 | G29: =$F$25/$B$20 -> 2518623.7 | H29: =F29-G29 -> 1.3431284e+08 | I29: =L28 -> 1.3950058e+08 | J29: =-C29 -> -2700000 | K29: =SUM(I29:J29)*$B$14/12 -> 820803.49 | L29: =SUM(I29:K29) -> 1.3762138e+08
A30: 45536 | B30: =A30-$A$25+1 -> 154 | C30: 2700000 | D30: =-PV($B$19,B30,,C30,1) -> 2619220.3 | F30: =H29 -> 1.3431284e+08 | G30: =$F$25/$B$20 -> 2518623.7 | H30: =F30-G30 -> 1.3179421e+08 | I30: =L29 -> 1.3762138e+08 | J30: =-C30 -> -2700000 | K30: =SUM(I30:J30)*$B$14/12 -> 809528.31 | L30: =SUM(I30:K30) -> 1.3573091e+08
A31: 45566 | B31: =A31-$A$25+1 -> 184 | C31: 2700000 | D31: =-PV($B$19,B31,,C31,1) -> 2603767.6 | F31: =H30 -> 1.3179421e+08 | G31: =$F$25/$B$20 -> 2518623.7 | H31: =F31-G31 -> 1.2927559e+08 | I31: =L30 -> 1.3573091e+08 | J31: =-C31 -> -2700000 | K31: =SUM(I31:J31)*$B$14/12 -> 798185.48 | L31: =SUM(I31:K31) -> 1.338291e+08
A32: 45597 | B32: =A32-$A$25+1 -> 215 | C32: 2700000 | D32: =-PV($B$19,B32,,C32,1) -> 2587895.5 | F32: =H31 -> 1.2927559e+08 | G32: =$F$25/$B$20 -> 2518623.7 | H32: =F32-G32 -> 1.2675696e+08 | I32: =L31 -> 1.338291e+08 | J32: =-C32 -> -2700000 | K32: =SUM(I32:J32)*$B$14/12 -> 786774.59 | L32: =SUM(I32:K32) -> 1.3191587e+08
A33: 45627 | B33: =A33-$A$25+1 -> 245 | C33: 2700000 | D33: =-PV($B$19,B33,,C33,1) -> 2572627.6 | F33: =H32 -> 1.2675696e+08 | G33: =$F$25/$B$20 -> 2518623.7 | H33: =F33-G33 -> 1.2423834e+08 | I33: =L32 -> 1.3191587e+08 | J33: =-C33 -> -2700000 | K33: =SUM(I33:J33)*$B$14/12 -> 775295.24 | L33: =SUM(I33:K33) -> 1.2999117e+08
A34: 45658 | B34: =A34-$A$25+1 -> 276 | C34: 2700000 | D34: =-PV($B$19,B34,,C34,1) -> 2556945.3 | F34: =H33 -> 1.2423834e+08 | G34: =$F$25/$B$20 -> 2518623.7 | H34: =F34-G34 -> 1.2171972e+08 | I34: =L33 -> 1.2999117e+08 | J34: =-C34 -> -2700000 | K34: =SUM(I34:J34)*$B$14/12 -> 763747.01 | L34: =SUM(I34:K34) -> 1.2805492e+08
A35: 45689 | B35: =A35-$A$25+1 -> 307 | C35: =C34*13/28+C36*15/28 -> 2772321.4 | D35: =-PV($B$19,B35,,C35,1) -> 2609430.8 | F35: =H34 -> 1.2171972e+08 | G35: =$F$25/$B$20 -> 2518623.7 | H35: =F35-G35 -> 1.1920109e+08 | I35: =L34 -> 1.2805492e+08 | J35: =-C35 -> -2772321.4 | K35: =SUM(I35:J35)*$B$14/12 -> 751695.56 | L35: =SUM(I35:K35) -> 1.2603429e+08
A36: 45717 | B36: =A36-$A$25+1 -> 335 | C36: 2835000 | D36: =-PV($B$19,B36,,C36,1) -> 2653730.2 | F36: =H35 -> 1.1920109e+08 | G36: =$F$25/$B$20 -> 2518623.7 | H36: =F36-G36 -> 1.1668247e+08 | I36: =L35 -> 1.2603429e+08 | J36: =-C36 -> -2835000 | K36: =SUM(I36:J36)*$B$14/12 -> 739195.74 | L36: =SUM(I36:K36) -> 1.2393849e+08
A37: 45748 | B37: =A37-$A$25+1 -> 366 | C37: 2835000 | D37: =-PV($B$19,B37,,C37,1) -> 2637553.5 | F37: =H36 -> 1.1668247e+08 | G37: =$F$25/$B$20 -> 2518623.7 | H37: =F37-G37 -> 1.1416385e+08 | I37: =L36 -> 1.2393849e+08 | J37: =-C37 -> -2835000 | K37: =SUM(I37:J37)*$B$14/12 -> 726620.91 | L37: =SUM(I37:K37) -> 1.2183011e+08
A38: 45778 | B38: =A38-$A$25+1 -> 396 | C38: 2835000 | D38: =-PV($B$19,B38,,C38,1) -> 2621992.6 | F38: =H37 -> 1.1416385e+08 | G38: =$F$25/$B$20 -> 2518623.7 | H38: =F38-G38 -> 1.1164522e+08 | I38: =L37 -> 1.2183011e+08 | J38: =-C38 -> -2835000 | K38: =SUM(I38:J38)*$B$14/12 -> 713970.64 | L38: =SUM(I38:K38) -> 1.1970908e+08
A39: 45809 | B39: =A39-$A$25+1 -> 427 | C39: 2835000 | D39: =-PV($B$19,B39,,C39,1) -> 2606009.5 | F39: =H38 -> 1.1164522e+08 | G39: =$F$25/$B$20 -> 2518623.7 | H39: =F39-G39 -> 1.091266e+08 | I39: =L38 -> 1.1970908e+08 | J39: =-C39 -> -2835000 | K39: =SUM(I39:J39)*$B$14/12 -> 701244.46 | L39: =SUM(I39:K39) -> 1.1757532e+08
A40: 45839 | B40: =A40-$A$25+1 -> 457 | C40: 2835000 | D40: =-PV($B$19,B40,,C40,1) -> 2590634.6 | F40: =H39 -> 1.091266e+08 | G40: =$F$25/$B$20 -> 2518623.7 | H40: =F40-G40 -> 1.0660797e+08 | I40: =L39 -> 1.1757532e+08 | J40: =-C40 -> -2835000 | K40: =SUM(I40:J40)*$B$14/12 -> 688441.93 | L40: =SUM(I40:K40) -> 1.1542876e+08
A41: 45870 | B41: =A41-$A$25+1 -> 488 | C41: 2835000 | D41: =-PV($B$19,B41,,C41,1) -> 2574842.6 | F41: =H40 -> 1.0660797e+08 | G41: =$F$25/$B$20 -> 2518623.7 | H41: =F41-G41 -> 1.0408935e+08 | I41: =L40 -> 1.1542876e+08 | J41: =-C41 -> -2835000 | K41: =SUM(I41:J41)*$B$14/12 -> 675562.58 | L41: =SUM(I41:K41) -> 1.1326933e+08
A42: 45901 | B42: =A42-$A$25+1 -> 519 | C42: 2835000 | D42: =-PV($B$19,B42,,C42,1) -> 2559146.9 | F42: =H41 -> 1.0408935e+08 | G42: =$F$25/$B$20 -> 2518623.7 | H42: =F42-G42 -> 1.0157073e+08 | I42: =L41 -> 1.1326933e+08 | J42: =-C42 -> -2835000 | K42: =SUM(I42:J42)*$B$14/12 -> 662605.95 | L42: =SUM(I42:K42) -> 1.1109693e+08
A43: 45931 | B43: =A43-$A$25+1 -> 549 | C43: 2835000 | D43: =-PV($B$19,B43,,C43,1) -> 2544048.5 | F43: =H42 -> 1.0157073e+08 | G43: =$F$25/$B$20 -> 2518623.7 | H43: =F43-G43 -> 99052104 | I43: =L42 -> 1.1109693e+08 | J43: =-C43 -> -2835000 | K43: =SUM(I43:J43)*$B$14/12 -> 649571.59 | L43: =SUM(I43:K43) -> 1.089115e+08
A44: 45962 | B44: =A44-$A$25+1 -> 580 | C44: 2835000 | D44: =-PV($B$19,B44,,C44,1) -> 2528540.5 | F44: =H43 -> 99052104 | G44: =$F$25/$B$20 -> 2518623.7 | H44: =F44-G44 -> 96533480 | I44: =L43 -> 1.089115e+08 | J44: =-C44 -> -2835000 | K44: =SUM(I44:J44)*$B$14/12 -> 636459.02 | L44: =SUM(I44:K44) -> 1.0671296e+08
A45: 45992 | B45: =A45-$A$25+1 -> 610 | C45: 2835000 | D45: =-PV($B$19,B45,,C45,1) -> 2513622.7 | F45: =H44 -> 96533480 | G45: =$F$25/$B$20 -> 2518623.7 | H45: =F45-G45 -> 94014856 | I45: =L44 -> 1.0671296e+08 | J45: =-C45 -> -2835000 | K45: =SUM(I45:J45)*$B$14/12 -> 623267.77 | L45: =SUM(I45:K45) -> 1.0450123e+08
A46: 46023 | B46: =A46-$A$25+1 -> 641 | C46: 2835000 | D46: =-PV($B$19,B46,,C46,1) -> 2498300.2 | F46: =H45 -> 94014856 | G46: =$F$25/$B$20 -> 2518623.7 | H46: =F46-G46 -> 91496232 | I46: =L45 -> 1.0450123e+08 | J46: =-C46 -> -2835000 | K46: =SUM(I46:J46)*$B$14/12 -> 609997.38 | L46: =SUM(I46:K46) -> 1.0227623e+08
A47: 46054 | B47: =A47-$A$25+1 -> 672 | C47: =C46*13/28+C48*15/28 -> 2910937.5 | D47: =-PV($B$19,B47,,C47,1) -> 2549581.8 | F47: =H46 -> 91496232 | G47: =$F$25/$B$20 -> 2518623.7 | H47: =F47-G47 -> 88977609 | I47: =L46 -> 1.0227623e+08 | J47: =-C47 -> -2910937.5 | K47: =SUM(I47:J47)*$B$14/12 -> 596191.74 | L47: =SUM(I47:K47) -> 99961482
A48: 46082 | B48: =A48-$A$25+1 -> 700 | C48: 2976750 | D48: =-PV($B$19,B48,,C48,1) -> 2592865.2 | F48: =H47 -> 88977609 | G48: =$F$25/$B$20 -> 2518623.7 | H48: =F48-G48 -> 86458985 | I48: =L47 -> 99961482 | J48: =-C48 -> -2976750 | K48: =SUM(I48:J48)*$B$14/12 -> 581908.39 | L48: =SUM(I48:K48) -> 97566640
A49: 46113 | B49: =A49-$A$25+1 -> 731 | C49: 2976750 | D49: =-PV($B$19,B49,,C49,1) -> 2577059.6 | F49: =H48 -> 86458985 | G49: =$F$25/$B$20 -> 2518623.7 | H49: =F49-G49 -> 83940361 | I49: =L48 -> 97566640 | J49: =-C49 -> -2976750 | K49: =SUM(I49:J49)*$B$14/12 -> 567539.34 | L49: =SUM(I49:K49) -> 95157430
A50: 46143 | B50: =A50-$A$25+1 -> 761 | C50: 2976750 | D50: =-PV($B$19,B50,,C50,1) -> 2561855.6 | F50: =H49 -> 83940361 | G50: =$F$25/$B$20 -> 2518623.7 | H50: =F50-G50 -> 81421738 | I50: =L49 -> 95157430 | J50: =-C50 -> -2976750 | K50: =SUM(I50:J50)*$B$14/12 -> 553084.08 | L50: =SUM(I50:K50) -> 92733764
A51: 46174 | B51: =A51-$A$25+1 -> 792 | C51: 2976750 | D51: =-PV($B$19,B51,,C51,1) -> 2546239 | F51: =H50 -> 81421738 | G51: =$F$25/$B$20 -> 2518623.7 | H51: =F51-G51 -> 78903114 | I51: =L50 -> 92733764 | J51: =-C51 -> -2976750 | K51: =SUM(I51:J51)*$B$14/12 -> 538542.08 | L51: =SUM(I51:K51) -> 90295556
A52: 46204 | B52: =A52-$A$25+1 -> 822 | C52: 2976750 | D52: =-PV($B$19,B52,,C52,1) -> 2531216.8 | F52: =H51 -> 78903114 | G52: =$F$25/$B$20 -> 2518623.7 | H52: =F52-G52 -> 76384490 | I52: =L51 -> 90295556 | J52: =-C52 -> -2976750 | K52: =SUM(I52:J52)*$B$14/12 -> 523912.83 | L52: =SUM(I52:K52) -> 87842719
A53: 46235 | B53: =A53-$A$25+1 -> 853 | C53: 2976750 | D53: =-PV($B$19,B53,,C53,1) -> 2515787 | F53: =H52 -> 76384490 | G53: =$F$25/$B$20 -> 2518623.7 | H53: =F53-G53 -> 73865866 | I53: =L52 -> 87842719 | J53: =-C53 -> -2976750 | K53: =SUM(I53:J53)*$B$14/12 -> 509195.81 | L53: =SUM(I53:K53) -> 85375164
A54: 46266 | B54: =A54-$A$25+1 -> 884 | C54: 2976750 | D54: =-PV($B$19,B54,,C54,1) -> 2500451.3 | F54: =H53 -> 73865866 | G54: =$F$25/$B$20 -> 2518623.7 | H54: =F54-G54 -> 71347243 | I54: =L53 -> 85375164 | J54: =-C54 -> -2976750 | K54: =SUM(I54:J54)*$B$14/12 -> 494390.49 | L54: =SUM(I54:K54) -> 82892805
A55: 46296 | B55: =A55-$A$25+1 -> 914 | C55: 2976750 | D55: =-PV($B$19,B55,,C55,1) -> 2485699.2 | F55: =H54 -> 71347243 | G55: =$F$25/$B$20 -> 2518623.7 | H55: =F55-G55 -> 68828619 | I55: =L54 -> 82892805 | J55: =-C55 -> -2976750 | K55: =SUM(I55:J55)*$B$14/12 -> 479496.33 | L55: =SUM(I55:K55) -> 80395551
A56: 46327 | B56: =A56-$A$25+1 -> 945 | C56: 2976750 | D56: =-PV($B$19,B56,,C56,1) -> 2470546.9 | F56: =H55 -> 68828619 | G56: =$F$25/$B$20 -> 2518623.7 | H56: =F56-G56 -> 66309995 | I56: =L55 -> 80395551 | J56: =-C56 -> -2976750 | K56: =SUM(I56:J56)*$B$14/12 -> 464512.81 | L56: =SUM(I56:K56) -> 77883314
A57: 46357 | B57: =A57-$A$25+1 -> 975 | C57: 2976750 | D57: =-PV($B$19,B57,,C57,1) -> 2455971.2 | F57: =H56 -> 66309995 | G57: =$F$25/$B$20 -> 2518623.7 | H57: =F57-G57 -> 63791371 | I57: =L56 -> 77883314 | J57: =-C57 -> -2976750 | K57: =SUM(I57:J57)*$B$14/12 -> 449439.38 | L57: =SUM(I57:K57) -> 75356003
A58: 46388 | B58: =A58-$A$25+1 -> 1006 | C58: 2976750 | D58: =-PV($B$19,B58,,C58,1) -> 2441000.1 | F58: =H57 -> 63791371 | G58: =$F$25/$B$20 -> 2518623.7 | H58: =F58-G58 -> 61272748 | I58: =L57 -> 75356003 | J58: =-C58 -> -2976750 | K58: =SUM(I58:J58)*$B$14/12 -> 434275.52 | L58: =SUM(I58:K58) -> 72813529
A59: 46419 | B59: =A59-$A$25+1 -> 1037 | C59: =C58*13/28+C60*15/28 -> 3056484.4 | D59: =-PV($B$19,B59,,C59,1) -> 2491105.6 | F59: =H58 -> 61272748 | G59: =$F$25/$B$20 -> 2518623.7 | H59: =F59-G59 -> 58754124 | I59: =L58 -> 72813529 | J59: =-C59 -> -3056484.4 | K59: =SUM(I59:J59)*$B$14/12 -> 418542.27 | L59: =SUM(I59:K59) -> 70175587
A60: 46447 | B60: =A60-$A$25+1 -> 1065 | C60: 3125587.5 | D60: =-PV($B$19,B60,,C60,1) -> 2533396.2 | F60: =H59 -> 58754124 | G60: =$F$25/$B$20 -> 2518623.7 | H60: =F60-G60 -> 56235500 | I60: =L59 -> 70175587 | J60: =-C60 -> -3125587.5 | K60: =SUM(I60:J60)*$B$14/12 -> 402300 | L60: =SUM(I60:K60) -> 67452299
A61: 46478 | B61: =A61-$A$25+1 -> 1096 | C61: 3125587.5 | D61: =-PV($B$19,B61,,C61,1) -> 2517953.1 | F61: =H60 -> 56235500 | G61: =$F$25/$B$20 -> 2518623.7 | H61: =F61-G61 -> 53716877 | I61: =L60 -> 67452299 | J61: =-C61 -> -3125587.5 | K61: =SUM(I61:J61)*$B$14/12 -> 385960.27 | L61: =SUM(I61:K61) -> 64712672
A62: 46508 | B62: =A62-$A$25+1 -> 1126 | C62: 3125587.5 | D62: =-PV($B$19,B62,,C62,1) -> 2503097.8 | F62: =H61 -> 53716877 | G62: =$F$25/$B$20 -> 2518623.7 | H62: =F62-G62 -> 51198253 | I62: =L61 -> 64712672 | J62: =-C62 -> -3125587.5 | K62: =SUM(I62:J62)*$B$14/12 -> 369522.51 | L62: =SUM(I62:K62) -> 61956607
A63: 46539 | B63: =A63-$A$25+1 -> 1157 | C63: 3125587.5 | D63: =-PV($B$19,B63,,C63,1) -> 2487839.4 | F63: =H62 -> 51198253 | G63: =$F$25/$B$20 -> 2518623.7 | H63: =F63-G63 -> 48679629 | I63: =L62 -> 61956607 | J63: =-C63 -> -3125587.5 | K63: =SUM(I63:J63)*$B$14/12 -> 352986.12 | L63: =SUM(I63:K63) -> 59184006
A64: 46569 | B64: =A64-$A$25+1 -> 1187 | C64: 3125587.5 | D64: =-PV($B$19,B64,,C64,1) -> 2473161.8 | F64: =H63 -> 48679629 | G64: =$F$25/$B$20 -> 2518623.7 | H64: =F64-G64 -> 46161005 | I64: =L63 -> 59184006 | J64: =-C64 -> -3125587.5 | K64: =SUM(I64:J64)*$B$14/12 -> 336350.51 | L64: =SUM(I64:K64) -> 56394769
A65: 46600 | B65: =A65-$A$25+1 -> 1218 | C65: 3125587.5 | D65: =-PV($B$19,B65,,C65,1) -> 2458085.9 | F65: =H64 -> 46161005 | G65: =$F$25/$B$20 -> 2518623.7 | H65: =F65-G65 -> 43642382 | I65: =L64 -> 56394769 | J65: =-C65 -> -3125587.5 | K65: =SUM(I65:J65)*$B$14/12 -> 319615.09 | L65: =SUM(I65:K65) -> 53588796
A66: 46631 | B66: =A66-$A$25+1 -> 1249 | C66: 3125587.5 | D66: =-PV($B$19,B66,,C66,1) -> 2443101.8 | F66: =H65 -> 43642382 | G66: =$F$25/$B$20 -> 2518623.7 | H66: =F66-G66 -> 41123758 | I66: =L65 -> 53588796 | J66: =-C66 -> -3125587.5 | K66: =SUM(I66:J66)*$B$14/12 -> 302779.25 | L66: =SUM(I66:K66) -> 50765988
A67: 46661 | B67: =A67-$A$25+1 -> 1279 | C67: 3125587.5 | D67: =-PV($B$19,B67,,C67,1) -> 2428688.2 | F67: =H66 -> 41123758 | G67: =$F$25/$B$20 -> 2518623.7 | H67: =F67-G67 -> 38605134 | I67: =L66 -> 50765988 | J67: =-C67 -> -3125587.5 | K67: =SUM(I67:J67)*$B$14/12 -> 285842.4 | L67: =SUM(I67:K67) -> 47926243
A68: 46692 | B68: =A68-$A$25+1 -> 1310 | C68: 3125587.5 | D68: =-PV($B$19,B68,,C68,1) -> 2413883.3 | F68: =H67 -> 38605134 | G68: =$F$25/$B$20 -> 2518623.7 | H68: =F68-G68 -> 36086510 | I68: =L67 -> 47926243 | J68: =-C68 -> -3125587.5 | K68: =SUM(I68:J68)*$B$14/12 -> 268803.93 | L68: =SUM(I68:K68) -> 45069459
A69: 46722 | B69: =A69-$A$25+1 -> 1340 | C69: 3125587.5 | D69: =-PV($B$19,B69,,C69,1) -> 2399642 | F69: =H68 -> 36086510 | G69: =$F$25/$B$20 -> 2518623.7 | H69: =F69-G69 -> 33567887 | I69: =L68 -> 45069459 | J69: =-C69 -> -3125587.5 | K69: =SUM(I69:J69)*$B$14/12 -> 251663.23 | L69: =SUM(I69:K69) -> 42195535
A70: 46753 | B70: =A70-$A$25+1 -> 1371 | C70: 3125587.5 | D70: =-PV($B$19,B70,,C70,1) -> 2385014.3 | F70: =H69 -> 33567887 | G70: =$F$25/$B$20 -> 2518623.7 | H70: =F70-G70 -> 31049263 | I70: =L69 -> 42195535 | J70: =-C70 -> -3125587.5 | K70: =SUM(I70:J70)*$B$14/12 -> 234419.69 | L70: =SUM(I70:K70) -> 39304367
A71: 46784 | B71: =A71-$A$25+1 -> 1402 | C71: =C70*13/28+C72*15/28 -> 3209308.6 | D71: =-PV($B$19,B71,,C71,1) -> 2433970.5 | F71: =H70 -> 31049263 | G71: =$F$25/$B$20 -> 2518623.7 | H71: =F71-G71 -> 28530639 | I71: =L70 -> 39304367 | J71: =-C71 -> -3209308.6 | K71: =SUM(I71:J71)*$B$14/12 -> 216570.35 | L71: =SUM(I71:K71) -> 36311629
A72: 46813 | B72: =A72-$A$25+1 -> 1431 | C72: 3281866.9 | D72: =-PV($B$19,B72,,C72,1) -> 2474803 | F72: =H71 -> 28530639 | G72: =$F$25/$B$20 -> 2518623.7 | H72: =F72-G72 -> 26012016 | I72: =L71 -> 36311629 | J72: =-C72 -> -3281866.9 | K72: =SUM(I72:J72)*$B$14/12 -> 198178.57 | L72: =SUM(I72:K72) -> 33227941
A73: 46844 | B73: =A73-$A$25+1 -> 1462 | C73: 3281866.9 | D73: =-PV($B$19,B73,,C73,1) -> 2459717.1 | F73: =H72 -> 26012016 | G73: =$F$25/$B$20 -> 2518623.7 | H73: =F73-G73 -> 23493392 | I73: =L72 -> 33227941 | J73: =-C73 -> -3281866.9 | K73: =SUM(I73:J73)*$B$14/12 -> 179676.44 | L73: =SUM(I73:K73) -> 30125750
A74: 46874 | B74: =A74-$A$25+1 -> 1492 | C74: 3281866.9 | D74: =-PV($B$19,B74,,C74,1) -> 2445205.4 | F74: =H73 -> 23493392 | G74: =$F$25/$B$20 -> 2518623.7 | H74: =F74-G74 -> 20974768 | I74: =L73 -> 30125750 | J74: =-C74 -> -3281866.9 | K74: =SUM(I74:J74)*$B$14/12 -> 161063.3 | L74: =SUM(I74:K74) -> 27004947
A75: 46905 | B75: =A75-$A$25+1 -> 1523 | C75: 3281866.9 | D75: =-PV($B$19,B75,,C75,1) -> 2430299.9 | F75: =H74 -> 20974768 | G75: =$F$25/$B$20 -> 2518623.7 | H75: =F75-G75 -> 18456144 | I75: =L74 -> 27004947 | J75: =-C75 -> -3281866.9 | K75: =SUM(I75:J75)*$B$14/12 -> 142338.48 | L75: =SUM(I75:K75) -> 23865418
A76: 46935 | B76: =A76-$A$25+1 -> 1553 | C76: 3281866.9 | D76: =-PV($B$19,B76,,C76,1) -> 2415961.7 | F76: =H75 -> 18456144 | G76: =$F$25/$B$20 -> 2518623.7 | H76: =F76-G76 -> 15937521 | I76: =L75 -> 23865418 | J76: =-C76 -> -3281866.9 | K76: =SUM(I76:J76)*$B$14/12 -> 123501.31 | L76: =SUM(I76:K76) -> 20707053
A77: 46966 | B77: =A77-$A$25+1 -> 1584 | C77: 3281866.9 | D77: =-PV($B$19,B77,,C77,1) -> 2401234.5 | F77: =H76 -> 15937521 | G77: =$F$25/$B$20 -> 2518623.7 | H77: =F77-G77 -> 13418897 | I77: =L76 -> 20707053 | J77: =-C77 -> -3281866.9 | K77: =SUM(I77:J77)*$B$14/12 -> 104551.12 | L77: =SUM(I77:K77) -> 17529737
A78: 46997 | B78: =A78-$A$25+1 -> 1615 | C78: 3281866.9 | D78: =-PV($B$19,B78,,C78,1) -> 2386597 | F78: =H77 -> 13418897 | G78: =$F$25/$B$20 -> 2518623.7 | H78: =F78-G78 -> 10900273 | I78: =L77 -> 17529737 | J78: =-C78 -> -3281866.9 | K78: =SUM(I78:J78)*$B$14/12 -> 85487.22 | L78: =SUM(I78:K78) -> 14333357
A79: 47027 | B79: =A79-$A$25+1 -> 1645 | C79: 3281866.9 | D79: =-PV($B$19,B79,,C79,1) -> 2372516.7 | F79: =H78 -> 10900273 | G79: =$F$25/$B$20 -> 2518623.7 | H79: =F79-G79 -> 8381649.5 | I79: =L78 -> 14333357 | J79: =-C79 -> -3281866.9 | K79: =SUM(I79:J79)*$B$14/12 -> 66308.943 | L79: =SUM(I79:K79) -> 11117799
A80: 47058 | B80: =A80-$A$25+1 -> 1676 | C80: 3281866.9 | D80: =-PV($B$19,B80,,C80,1) -> 2358054.3 | F80: =H79 -> 8381649.5 | G80: =$F$25/$B$20 -> 2518623.7 | H80: =F80-G80 -> 5863025.7 | I80: =L79 -> 11117799 | J80: =-C80 -> -3281866.9 | K80: =SUM(I80:J80)*$B$14/12 -> 47015.595 | L80: =SUM(I80:K80) -> 7882948.1
A81: 47088 | B81: =A81-$A$25+1 -> 1706 | C81: 3281866.9 | D81: =-PV($B$19,B81,,C81,1) -> 2344142.3 | F81: =H80 -> 5863025.7 | G81: =$F$25/$B$20 -> 2518623.7 | H81: =F81-G81 -> 3344402 | I81: =L80 -> 7882948.1 | J81: =-C81 -> -3281866.9 | K81: =SUM(I81:J81)*$B$14/12 -> 27606.487 | L81: =SUM(I81:K81) -> 4628687.7
A82: 47119 | B82: =A82-$A$25+1 -> 1737 | C82: 3281866.9 | D82: =-PV($B$19,B82,,C82,1) -> 2329852.9 | F82: =H81 -> 3344402 | G82: =$F$25/$B$20 -> 2518623.7 | H82: =F82-G82 -> 825778.27 | I82: =L81 -> 4628687.7 | J82: =-C82 -> -3281866.9 | K82: =SUM(I82:J82)*$B$14/12 -> 8080.9249 | L82: =SUM(I82:K82) -> 1354901.7
A83: 47150 | B83: =A83-$A$25+1 -> 1768 | C83: =C82*13/28 -> 1523723.9 | D83: =-PV($B$19,B83,,C83,1) -> 1075123.5 | F83: =H82 -> 825778.27 | G83: =F83 -> 825778.27 | H83: =F83-G83 -> 0 | I83: =L82 -> 1354901.7 | J83: =-I83 -> -1354901.7 | K83: =SUM(I83:J83)*$B$14/12 -> 0 | L83: =SUM(I83:K83) -> 0

Sheet OCL 64418-2
A6: =[4]Scope!A5 -> Purpose
A7: To verify the lease working of the sample selected
A10: Summary
A12: Particulars | B12: Discount Rate | C12: Commencement Date | D12: Expiration Date | E12: Addition during FY 2025-26 | F12: Amortisation during FY 2025-26 | G12: Closing WDV | H12: Interest | I12: Repayment | J12: Closing Balance | K12: ST | L12: LT
A13: As per Lease Report | B13: 0.0757 | C13: 45606 | D13: 47163 | E13: 0 | F13: 10685371 | G13: 30720442 | H13: 2793767.7 | I13: 11610541 | J13: 32999688 | K13: 11170343 | L13: 21829345
A14: As per DHS Working | B14: ='G Sec 1 Apr'!C22/100 -> 0.072 | C14: 45606 | D14: 47163 | E14: 0 | F14: =SUM(G30:G41) -> 11013565 | G14: =H41 -> 31250237 | H14: =SUM(K30:K41) -> 2761898 | I14: =-SUM(J30:J41) -> 11843884 | J14: =L41 -> 34302059 | K14: =-(L54-L42) -> 10486432 | L14: =J14-K14 -> 23815627
A15: Difference | B15: =B13-B14 -> 0.0037 | C15: =C13-C14 -> 0 | D15: =D13-D14 -> 0 | E15: =E13-E14 -> 0 | F15: =F13-F14 -> -328193.47 | G15: =G13-G14 -> -529795.4 | H15: =H13-H14 -> 31869.683 | I15: =I13-I14 -> -233343.21 | ... L15: =L13-L14 -> -1986282.3
A18: Monthly Rent | B18: 960825 | C18: << As per agreement >>
A19: Monthly discount rate | B19: =B14/365 -> 0.00019726027 | C19: << Link >>
A20: No of Months | B20: =(D14-C14)/30.5 -> 51.04918 | C20: << Formula >>
A21: PV of rent payments | B21: =SUM(D25:D76) -> 46852787 | C21: << Formula >>
A23: Calculation of PV of lease payments | F23: Right of Use Asset | I23: Lease Liability
A24: Date | B24: Cumulative Days | C24: Lease payments | D24: PV of Lease payments | F24: Opening Balance | G24: Depreciation | H24: Closing Balance | I24: Opening Liability | J24: Repayment | K24: Interest | L24: Closing Lease Liability
A25: 45597 | B25: 1 | C25: 960825 | D25: =-PV($B$19,B25,,C25,1) -> 960635.5 | F25: =B21 -> 46852787 | G25: =$F$25/$B$20 -> 917797.05 | H25: =F25-G25 -> 45934990 | I25: =F25 -> 46852787 | J25: =-C25 -> -960825 | K25: =SUM(I25:J25)*$B$14/12 -> 275351.77 | L25: =SUM(I25:K25) -> 46167314
A26: 45627 | B26: =A26-$A$25+1 -> 31 | C26: 960825 | D26: =-PV($B$19,B26,,C26,1) -> 954967.99 | F26: =H25 -> 45934990 | G26: =$F$25/$B$20 -> 917797.05 | H26: =F26-G26 -> 45017193 | I26: =L25 -> 46167314 | J26: =-C26 -> -960825 | K26: =SUM(I26:J26)*$B$14/12 -> 271238.93 | L26: =SUM(I26:K26) -> 45477728
A27: 45658 | B27: =A27-$A$25+1 -> 62 | C27: 960825 | D27: =-PV($B$19,B27,,C27,1) -> 949146.69 | F27: =H26 -> 45017193 | G27: =$F$25/$B$20 -> 917797.05 | H27: =F27-G27 -> 44099396 | I27: =L26 -> 45477728 | J27: =-C27 -> -960825 | K27: =SUM(I27:J27)*$B$14/12 -> 267101.42 | L27: =SUM(I27:K27) -> 44784004
A28: 45689 | B28: =A28-$A$25+1 -> 93 | C28: 960825 | D28: =-PV($B$19,B28,,C28,1) -> 943360.87 | F28: =H27 -> 44099396 | G28: =$F$25/$B$20 -> 917797.05 | H28: =F28-G28 -> 43181599 | I28: =L27 -> 44784004 | J28: =-C28 -> -960825 | K28: =SUM(I28:J28)*$B$14/12 -> 262939.07 | L28: =SUM(I28:K28) -> 44086118
A29: 45717 | B29: =A29-$A$25+1 -> 121 | C29: 960825 | D29: =-PV($B$19,B29,,C29,1) -> 938165.29 | F29: =H28 -> 43181599 | G29: =$F$25/$B$20 -> 917797.05 | H29: =F29-G29 -> 42263802 | I29: =L28 -> 44086118 | J29: =-C29 -> -960825 | K29: =SUM(I29:J29)*$B$14/12 -> 258751.76 | L29: =SUM(I29:K29) -> 43384045
A30: 45748 | B30: =A30-$A$25+1 -> 152 | C30: 960825 | D30: =-PV($B$19,B30,,C30,1) -> 932446.41 | F30: =H29 -> 42263802 | G30: =$F$25/$B$20 -> 917797.05 | H30: =F30-G30 -> 41346005 | I30: =L29 -> 43384045 | J30: =-C30 -> -960825 | K30: =SUM(I30:J30)*$B$14/12 -> 254539.32 | L30: =SUM(I30:K30) -> 42677759
A31: 45778 | B31: =A31-$A$25+1 -> 182 | C31: 960825 | D31: =-PV($B$19,B31,,C31,1) -> 926945.21 | F31: =H30 -> 41346005 | G31: =$F$25/$B$20 -> 917797.05 | H31: =F31-G31 -> 40428208 | I31: =L30 -> 42677759 | J31: =-C31 -> -960825 | K31: =SUM(I31:J31)*$B$14/12 -> 250301.61 | L31: =SUM(I31:K31) -> 41967236
A32: 45809 | B32: =A32-$A$25+1 -> 213 | C32: 960825 | D32: =-PV($B$19,B32,,C32,1) -> 921294.73 | F32: =H31 -> 40428208 | G32: =$F$25/$B$20 -> 917797.05 | H32: =F32-G32 -> 39510411 | I32: =L31 -> 41967236 | J32: =-C32 -> -960825 | K32: =SUM(I32:J32)*$B$14/12 -> 246038.46 | L32: =SUM(I32:K32) -> 41252449
A33: 45839 | B33: =A33-$A$25+1 -> 243 | C33: 960825 | D33: =-PV($B$19,B33,,C33,1) -> 915859.32 | F33: =H32 -> 39510411 | G33: =$F$25/$B$20 -> 917797.05 | H33: =F33-G33 -> 38592613 | I33: =L32 -> 41252449 | J33: =-C33 -> -960825 | K33: =SUM(I33:J33)*$B$14/12 -> 241749.75 | L33: =SUM(I33:K33) -> 40533374
A34: 45870 | B34: =A34-$A$25+1 -> 274 | C34: 960825 | D34: =-PV($B$19,B34,,C34,1) -> 910276.41 | F34: =H33 -> 38592613 | G34: =$F$25/$B$20 -> 917797.05 | H34: =F34-G34 -> 37674816 | I34: =L33 -> 40533374 | J34: =-C34 -> -960825 | K34: =SUM(I34:J34)*$B$14/12 -> 237435.29 | L34: =SUM(I34:K34) -> 39809984
A35: 45901 | B35: =A35-$A$25+1 -> 305 | C35: =C34*13/28+C36*15/28 -> 986561.38 | D35: =-PV($B$19,B35,,C35,1) -> 928961.32 | F35: =H34 -> 37674816 | G35: =$F$25/$B$20 -> 917797.05 | H35: =F35-G35 -> 36757019 | I35: =L34 -> 39809984 | J35: =-C35 -> -986561.38 | K35: =SUM(I35:J35)*$B$14/12 -> 232940.54 | L35: =SUM(I35:K35) -> 39056363
A36: 45931 | B36: =A36-$A$25+1 -> 335 | C36: 1008866.2 | D36: =-PV($B$19,B36,,C36,1) -> 944359.37 | F36: =H35 -> 36757019 | G36: =$F$25/$B$20 -> 917797.05 | H36: =F36-G36 -> 35839222 | I36: =L35 -> 39056363 | J36: =-C36 -> -1008866.2 | K36: =SUM(I36:J36)*$B$14/12 -> 228284.98 | L36: =SUM(I36:K36) -> 38275782
A37: 45962 | B37: =A37-$A$25+1 -> 366 | C37: 1008866.2 | D37: =-PV($B$19,B37,,C37,1) -> 938602.73 | F37: =H36 -> 35839222 | G37: =$F$25/$B$20 -> 917797.05 | H37: =F37-G37 -> 34921425 | I37: =L36 -> 38275782 | J37: =-C37 -> -1008866.2 | K37: =SUM(I37:J37)*$B$14/12 -> 223601.5 | L37: =SUM(I37:K37) -> 37490517
A38: 45992 | B38: =A38-$A$25+1 -> 396 | C38: 1008866.2 | D38: =-PV($B$19,B38,,C38,1) -> 933065.21 | F38: =H37 -> 34921425 | G38: =$F$25/$B$20 -> 917797.05 | H38: =F38-G38 -> 34003628 | I38: =L37 -> 37490517 | J38: =-C38 -> -1008866.2 | K38: =SUM(I38:J38)*$B$14/12 -> 218889.91 | L38: =SUM(I38:K38) -> 36700541
A39: 46023 | B39: =A39-$A$25+1 -> 427 | C39: 1008866.2 | D39: =-PV($B$19,B39,,C39,1) -> 927377.42 | F39: =H38 -> 34003628 | G39: =$F$25/$B$20 -> 917797.05 | H39: =F39-G39 -> 33085831 | I39: =L38 -> 36700541 | J39: =-C39 -> -1008866.2 | K39: =SUM(I39:J39)*$B$14/12 -> 214150.05 | L39: =SUM(I39:K39) -> 35905825
A40: 46054 | B40: =A40-$A$25+1 -> 458 | C40: 1008866.2 | D40: =-PV($B$19,B40,,C40,1) -> 921724.3 | F40: =H39 -> 33085831 | G40: =$F$25/$B$20 -> 917797.05 | H40: =F40-G40 -> 32168034 | I40: =L39 -> 35905825 | J40: =-C40 -> -1008866.2 | K40: =SUM(I40:J40)*$B$14/12 -> 209381.75 | L40: =SUM(I40:K40) -> 35106340
A41: 46082 | B41: =A41-$A$25+1 -> 486 | C41: 1008866.2 | D41: =-PV($B$19,B41,,C41,1) -> 916647.89 | F41: =H40 -> 32168034 | G41: =$F$25/$B$20 -> 917797.05 | H41: =F41-G41 -> 31250237 | I41: =L40 -> 35106340 | J41: =-C41 -> -1008866.2 | K41: =SUM(I41:J41)*$B$14/12 -> 204584.84 | L41: =SUM(I41:K41) -> 34302059
A42: 46113 | B42: =A42-$A$25+1 -> 517 | C42: 1008866.2 | D42: =-PV($B$19,B42,,C42,1) -> 911060.18 | F42: =H41 -> 31250237 | G42: =$F$25/$B$20 -> 917797.05 | H42: =F42-G42 -> 30332440 | I42: =L41 -> 34302059 | J42: =-C42 -> -1008866.2 | K42: =SUM(I42:J42)*$B$14/12 -> 199759.16 | L42: =SUM(I42:K42) -> 33492952
A43: 46143 | B43: =A43-$A$25+1 -> 547 | C43: 1008866.2 | D43: =-PV($B$19,B43,,C43,1) -> 905685.15 | F43: =H42 -> 30332440 | G43: =$F$25/$B$20 -> 917797.05 | H43: =F43-G43 -> 29414643 | I43: =L42 -> 33492952 | J43: =-C43 -> -1008866.2 | K43: =SUM(I43:J43)*$B$14/12 -> 194904.51 | L43: =SUM(I43:K43) -> 32678990
A44: 46174 | B44: =A44-$A$25+1 -> 578 | C44: 1008866.2 | D44: =-PV($B$19,B44,,C44,1) -> 900164.26 | F44: =H43 -> 29414643 | G44: =$F$25/$B$20 -> 917797.05 | H44: =F44-G44 -> 28496846 | I44: =L43 -> 32678990 | J44: =-C44 -> -1008866.2 | K44: =SUM(I44:J44)*$B$14/12 -> 190020.74 | L44: =SUM(I44:K44) -> 31860145
A45: 46204 | B45: =A45-$A$25+1 -> 608 | C45: 1008866.2 | D45: =-PV($B$19,B45,,C45,1) -> 894853.52 | F45: =H44 -> 28496846 | G45: =$F$25/$B$20 -> 917797.05 | H45: =F45-G45 -> 27579049 | I45: =L44 -> 31860145 | J45: =-C45 -> -1008866.2 | K45: =SUM(I45:J45)*$B$14/12 -> 185107.67 | L45: =SUM(I45:K45) -> 31036386
A46: 46235 | B46: =A46-$A$25+1 -> 639 | C46: 1008866.2 | D46: =-PV($B$19,B46,,C46,1) -> 889398.66 | F46: =H45 -> 27579049 | G46: =$F$25/$B$20 -> 917797.05 | H46: =F46-G46 -> 26661252 | I46: =L45 -> 31036386 | J46: =-C46 -> -1008866.2 | K46: =SUM(I46:J46)*$B$14/12 -> 180165.12 | L46: =SUM(I46:K46) -> 30207685
A47: 46266 | B47: =A47-$A$25+1 -> 670 | C47: =C46*13/28+C48*15/28 -> 1035889.5 | D47: =-PV($B$19,B47,,C47,1) -> 907655.01 | F47: =H46 -> 26661252 | G47: =$F$25/$B$20 -> 917797.05 | H47: =F47-G47 -> 25743455 | I47: =L46 -> 30207685 | J47: =-C47 -> -1035889.5 | K47: =SUM(I47:J47)*$B$14/12 -> 175030.77 | L47: =SUM(I47:K47) -> 29346826
A48: 46296 | B48: =A48-$A$25+1 -> 700 | C48: 1059309.6 | D48: =-PV($B$19,B48,,C48,1) -> 922699.9 | F48: =H47 -> 25743455 | G48: =$F$25/$B$20 -> 917797.05 | H48: =F48-G48 -> 24825658 | I48: =L47 -> 29346826 | J48: =-C48 -> -1059309.6 | K48: =SUM(I48:J48)*$B$14/12 -> 169725.1 | L48: =SUM(I48:K48) -> 28457242
A49: 46327 | B49: =A49-$A$25+1 -> 731 | C49: 1059309.6 | D49: =-PV($B$19,B49,,C49,1) -> 917075.29 | F49: =H48 -> 24825658 | G49: =$F$25/$B$20 -> 917797.05 | H49: =F49-G49 -> 23907861 | I49: =L48 -> 28457242 | J49: =-C49 -> -1059309.6 | K49: =SUM(I49:J49)*$B$14/12 -> 164387.59 | L49: =SUM(I49:K49) -> 27562320
A50: 46357 | B50: =A50-$A$25+1 -> 761 | C50: 1059309.6 | D50: =-PV($B$19,B50,,C50,1) -> 911664.78 | F50: =H49 -> 23907861 | G50: =$F$25/$B$20 -> 917797.05 | H50: =F50-G50 -> 22990064 | I50: =L49 -> 27562320 | J50: =-C50 -> -1059309.6 | K50: =SUM(I50:J50)*$B$14/12 -> 159018.06 | L50: =SUM(I50:K50) -> 26662028
A51: 46388 | B51: =A51-$A$25+1 -> 792 | C51: 1059309.6 | D51: =-PV($B$19,B51,,C51,1) -> 906107.44 | F51: =H50 -> 22990064 | G51: =$F$25/$B$20 -> 917797.05 | H51: =F51-G51 -> 22072267 | I51: =L50 -> 26662028 | J51: =-C51 -> -1059309.6 | K51: =SUM(I51:J51)*$B$14/12 -> 153616.31 | L51: =SUM(I51:K51) -> 25756335
A52: 46419 | B52: =A52-$A$25+1 -> 823 | C52: 1059309.6 | D52: =-PV($B$19,B52,,C52,1) -> 900583.98 | F52: =H51 -> 22072267 | G52: =$F$25/$B$20 -> 917797.05 | H52: =F52-G52 -> 21154470 | I52: =L51 -> 25756335 | J52: =-C52 -> -1059309.6 | K52: =SUM(I52:J52)*$B$14/12 -> 148182.15 | L52: =SUM(I52:K52) -> 24845208
A53: 46447 | B53: =A53-$A$25+1 -> 851 | C53: 1059309.6 | D53: =-PV($B$19,B53,,C53,1) -> 895624 | F53: =H52 -> 21154470 | G53: =$F$25/$B$20 -> 917797.05 | H53: =F53-G53 -> 20236673 | I53: =L52 -> 24845208 | J53: =-C53 -> -1059309.6 | K53: =SUM(I53:J53)*$B$14/12 -> 142715.39 | L53: =SUM(I53:K53) -> 23928613
A54: 46478 | B54: =A54-$A$25+1 -> 882 | C54: 1059309.6 | D54: =-PV($B$19,B54,,C54,1) -> 890164.44 | F54: =H53 -> 20236673 | G54: =$F$25/$B$20 -> 917797.05 | H54: =F54-G54 -> 19318876 | I54: =L53 -> 23928613 | J54: =-C54 -> -1059309.6 | K54: =SUM(I54:J54)*$B$14/12 -> 137215.82 | L54: =SUM(I54:K54) -> 23006520
A55: 46508 | B55: =A55-$A$25+1 -> 912 | C55: 1059309.6 | D55: =-PV($B$19,B55,,C55,1) -> 884912.69 | F55: =H54 -> 19318876 | G55: =$F$25/$B$20 -> 917797.05 | H55: =F55-G55 -> 18401078 | I55: =L54 -> 23006520 | J55: =-C55 -> -1059309.6 | K55: =SUM(I55:J55)*$B$14/12 -> 131683.26 | L55: =SUM(I55:K55) -> 22078893
A56: 46539 | B56: =A56-$A$25+1 -> 943 | C56: 1059309.6 | D56: =-PV($B$19,B56,,C56,1) -> 879518.44 | F56: =H55 -> 18401078 | G56: =$F$25/$B$20 -> 917797.05 | H56: =F56-G56 -> 17483281 | I56: =L55 -> 22078893 | J56: =-C56 -> -1059309.6 | K56: =SUM(I56:J56)*$B$14/12 -> 126117.5 | L56: =SUM(I56:K56) -> 21145701
A57: 46569 | B57: =A57-$A$25+1 -> 973 | C57: 1059309.6 | D57: =-PV($B$19,B57,,C57,1) -> 874329.49 | F57: =H56 -> 17483281 | G57: =$F$25/$B$20 -> 917797.05 | H57: =F57-G57 -> 16565484 | I57: =L56 -> 21145701 | J57: =-C57 -> -1059309.6 | K57: =SUM(I57:J57)*$B$14/12 -> 120518.35 | L57: =SUM(I57:K57) -> 20206910
A58: 46600 | B58: =A58-$A$25+1 -> 1004 | C58: 1059309.6 | D58: =-PV($B$19,B58,,C58,1) -> 868999.75 | F58: =H57 -> 16565484 | G58: =$F$25/$B$20 -> 917797.05 | H58: =F58-G58 -> 15647687 | I58: =L57 -> 20206910 | J58: =-C58 -> -1059309.6 | K58: =SUM(I58:J58)*$B$14/12 -> 114885.6 | L58: =SUM(I58:K58) -> 19262486
A59: 46631 | B59: =A59-$A$25+1 -> 1035 | C59: =C58*13/28+C60*15/28 -> 1087683.9 | D59: =-PV($B$19,B59,,C59,1) -> 886837.38 | F59: =H58 -> 15647687 | G59: =$F$25/$B$20 -> 917797.05 | H59: =F59-G59 -> 14729890 | I59: =L58 -> 19262486 | J59: =-C59 -> -1087683.9 | K59: =SUM(I59:J59)*$B$14/12 -> 109048.81 | L59: =SUM(I59:K59) -> 18283851
A60: 46661 | B60: =A60-$A$25+1 -> 1065 | C60: 1112275 | D60: =-PV($B$19,B60,,C60,1) -> 901537.2 | F60: =H59 -> 14729890 | G60: =$F$25/$B$20 -> 917797.05 | H60: =F60-G60 -> 13812093 | I60: =L59 -> 18283851 | J60: =-C60 -> -1112275 | K60: =SUM(I60:J60)*$B$14/12 -> 103029.46 | L60: =SUM(I60:K60) -> 17274606
A61: 46692 | B61: =A61-$A$25+1 -> 1096 | C61: 1112275 | D61: =-PV($B$19,B61,,C61,1) -> 896041.6 | F61: =H60 -> 13812093 | G61: =$F$25/$B$20 -> 917797.05 | H61: =F61-G61 -> 12894296 | I61: =L60 -> 17274606 | J61: =-C61 -> -1112275 | K61: =SUM(I61:J61)*$B$14/12 -> 96973.983 | L61: =SUM(I61:K61) -> 16259304
A62: 46722 | B62: =A62-$A$25+1 -> 1126 | C62: 1112275 | D62: =-PV($B$19,B62,,C62,1) -> 890755.18 | F62: =H61 -> 12894296 | G62: =$F$25/$B$20 -> 917797.05 | H62: =F62-G62 -> 11976499 | I62: =L61 -> 16259304 | J62: =-C62 -> -1112275 | K62: =SUM(I62:J62)*$B$14/12 -> 90882.177 | L62: =SUM(I62:K62) -> 15237912
A63: 46753 | B63: =A63-$A$25+1 -> 1157 | C63: 1112275 | D63: =-PV($B$19,B63,,C63,1) -> 885325.3 | F63: =H62 -> 11976499 | G63: =$F$25/$B$20 -> 917797.05 | H63: =F63-G63 -> 11058702 | I63: =L62 -> 15237912 | J63: =-C63 -> -1112275 | K63: =SUM(I63:J63)*$B$14/12 -> 84753.819 | L63: =SUM(I63:K63) -> 14210390
A64: 46784 | B64: =A64-$A$25+1 -> 1188 | C64: 1112275 | D64: =-PV($B$19,B64,,C64,1) -> 879928.53 | F64: =H63 -> 11058702 | G64: =$F$25/$B$20 -> 917797.05 | H64: =F64-G64 -> 10140905 | I64: =L63 -> 14210390 | J64: =-C64 -> -1112275 | K64: =SUM(I64:J64)*$B$14/12 -> 78588.692 | L64: =SUM(I64:K64) -> 13176704
A65: 46813 | B65: =A65-$A$25+1 -> 1217 | C65: 1112275 | D65: =-PV($B$19,B65,,C65,1) -> 874909.72 | F65: =H64 -> 10140905 | G65: =$F$25/$B$20 -> 917797.05 | H65: =F65-G65 -> 9223108 | I65: =L64 -> 13176704 | J65: =-C65 -> -1112275 | K65: =SUM(I65:J65)*$B$14/12 -> 72386.574 | L65: =SUM(I65:K65) -> 12136816
A66: 46844 | B66: =A66-$A$25+1 -> 1248 | C66: 1112275 | D66: =-PV($B$19,B66,,C66,1) -> 869576.44 | F66: =H65 -> 9223108 | G66: =$F$25/$B$20 -> 917797.05 | H66: =F66-G66 -> 8305311 | I66: =L65 -> 12136816 | J66: =-C66 -> -1112275 | K66: =SUM(I66:J66)*$B$14/12 -> 66147.243 | L66: =SUM(I66:K66) -> 11090688
A67: 46874 | B67: =A67-$A$25+1 -> 1278 | C67: 1112275 | D67: =-PV($B$19,B67,,C67,1) -> 864446.15 | F67: =H66 -> 8305311 | G67: =$F$25/$B$20 -> 917797.05 | H67: =F67-G67 -> 7387513.9 | I67: =L66 -> 11090688 | J67: =-C67 -> -1112275 | K67: =SUM(I67:J67)*$B$14/12 -> 59870.476 | L67: =SUM(I67:K67) -> 10038283
A68: 46905 | B68: =A68-$A$25+1 -> 1309 | C68: 1112275 | D68: =-PV($B$19,B68,,C68,1) -> 859176.65 | F68: =H67 -> 7387513.9 | G68: =$F$25/$B$20 -> 917797.05 | H68: =F68-G68 -> 6469716.9 | I68: =L67 -> 10038283 | J68: =-C68 -> -1112275 | K68: =SUM(I68:J68)*$B$14/12 -> 53556.049 | L68: =SUM(I68:K68) -> 8979564.2
A69: 46935 | B69: =A69-$A$25+1 -> 1339 | C69: 1112275 | D69: =-PV($B$19,B69,,C69,1) -> 854107.72 | F69: =H68 -> 6469716.9 | G69: =$F$25/$B$20 -> 917797.05 | H69: =F69-G69 -> 5551919.8 | I69: =L68 -> 8979564.2 | J69: =-C69 -> -1112275 | K69: =SUM(I69:J69)*$B$14/12 -> 47203.735 | L69: =SUM(I69:K69) -> 7914492.9
A70: 46966 | B70: =A70-$A$25+1 -> 1370 | C70: 1112275 | D70: =-PV($B$19,B70,,C70,1) -> 848901.24 | F70: =H69 -> 5551919.8 | G70: =$F$25/$B$20 -> 917797.05 | H70: =F70-G70 -> 4634122.8 | I70: =L69 -> 7914492.9 | J70: =-C70 -> -1112275 | K70: =SUM(I70:J70)*$B$14/12 -> 40813.307 | L70: =SUM(I70:K70) -> 6843031.2
A71: 46997 | B71: =A71-$A$25+1 -> 1401 | C71: =C70*13/28+C72*15/28 -> 1142068.1 | D71: =-PV($B$19,B71,,C71,1) -> 866326.32 | F71: =H70 -> 4634122.8 | G71: =$F$25/$B$20 -> 917797.05 | H71: =F71-G71 -> 3716325.7 | I71: =L70 -> 6843031.2 | J71: =-C71 -> -1142068.1 | K71: =SUM(I71:J71)*$B$14/12 -> 34205.778 | L71: =SUM(I71:K71) -> 5735168.8
A72: 47027 | B72: =A72-$A$25+1 -> 1431 | C72: 1167888.8 | D72: =-PV($B$19,B72,,C72,1) -> 880686.16 | F72: =H71 -> 3716325.7 | G72: =$F$25/$B$20 -> 917797.05 | H72: =F72-G72 -> 2798528.7 | I72: =L71 -> 5735168.8 | J72: =-C72 -> -1167888.8 | K72: =SUM(I72:J72)*$B$14/12 -> 27403.68 | L72: =SUM(I72:K72) -> 4594683.7
A73: 47058 | B73: =A73-$A$25+1 -> 1462 | C73: 1167888.8 | D73: =-PV($B$19,B73,,C73,1) -> 875317.67 | F73: =H72 -> 2798528.7 | G73: =$F$25/$B$20 -> 917797.05 | H73: =F73-G73 -> 1880731.7 | I73: =L72 -> 4594683.7 | J73: =-C73 -> -1167888.8 | K73: =SUM(I73:J73)*$B$14/12 -> 20560.77 | L73: =SUM(I73:K73) -> 3447355.7
A74: 47088 | B74: =A74-$A$25+1 -> 1492 | C74: 1167888.8 | D74: =-PV($B$19,B74,,C74,1) -> 870153.51 | F74: =H73 -> 1880731.7 | G74: =$F$25/$B$20 -> 917797.05 | H74: =F74-G74 -> 962934.61 | I74: =L73 -> 3447355.7 | J74: =-C74 -> -1167888.8 | K74: =SUM(I74:J74)*$B$14/12 -> 13676.801 | L74: =SUM(I74:K74) -> 2293143.7
A75: 47119 | B75: =A75-$A$25+1 -> 1523 | C75: 1167888.8 | D75: =-PV($B$19,B75,,C75,1) -> 864849.22 | F75: =H74 -> 962934.61 | G75: =$F$25/$B$20 -> 917797.05 | H75: =F75-G75 -> 45137.56 | I75: =L74 -> 2293143.7 | J75: =-C75 -> -1167888.8 | K75: =SUM(I75:J75)*$B$14/12 -> 6751.5294 | L75: =SUM(I75:K75) -> 1132006.4
A76: 47150 | B76: =A76-$A$25+1 -> 1554 | C76: 1167888.8 | D76: =-PV($B$19,B76,,C76,1) -> 859577.26 | F76: =H75 -> 45137.56 | G76: =F76 -> 45137.56 | H76: =F76-G76 -> 0 | I76: =L75 -> 1132006.4 | J76: =-I76 -> -1132006.4 | K76: =SUM(I76:J76)*$B$14/12 -> 0 | L76: =SUM(I76:K76) -> 0

Sheet ITC-64807
A1: =Scope!#REF! -> #REF!
A2: =Scope!#REF! -> #REF!
A3: =Scope!#REF! -> #REF!
A6: =Scope!A2 -> Purpose
A7: To verify the lease working of the sample selected
A10: Summary
A12: Particulars | B12: Discount Rate | C12: Commencement Date | D12: Expiration Date | E12: Addition during FY 2025-26 | F12: Amortisation during FY 2025-26 | G12: Closing WDV | H12: Interest | I12: Repayment | J12: Closing Balance | K12: ST | L12: LT
A13: As per Lease Report | B13: 0.075 | C13: 45505 | D13: 46599 | E13: 0 | F13: 13304138 | G13: 17738851 | H13: 1762214.3 | I13: 14714582 | J13: 17614111 | K13: 13958324 | L13: 3655787.4
A14: As per DHS Working | B14: ='G Sec 1 Aug'!C17/100 -> 0.0694 | C14: 45505 | D14: 46599 | E14: 0 | F14: =(D27*1/3)+SUM(D28:D30)+D31*2/3 -> 13409919 | G14: =E31+(D31*1/3) -> 17879893 | H14: =(H27*1/3)+SUM(H28:H30)+H31*2/3 -> 1628946.3 | I14: =-SUM(G28:G31) -> 14714582 | J14: =I31-(H31*1/3) -> 17675422 | K14: =J14-L14 -> 14017688 | L14: =I35-(H35/3) -> 3657733.6
A15: Difference | B15: =B13-B14 -> 0.0056 | C15: =C13-C14 -> 0 | D15: =D13-D14 -> 0 | E15: =E13-E14 -> 0 | F15: =F13-F14 -> -105781.49 | G15: =G13-G14 -> -141041.89 | H15: =H13-H14 -> 133268.04 | I15: =I13-I14 -> 0 | ... L15: =L13-L14 -> -1946.1498
A17: Quarterly Rent (In Advance) | B17: =3678645.58 -> 3678645.6 | C17: << As per agreement >>
A18: Quarterly discount rate | B18: =B14/4 -> 0.01735 | C18: << Link >>
A19: No of Quarters | B19: =ROUND(((D14-C14)/30.5),0)/3 -> 12 | C19: << Formula >>
A20: PV of rent payments | B20: =-PV(B18,B19,B17,,1) -> 40229758 | C20: << Formula >>
C23: Right of Use Asset | F23: Lease Liability
A24: From | B24: To | C24: Opening WDV | D24: Depreciation | E24: Closing WDV | F24: Opening Liability | G24: Repayment | H24: Interest | I24: Closing Lease Liability
A25: 45505 | B25: 45596 | C25: =B20 -> 40229758 | D25: =$B$20/$B$19 -> 3352479.9 | E25: =C25-D25 -> 36877278 | F25: =C25 -> 40229758 | G25: =-$B$17 -> -3678645.6 | H25: =(F25+G25)*$B$18 -> 634161.8 | I25: =F25+G25+H25 -> 37185274
A26: 45597 | B26: 45688 | C26: =E25 -> 36877278 | D26: =$B$20/$B$19 -> 3352479.9 | E26: =C26-D26 -> 33524799 | F26: =I25 -> 37185274 | G26: =-$B$17 -> -3678645.6 | H26: =(F26+G26)*$B$18 -> 581340.01 | I26: =F26+G26+H26 -> 34087969
A27: 45689 | B27: 45777 | C27: =E26 -> 33524799 | D27: =$B$20/$B$19 -> 3352479.9 | E27: =C27-D27 -> 30172319 | F27: =I26 -> 34087969 | G27: =-$B$17 -> -3678645.6 | H27: =(F27+G27)*$B$18 -> 527601.76 | I27: =F27+G27+H27 -> 30936925
A28: 45778 | B28: 45869 | C28: =E27 -> 30172319 | D28: =$B$20/$B$19 -> 3352479.9 | E28: =C28-D28 -> 26819839 | F28: =I27 -> 30936925 | G28: =-$B$17 -> -3678645.6 | H28: =(F28+G28)*$B$18 -> 472931.15 | I28: =F28+G28+H28 -> 27731211
A29: 45870 | B29: 45961 | C29: =E28 -> 26819839 | D29: =$B$20/$B$19 -> 3352479.9 | E29: =C29-D29 -> 23467359 | F29: =I28 -> 27731211 | G29: =-$B$17 -> -3678645.6 | H29: =(F29+G29)*$B$18 -> 417312 | I29: =F29+G29+H29 -> 24469877
A30: 45962 | B30: 46053 | C30: =E29 -> 23467359 | D30: =$B$20/$B$19 -> 3352479.9 | E30: =C30-D30 -> 20114879 | F30: =I29 -> 24469877 | G30: =-$B$17 -> -3678645.6 | H30: =(F30+G30)*$B$18 -> 360727.87 | I30: =F30+G30+H30 -> 21151959
A31: 46054 | B31: 46142 | C31: =E30 -> 20114879 | D31: =$B$20/$B$19 -> 3352479.9 | E31: =C31-D31 -> 16762399 | F31: =I30 -> 21151959 | G31: =-$B$17 -> -3678645.6 | H31: =(F31+G31)*$B$18 -> 303161.99 | I31: =F31+G31+H31 -> 17776476
A32: 46143 | B32: 46234 | C32: =E31 -> 16762399 | D32: =$B$20/$B$19 -> 3352479.9 | E32: =C32-D32 -> 13409919 | F32: =I31 -> 17776476 | G32: =-$B$17 -> -3678645.6 | H32: =(F32+G32)*$B$18 -> 244597.35 | I32: =F32+G32+H32 -> 14342428
A33: 46235 | B33: 46326 | C33: =E32 -> 13409919 | D33: =$B$20/$B$19 -> 3352479.9 | E33: =C33-D33 -> 10057440 | F33: =I32 -> 14342428 | G33: =-$B$17 -> -3678645.6 | H33: =(F33+G33)*$B$18 -> 185016.62 | I33: =F33+G33+H33 -> 10848799
A34: 46327 | B34: 46418 | C34: =E33 -> 10057440 | D34: =$B$20/$B$19 -> 3352479.9 | E34: =C34-D34 -> 6704959.7 | F34: =I33 -> 10848799 | G34: =-$B$17 -> -3678645.6 | H34: =(F34+G34)*$B$18 -> 124402.15 | I34: =F34+G34+H34 -> 7294555.1
A35: 46419 | B35: 46507 | C35: =E34 -> 6704959.7 | D35: =$B$20/$B$19 -> 3352479.9 | E35: =C35-D35 -> 3352479.9 | F35: =I34 -> 7294555.1 | G35: =-$B$17 -> -3678645.6 | H35: =(F35+G35)*$B$18 -> 62736.031 | I35: =F35+G35+H35 -> 3678645.6
A36: 46508 | B36: 46599 | C36: =E35 -> 3352479.9 | D36: =$B$20/$B$19 -> 3352479.9 | E36: =C36-D36 -> -1.1175871e-08 | F36: =I35 -> 3678645.6 | G36: =-$B$17 -> -3678645.6 | H36: =(F36+G36)*$B$18 -> -7.0289243e-10 | I36: =F36+G36+H36 -> -4.1215424e-08

Sheet ITC-64806
A1: =Scope!#REF! -> #REF!
A2: =Scope!#REF! -> #REF!
A3: =Scope!#REF! -> #REF!
A6: =Scope!A2 -> Purpose
A7: To verify the lease working of the sample selected
A10: Summary
A12: Particulars | B12: Discount Rate | C12: Commencement Date | D12: Expiration Date | E12: Addition during FY 2024-25 | F12: Amortisation during FY 2024-25 | G12: Closing WDV | H12: Interest | I12: Repayment | J12: Closing Balance | K12: ST | L12: LT
A13: As per Lease Report | B13: 0.075 | C13: 45505 | D13: 46599 | E13: 0 | F13: 1.0852964e+08 | G13: 1.4470619e+08 | H13: 14375414 | I13: 120035464 | J13: 1.4368862e+08 | K13: 1.1386622e+08 | L13: 29822399
A14: As per DHS Working | B14: ='G Sec 1 Aug'!C17/100 -> 0.0694 | C14: 45505 | D14: 46599 | E14: 0 | F14: =D27*1/3+SUM(D28:D30)+D31*2/3 -> 1.0939256e+08 | G14: =E31+(D31/3) -> 1.4585675e+08 | H14: =(H27*1/3)+SUM(H28:H30)+(H31*2/3) -> 13288269 | I14: =-SUM(G28:G31) -> 120035464 | J14: =I31-(H31/3) -> 1.4418876e+08 | K14: =J14-L14 -> 1.1435049e+08 | L14: =I35-H35*1/3 -> 29838274
A15: Difference | B15: =B13-B14 -> 0.0056 | C15: =C13-C14 -> 0 | D15: =D13-D14 -> 0 | E15: =E13-E14 -> 0 | F15: =F13-F14 -> -862921.28 | G15: =G13-G14 -> -1150561.7 | H15: =H13-H14 -> 1087145.6 | I15: =I13-I14 -> 0 | ... L15: =L13-L14 -> -15875.518
A17: Quarterly Rent (In Advance) | B17: 30008866 | C17: << As per agreement >>
A18: Quarterly discount rate | B18: =B14/4 -> 0.01735 | C18: << Link >>
A19: No of Quarters | B19: =ROUND(((D14-C14)/30.5),0)/3 -> 12 | C19: << Formula >>
A20: PV of rent payments | B20: =-PV(B18,B19,B17,,1) -> 3.2817769e+08 | C20: << Formula >>
C23: Right of Use Asset | F23: Lease Liability
A24: From | B24: To | C24: Opening WDV | D24: Dep | E24: Closing WDV | F24: Opening Liability | G24: Repayment | H24: Interest | I24: Closing Lease Liability
A25: 45505 | B25: 45596 | C25: =B20 -> 3.2817769e+08 | D25: =$B$20/12 -> 27348141 | E25: =C25-D25 -> 3.0082955e+08 | F25: =C25 -> 3.2817769e+08 | G25: =-$B$17 -> -30008866 | H25: =(F25+G25)*$B$18 -> 5173229.2 | I25: =F25+G25+H25 -> 3.0334206e+08
A26: 45597 | B26: 45688 | C26: =E25 -> 3.0082955e+08 | D26: =$B$20/12 -> 27348141 | E26: =C26-D26 -> 2.7348141e+08 | F26: =I25 -> 3.0334206e+08 | G26: =-$B$17 -> -30008866 | H26: =(F26+G26)*$B$18 -> 4742330.9 | I26: =F26+G26+H26 -> 2.7807552e+08
A27: 45689 | B27: 45777 | C27: =E26 -> 2.7348141e+08 | D27: =$B$20/12 -> 27348141 | E27: =C27-D27 -> 2.4613327e+08 | F27: =I26 -> 2.7807552e+08 | G27: =-$B$17 -> -30008866 | H27: =(F27+G27)*$B$18 -> 4303956.5 | I27: =F27+G27+H27 -> 2.5237061e+08
A28: 45778 | B28: 45869 | C28: =E27 -> 2.4613327e+08 | D28: =$B$20/12 -> 27348141 | E28: =C28-D28 -> 2.1878513e+08 | F28: =I27 -> 2.5237061e+08 | G28: =-$B$17 -> -30008866 | H28: =(F28+G28)*$B$18 -> 3857976.3 | I28: =F28+G28+H28 -> 2.2621972e+08
A29: 45870 | B29: 45961 | C29: =E28 -> 2.1878513e+08 | D29: =$B$20/12 -> 27348141 | E29: =C29-D29 -> 1.9143699e+08 | F29: =I28 -> 2.2621972e+08 | G29: =-$B$17 -> -30008866 | H29: =(F29+G29)*$B$18 -> 3404258.4 | I29: =F29+G29+H29 -> 1.9961512e+08
A30: 45962 | B30: 46053 | C30: =E29 -> 1.9143699e+08 | D30: =$B$20/12 -> 27348141 | E30: =C30-D30 -> 1.6408885e+08 | F30: =I29 -> 1.9961512e+08 | G30: =-$B$17 -> -30008866 | H30: =(F30+G30)*$B$18 -> 2942668.4 | I30: =F30+G30+H30 -> 1.7254892e+08
A31: 46054 | B31: 46142 | C31: =E30 -> 1.6408885e+08 | D31: =$B$20/12 -> 27348141 | E31: =C31-D31 -> 1.3674071e+08 | F31: =I30 -> 1.7254892e+08 | G31: =-$B$17 -> -30008866 | H31: =(F31+G31)*$B$18 -> 2473069.9 | I31: =F31+G31+H31 -> 1.4501312e+08
A32: 46143 | B32: 46234 | C32: =E31 -> 1.3674071e+08 | D32: =$B$20/12 -> 27348141 | E32: =C32-D32 -> 1.0939256e+08 | F32: =I31 -> 1.4501312e+08 | G32: =-$B$17 -> -30008866 | H32: =(F32+G32)*$B$18 -> 1995323.8 | I32: =F32+G32+H32 -> 1.1699958e+08
A33: 46235 | B33: 46326 | C33: =E32 -> 1.0939256e+08 | D33: =$B$20/12 -> 27348141 | E33: =C33-D33 -> 82044424 | F33: =I32 -> 1.1699958e+08 | G33: =-$B$17 -> -30008866 | H33: =(F33+G33)*$B$18 -> 1509288.9 | I33: =F33+G33+H33 -> 88500002
A34: 46327 | B34: 46418 | C34: =E33 -> 82044424 | D34: =$B$20/12 -> 27348141 | E34: =C34-D34 -> 54696282 | F34: =I33 -> 88500002 | G34: =-$B$17 -> -30008866 | H34: =(F34+G34)*$B$18 -> 1014821.2 | I34: =F34+G34+H34 -> 59505957
A35: 46419 | B35: 46507 | C35: =E34 -> 54696282 | D35: =$B$20/12 -> 27348141 | E35: =C35-D35 -> 27348141 | F35: =I34 -> 59505957 | G35: =-$B$17 -> -30008866 | H35: =(F35+G35)*$B$18 -> 511774.54 | I35: =F35+G35+H35 -> 30008866
A36: 46508 | B36: 46599 | C36: =E35 -> 27348141 | D36: =$B$20/12 -> 27348141 | E36: =C36-D36 -> 1.0430813e-07 | F36: =I35 -> 30008866 | G36: =-$B$17 -> -30008866 | H36: =(F36+G36)*$B$18 -> -8.4023923e-09 | I36: =F36+G36+H36 -> -4.9269013e-07

Sheet ITC-64797
A1: =Scope!#REF! -> #REF!
A2: =Scope!#REF! -> #REF!
A3: =Scope!#REF! -> #REF!
A6: =Scope!A2 -> Purpose
A7: To verify the lease working of the sample selected
A10: Summary
A12: Particulars | B12: Discount Rate | C12: Commencement Date | D12: Expiration Date | E12: Addition during FY 2025-26 | F12: Amortisation during FY 2025-26 | G12: Closing WDV | H12: Interest | I12: Repayment | J12: Closing Balance | K12: ST | L12: LT
A13: As per Lease Report | B13: =7.5031/100 -> 0.075031 | C13: 45474 | D13: 46568 | E13: 0 | F13: 8256104.4 | G13: 10320130 | H13: 1043314.4 | I13: 9131379.1 | J13: 10999075 | K13: 8716230.7 | L13: 2282844.8
A14: As per DHS Working | B14: ='G Sec 1 July'!C17/100 -> 0.0709 | C14: 45474 | D14: 46568 | E14: 0 | F14: =(D27*1/3)+SUM(D28:D30)+D31*2/3 -> 8305531.7 | G14: =E31+(D31/3) -> 11074042 | H14: =(H27*1/3)+SUM(H28:H30)+H31*2/3 -> 1031217.8 | I14: =-SUM(G28:G31) -> 9131379.1 | J14: =I31-H31/3 -> 10959505 | K14: =J14-L14 -> 8689913.2 | L14: =I35-H35/3 -> 2269591.9
A15: Difference | B15: =B13-B14 -> 0.004131 | C15: =C13-C14 -> 0 | D15: =D13-D14 -> 0 | E15: =E13-E14 -> 0 | F15: =F13-F14 -> -49427.339 | G15: =G13-G14 -> -753912 | H15: =H13-H14 -> 12096.585 | I15: =I13-I14 -> 0 | ... L15: =L13-L14 -> 13252.9
A16: ='ITC-60014'!A16 -> *Lease was started in FY 23-24. Hence, no addition during the year
A18: Quarterly Rent (In Advance) | B18: =2282844.77 -> 2282844.8 | C18: << As per agreement >>
A19: Quarterly discount rate | B19: =B14/4 -> 0.017725 | C19: << Link >>
A20: No of Quarters | B20: =ROUND(((D14-C14)/30.5),0)/3 -> 12 | C20: << Formula >>
A21: PV of rent payments | B21: =-PV(B19,B20,B18,,1) -> 24916595 | C21: << Formula >>
C23: Right of Use Asset | F23: Lease Liability
A24: From | B24: To | C24: Opening WDV | D24: Dep | E24: Closing WDV | F24: Opening Liability | G24: Repayment | H24: Interest | I24: Closing Lease Liability
A25: 45505 | B25: 45596 | C25: =B21 -> 24916595 | D25: =$B$21/$B$20 -> 2076382.9 | E25: =C25-D25 -> 22840212 | F25: =B21 -> 24916595 | G25: =-$B$18 -> -2282844.8 | H25: =(F25+G25)*$B$19 -> 401183.23 | I25: =F25+G25+H25 -> 23034934
A26: 45597 | B26: 45688 | C26: =E25 -> 22840212 | D26: =$B$21/$B$20 -> 2076382.9 | E26: =C26-D26 -> 20763829 | F26: =I25 -> 23034934 | G26: =-$B$18 -> -2282844.8 | H26: =(F26+G26)*$B$19 -> 367830.78 | I26: =F26+G26+H26 -> 21119920
A27: 45689 | B27: 45777 | C27: =E26 -> 20763829 | D27: =$B$21/$B$20 -> 2076382.9 | E27: =C27-D27 -> 18687446 | F27: =I26 -> 21119920 | G27: =-$B$18 -> -2282844.8 | H27: =(F27+G27)*$B$19 -> 333887.15 | I27: =F27+G27+H27 -> 19170962
A28: 45778 | B28: 45869 | C28: =E27 -> 18687446 | D28: =$B$21/$B$20 -> 2076382.9 | E28: =C28-D28 -> 16611063 | F28: =I27 -> 19170962 | G28: =-$B$18 -> -2282844.8 | H28: =(F28+G28)*$B$19 -> 299341.88 | I28: =F28+G28+H28 -> 17187459
A29: 45870 | B29: 45961 | C29: =E28 -> 16611063 | D29: =$B$21/$B$20 -> 2076382.9 | E29: =C29-D29 -> 14534681 | F29: =I28 -> 17187459 | G29: =-$B$18 -> -2282844.8 | H29: =(F29+G29)*$B$19 -> 264184.29 | I29: =F29+G29+H29 -> 15168799
A30: 45962 | B30: 46053 | C30: =E29 -> 14534681 | D30: =$B$21/$B$20 -> 2076382.9 | E30: =C30-D30 -> 12458298 | F30: =I29 -> 15168799 | G30: =-$B$18 -> -2282844.8 | H30: =(F30+G30)*$B$19 -> 228403.53 | I30: =F30+G30+H30 -> 13114357
A31: 46054 | B31: 46142 | C31: =E30 -> 12458298 | D31: =$B$21/$B$20 -> 2076382.9 | E31: =C31-D31 -> 10381915 | F31: =I30 -> 13114357 | G31: =-$B$18 -> -2282844.8 | H31: =(F31+G31)*$B$19 -> 191988.56 | I31: =F31+G31+H31 -> 11023501
A32: 46143 | B32: 46234 | C32: =E31 -> 10381915 | D32: =$B$21/$B$20 -> 2076382.9 | E32: =C32-D32 -> 8305531.7 | F32: =I31 -> 11023501 | G32: =-$B$18 -> -2282844.8 | H32: =(F32+G32)*$B$19 -> 154928.14 | I32: =F32+G32+H32 -> 8895584.6
A33: 46235 | B33: 46326 | C33: =E32 -> 8305531.7 | D33: =$B$21/$B$20 -> 2076382.9 | E33: =C33-D33 -> 6229148.8 | F33: =I32 -> 8895584.6 | G33: =-$B$18 -> -2282844.8 | H33: =(F33+G33)*$B$19 -> 117210.81 | I33: =F33+G33+H33 -> 6729950.7
A34: 46327 | B34: 46418 | C34: =E33 -> 6229148.8 | D34: =$B$21/$B$20 -> 2076382.9 | E34: =C34-D34 -> 4152765.9 | F34: =I33 -> 6729950.7 | G34: =-$B$18 -> -2282844.8 | H34: =(F34+G34)*$B$19 -> 78824.952 | I34: =F34+G34+H34 -> 4525930.8
A35: 46419 | B35: 46507 | C35: =E34 -> 4152765.9 | D35: =$B$21/$B$20 -> 2076382.9 | E35: =C35-D35 -> 2076382.9 | F35: =I34 -> 4525930.8 | G35: =-$B$18 -> -2282844.8 | H35: =(F35+G35)*$B$19 -> 39758.701 | I35: =F35+G35+H35 -> 2282844.8
A36: 46508 | B36: 46599 | C36: =E35 -> 2076382.9 | D36: =$B$21/$B$20 -> 2076382.9 | E36: =C36-D36 -> 3.259629e-09 | F36: =I35 -> 2282844.8 | G36: =-$B$18 -> -2282844.8 | H36: =(F36+G36)*$B$19 -> 2.2285385e-10 | I36: =F36+G36+H36 -> 1.2795709e-08

Sheet ITC-60014
A1: =[3]Scope!A1 -> Deloitte Haskins & Sells
A2: =[3]Scope!A2 -> GE India Industrial Private Limited
A3: =[3]Scope!A3 -> Audit for the year ended March 31, 2024
A6: =[3]Scope!A6 -> Purpose
A7: To verify the lease working of the sample selected
A10: Summary
B11: << Link >> | C11: << As per agreement >> | D11: << As per agreement >> | E11: << Link >> | F11: << Link >> | G11: << Link >> | H11: << Link >> | I11: << Link >> | J11: << Link >>
A12: Particulars | B12: Discount Rate | C12: Commencement Date | D12: Expiration Date | E12: Addition during FY 2025-26 | F12: Amortisation during FY 2025-26 | G12: Closing Balance | H12: Interest | I12: Repayment | J12: Closing Balance | K12: ST | L12: LT
A13: As per Lease Report | B13: 0.08090042 | C13: 45017 | D13: 46112 | E13: 0 | F13: 46481791 | G13: 0 | H13: 1530189.2 | I13: 51805984 | J13: ='Details 25-26'!S84 -> 0 | K13: 0 | L13: 0
A14: As per DHS Working | B14: ='G-Sec 1 March'!E27/100 -> 0.074172 | C14: 45017 | D14: 46112 | E14: 0 | F14: =SUM(C48:C59) -> 46319223 | G14: =D59 -> 6.9849193e-08 | H14: =SUM(F48:F59) -> 2022710.8 | I14: =-SUM(G48:G59) -> 51805984 | J14: =H59 -> -1.125969e-06 | K14: -1.125969e-06 | L14: 0
A15: Difference | B15: =B13-B14 -> 0.00672842 | C15: =C13-C14 -> 0 | D15: =D13-D14 -> 0 | E15: =E13-E14 -> 0 | F15: =F13-F14 -> 162567.76 | G15: =G13-G14 -> -6.9849193e-08 | H15: =H13-H14 -> -492521.64 | I15: =I13-I14 -> 0 | ... L15: =L13-L14 -> 0
A16: *Lease was started in FY 23-24. Hence, no addition during the year
A18: Monthly Rent | B18: =12951496/3 -> 4317165.3 | C18: << As per agreement >>
A19: Monthly discount rate | B19: =B14/12 -> 0.006181 | C19: << Link >>
A20: No of Months | B20: =ROUND(((D14-C14)/30.5),0) -> 36 | C20: << Formula >>
A21: PV of rent payments | B21: =-PV(B19,B20,B18) -> 1.3895767e+08 | C21: << Formula >>
A23: Month | B23: Opening WDV | C23: Dep | D23: Closing WDV | E23: Opening Liability | F23: Interest | G23: Repayment | H23: Closing Lease Liability
A24: 45017 | B24: =$B$21 -> 1.3895767e+08 | C24: =$B$21/$B$20 -> 3859935.3 | D24: =B24-C24 -> 1.3509773e+08 | E24: =$B$21 -> 1.3895767e+08 | F24: =E24*$B$19 -> 858897.36 | G24: =-$B$18 -> -4317165.3 | H24: =SUM(E24:G24) -> 1.354994e+08
A25: 45047 | B25: =D24 -> 1.3509773e+08 | C25: =$B$21/$B$20 -> 3859935.3 | D25: =B25-C25 -> 1.312378e+08 | E25: =H24 -> 1.354994e+08 | F25: =E25*$B$19 -> 837521.8 | G25: =-$B$18 -> -4317165.3 | H25: =SUM(E25:G25) -> 1.3201976e+08
A26: 45078 | B26: =D25 -> 1.312378e+08 | C26: =$B$21/$B$20 -> 3859935.3 | D26: =B26-C26 -> 1.2737786e+08 | E26: =H25 -> 1.3201976e+08 | F26: =E26*$B$19 -> 816014.13 | G26: =-$B$18 -> -4317165.3 | H26: =SUM(E26:G26) -> 1.2851861e+08
A27: 45108 | B27: =D26 -> 1.2737786e+08 | C27: =$B$21/$B$20 -> 3859935.3 | D27: =B27-C27 -> 1.2351793e+08 | E27: =H26 -> 1.2851861e+08 | F27: =E27*$B$19 -> 794373.51 | G27: =-$B$18 -> -4317165.3 | H27: =SUM(E27:G27) -> 1.2499582e+08
A28: 45139 | B28: =D27 -> 1.2351793e+08 | C28: =$B$21/$B$20 -> 3859935.3 | D28: =B28-C28 -> 1.1965799e+08 | E28: =H27 -> 1.2499582e+08 | F28: =E28*$B$19 -> 772599.13 | G28: =-$B$18 -> -4317165.3 | H28: =SUM(E28:G28) -> 1.2145125e+08
A29: 45170 | B29: =D28 -> 1.1965799e+08 | C29: =$B$21/$B$20 -> 3859935.3 | D29: =B29-C29 -> 1.1579806e+08 | E29: =H28 -> 1.2145125e+08 | F29: =E29*$B$19 -> 750690.17 | G29: =-$B$18 -> -4317165.3 | H29: =SUM(E29:G29) -> 1.1788477e+08
A30: 45200 | B30: =D29 -> 1.1579806e+08 | C30: =$B$21/$B$20 -> 3859935.3 | D30: =B30-C30 -> 1.1193812e+08 | E30: =H29 -> 1.1788477e+08 | F30: =E30*$B$19 -> 728645.79 | G30: =-$B$18 -> -4317165.3 | H30: =SUM(E30:G30) -> 1.1429625e+08
A31: 45231 | B31: =D30 -> 1.1193812e+08 | C31: =$B$21/$B$20 -> 3859935.3 | D31: =B31-C31 -> 1.0807819e+08 | E31: =H30 -> 1.1429625e+08 | F31: =E31*$B$19 -> 706465.15 | G31: =-$B$18 -> -4317165.3 | H31: =SUM(E31:G31) -> 1.1068555e+08
A32: 45261 | B32: =D31 -> 1.0807819e+08 | C32: =$B$21/$B$20 -> 3859935.3 | D32: =B32-C32 -> 1.0421825e+08 | E32: =H31 -> 1.1068555e+08 | F32: =E32*$B$19 -> 684147.41 | G32: =-$B$18 -> -4317165.3 | H32: =SUM(E32:G32) -> 1.0705254e+08
A33: 45292 | B33: =D32 -> 1.0421825e+08 | C33: =$B$21/$B$20 -> 3859935.3 | D33: =B33-C33 -> 1.0035832e+08 | E33: =H32 -> 1.0705254e+08 | F33: =E33*$B$19 -> 661691.73 | G33: =-$B$18 -> -4317165.3 | H33: =SUM(E33:G33) -> 1.0339706e+08
A34: 45323 | B34: =D33 -> 1.0035832e+08 | C34: =$B$21/$B$20 -> 3859935.3 | D34: =B34-C34 -> 96498382 | E34: =H33 -> 1.0339706e+08 | F34: =E34*$B$19 -> 639097.24 | G34: =-$B$18 -> -4317165.3 | H34: =SUM(E34:G34) -> 99718994
A35: 45352 | B35: =D34 -> 96498382 | C35: =$B$21/$B$20 -> 3859935.3 | D35: =B35-C35 -> 92638446 | E35: =H34 -> 99718994 | F35: =E35*$B$19 -> 616363.1 | G35: =-$B$18 -> -4317165.3 | H35: =SUM(E35:G35) -> 96018192
A36: 45383 | B36: =D35 -> 92638446 | C36: =$B$21/$B$20 -> 3859935.3 | D36: =B36-C36 -> 88778511 | E36: =H35 -> 96018192 | F36: =E36*$B$19 -> 593488.45 | G36: =-$B$18 -> -4317165.3 | H36: =SUM(E36:G36) -> 92294515
... A59: 46082 | B59: =D58 -> 3859935.3 | C59: =$B$21/$B$20 -> 3859935.3 | D59: =B59-C59 -> 6.9849193e-08 | E59: =H58 -> 4290644.9 | F59: =E59*$B$19 -> 26520.476 | G59: =-$B$18 -> -4317165.3 | H59: =SUM(E59:G59) -> -1.125969e-06

Sheet ITC- 63100
A1: =Summary!A1 -> #REF!
A2: =Summary!A2 -> #REF!
A3: =Summary!A3 -> #REF!
A6: Purpose
A7: To verify the lease working of the sample selected
A10: Summary
B11: << Link >> | C11: << As per agreement >> | D11: << As per agreement >> | E11: << Link >> | F11: << Link >> | G11: << Link >> | H11: << Link >> | I11: << Link >> | J11: << Link >>
A12: Particulars | B12: Discount Rate | C12: Commencement Date | D12: Expiration Date | E12: Addition during FY 2025-26 | F12: Amortisation during FY 2025-26 | G12: Closing WDV | H12: Interest | I12: Repayment | J12: Closing Balance | K12: ST | L12: LT
A13: As per Lease Report | B13: 0.08005165 | C13: 45200 | D13: 46295 | E13: 0 | F13: 7256635.1 | G13: ='Details 25-26'!M118 -> 3628317.7 | H13: 542896.31 | I13: 8078872.3 | J13: ='Details 25-26'!S118 -> 3999549.1 | K13: 3999549.1 | L13: 0
A14: As per DHS Working | B14: ='G-Sec 29 Sept'!E26/100 -> 0.073143 | C14: 45200 | D14: 46295 | E14: 0 | F14: =SUM(C42:C53) -> 7234231.6 | G14: =D53 -> 3617115.8 | H14: =SUM(F42:F53) -> 589290.62 | I14: =-SUM(G42:G53) -> 8078872.3 | J14: =H53 -> 3954643 | K14: =H53-H59 -> 3954643 | L14: =J14-K14 -> 1.4528632e-07
A15: Difference | B15: =B13-B14 -> 0.00690865 | C15: =C13-C14 -> 0 | D15: =D13-D14 -> 0 | E15: =E13-E14 -> 0 | F15: =F13-F14 -> 22403.445 | G15: =G13-G14 -> 11201.873 | H15: =H13-H14 -> -46394.312 | I15: =I13-I14 -> 0 | ... L15: =L13-L14 -> -1.4528632e-07
A16: *Lease was started in FY 23-24. Hence, no addition during the year
A18: Monthly Rent | B18: =2019718.07/3 -> 673239.36 | C18: << As per agreement >>
A19: Monthly discount rate | B19: =B14/12 -> 0.00609525 | C19: << Link >>
A20: No of Months | B20: =ROUND(((D14-C14)/30.5),0) -> 36 | C20: << Formula >>
A21: PV of rent payments | B21: =-PV(B19,B20,B18,) -> 21702695 | C21: << Formula >>
A23: Month | B23: Opening WDV | C23: Dep | D23: Closing WDV | E23: Opening Liability | F23: Interest | G23: Repayment | H23: Closing Lease Liability
A24: 45200 | B24: =B21 -> 21702695 | C24: =$B$21/36 -> 602852.64 | D24: =B24-C24 -> 21099842 | E24: =B21 -> 21702695 | F24: =E24*$B$19 -> 132283.35 | G24: =-$B$18 -> -673239.36 | H24: =SUM(E24:G24) -> 21161739
A25: 45231 | B25: =D24 -> 21099842 | C25: =$B$21/36 -> 602852.64 | D25: =B25-C25 -> 20496990 | E25: =H24 -> 21161739 | F25: =E25*$B$19 -> 128986.09 | G25: =-$B$18 -> -673239.36 | H25: =SUM(E25:G25) -> 20617486
A26: 45261 | B26: =D25 -> 20496990 | C26: =$B$21/36 -> 602852.64 | D26: =B26-C26 -> 19894137 | E26: =H25 -> 20617486 | F26: =E26*$B$19 -> 125668.73 | G26: =-$B$18 -> -673239.36 | H26: =SUM(E26:G26) -> 20069915
A27: 45292 | B27: =D26 -> 19894137 | C27: =$B$21/36 -> 602852.64 | D27: =B27-C27 -> 19291284 | E27: =H26 -> 20069915 | F27: =E27*$B$19 -> 122331.15 | G27: =-$B$18 -> -673239.36 | H27: =SUM(E27:G27) -> 19519007
A28: 45323 | B28: =D27 -> 19291284 | C28: =$B$21/36 -> 602852.64 | D28: =B28-C28 -> 18688432 | E28: =H27 -> 19519007 | F28: =E28*$B$19 -> 118973.23 | G28: =-$B$18 -> -673239.36 | H28: =SUM(E28:G28) -> 18964741
A29: 45352 | B29: =D28 -> 18688432 | C29: =$B$21/36 -> 602852.64 | D29: =B29-C29 -> 18085579 | E29: =H28 -> 18964741 | F29: =E29*$B$19 -> 115594.84 | G29: =-$B$18 -> -673239.36 | H29: =SUM(E29:G29) -> 18407096
A30: 45383 | B30: =D29 -> 18085579 | C30: =$B$21/36 -> 602852.64 | D30: =B30-C30 -> 17482726 | E30: =H29 -> 18407096 | F30: =E30*$B$19 -> 112195.85 | G30: =-$B$18 -> -673239.36 | H30: =SUM(E30:G30) -> 17846053
A31: 45413 | B31: =D30 -> 17482726 | C31: =$B$21/36 -> 602852.64 | D31: =B31-C31 -> 16879874 | E31: =H30 -> 17846053 | F31: =E31*$B$19 -> 108776.15 | G31: =-$B$18 -> -673239.36 | H31: =SUM(E31:G31) -> 17281589
A32: 45444 | B32: =D31 -> 16879874 | C32: =$B$21/36 -> 602852.64 | D32: =B32-C32 -> 16277021 | E32: =H31 -> 17281589 | F32: =E32*$B$19 -> 105335.61 | G32: =-$B$18 -> -673239.36 | H32: =SUM(E32:G32) -> 16713686
A33: 45474 | B33: =D32 -> 16277021 | C33: =$B$21/36 -> 602852.64 | D33: =B33-C33 -> 15674169 | E33: =H32 -> 16713686 | F33: =E33*$B$19 -> 101874.09 | G33: =-$B$18 -> -673239.36 | H33: =SUM(E33:G33) -> 16142320
A34: 45505 | B34: =D33 -> 15674169 | C34: =$B$21/36 -> 602852.64 | D34: =B34-C34 -> 15071316 | E34: =H33 -> 16142320 | F34: =E34*$B$19 -> 98391.479 | G34: =-$B$18 -> -673239.36 | H34: =SUM(E34:G34) -> 15567473
A35: 45536 | B35: =D34 -> 15071316 | C35: =$B$21/36 -> 602852.64 | D35: =B35-C35 -> 14468463 | E35: =H34 -> 15567473 | F35: =E35*$B$19 -> 94887.637 | G35: =-$B$18 -> -673239.36 | H35: =SUM(E35:G35) -> 14989121
A36: 45566 | B36: =D35 -> 14468463 | C36: =$B$21/36 -> 602852.64 | D36: =B36-C36 -> 13865611 | E36: =H35 -> 14989121 | F36: =E36*$B$19 -> 91362.439 | G36: =-$B$18 -> -673239.36 | H36: =SUM(E36:G36) -> 14407244
... A59: 46266 | B59: =D58 -> 602852.64 | C59: =$B$21/36 -> 602852.64 | D59: =B59-C59 -> 0 | E59: =H58 -> 669160.66 | F59: =E59*$B$19 -> 4078.7015 | G59: =-$B$18 -> -673239.36 | H59: =SUM(E59:G59) -> 1.4551915e-07

Sheet ITC-62561
A6: =[3]Scope!A6 -> Purpose
A7: To verify the lease working of the sample selected
A10: Summary
B11: << Link >> | C11: << As per agreement >> | D11: << As per agreement >> | E11: << Link >> | F11: << Link >> | G11: << Link >> | H11: << Link >> | I11: << Link >> | J11: << Link >>
A12: Particulars | B12: Discount Rate | C12: Commencement Date | D12: Expiration Date | E12: Addition during FY 2025-26 | F12: Amortisation during FY 2025-26 | G12: Closing Balance | H12: Interest | I12: Repayment | J12: Closing Balance | K12: ST | L12: LT
A13: As per Lease Report | B13: 0.07562888 | C13: 45139 | D13: 46234 | E13: 0 | F13: 62458473 | G13: 20819491 | H13: 3580529.3 | I13: 69134200 | J13: 17175304 | K13: 17175304 | L13: 0
A14: As per DHS Working | B14: ='G-Sec 1 Aug'!E27/100 -> 0.071232 | C14: 45139 | D14: 46234 | E14: 0 | F14: =SUM(C44:C55) -> 62081469 | G14: =D55 -> 20693823 | H14: =SUM(F44:F55) -> 4151927.4 | I14: =-SUM(G44:G55) -> 69134200 | J14: =H55 -> 22706768 | K14: =H55-H59 -> 22706768 | L14: =J14-K14 -> -1.3001263e-06
A15: Difference | B15: =B13-B14 -> 0.00439688 | C15: =C13-C14 -> 0 | D15: =D13-D14 -> 0 | E15: =E13-E14 -> 0 | F15: =F13-F14 -> 377004.28 | G15: =G13-G14 -> 125667.99 | H15: =H13-H14 -> -571398.1 | I15: =I13-I14 -> 0 | ... L15: =L13-L14 -> 1.3001263e-06
A16: *Lease was started in FY 23-24. Hence, no addition during the year
A18: Monthly Rent | B18: =17283550/3 -> 5761183.3 | C18: << As per agreement >>
A19: Monthly discount rate | B19: =B14/12 -> 0.005936 | C19: << Link >>
A20: No of Months | B20: =ROUND(((D14-C14)/30.5),0) -> 36 | C20: << Formula >>
A21: PV of rent payments | B21: =-PV(B19,B20,B18) -> 1.8624441e+08 | C21: << Formula >>
A23: Month | B23: Opening WDV | C23: Dep | D23: Closing WDV | E23: Opening Liability | F23: Interest | G23: Repayment | H23: Closing Lease Liability
A24: 45139 | B24: =B21 -> 1.8624441e+08 | C24: =$B$21/$B$20 -> 5173455.7 | D24: =B24-C24 -> 1.8107095e+08 | E24: =B21 -> 1.8624441e+08 | F24: =E24*$B$19 -> 1105546.8 | G24: =-$B$18 -> -5761183.3 | H24: =SUM(E24:G24) -> 1.8158877e+08
A25: 45170 | B25: =D24 -> 1.8107095e+08 | C25: =$B$21/$B$20 -> 5173455.7 | D25: =B25-C25 -> 1.7589749e+08 | E25: =H24 -> 1.8158877e+08 | F25: =E25*$B$19 -> 1077910.9 | G25: =-$B$18 -> -5761183.3 | H25: =SUM(E25:G25) -> 1.769055e+08
A26: 45200 | B26: =D25 -> 1.7589749e+08 | C26: =$B$21/$B$20 -> 5173455.7 | D26: =B26-C26 -> 1.7072404e+08 | E26: =H25 -> 1.769055e+08 | F26: =E26*$B$19 -> 1050111 | G26: =-$B$18 -> -5761183.3 | H26: =SUM(E26:G26) -> 1.7219442e+08
A27: 45231 | B27: =D26 -> 1.7072404e+08 | C27: =$B$21/$B$20 -> 5173455.7 | D27: =B27-C27 -> 1.6555058e+08 | E27: =H26 -> 1.7219442e+08 | F27: =E27*$B$19 -> 1022146.1 | G27: =-$B$18 -> -5761183.3 | H27: =SUM(E27:G27) -> 1.6745539e+08
A28: 45261 | B28: =D27 -> 1.6555058e+08 | C28: =$B$21/$B$20 -> 5173455.7 | D28: =B28-C28 -> 1.6037713e+08 | E28: =H27 -> 1.6745539e+08 | F28: =E28*$B$19 -> 994015.18 | G28: =-$B$18 -> -5761183.3 | H28: =SUM(E28:G28) -> 1.6268822e+08
A29: 45292 | B29: =D28 -> 1.6037713e+08 | C29: =$B$21/$B$20 -> 5173455.7 | D29: =B29-C29 -> 1.5520367e+08 | E29: =H28 -> 1.6268822e+08 | F29: =E29*$B$19 -> 965717.27 | G29: =-$B$18 -> -5761183.3 | H29: =SUM(E29:G29) -> 1.5789275e+08
A30: 45323 | B30: =D29 -> 1.5520367e+08 | C30: =$B$21/$B$20 -> 5173455.7 | D30: =B30-C30 -> 1.5003022e+08 | E30: =H29 -> 1.5789275e+08 | F30: =E30*$B$19 -> 937251.38 | G30: =-$B$18 -> -5761183.3 | H30: =SUM(E30:G30) -> 1.5306882e+08
A31: 45352 | B31: =D30 -> 1.5003022e+08 | C31: =$B$21/$B$20 -> 5173455.7 | D31: =B31-C31 -> 1.4485676e+08 | E31: =H30 -> 1.5306882e+08 | F31: =E31*$B$19 -> 908616.52 | G31: =-$B$18 -> -5761183.3 | H31: =SUM(E31:G31) -> 1.4821625e+08
A32: 45383 | B32: =D31 -> 1.4485676e+08 | C32: =$B$21/$B$20 -> 5173455.7 | D32: =B32-C32 -> 1.396833e+08 | E32: =H31 -> 1.4821625e+08 | F32: =E32*$B$19 -> 879811.69 | G32: =-$B$18 -> -5761183.3 | H32: =SUM(E32:G32) -> 1.4333488e+08
A33: 45413 | B33: =D32 -> 1.396833e+08 | C33: =$B$21/$B$20 -> 5173455.7 | D33: =B33-C33 -> 1.3450985e+08 | E33: =H32 -> 1.4333488e+08 | F33: =E33*$B$19 -> 850835.87 | G33: =-$B$18 -> -5761183.3 | H33: =SUM(E33:G33) -> 1.3842454e+08
A34: 45444 | B34: =D33 -> 1.3450985e+08 | C34: =$B$21/$B$20 -> 5173455.7 | D34: =B34-C34 -> 1.2933639e+08 | E34: =H33 -> 1.3842454e+08 | F34: =E34*$B$19 -> 821688.04 | G34: =-$B$18 -> -5761183.3 | H34: =SUM(E34:G34) -> 1.3348504e+08
A35: 45474 | B35: =D34 -> 1.2933639e+08 | C35: =$B$21/$B$20 -> 5173455.7 | D35: =B35-C35 -> 1.2416294e+08 | E35: =H34 -> 1.3348504e+08 | F35: =E35*$B$19 -> 792367.2 | G35: =-$B$18 -> -5761183.3 | H35: =SUM(E35:G35) -> 1.2851622e+08
A36: 45505 | B36: =D35 -> 1.2416294e+08 | C36: =$B$21/$B$20 -> 5173455.7 | D36: =B36-C36 -> 1.1898948e+08 | E36: =H35 -> 1.2851622e+08 | F36: =E36*$B$19 -> 762872.31 | G36: =-$B$18 -> -5761183.3 | H36: =SUM(E36:G36) -> 1.2351791e+08
... A59: 46204 | B59: =D58 -> 5173455.7 | C59: =$B$21/$B$20 -> 5173455.7 | D59: =B59-C59 -> 9.6857548e-08 | E59: =H58 -> 5727186.8 | F59: =E59*$B$19 -> 33996.581 | G59: =-$B$18 -> -5761183.3 | H59: =SUM(E59:G59) -> -1.301989e-06

Sheet Security Deposit Discounting
A1: =Scope!#REF! -> #REF!
A2: =Scope!#REF! -> #REF!
A3: =Scope!#REF! -> #REF!
A5: =Scope!A2 -> Purpose
A6: To document the impact of discounting of security deposit as per IND AS 109
A8: Ind As 109 - Relevant Extract for security deposit discounting
